{"name": "Bảo hộ lao động", "description": "Bảo hộ lao động là ngành học đón đầu xu hướng mới trong nền kinh tế hội nhập toàn cầu, ứng dụng các kiến thức về an toàn và vệ sinh lao động để nghiên cứu nguyên nhân và tìm ra các giải pháp phòng ngừa tai nạn lao động, các yếu tố độc hại gây ảnh hưởng đến sức khỏe và môi trường, sự cố cháy nổ trong sản xuất, … nhằm đảm bảo sức khỏe và an toàn tính mạng cho người lao động và tài sản cho doanh nghiệp.\n\nKỹ sư bảo hộ lao động có thể tự tin ứng tuyển làm việc tại tất cả các doanh nghiệp sản xuất, các tập đoàn đa quốc gia, các dự án công trình xây dựng, cơ quan quản lý nhà nước về an toàn lao động ở những vị trí như tư vấn xây dựng hệ thống an toàn sức khỏe nghề nghiệp theo tiêu chuẩn quốc tế, vận hành và đánh giá hệ thống an toàn sức khỏe nghề nghiệp tại các doanh nghiệp/tập đoàn, quản lý rủi ro trong lao động, đánh giá viên các hệ thống quản lý chất lượng, an toàn, môi trường doanh nghiệp, thanh - kiểm tra và kiểm định tại các cơ quan quản lý Nhà nước về an toàn vệ sinh lao động. Ngoài ra, sinh viên sau khi tốt nghiệp còn có khả năng khởi nghiệp các công ty tư vấn, đào tạo và xử lý sự cố liên quan đến an toàn vệ sinh lao động cho các đối tượng khách hàng cá nhân và doanh nghiệp.", "reasons": ["Liên tục cập nhật xu hướng", "Đội ngũ giảng viên giàu kinh nghiệm", "100% sinh viên ra trường có việc làm trong vòng 12 tháng kể từ khi tốt nghiệp"], "programs": [{"tab": "Tiêu chuẩn", "major_code": "7850201", "description": "Sinh viên được đào tạo kiến thức tích hợp cả 2 lĩnh vực bao gồm quản lý và kỹ thuật an toàn vệ sinh lao động. Ngoài các kiến thức cơ bản, sinh viên được trang bị các kiến thức về kỹ thuật an toàn cơ khí, máy móc thiết bị, điện, hoá chất, phòng chống cháy nổ, sức khỏe nghề nghiệp, tâm lý lao động, ergonomics, … và kỹ năng chuyên ngành về quản lý dự án; điều tra, khảo sát, phân tích, đánh giá và quản lý môi trường lao động; đề xuất các giải pháp công nghệ và tổ chức nhằm đảm bảo an toàn vệ sinh và bảo vệ sức khỏe người lao động.\nĐiểm nổi bật của chương trình đào tạo là được thiết kế với hơn 45% thời lượng học tại doanh nghiệp hoặc các phòng thí nghiệm, với sự tham gia giảng dạy của đội ngũ các nhà khoa học trong lĩnh vực an toàn – sức khỏe nghề nghiệp và các chuyên gia OHS đang làm việc tại doanh nghiệp, qua đó giúp sinh viên củng cố kiến thức đã học, nâng cao năng lực tư duy và rèn luyện kỹ năng làm việc độc lập, đáp ứng tối đa nhu cầu tuyển dụng nguồn nhân lực chất lượng cao cho xã hội.\nNhà trường thường xuyên cập nhật, cải tiến chương trình đào tạo của ngành theo hướng ứng dụng, thực tiễn, gắn kết chặt chẽ với doanh nghiệp, các tổ chức nghiên cứu - đào tạo trong và ngoài nước. Thông qua các buổi hội thảo chuyên đề nghiên cứu ứng dụng, các buổi sinh hoạt học thuật hoặc cán dự án nghiên cứu khoa học đầy tiềm năng, sinh viên được tạo điều kiện để tham gia học hỏi, tìm hiểu, thu thập dữ liệu để phân tích, đánh giá và tìm ra các giải pháp khắc phục hoặc đổi mới giúp hạn chế tối đa những thương tích, giảm thiểu thiệt hại về tính mạng, tài sản cho người lao động và doanh nghiệp, dưới sự dẫn dắt của các chuyên gia hàng đầu đến từ các công ty trong nước và quốc tế.\nSinh viên ngành Bảo hộ lao động sau khi tốt nghiệp có năng lực vận dụng kiến thức và kỹ năng chuyên môn đã được trang bị để tư vấn, tham mưu và triển khai cho doanh nghiệp các giải pháp về kỹ thuật; quản lý và huấn luyện nhằm đảm bảo an toàn trong sản xuất, bảo vệ tính mạng, sức khỏe cho người lao động và tài sản cho doanh nghiệp.\nCử nhân\nKỹ sư\nToàn thời gian: 4 năm\nToàn thời gian: 5 năm\nXem thông tin chi tiết về chương trình đào tạo\nXem thông tin chi tiết về chuẩn đầu ra\nKết quả quá trình học tập THPT\nKết quả bài thi ĐGNL năm 2025 của ĐHQG TP. HCM\nTổ hợp: Đang cập nhật\nĐiểm trúng tuyển 2024 (thang 40):22,00\nTháng 9, năm 2025\nKhoảng 31 đến 32 triệu đồng/năm (năm 2024)", "content": {"Bằng cấp": "Cử nhân Kỹ sư", "Thời gian đào tạo": "Toàn thời gian: 4 năm Toàn thời gian: 5 năm", "Chương trình đào tạo": "Xem thông tin chi tiết về chương trình đào tạo", "Chuẩn đầu ra": "Xem thông tin chi tiết về chuẩn đầu ra", "Phương thức xét tuyển riêng": "Kết quả quá trình học tập THPT Kết quả bài thi ĐGNL năm 2025 của ĐHQG TP. HCM", "Xét tuyển theo điểm thi THPT": "Tổ hợp: Đang cập nhật Điểm trúng tuyển 2024 (thang 40):22,00", "Khai giảng": "Tháng 9, năm 2025", "Học phí": "Khoảng 31 đến 32 triệu đồng/năm (năm 2024)"}, "name": "Bảo hộ lao động"}], "images": ["https://admission.tdtu.edu.vn/sites/admission23/files/Tuyen-sinh/Dai-hoc/Nganh/BHLD/1.jpg", "https://admission.tdtu.edu.vn/sites/admission23/files/Tuyen-sinh/Dai-hoc/Nganh/BHLD/2.png", "https://admission.tdtu.edu.vn/sites/admission23/files/Tuyen-sinh/Dai-hoc/Nganh/BHLD/3.jpg"]}
{"name": "Công nghệ kỹ thuật môi trường - Chuyên ngành Cấp thoát nước và môi trường nước", "description": "Bảo vệ môi trường, đặc biệt là môi trường nước hiện nay không còn là vấn đề của riêng mỗi quốc gia mà đã trở thành mối quan tâm của toàn cầu. Chuyên ngành Cấp thoát nước và môi trường nước thuộc ngành Công nghệ kỹ thuật môi trường là ngành học ứng dụng kỹ thuật và công nghệ để giải quyết các vấn đề về môi trường, hạ tầng đô thị, cấp thoát nước và chữa cháy nhằm đáp ứng nhu cầu nhân lực ngày càng tăng trong lĩnh vực này ở hầu hết các công trình và dự án xây dựng.\nHiện nay, nhu cầu nhân lực của khối ngành này ở các đơn vị sự nghiệp trong lĩnh vực xây dựng và quản lý hạ tầng kỹ thuật rất cao, phạm vi công việc rộng, bao gồm thiết kế, thi công, vận hành, và quản lý công trình trong các hệ thống cấp, thoát nước; xử lý nước cấp cho sinh hoạt và công nghiệp; xử lý nước thải sinh hoạt và sản xuất; thiết kế hệ thống cơ điện.\n\nSau khi tốt nghiệp, Kỹ sư Công nghệ kỹ thuật môi trường - Chuyên ngành Cấp thoát nước và môi trường nước có đầy đủ năng lực để tự tin ứng tuyển vào nghiên cứu và làm việc ở các công ty cấp thoát nước và môi trường đô thị; công ty tư vấn, thiết kế, thi công xây dựng, doanh nghiệp sản xuất kinh doanh vật tư thiết bị chuyên ngành cấp thoát nước, trung tâm nước sạch và vệ sinh nông thôn, viện nghiên cứu cấp thoát nước và môi trường, Sở Tài nguyên Môi trường các tỉnh, thành phố, Phòng Tài nguyên Môi trường các quận, huyện hoặc ứng tuyển vào vị trí chuyên gia của các dự án cấp thoát nước, môi trường trong nước và quốc tế, …", "reasons": ["Đội ngũ giảng viên giàu kinh nghiệm", "Liên tục cập nhật xu hướng", "Số tiết học thực tế chiếm hơn 40% chương trình đào tạo"], "programs": [{"tab": "Tiêu chuẩn", "major_code": "7510406", "description": "Ngoài các kiến thức cơ bản về thành phần, tính chất hóa lý và sinh học của nguồn nước và nước thải; các nội dung liên quan đến công tác bảo vệ nguồn tài nguyên nước, sinh viên còn được trang bị các kỹ năng chuyên ngành về tính toán thiết kế các công trình thủy lực, hệ thống xử lý nước cấp, nước thải sinh hoạt và nước thải công nghiệp; kỹ năng tính toán thiết kế, quản lý mạng lưới cấp thoát nước bên trong và ngoài công trình; kỹ năng vận hành, bảo dưỡng và tự động hoá các công trình cấp thoát nước. Ngoài ra, sinh viên còn được trang bị kỹ năng sử dụng các phần mềm chuyên nghiệp để thiết kế các mô hình cấp thoát nước ứng dụng trực tiếp vào thực tiễn.\nChương trình học là được đào tạo theo hướng ứng dụng với hơn 40% thời lượng sinh viên được học tại doanh nghiệp hoặc các khu vực thực hành được trang bị đầy đủ hệ thống xử lý cấp thoát nước hiện đại. Trong quá trình học, sinh viên được tham gia các học phần, dự án nghiên cứu cùng chuyên gia, giảng viên trong và ngoài nước.\nThông qua các buổi hội thảo chuyên đề nghiên cứu ứng dụng, các buổi sinh hoạt học thuật hoặc cán dự án nghiên cứu khoa học đầy tiềm năng dưới sự dẫn dắt của các chuyên gia hàng đầu tại các doanh nghiệp, sinh viên được tạo điều kiện để tham gia học hỏi, thiết kế, thi công và vận hành các công trình cấp thoát nước ở đô thị, quản lý các chương trình, dự án cấp thoát nước, ứng dụng tiến bộ của ngành cấp thoát nước trong tính toán thiết kế và quản lý mạng lưới cấp thoát nước, vận dụng các kỹ thuật xử lý nước cấp, xử lý nước thải sinh hoạt và nước thải công nghiệp. Đặc biệt, sinh viên có từ 5 - 6 tháng tham gia kiến tập tại các công ty Việt Nam và tập đoàn đa quốc gia để làm quen với môi trường và văn hoá làm việc, tích lũy kinh nghiệm thực tế và nâng cao năng lực chuyên môn.\nSinh viên ngành Công nghệ kỹ thuật môi trường sau khi tốt nghiệp có đầy đủ kiến thức và kỹ năng để vận dụng hệ thống văn bản pháp luật, các kiến thức về kinh tế cho hoạt động tư vấn, thiết kế, xây dựng cơ sở hạ tầng cấp thoát nước và các công trình bảo vệ môi trường; biết xác định các giải pháp kỹ thuật tối ưu trong các công trình hạ tầng cơ sở cấp thoát nước, các công trình ngăn ngừa ô nhiễm và xử lý chất thải; ứng dụng kiến thức chuyên ngành để thiết kế, thi công vận hành và bảo dưỡng các công trình xử lý chất thải, mạng lưới cấp thoát nước cho một khu vực hoặc một công trình cụ thể; xây dựng chương trình kiểm soát ô nhiễm môi trường và chương trình vận hành, quản lý hệ thống cấp thoát nước tại doanh nghiệp và địa phương, …\nCử nhân\nKỹ sư\nToàn thời gian: 4 năm\nToàn thời gian: 5 năm\nXem thông tin chi tiết về chương trình đào tạo\nXem thông tin chi tiết về chuẩn đầu ra\nKết quả quá trình học tập THPT\nKết quả bài thi ĐGNL năm 2025 của ĐHQG TP. HCM\nTổ hợp: Đang cập nhật\nĐiểm trúng tuyển 2024 (thang 40):22,00\nTháng 9, năm 2025\nKhoảng 31 đến 32 triệu đồng/năm (năm 2024)", "content": {"Bằng cấp": "Cử nhân Kỹ sư", "Thời gian đào tạo": "Toàn thời gian: 4 năm Toàn thời gian: 5 năm", "Chương trình đào tạo": "Xem thông tin chi tiết về chương trình đào tạo", "Chuẩn đầu ra": "Xem thông tin chi tiết về chuẩn đầu ra", "Phương thức xét tuyển riêng": "Kết quả quá trình học tập THPT Kết quả bài thi ĐGNL năm 2025 của ĐHQG TP. HCM", "Xét tuyển theo điểm thi THPT": "Tổ hợp: Đang cập nhật Điểm trúng tuyển 2024 (thang 40):22,00", "Khai giảng": "Tháng 9, năm 2025", "Học phí": "Khoảng 31 đến 32 triệu đồng/năm (năm 2024)"}, "name": "Công nghệ kỹ thuật môi trường (Chuyên ngành Cấp thoát nước và môi trường nước)"}], "images": ["https://admission.tdtu.edu.vn/sites/admission23/files/Tuyen-sinh/Dai-hoc/Nganh/CNKTMT/1.jpg", "https://admission.tdtu.edu.vn/sites/admission23/files/Tuyen-sinh/Dai-hoc/Nganh/CNKTMT/2.jpg", "https://admission.tdtu.edu.vn/sites/admission23/files/Tuyen-sinh/Dai-hoc/Nganh/CNKTMT/3.jpg"]}
{"name": "Công nghệ sinh học", "description": "Công nghệ sinh học là ngành ứng dụng các kiến thức trong lĩnh vực sinh học nhằm nghiên cứu và sản xuất ra các sản phẩm sinh học thiết yếu, sản phẩm có giá trị cao như vaccine, kháng sinh, xăng sinh học; cải tiến chất lượng giống cây trồng, ứng dụng vi sinh để xử lý nước thải công nghiệp, ứng dụng các hợp chất tự nhiên để điều trị bệnh và những ứng dụng khác phục vụ cho đời sống con người.\nVới cách tiếp cận và xây dựng chương trình đào tạo hiện đại, tiệm cận với các nền giáo dục tiên tiến và sát với yêu cầu về nguồn nhân lực của thị trường lao động, sinh viên sau khi tốt nghiệp ngành Công nghệ sinh học có thể đảm nhiệm các vị trí như: Phụ trách nghiên cứu và phát triển sản phẩm mới; phụ trách quản lý hệ thống và kiểm định dây chuyền sản xuất của nhà máy; phụ trách theo dõi và kiểm soát vi sinh sản phẩm; chẩn đoán bệnh bằng công nghệ di truyền, liệu pháp gene, công nghệ tế bào gốc; phụ trách theo dõi và phát triển phôi thụ tinh trong ống nghiệm, nghiên cứu và chế tạo vaccine; phụ trách lai tạo, chuyển gen để tạo ra giống cây trồng mới,… Ngoài ra, Kỹ sư Công nghệ sinh học còn có thể tiếp tục học lên cao học trong các lĩnh vực tin sinh học, di truyền,…", "reasons": ["Đội ngũ giảng viên giàu kinh nghiệm", "Số tiết học thực tế chiếm gần 50% chương trình đào tạo", "100% sinh viên ra trường có việc làm trong vòng 12 tháng kể từ khi tốt nghiệp"], "programs": [{"tab": "Tiêu chuẩn", "major_code": "7420201", "description": "Sinh viên được học các kiến thức từ cơ bản đến chuyên sâu như sinh học phân tử, sinh học tế bào, di truyền học, vi sinh vật học, hóa sinh, hóa lý, sinh thái học, công nghệ protein - enzyme, công nghệ gene tái tổ hợp…\nNgoài kiến thức chuyên môn được trang bị theo chương trình đào tạo quốc tế, sinh viên còn được thực hành trong các trung tâm thí nghiệm với thiết bị hiện đại và liên tục cập nhật. Ngoài ra, Nhà trường còn chú trọng đầu tư xây dựng các phòng thí nghiệm vi sinh, sinh học phân tử, nuôi cấy mô, vườn ươm, nhà kính thủy canh, nhà nấm, vườn dược liệu,… nhằm phục vụ nhu cầu học tập và nghiên cứu của sinh viên.\nSố tiết học thực hành chiếm khoảng 50% trong chương trình đào tạo, giúp sinh viên được trải nghiệm thực tế, góp phần nâng cao tay nghề bên cạnh việc tiếp thu kiến thức chuyên môn.\nCác học phần thuộc khối kiến thức chuyên ngành đều có sự tham gia của các doanh nghiệp dưới hình thức tham quan, trải nghiệm thực tế quy trình sản xuất, phân tích tình huống hoặc các buổi sinh hoạt học thuật về ứng dụng kiến thức sinh học vào thực tiễn như: quản lý nước thải, cải tiến chất lượng giống cây trồng, sản xuất nhiên liệu sinh học, nghiên cứu phương pháp chế tạo vaccine, thiết kế thuốc và liệu pháp gene,…\nTrong một số môn học chuyên sâu, các chuyên gia đến từ doanh nghiệp sẽ cùng với giảng viên của trường giảng dạy và hướng dẫn sinh viên thực hiện các dự án nghiên cứu ngay tại doanh nghiệp, từ đó nâng cao khả năng thực hành nghề nghiệp cho sinh viên ngay khi còn ngồi trên ghế Nhà trường. Tính ứng dụng của các học phần được thiết kế theo hướng tăng dần từ cấp độ cơ bản đến cấp độ sinh viên tự mình nghiên cứu và thực nghiệm các đề tài khoa học mang tính ứng dụng vào thực tiễn trong quá trình thực hiện khóa luận tốt nghiệp.\nCử nhân\nKỹ sư\nToàn thời gian: 4 năm\nToàn thời gian: 5 năm\nXem thông tin chi tiết về chương trình đào tạo\nXem thông tin chi tiết về chuẩn đầu ra\nKết quả quá trình học tập THPT\nKết quả bài thi ĐGNL năm 2025 của ĐHQG TP. HCM\nTổ hợp: Đang cập nhật\nĐiểm trúng tuyển 2024 (thang 40):25,00\nTháng 9, năm 2025\nKhoảng 31 đến 32 triệu đồng/năm (năm 2024)", "content": {"Bằng cấp": "Cử nhân Kỹ sư", "Thời gian đào tạo": "Toàn thời gian: 4 năm Toàn thời gian: 5 năm", "Chương trình đào tạo": "Xem thông tin chi tiết về chương trình đào tạo", "Chuẩn đầu ra": "Xem thông tin chi tiết về chuẩn đầu ra", "Phương thức xét tuyển riêng": "Kết quả quá trình học tập THPT Kết quả bài thi ĐGNL năm 2025 của ĐHQG TP. HCM", "Xét tuyển theo điểm thi THPT": "Tổ hợp: Đang cập nhật Điểm trúng tuyển 2024 (thang 40):25,00", "Khai giảng": "Tháng 9, năm 2025", "Học phí": "Khoảng 31 đến 32 triệu đồng/năm (năm 2024)"}, "name": "Công nghệ sinh học"}, {"tab": "Tiên tiến", "major_code": "F7420201", "description": "Chương trình tiên tiến ngành Công nghệ sinh học đã tuyển sinh và tổ chức đào tạo từ năm 2015.\nSinh viên được trang bị các kiến thức về hóa sinh, vi sinh, sinh học phân tử, dược sinh, y sinh, kỹ thuật trồng nấm, nuôi cấy mô, trồng cây thủy canh, kiểm nghiệm thực phẩm, thiết kế và xây dựng quy trình sản xuất các sản phẩm thực phẩm cũng như các chế phẩm sinh học ứng dụng trong chăn nuôi, trồng trọt, y dược. Trong quá trình học tập, sinh viên được thực hành tại phòng thí nghiệm, tham gia các đợt học tập ngoài thực địa, tại doanh nghiệp; được tham gia cùng thực hiện các đề tài, dự án cùng với giảng viên và doanh nghiệp. Do đặc điểm chương trình được giảng dạy bằng tiếng Anh ngay từ năm đầu tiên, sinh viên có nhiều cơ hội tiếp cận, giao lưu  và được tham gia tất cả các sự kiện quốc tế diễn ra tại Khoa, Trường; tham gia học tập cùng với các đoàn sinh viên quốc tế cùng nhiều hoạt động học thuật khác, giúp sinh viên nâng cao kiến thức, năng lực ngoại ngữ và kỹ năng thực hành chuyên môn.\nCử nhân\nKỹ sư\nToàn thời gian: 4 năm\nToàn thời gian: 5 năm\nXem thông tin chi tiết về chương trình đào tạo\nXem thông tin chi tiết về chuẩn đầu ra\nTổ hợp: Toán, Anh, Sinh*2\nKQ ĐGNL của ĐHQG TP. HCM\nƯu tiên xét tuyển theo TDTU\nTổ hợp: A00; B00; D08\nĐiểm trúng tuyển 2024 (thang 40):23,00\nTháng 9, năm 2025\nKhoảng 53 đến 54 triệu đồng/năm (năm 2024)", "content": {"Bằng cấp": "Cử nhân Kỹ sư", "Thời gian đào tạo": "Toàn thời gian: 4 năm Toàn thời gian: 5 năm", "Chương trình đào tạo": "Xem thông tin chi tiết về chương trình đào tạo", "Chuẩn đầu ra": "Xem thông tin chi tiết về chuẩn đầu ra", "Phương thức xét tuyển riêng": "Tổ hợp: Toán, Anh, Sinh*2 KQ ĐGNL của ĐHQG TP. HCM Ưu tiên xét tuyển theo TDTU", "Xét tuyển theo điểm thi THPT": "Tổ hợp: A00; B00; D08 Điểm trúng tuyển 2024 (thang 40):23,00", "Khai giảng": "Tháng 9, năm 2025", "Học phí": "Khoảng 53 đến 54 triệu đồng/năm (năm 2024)"}, "name": "Công nghệ sinh học"}, {"tab": "Đại học bằng tiếng Anh", "major_code": "FA7420201", "description": "Chương trình đại học bằng tiếng Anh - ngành Công nghệ sinh học được xây dựng có tính chuyên môn cao nhằm đáp ứng được các nhu cầu xã hội của ngành Công nghệ sinh học về việc làm, giáo dục và nghiên cứu ứng dụng.\nSinh viên được trang bị các kiến thức về hóa sinh, vi sinh, sinh học phân tử, dược sinh, y sinh, kỹ thuật trồng nấm, nuôi cấy mô, trồng cây thủy canh, kiểm nghiệm thực phẩm, thiết kế và xây dựng quy trình sản xuất các sản phẩm thực phẩm cũng như các chế phẩm sinh học ứng dụng trong chăn nuôi, trồng trọt, y dược. Trong quá trình học tập, sinh viên được thực hành tại phòng thí nghiệm, tham gia các đợt học tập ngoài thực địa, tại doanh nghiệp; được tham gia cùng thực hiện các đề tài, dự án cùng với giảng viên và doanh nghiệp.\nCác chuyên ngành của chương trình đào tạo mở rộng cơ hội nghề nghiệp cho sinh viên sau ra trường gồm: Khoa học Y sinh, Nông nghiệp và Khoa học Thực phẩm.\nDo đặc điểm chương trình được giảng dạy bằng tiếng Anh ngay từ năm đầu tiên, sinh viên có nhiều cơ hội tiếp cận, giao lưu  và được tham gia tất cả các sự kiện quốc tế diễn ra tại Khoa, Trường; tham gia học tập cùng với các đoàn sinh viên quốc tế cùng nhiều hoạt động học thuật khác, giúp sinh viên nâng cao kiến thức, năng lực ngoại ngữ và kỹ năng thực hành chuyên môn.\nCử nhân\nKỹ sư\nToàn thời gian: 4 năm\nToàn thời gian: 5 năm\nXem thông tin chi tiết về chương trình đào tạo\nXem thông tin chi tiết về chuẩn đầu ra\nXét theo điểm trung bình HK\nKQ ĐGNL của ĐHQG TP. HCM\nƯu tiên xét tuyển theo TDTU\nTổ hợp: E05; B00; D08\nĐiểm trúng tuyển 2024 (thang 40):24,00\nTháng 9, năm 2025\nKhoảng 81 đến 83 triệu đồng/năm (năm 2024)", "content": {"Bằng cấp": "Cử nhân Kỹ sư", "Thời gian đào tạo": "Toàn thời gian: 4 năm Toàn thời gian: 5 năm", "Chương trình đào tạo": "Xem thông tin chi tiết về chương trình đào tạo", "Chuẩn đầu ra": "Xem thông tin chi tiết về chuẩn đầu ra", "Phương thức xét tuyển riêng": "Xét theo điểm trung bình HK KQ ĐGNL của ĐHQG TP. HCM Ưu tiên xét tuyển theo TDTU", "Xét tuyển theo điểm thi THPT": "Tổ hợp: E05; B00; D08 Điểm trúng tuyển 2024 (thang 40):24,00", "Khai giảng": "Tháng 9, năm 2025", "Học phí": "Khoảng 81 đến 83 triệu đồng/năm (năm 2024)"}, "name": "Công nghệ sinh học"}], "images": ["https://admission.tdtu.edu.vn", "https://admission.tdtu.edu.vn/sites/admission23/files/Tuyen-sinh/Dai-hoc/Nganh/Cong-nghe-sinh-hoc/1.jpg", "https://admission.tdtu.edu.vn/sites/admission23/files/Tuyen-sinh/Dai-hoc/Nganh/Cong-nghe-sinh-hoc/2.jpg", "https://admission.tdtu.edu.vn/sites/admission23/files/Tuyen-sinh/Dai-hoc/Nganh/Cong-nghe-sinh-hoc/3.jpg"]}
{"name": "Công tác xã hội", "description": "Công tác xã hội là ngành khoa học vận dụng những lý thuyếtvà kiến thức bản địa nhằm thúc đẩy sự tiến bộ và phát triển xã hội, giúp con người tự giải quyết vấn đề của chính mình nhờ vào các nguyên tắc công bằng xã hội, quyền con người, tinh thần trách nhiệm chung và tôn trọng sự đa dạng bản sắc văn hóa dân tộc.\n\nCử nhân ngành Công tác xã hội sẽ có khả năng làm việc tại các tổ chức xã hội Việt Nam và quốc tế; các cơ quan quản lý nhà nước về mặt xã hội như Phòng, Sở Lao động, Thương binh và Xã hội; các tổ chức chính trị - xã hội như Đoàn thanh niên, Hội phụ nữ. Bên cạnh đó, sinh viên tốt nghiệp có thể làm chuyên viên cao cấp trong các trường học, bệnh viện, bộ phận trách nhiệm xã hội của doanh nghiệp, tham vấn và tư vấn ban đầu về tâm lý và sức khỏe cộng đồng; là nền tảng để người học tiếp tục học tập, giảng dạy và nghiên cứu tại các trường đại học, học viện hoặc có thể tự thành lập và điều hành các doanh nghiệp xã hội, tổ chức phi chính phủ, cơ sở trợ giúp xã hội.", "reasons": ["Sinh viên được đi thực tế và thực hành tại nhiều tổ chức công tác xã hội", "Chương trình đào tạo có tính liên thông với các chương trình sau đại học của khoa", "100% sinh viên ra trường có việc làm trong vòng 12 tháng kể từ khi tốt nghiệp"], "programs": [{"tab": "Tiêu chuẩn", "major_code": "7760101", "description": "Chương trình đào tạo ngành Công tác xã hội cung cấp cho sinh viênnhững kiến thức cơ bản về tâm lý, hành vi con người và môi trường xã hội, cách thức làm việc hiệu quả với những người gặp vấn đề khó khăn trong xã hội. Bên cạnh đó, sinh viên còn được trang bị các kỹ năng để thấu hiểu hành vi của con người; phân tích và xác định nhu cầu của con người; vận động và thu hút nguồn lực xã hội; xây dựng và quản lý dự án phát triển cộng đồng; làm việc hiệu quả trong môi trường đa dạng về dân tộc, văn hóa, …\nVới phương châm “đem thực tiễn đến giảng đường, đem lý thuyết ra thực địa”, Nhà trường đã ký kết hợp tác với nhiều trung tâm công tác xã hội, cơ sở xã hội, các cơ quan, tổ chức thuộc Đoàn thể Nhà nước, doanh nghiệp trong lĩnh vực xã hội - tâm lý với đa dạng các hoạt động chuyên môn: chia sẻ chuyên đề, hội thảo của chuyên gia đến từ các tổ chức/doanh nghiệp; kiến tập, thực hành để tạo cơ hội cho sinh viên sớm tiếp cận và nâng cao tay nghề,  góp phần hỗ trợ và giải quyết các vấn đề tâm lý – xã hội của các nhóm đối tượng thực tế ngay tại nơi làm việc.\nCử nhân\nToàn thời gian: 4 năm\nXem thông tin chi tiết về chương trình đào tạo\nXem thông tin chi tiết về chuẩn đầu ra\nKết quả quá trình học tập THPT\nKết quả bài thi ĐGNL năm 2025 của ĐHQG TP. HCM\nTổ hợp: Đang cập nhật\nĐiểm trúng tuyển 2024 (thang 40):29,45\nTháng 9, năm 2025\nKhoảng 27 đến 28 triệu đồng/năm (năm 2024)", "content": {"Bằng cấp": "Cử nhân", "Thời gian đào tạo": "Toàn thời gian: 4 năm", "Chương trình đào tạo": "Xem thông tin chi tiết về chương trình đào tạo", "Chuẩn đầu ra": "Xem thông tin chi tiết về chuẩn đầu ra", "Phương thức xét tuyển riêng": "Kết quả quá trình học tập THPT Kết quả bài thi ĐGNL năm 2025 của ĐHQG TP. HCM", "Xét tuyển theo điểm thi THPT": "Tổ hợp: Đang cập nhật Điểm trúng tuyển 2024 (thang 40):29,45", "Khai giảng": "Tháng 9, năm 2025", "Học phí": "Khoảng 27 đến 28 triệu đồng/năm (năm 2024)"}, "name": "Công tác xã hội"}], "images": ["https://admission.tdtu.edu.vn", "https://admission.tdtu.edu.vn/sites/admission23/files/Tuyen-sinh/Dai-hoc/Nganh/Cong-tac-xa-hoi/1.png", "https://admission.tdtu.edu.vn/sites/admission23/files/Tuyen-sinh/Dai-hoc/Nganh/Cong-tac-xa-hoi/2.JPG", "https://admission.tdtu.edu.vn/sites/admission23/files/Tuyen-sinh/Dai-hoc/Nganh/Cong-tac-xa-hoi/3.jpg"]}
{"name": "Du lịch (Chuyên ngành Hướng dẫn viên du lịch)", "description": "Du lịch là một trong những ngành kinh tế quan trọng nhất trên thế giới, mang lại nguồn thu lớn cho nhiều quốc gia và được xem là là ngành \"công nghiệp không khói\" và giàu tiềm năng trong xu hướng toàn cầu hóa như hiện nay.\nHướng dẫn du lịch là ngành đào tạo chuyên sâu về các nghiệp vụ trong ngành du lịch, bao gồm quá trình quản lý và điều hành hoạt động du lịch, tiếp nhận thông tin để phối hợp với các bộ phận, cơ quan chức năng giải quyết những phát sinh, thiết kế các chương trình du lịch, sự kiện liên quan tới du lịch, hướng dẫn viên du lịch,…\nCử nhân ngành Du lịch (Chuyên ngành Hướng dẫn du lịch) có thể tự tin ứng tuyển vào các vị trí như hướng dẫn viên du lịch chuyên nghiệp; thuyết minh viên tại điểm; nhân viên kinh doanh trong các bộ phận của công ty du lịch lữ hành; chuyên viên tư vấn tổ chức tour, tổ chức sự kiện, teambuilding; cán bộ phụ trách công việc ở bộ phận lữ hành, xúc tiến quảng bá du lịch, hợp tác quốc tế và bồi dưỡng nghiệp vụ du lịch tại các Cơ quan quản lý Nhà nước về du lịch hoặc tham gia giảng dạy tại các cơ sở đào tạo về du lịch.", "reasons": ["Đội ngũ giảng viên có chuyên môn cao, kinh nghiệm nghiên cứu và hướng dẫn sinh viên thực hiện các dự án nghiên cứu khoa học", "Đi thực tế, thực hành nghiệp vụ, tập sự nghề nghiệp tại hơn 60 doanh nghiệp lữ hành, khách sạn, điểm du lịch trên địa bàn TP. Hồ Chí Minh", "100% sinh viên ra trường có việc làm trong vòng 12 tháng kể từ khi tốt nghiệp"], "programs": [{"tab": "Tiêu chuẩn", "major_code": "7810101H", "description": "Chương trình Du lịch (Chuyên ngành Hướng dẫn du lịch) trang bị cho sinh viên những kiến thức cơ bản cũng như chuyên sâu về văn hóa, lịch sử, địa lý, kinh tế – xã hội Việt Nam và quản lý dịch vụ lữ hành; đồng thời rèn luyện những kỹ năng chuyên môn của nghiệp vụ lữ hành gồm hướng dẫn viên du lịch, khai thác và xây dựng chương trình tour, điều hành và tổ chức thực hiện tour. Qua đó, giúp sinh viên có khả năng ứ́ng xử, giải quyết các vấn đề liên quan đến chương trình tour và tạo lập kỹ năng thực hành nghề nghiệp tương xứng với trình độ trong khu vực, đáp ứng được nhu cầu của thời đại.\nCử nhân\nToàn thời gian: 4 năm\nXem thông tin chi tiết về chương trình đào tạo\nXem thông tin chi tiết về chuẩn đầu ra\nKết quả quá trình học tập THPT\nKết quả bài thi ĐGNL năm 2025 của ĐHQG TP. HCM\nTổ hợp: Đang cập nhật\nTháng 9, năm 2025\nĐang cập nhật", "content": {"Bằng cấp": "Cử nhân", "Thời gian đào tạo": "Toàn thời gian: 4 năm", "Chương trình đào tạo": "Xem thông tin chi tiết về chương trình đào tạo", "Chuẩn đầu ra": "Xem thông tin chi tiết về chuẩn đầu ra", "Phương thức xét tuyển riêng": "Kết quả quá trình học tập THPT Kết quả bài thi ĐGNL năm 2025 của ĐHQG TP. HCM", "Xét tuyển theo điểm thi THPT": "Tổ hợp: Đang cập nhật", "Khai giảng": "Tháng 9, năm 2025", "Học phí": "Đang cập nhật"}, "name": "Du lịch (Chuyên ngành Hướng dẫn du lịch)"}], "images": ["https://admission.tdtu.edu.vn/sites/admission23/files/Tuyen-sinh/Dai-hoc/Nganh/Huong-dan-vien-du-lich/1.jpg", "https://admission.tdtu.edu.vn/sites/admission23/files/Tuyen-sinh/Dai-hoc/Nganh/Huong-dan-vien-du-lich/2.jpg", "https://admission.tdtu.edu.vn/sites/admission23/files/Tuyen-sinh/Dai-hoc/Nganh/Huong-dan-vien-du-lich/3.jpg"]}
{"name": "Du lịch (Chuyên ngành Quản lý du lịch)", "description": "Du lịch là một trong những ngành kinh tế quan trọng nhất trên thế giới, mang lại nguồn thu lớn cho nhiều quốc gia và được xem làlà ngành “công nghiệp không khói” và giàu tiềm năng trong xu hướng toàn cầu hóa như hiện nay.\nQuản lý du lịch là một ngành năng động, bao gồm quá trình hoạch định, tổ chức, lãnh đạo và kiểm soát liên quan đến dịch vụ du lịch; quản lý và tổ chức các hoạt động tham quan của du khách một cách hợp lý; xây dựng kế hoạch kinh doanh du lịch, dịch vụ du lịch; báo cáo kết quả tài chính; quản lý nhân sự, … một cách có hiệu quả.\n\nCử nhân ngành Du lịch (Chuyên ngành Quản lý du lịch) có đầy đủ năng lực để ứng tuyển vào các vị trí như chuyên viên cung cấp dịch vụ du lịch tại các khu du lịch, điểm vui chơi tham quan du lịch; chuyên gia tư vấn về chiến lược kinh doanh, khai thác, xây dựng và cung cấp sản phẩm du lịch; chuyên viên thuộc Bộ và Sở Văn hóa, Thể thao và Du lịch như Trung tâm bồi dưỡng nghiệp vụ du lịch, Viện nghiên cứu và phát triển du lịch, Quy hoạch du lịch, Trung tâm xúc tiến du lịch; tự tạo lập doanh nghiệp du lịch mới với quy mô nhỏ hoặc tham gia giảng dạy tại các cơ sở đào tạo về du lịch.", "reasons": ["Đội ngũ giảng viên có chuyên môn cao, kinh nghiệm nghiên cứu và hướng dẫn sinh viên thực hiện các dự án nghiên cứu khoa học", "Đi thực tế, thực hành nghiệp vụ, tập sự nghề nghiệp tại hơn 60 doanh nghiệp lữ hành, khách sạn, điểm du lịch trên địa bàn TP. Hồ Chí Minh", "100% sinh viên ra trường có việc làm trong vòng 12 tháng kể từ khi tốt nghiệp"], "programs": [{"tab": "Tiêu chuẩn", "major_code": "7810101", "description": "Sinh viên được trang bị những kiến thức cơ bản về văn hóa, kinh tế - xã hội; kiến thức về quản lý, hoạch định kế hoạch và thực hiện các dịch vụ du lịch; thành thạo kỹ năng chuyên môn về quản lý, điều hành, tổ chức, giám sát và giải quyết các vấn đề liên quan đến việc cung cấp dịch vụ du lịch. Bên cạnh đó, sinh viên được học thực tế nghề nghiệp, tập sự tại doanh nghiệp du lịch. Chương trình được tổ chức giảng dạy với nhiều hình thức đa dạng như thảo luận nhóm nhỏ, làm việc cá nhân, trao đổi với chuyên gia, thực hành tại doanh nghiệp với phương pháp giảng dạy tích cực và phương tiện hỗ trợ hiện đại, giúp sinh viên nâng cao kỹ năng chuyên môn, rèn luyện tư duy nhạy bén và tự tin với môi trường kinh doanh cũng như trong môi trường đa văn hóa.\nSinh viên tốt nghiệp có khả năng phân tích vấn đề, giá trị, xu hướng của du lịch trong thời kỳ mới và bối cảnh kinh tế toàn cầu; phân tích, đánh giá và vận dụng kiến thức chuyên ngành của khoa học quản lý vào kinh doanh du lịch, đặc biệt trong lĩnh vực kinh doanh điểm đến du lịch và công nghệ giải trí du lịch; khai thác sản phẩm du lịch, tổ chức quản lý trong hoạt động du lịch.\nCử nhân\nToàn thời gian: 4 năm\nXem thông tin chi tiết về chương trình đào tạo\nXem thông tin chi tiết về chuẩn đầu ra\nKết quả quá trình học tập THPT\nKết quả bài thi ĐGNL năm 2025 của ĐHQG TP. HCM\nTổ hợp: Đang cập nhật\nTháng 9, năm 2025\nĐang cập nhật", "content": {"Bằng cấp": "Cử nhân", "Thời gian đào tạo": "Toàn thời gian: 4 năm", "Chương trình đào tạo": "Xem thông tin chi tiết về chương trình đào tạo", "Chuẩn đầu ra": "Xem thông tin chi tiết về chuẩn đầu ra", "Phương thức xét tuyển riêng": "Kết quả quá trình học tập THPT Kết quả bài thi ĐGNL năm 2025 của ĐHQG TP. HCM", "Xét tuyển theo điểm thi THPT": "Tổ hợp: Đang cập nhật", "Khai giảng": "Tháng 9, năm 2025", "Học phí": "Đang cập nhật"}, "name": "Du lịch (Chuyên ngành Quản lý du lịch)"}], "images": ["https://admission.tdtu.edu.vn/sites/admission23/files/Tuyen-sinh/Dai-hoc/Nganh/Quan-ly-du-lich/1.jpg", "https://admission.tdtu.edu.vn/sites/admission23/files/Tuyen-sinh/Dai-hoc/Nganh/Quan-ly-du-lich/2.JPG", "https://admission.tdtu.edu.vn/sites/admission23/files/Tuyen-sinh/Dai-hoc/Nganh/Quan-ly-du-lich/3.JPG"]}
{"name": "Dược", "description": "Ngành Dược làngành học trong khối ngành sức khỏe vớisứ mạng sản xuất thuốc và nguyên liệu làm thuốc, kiểm soát chất lượng thuốc trên thị trường cũng như đảm bảo việc sử dụng thuốc hợp lý, an toàn, hiệu quả trong cộng đồng.\nSinh viên khoa Dược TDTUtrong quá trình họcđược cung cấp đầy đủ kiến thức, kỹ năng cần thiết về lý thuyết và thực hành, đặc biệt là chương trình tập sự nghề nghiệp 3 tháng để có thể tự tin làm việc tại tất cả cơ sở hành nghề Dược tại Việt Nam từ sản xuất, đảm bảo chất lượng thuốc, dược bệnh viện, nhà thuốc…\n\nTrong quá trình học, sinh viên được tiếp cận với môi trường quốc tế thông qua các hội thảo quốc tế, seminar học thuật, chương trình trao đổi học thuật. Ngoài ra, sinh viên cũng được tham gia vào các hoạt động nghiên cứu khoa học dưới sự hướng dẫn của các giảng viên giàu kinh nghiệm. Nhiều sinh viên đã đạt giải cao tại các cuộc thi Nghiên cứu khoa học sinh viên như Eureka, công bố các bài báo quốc tế cũng như tiếp tục con đường học thuật tại các trường đại học uy tín trên thế giới", "reasons": ["Đội ngũ giảng viên giàu kinh nghiệm", "Liên tục cập nhật xu hướng", "100% sinh viên ra trường có việc làm trong vòng 12 tháng kể từ khi tốt nghiệp"], "programs": [{"tab": "Tiêu chuẩn", "major_code": "7720201", "description": "Với chương trình học được xây dựng theo hướng kết nối với doanh nghiệp, sinh viên được tạo điều kiện để tham gia học hỏi và kiến tập tại các cơ sở hành nghề Dược uy tín như chuỗi nhà thuốc Long Châu, An Khang, công ty Bepharco, Tipharco, Trung tâm bảo tồn Dược liệu Mephydica, Bệnh viện Pháp Việt, Vinmec, …giúp sinh viên làm quen với môi trường nghề nghiệp thực tế, rèn luyện tác phong, kỷ luật làm việc cũng như tích lũy kinh nghiệm chuyên môn.\nDược sĩ\nToàn thời gian: 5 năm\nXem thông tin chi tiết về chương trình đào tạo\nXem thông tin chi tiết về chuẩn đầu ra\nKết quả quá trình học tập THPT\nKết quả bài thi ĐGNL năm 2025 của ĐHQG TP. HCM\nTổ hợp: Đang cập nhật\nĐiểm trúng tuyển 2024 (thang 40):31,45\nTháng 9, năm 2025\nKhoảng 60 đến 61 triệu đồng/năm (năm 2024)", "content": {"Bằng cấp": "Dược sĩ", "Thời gian đào tạo": "Toàn thời gian: 5 năm", "Chương trình đào tạo": "Xem thông tin chi tiết về chương trình đào tạo", "Chuẩn đầu ra": "Xem thông tin chi tiết về chuẩn đầu ra", "Phương thức xét tuyển riêng": "Kết quả quá trình học tập THPT Kết quả bài thi ĐGNL năm 2025 của ĐHQG TP. HCM", "Xét tuyển theo điểm thi THPT": "Tổ hợp: Đang cập nhật Điểm trúng tuyển 2024 (thang 40):31,45", "Khai giảng": "Tháng 9, năm 2025", "Học phí": "Khoảng 60 đến 61 triệu đồng/năm (năm 2024)"}, "name": "Dược"}], "images": ["https://admission.tdtu.edu.vn/sites/admission23/files/Tuyen-sinh/Dai-hoc/Nganh/Duoc/1.jpg", "https://admission.tdtu.edu.vn/sites/admission23/files/Tuyen-sinh/Dai-hoc/Nganh/Duoc/2.jpg", "https://admission.tdtu.edu.vn/sites/admission23/files/Tuyen-sinh/Dai-hoc/Nganh/Duoc/3.jpg", "https://admission.tdtu.edu.vn"]}
{"name": "Kế toán", "description": "Kế toán không chỉ là công cụ quản lý kinh tế – tài chính thuần túy, mà đã trở thành một lĩnh vực dịch vụ, một nghề nghiệp then chốt trong nền kinh tế thị trường. Đây là ngành quan trọng trong việc chuyển tải những thông tin kinh doanh đến các bên liên quan để làm nền tảng cho những quyết định chiến lược về những vấn đề tài chính doanh nghiệp và cá nhân, tuân thủ các quy định luật pháp, đáp ứng nhu cầu phát triển kinh tế của doanh nghiệp toàn cầu.", "reasons": ["Đội ngũ giảng viên tâm huyết với nghề", "Môi trường học tập hiện đại, chương trình đào tạo tích hợp chứng chỉ nghề nghiệp quốc tế", "Mạng lưới đối tác mạnh mẽ"], "programs": [{"tab": "Tiêu chuẩn", "major_code": "7340301", "description": "Chương trình đào tạo ngành Kế toán sẽ trang bị cho sinh viên các khối kiến thức chung (ngoại ngữ, tin học, toán học, kiến thức xã hội), kiến thức cơ bản đến chuyên ngành về kế toán tài chính và quản trị, quản lý tài chính, thuế, kiểm toán, và luật thương mại, …\nBên cạnh đó, sinh viên còn được mở rộng kiến thức của mình trong nhiều lĩnh vực kinh doanh khác như marketing, kinh tế và tài chính, quản lý và khởi nghiệp, … Chương trình còn cung cấp thêm cho sinh viên một số phần mềm chuyên dụng được cập nhật liên tục theo xu hướng hiện đại của thế giới để làm công cụ hỗ trợ cho sự nghiệp trong tương lai.\nThông qua chương trình đào tạo được xây dựng theo chuẩn quốc tế và bám sát với nhu cầu thực tiễn của xã hội, Nhà trường luôn chú trọng hợp tác và mở rộng mạng lưới doanh nghiệp nhằm tạo điều kiện cho sinh viên có cơ hội học hỏi và tiếp xúc sớm với môi trường công việc thực tế ngay từ những năm đầu Đại học để phát triển khả năng tư duy, phân tích và đánh giá kinh tế thị trường.\nNhà trường còn thường xuyên tổ chức các buổi hội thảo, sinh hoạt học thuật hoặc các cuộc thi chuyên ngành về lĩnh vực kế toán - kiểm toán, tạo môi trường cho sinh viên được giao lưu và trải nghiệm nghề nghiệp trong cùng lĩnh vực. Sinh viên còn có cơ hội học tập thêm các chứng chỉ quốc tế về kế toán, kiểm toán để mở rộng cơ hội nghề nghiệp tại các doanh nghiệp nước ngoài và các tập đoàn đa quốc gia.\nCử nhân\nToàn thời gian: 4 năm\nXem thông tin chi tiết về chương trình đào tạo\nXem thông tin chi tiết về chuẩn đầu ra\nKết quả quá trình học tập THPT\nKết quả bài thi ĐGNL năm 2025 của ĐHQG TP. HCM\nTổ hợp: Đang cập nhật\nĐiểm trúng tuyển 2024 (thang 40):32.40\nTháng 9, năm 2025\nKhoảng 27 đến 28 triệu đồng/năm (năm 2024)", "content": {"Bằng cấp": "Cử nhân", "Thời gian đào tạo": "Toàn thời gian: 4 năm", "Chương trình đào tạo": "Xem thông tin chi tiết về chương trình đào tạo", "Chuẩn đầu ra": "Xem thông tin chi tiết về chuẩn đầu ra", "Phương thức xét tuyển riêng": "Kết quả quá trình học tập THPT Kết quả bài thi ĐGNL năm 2025 của ĐHQG TP. HCM", "Xét tuyển theo điểm thi THPT": "Tổ hợp: Đang cập nhật Điểm trúng tuyển 2024 (thang 40):32.40", "Khai giảng": "Tháng 9, năm 2025", "Học phí": "Khoảng 27 đến 28 triệu đồng/năm (năm 2024)"}, "name": "Kế toán"}, {"tab": "Tiên tiến", "major_code": "F7340301", "description": "Sinh viên được trang bị thêm các kỹ năng nghề nghiệp cần thiết cho tương lai cùng các cơ hội thực tập sớm, cơ hội giao lưu nghề nghiệp trong nước và quốc tế ngay trong quá trình học.\nTấm bằng cử nhân Kế toán - Chương trình tiên tiến tại TDTU sẽ là thẻ thông hành để bạn làm việc bất cứ nơi nào trên thế giới. Các vị trí nghề nghiệp về tài chính, kế toán, kiểm toán, tư vấn tài chính, tư vấn thuế, quản trị rủi ro, kiểm soát nội bộ… tại bất kỳ ngành nghề và lĩnh vực nào từ các cơ quan nhà nước, doanh nghiệp trong nước và quốc tế, công ty đa quốc gia, tổ chức tài chính (ngân hàng, chứng khoán, bảo hiểm, quỹ tài chính), tổ chức phi chính phủ cũng như quản lý doanh nghiệp gia đình.\nCử nhân\nToàn thời gian: 4 năm\nXem thông tin chi tiết về chương trình đào tạo\nXem thông tin chi tiết về chuẩn đầu ra\nKết quả quá trình học tập THPT\nKết quả bài thi ĐGNL năm 2025 của ĐHQG TP. HCM\nTổ hợp: Đang cập nhật\nĐiểm trúng tuyển 2024 (thang 40):27,00\nTháng 9, năm 2025\nKhoảng 50 đến 52 triệu đồng/năm (năm 2024)", "content": {"Bằng cấp": "Cử nhân", "Thời gian đào tạo": "Toàn thời gian: 4 năm", "Chương trình đào tạo": "Xem thông tin chi tiết về chương trình đào tạo", "Chuẩn đầu ra": "Xem thông tin chi tiết về chuẩn đầu ra", "Phương thức xét tuyển riêng": "Kết quả quá trình học tập THPT Kết quả bài thi ĐGNL năm 2025 của ĐHQG TP. HCM", "Xét tuyển theo điểm thi THPT": "Tổ hợp: Đang cập nhật Điểm trúng tuyển 2024 (thang 40):27,00", "Khai giảng": "Tháng 9, năm 2025", "Học phí": "Khoảng 50 đến 52 triệu đồng/năm (năm 2024)"}, "name": "Kế toán"}, {"tab": "Đại học bằng tiếng Anh", "major_code": "FA7340301", "description": "Kế toán - Chương trình đại học bằng tiếng Anh trang bị cho sinh viên các kiến thức và kỹ năng chuyên môn kế toán theo chuẩn mực và thông lệ quốc tế. Chương trình được thiết kế và giảng dạy hoàn toàn bằng tiếng Anh. Sinh viên được trang bị kiến thức và tiếp cận các mô hình thực hành theo chuẩn quốc tế. Một môi trường giáo dục chuyên nghiệp và hiện đại để sinh viên học hỏi và trau dồi tất cả các kĩ năng cần thiết làm nền tảng cho việc hội nhập vào lĩnh vực kế toán - kiểm toán quốc tế tại Việt Nam cũng như các nước trên thế giới.\nCử nhân\nToàn thời gian: 4 năm\nXem thông tin chi tiết về chương trình đào tạo\nXem thông tin chi tiết về chuẩn đầu ra\nKết quả quá trình học tập THPT\nKết quả bài thi ĐGNL năm 2025 của ĐHQG TP. HCM\nTổ hợp: Đang cập nhật\nĐiểm trúng tuyển 2024 (thang 40):24,00\nTháng 9, năm 2025\nKhoảng 76 đến 80 triệu đồng/năm (năm 2024)", "content": {"Bằng cấp": "Cử nhân", "Thời gian đào tạo": "Toàn thời gian: 4 năm", "Chương trình đào tạo": "Xem thông tin chi tiết về chương trình đào tạo", "Chuẩn đầu ra": "Xem thông tin chi tiết về chuẩn đầu ra", "Phương thức xét tuyển riêng": "Kết quả quá trình học tập THPT Kết quả bài thi ĐGNL năm 2025 của ĐHQG TP. HCM", "Xét tuyển theo điểm thi THPT": "Tổ hợp: Đang cập nhật Điểm trúng tuyển 2024 (thang 40):24,00", "Khai giảng": "Tháng 9, năm 2025", "Học phí": "Khoảng 76 đến 80 triệu đồng/năm (năm 2024)"}, "name": "Kế toán"}, {"tab": "Liên kết quốc tế", "major_code": "K7340301", "description": "Cử nhân (song bằng)\n4 năm (3 năm đầu học tại TDTU, 1 năm sau học tại Trường liên kết)\nXem thông tin chi tiết về chương trình đào tạo\nXem thông tin chi tiết về chuẩn đầu ra\nKết quả quá trình học tập THPT\nKết quả bài thi ĐGNL năm 2025 của ĐHQG TP. HCM\nTổ hợp: Đang cập nhật\nĐiểm trúng tuyển 2024 (thang 40):24,00\nTháng 9, năm 2025\nGiai đoạn 1: khoảng 77 đến 78 triệu đồng/năm (năm 2024)", "content": {"Bằng cấp": "Cử nhân (song bằng)", "Thời gian đào tạo": "4 năm (3 năm đầu học tại TDTU, 1 năm sau học tại Trường liên kết)", "Chương trình đào tạo": "Xem thông tin chi tiết về chương trình đào tạo", "Chuẩn đầu ra": "Xem thông tin chi tiết về chuẩn đầu ra", "Phương thức xét tuyển riêng": "Kết quả quá trình học tập THPT Kết quả bài thi ĐGNL năm 2025 của ĐHQG TP. HCM", "Xét tuyển theo điểm thi THPT": "Tổ hợp: Đang cập nhật Điểm trúng tuyển 2024 (thang 40):24,00", "Khai giảng": "Tháng 9, năm 2025", "Học phí": "Giai đoạn 1: khoảng 77 đến 78 triệu đồng/năm (năm 2024)"}, "name": "Kế toán liên kết Đại học West of England, Bristol"}], "images": ["https://admission.tdtu.edu.vn", "https://admission.tdtu.edu.vn/sites/admission23/files/Tuyen-sinh/Dai-hoc/Nganh/KT/1.jpg", "https://admission.tdtu.edu.vn/sites/admission23/files/Tuyen-sinh/Dai-hoc/Nganh/KT/2.jpg", "https://admission.tdtu.edu.vn/sites/admission23/files/Tuyen-sinh/Dai-hoc/Nganh/KT/3.jpg"]}
{"name": "Khoa học máy tính", "description": "Khoa học máy tính là ngành ứng dụng kiến thức về thuật toán, phương pháp tính toán, ngôn ngữ lập trình, phương pháp phân tích và xây dựng hệ thống thông tin, … để giải quyết các vấn đề thuộc lĩnh vực Khoa học máy tính; phát triển các hệ thống phần mềm máy tính, mô hình tính toán thông minh, các ứng dụng trên các nền tảng hiện đại để phục vụ cho nhiệm vụ công nghiệp hoá, hiện đại hoá đất nước trong lĩnh vực chuyển đổi số.\n\nSau khi tốt nghiệp, cử nhân Khoa học máy tính có thể tự tin đảm nhận tốt các vị trí như chuyên viên thiết kế và xây dựng các phần mềm máy tính, ứng dụng cho thiết bị di động, ứng dụng thương mại điện tử trên nền Web, các trò chơi trên máy tính và di động; chuyên viên quản trị và xây dựng các giải pháp đảm bảo an toàn cho các hệ thống máy tính và hệ thống mạng máy tính; chuyên viên lập trình; chuyên viên phát triển hệ thống thông minh; chuyên viên tư vấn, thẩm định và phát triển các dự án, giải pháp công nghệ thông tin; cán bộ chuyên trách tại các cơ quan nhà nước, … hoặc có thể tiếp tục học tập và nghiên cứu ở các bậc học cao hơn.", "reasons": ["Liên tục cập nhật xu hướng", "Số tiết học thực tế chiếm gần 50% chương trình đào tạo", "100% sinh viên ra trường có việc làm trong vòng 12 tháng kể từ khi tốt nghiệp"], "programs": [{"tab": "Tiêu chuẩn", "major_code": "7480101", "description": "Chương trình cung cấp nền tảng vững chắc về Khoa học máy tính, tập trung vào các lĩnh vực hiện đại như: trí tuệ nhân tạo (AI), khai phá dữ liệu, khoa học dữ liệu, phát triển ứng dụng thông minh, ...\nKết hợp lý thuyết và thực hành, sinh viên áp dụng kiến thức qua các dự án thực tế liên quan đến AI, phân tích dữ liệu lớn, và xây dựng hệ thống thông minh.\nNgười học có hội tham quan và thực tập ở các doanh nghiệp từ năm thứ hai và học hỏi từ các chuyên gia đầu ngành trong lĩnh vực công nghệ tiên tiến.\nSau khi tốt nghiệp, sinh viên có kỹ năng phân tích dữ liệu, xây dựng mô hình AI, phát triển hệ thống hỗ trợ quyết định, và triển khai giải pháp công nghệ tiên tiến.\nCử nhân\nToàn thời gian: 4 năm\nXem thông tin chi tiết về chương trình đào tạo\nXem thông tin chi tiết về chuẩn đầu ra\nKết quả quá trình học tập THPT\nKết quả bài thi ĐGNL năm 2025 của ĐHQG TP. HCM\nTổ hợp: Đang cập nhật\nĐiểm trúng tuyển 2024 (thang 40):33,00\nTháng 9, năm 2025\nKhoảng 31 đếnn 32 triệu đồng/năm (năm 2024)", "content": {"Bằng cấp": "Cử nhân", "Thời gian đào tạo": "Toàn thời gian: 4 năm", "Chương trình đào tạo": "Xem thông tin chi tiết về chương trình đào tạo", "Chuẩn đầu ra": "Xem thông tin chi tiết về chuẩn đầu ra", "Phương thức xét tuyển riêng": "Kết quả quá trình học tập THPT Kết quả bài thi ĐGNL năm 2025 của ĐHQG TP. HCM", "Xét tuyển theo điểm thi THPT": "Tổ hợp: Đang cập nhật Điểm trúng tuyển 2024 (thang 40):33,00", "Khai giảng": "Tháng 9, năm 2025", "Học phí": "Khoảng 31 đếnn 32 triệu đồng/năm (năm 2024)"}, "name": "Khoa học máy tính"}, {"tab": "Tiên tiến", "major_code": "F7480101", "description": "Chương trình Tiên tiến chú trọng tính chuyên nghiệp và khả năng ứng dụng vào thực tiễn trong các lĩnh vực AI và khoa học dữ liệu. Chương trình được thiết kế mở rộng, nhằm đáp ứng nhu cầu ngày càng cao của xã hội, đồng thời kết hợp chặt chẽ giữa lý thuyết và ứng dụng. Không chỉ cung cấp kiến thức chuyên môn sâu rộng, chương trình còn rèn luyện kỹ năng thực hành, phát triển kỹ năng mềm, và tạo cơ hội thực tập thực tế tại các doanh nghiệp. Sinh viên sẽ được trang bị kiến thức toàn diện về công nghệ hiện đại trong trí tuệ nhân tạo và khoa học dữ liệu.\nĐặc điểm nổi bật:\n- Đội ngũ giảng viên: Giỏi chuyên môn, giàu kinh nghiệm trong lĩnh AI và phân tích dữ liệu.\n- Giảng dạy bằng tiếng Anh: 50% các môn học chuyên ngành.\n- Có cơ hội trao đổi hoặc thực tập tại các trường ở Mỹ, Hàn Quốc, Đài Loan, Cộng hòa Séc, …\nCử nhân\nToàn thời gian: 4 năm\nXem thông tin chi tiết về chương trình đào tạo\nXem thông tin chi tiết về chuẩn đầu ra\nKết quả quá trình học tập THPT\nKết quả bài thi ĐGNL năm 2025 của ĐHQG TP. HCM\nTổ hợp: Đang cập nhật\nĐiểm trúng tuyển 2024 (thang 40):30,80\nTháng 9, năm 2025\nKhoảng 53 đến 54 triệu đồng/năm (năm 2024)", "content": {"Bằng cấp": "Cử nhân", "Thời gian đào tạo": "Toàn thời gian: 4 năm", "Chương trình đào tạo": "Xem thông tin chi tiết về chương trình đào tạo", "Chuẩn đầu ra": "Xem thông tin chi tiết về chuẩn đầu ra", "Phương thức xét tuyển riêng": "Kết quả quá trình học tập THPT Kết quả bài thi ĐGNL năm 2025 của ĐHQG TP. HCM", "Xét tuyển theo điểm thi THPT": "Tổ hợp: Đang cập nhật Điểm trúng tuyển 2024 (thang 40):30,80", "Khai giảng": "Tháng 9, năm 2025", "Học phí": "Khoảng 53 đến 54 triệu đồng/năm (năm 2024)"}, "name": "Khoa học máy tính"}, {"tab": "Đại học bằng tiếng Anh", "major_code": "FA7480101", "description": "Chương trình được mở rộng toàn diện nhất, quốc tế hóa với các đặc điểm:\n- 100% bằng tiếng Anh:Từ các môn cơ sở đến chuyên ngành, tập trung vào trí tuệ nhân tạo, học máy, và khai phá dữ liệu, rèn luyện ngoại ngữ và tư duy toàn cầu.\n- Hợp tác quốc tế:Kết nối với doanh nghiệp và cơ hội học tập tại nước ngoài.\n- Cơ sở vật chất:Môi trường học tập hiện đại, lớp học nhỏ có quy mô 20-25 sinh viên, tăng cường tương tác.\nCử nhân\nToàn thời gian: 4 năm\nXem thông tin chi tiết về chương trình đào tạo\nXem thông tin chi tiết về chuẩn đầu ra\nKết quả quá trình học tập THPT\nKết quả bài thi ĐGNL năm 2025 của ĐHQG TP. HCM\nTổ hợp: Đang cập nhật\nĐiểm trúng tuyển 2024 (thang 40):28,00\nTháng 9, năm 2025\nKhoảng 81 đến 83 triệu đồng/năm (năm 2024)", "content": {"Bằng cấp": "Cử nhân", "Thời gian đào tạo": "Toàn thời gian: 4 năm", "Chương trình đào tạo": "Xem thông tin chi tiết về chương trình đào tạo", "Chuẩn đầu ra": "Xem thông tin chi tiết về chuẩn đầu ra", "Phương thức xét tuyển riêng": "Kết quả quá trình học tập THPT Kết quả bài thi ĐGNL năm 2025 của ĐHQG TP. HCM", "Xét tuyển theo điểm thi THPT": "Tổ hợp: Đang cập nhật Điểm trúng tuyển 2024 (thang 40):28,00", "Khai giảng": "Tháng 9, năm 2025", "Học phí": "Khoảng 81 đến 83 triệu đồng/năm (năm 2024)"}, "name": "Khoa học máy tính"}, {"tab": "Liên kết quốc tế - K7480101T", "major_code": "K7480101T", "description": "Cử nhân (đơn bằng)\n4 năm (2 năm đầu học tại TDTU, 2 năm sau học tại Trường liên kết)\nXem thông tin chi tiết về chương trình đào tạo\nXem thông tin chi tiết về chuẩn đầu ra\nKết quả quá trình học tập THPT\nKết quả bài thi ĐGNL năm 2025 của ĐHQG TP. HCM\nTổ hợp: Đang cập nhật\nĐiểm trúng tuyển 2024 (thang 40):28,00\nTháng 9, năm 2025\nGiai đoạn 1: khoảng 76 đến 77 triệu đồng/năm (năm 2024)", "content": {"Bằng cấp": "Cử nhân (đơn bằng)", "Thời gian đào tạo": "4 năm (2 năm đầu học tại TDTU, 2 năm sau học tại Trường liên kết)", "Chương trình đào tạo": "Xem thông tin chi tiết về chương trình đào tạo", "Chuẩn đầu ra": "Xem thông tin chi tiết về chuẩn đầu ra", "Phương thức xét tuyển riêng": "Kết quả quá trình học tập THPT Kết quả bài thi ĐGNL năm 2025 của ĐHQG TP. HCM", "Xét tuyển theo điểm thi THPT": "Tổ hợp: Đang cập nhật Điểm trúng tuyển 2024 (thang 40):28,00", "Khai giảng": "Tháng 9, năm 2025", "Học phí": "Giai đoạn 1: khoảng 76 đến 77 triệu đồng/năm (năm 2024)"}, "name": "Khoa học máy tính liên kết Đại học Kỹ thuật Ostrava, Cộng hòa Séc"}, {"tab": "Liên kết quốc tế - K7480101L", "major_code": "K7480101L", "description": "Cử nhân (song bằng)\n4 năm (2 năm đầu học tại TDTU, 2 năm sau học tại Trường liên kết)\nXem thông tin chi tiết về chương trình đào tạo\nXem thông tin chi tiết về chuẩn đầu ra\nKết quả quá trình học tập THPT\nKết quả bài thi ĐGNL năm 2025 của ĐHQG TP. HCM\nTổ hợp: Đang cập nhật\nĐiểm trúng tuyển 2024 (thang 40):28,00\nTháng 9, năm 2025\nGiai đoạn 1: khoảng 76 đến 77 triệu đồng/năm (năm 2024)", "content": {"Bằng cấp": "Cử nhân (song bằng)", "Thời gian đào tạo": "4 năm (2 năm đầu học tại TDTU, 2 năm sau học tại Trường liên kết)", "Chương trình đào tạo": "Xem thông tin chi tiết về chương trình đào tạo", "Chuẩn đầu ra": "Xem thông tin chi tiết về chuẩn đầu ra", "Phương thức xét tuyển riêng": "Kết quả quá trình học tập THPT Kết quả bài thi ĐGNL năm 2025 của ĐHQG TP. HCM", "Xét tuyển theo điểm thi THPT": "Tổ hợp: Đang cập nhật Điểm trúng tuyển 2024 (thang 40):28,00", "Khai giảng": "Tháng 9, năm 2025", "Học phí": "Giai đoạn 1: khoảng 76 đến 77 triệu đồng/năm (năm 2024)"}, "name": "Công nghệ thông tin liên kết Đại học La Trobe, Úc"}], "images": ["https://admission.tdtu.edu.vn/sites/admission23/files/Tuyen-sinh/Dai-hoc/Nganh/KHMTinh/3.JPG", "https://admission.tdtu.edu.vn/sites/admission23/files/Tuyen-sinh/Dai-hoc/Nganh/KHMTinh/1.jpg", "https://admission.tdtu.edu.vn/sites/admission23/files/Tuyen-sinh/Dai-hoc/Nganh/KHMTinh/2.jpg"]}
{"name": "Khoa học môi trường", "description": "Nền kinh tế của Việt Nam ngày càng phát triển, song tình trạng ô nhiễm môi trường cũng ngày càng nghiêm trọng. Việc quốc tế hóa nền kinh tế đang yêu cầu các doanh nghiệp của Việt Nam phải đáp ứng được các tiêu chuẩn và môi trường cả trong nước và quốc tế; mục tiêu phát triển bền vững của các doanh nghiệp đang đòi hỏi nguồn nhân sự rất cao ở vị trí tư vấn, hoạch định và thực hiện các dự án về phát biển bền vững, đáp ứng yêu cầu phát triển kinh tế đi đôi với bảo vệ môi trường. Chính vì vậy, ngành Khoa học môi trường được coi là ngành học có vai trò đặc biệt quan trọng trong đời sống xã hội, là yếu tố tiên quyết cho sự phát triển bền vững của nền kinh tế quốc gia.\nSinh viên ngành Khoa học môi trường được đào tạo các kiến thức  về quản lý môi trường đô thị và khu công nghiệp, đánh giá tác động môi trường, theo dõi đánh giá diễn biến chất lượng môi trường, quản lý tài nguyên thiên nhiên, quản lý năng lượng; kỹ thuật kiểm soát và xử lý ô nhiễm môi trường nước, không khí; xử lý chất thải rắn và chất thải nguy hại.\nKỹ sư ngành Khoa học môi trường có đầy đủ năng lực để tự tin ứng tuyển vào nghiên cứu và làm việc ở các vị trí như chuyên viên thiết kế, vận hành và giám sát công trình xử lý khí thải, nước thải, nước cấp, chất thải rắn và chất thải nguy hại; chuyên gia tư vấn, đánh giá tác động, quản lý môi trường đô thị và khu dân cư, quản lý dự án môi trường - tài nguyên.", "reasons": ["Đội ngũ giảng viên giàu kinh nghiệm", "Liên tục cập nhật xu hướng", "Số tiết học thực tế chiếm hơn 40% chương trình đào tạo"], "programs": [{"tab": "Tiêu chuẩn", "major_code": "7440301", "description": "Sinh viên được đào tạo kiến thức tích hợp cả 2 lĩnh vực bao gồm quản lý và kỹ thuật môi trường. Ngoài các kiến thức cơ bản về khoa học tự nhiên, sinh viên được trang bị các kiến thức và kỹ năng chuyên ngành về kỹ thuật kiểm soát và xử lý ô nhiễm môi trường nước, không khí; thiết kế phát triển công nghệ nhằm giảm thiểu những tác động có hại của phát triển kinh tế - xã hội ảnh hưởng đến môi trường và tài nguyên thiên nhiên; theo dõi đánh giá diễn biến chất lượng môi trường; bảo tồn tài nguyên thiên nhiên; quản lý năng lượng, xử lý chất thải rắn và chất thải nguy hại, …\nĐiểm nổi bật của chương trình học là được đào tạo theo hướng ứng dụng với hơn 40% thời lượng sinh viên được học tại doanh nghiệp hoặc các phòng thí nghiệm, phòng máy tính được trang bị đầy đủ trang thiết bị và máy móc hiện đại. Trong quá trình học, sinh viên được tham gia các học phần, dự án nghiên cứu cùng chuyên gia, giảng viên trong và ngoài nước, qua đó giúp sinh viên củng cố kiến thức đã học, nâng cao năng lực tư duy và rèn luyện kỹ năng làm việc độc lập, đáp ứng tối đa nhu cầu tuyển dụng nguồn nhân lực chất lượng cao cho xã hội.\nSinh viên có từ 5 - 6 tháng tham gia kiến tập tại các công ty Việt Nam và tập đoàn đa quốc gia để làm quen với môi trường và văn hoá làm việc, tích lũy kinh nghiệm thực tế và nâng cao năng lực chuyên môn.\nSinh viên ngành Khoa học môi trường sau khi tốt nghiệp có đầy đủ kiến thức và kỹ năng để tự lập kế hoạch, nghiên cứu và giải quyết các vấn đề liên quan đến môi trường; kiểm soát ô nhiễm môi trường, quản trị tài nguyên, phục hồi sinh thái; đánh giá, phân tích, thiết kế, tư vấn kỹ thuật, quản lý và vận hành các công trình xử lý chất thải hoặc hệ thống kiểm soát ô nhiễm môi trường đô thị và khu công nghiệp; tổ chức, thực thi các chương trình xử lý, khắc phục, phòng tránh sự cố môi trường.\nCử nhân\nKỹ sư\nToàn thời gian: 4 năm\nToàn thời gian: 5 năm\nXem thông tin chi tiết về chương trình đào tạo\nXem thông tin chi tiết về chuẩn đầu ra\nKết quả quá trình học tập THPT\nKết quả bài thi ĐGNL năm 2025 của ĐHQG TP. HCM\nTổ hợp: Đang cập nhật\nĐiểm trúng tuyển 2024 (thang 40):22,00\nTháng 9, năm 2025\nKhoảng 31 đến 32 triệu đồng/năm (năm 2024)", "content": {"Bằng cấp": "Cử nhân Kỹ sư", "Thời gian đào tạo": "Toàn thời gian: 4 năm Toàn thời gian: 5 năm", "Chương trình đào tạo": "Xem thông tin chi tiết về chương trình đào tạo", "Chuẩn đầu ra": "Xem thông tin chi tiết về chuẩn đầu ra", "Phương thức xét tuyển riêng": "Kết quả quá trình học tập THPT Kết quả bài thi ĐGNL năm 2025 của ĐHQG TP. HCM", "Xét tuyển theo điểm thi THPT": "Tổ hợp: Đang cập nhật Điểm trúng tuyển 2024 (thang 40):22,00", "Khai giảng": "Tháng 9, năm 2025", "Học phí": "Khoảng 31 đến 32 triệu đồng/năm (năm 2024)"}, "name": "Khoa học môi trường"}], "images": ["https://admission.tdtu.edu.vn/sites/admission23/files/Tuyen-sinh/Dai-hoc/Nganh/KHMT/MT-13.jpg", "https://admission.tdtu.edu.vn/sites/admission23/files/Tuyen-sinh/Dai-hoc/Nganh/KHMT/MT-2.jpg", "https://admission.tdtu.edu.vn/sites/admission23/files/Tuyen-sinh/Dai-hoc/Nganh/KHMT/MT-3.jpg"]}
{"name": "Kiểm toán (Chuyên ngành Kiểm toán và Phân tích dữ liệu)", "description": "Kiểm toán không chỉ là công cụ quản lý kinh tế - tài chính thuần túy, mà đã trở thành một lĩnh vực dịch vụ, một nghề nghiệp then chốt trong nền kinh tế thị trường. Đây là ngành quan trọng trong việc chuyển tải những thông tin kinh doanh đến các bên liên quan để làm nền tảng cho những quyết định chiến lược về những vấn đề tài chính doanh nghiệp và cá nhân, tuân thủ các quy định luật pháp, đáp ứng nhu cầu phát triển kinh tế của doanh nghiệp toàn cầu.", "reasons": ["Đội ngũ giảng viên tâm huyết với nghề", "Môi trường học tập hiện đại, chương trình đào tạo tích hợp chứng chỉ nghề nghiệp quốc tế", "Mạng lưới đối tác mạnh mẽ"], "programs": [{"tab": "Tiêu chuẩn", "major_code": "7340302", "description": "Cử nhân ngành Kiểm toán (Chuyên ngành Kiểm toán và Phân tích dữ liệu), sau khi tốt nghiệp đủ khả năng và tự tin làm việc tại các cơ quan nhà nước, doanh nghiệp, các công ty kiểm toán độc lập trong nước và quốc tế, công ty dịch vụ Kiểm toán, Kế toán, đặc biệt là cơ hội làm việc tại các công ty đa quốc gia, các công ty kiểm toán quốc tế, kiểm toán độc lập, kiểm toán nội bộ, kiểm toán nhà nước, nhân viên kế toán, nhân viên tư vấn kế toán - tài chính, chuyên viên tư vấn kế toán - thuế, chuyên viên phân tích dữ liệu hoặc trở thành cán bộ nghiên cứu, giảng viên ngành Kiểm toán tại các Trường, Viện, các cơ sở đào tạo nguồn nhân lực kiểm toán.\nCử nhân\nToàn thời gian: 4 năm\nXem thông tin chi tiết về chương trình đào tạo\nXem thông tin chi tiết về chuẩn đầu ra\nKết quả quá trình học tập THPT\nKết quả bài thi ĐGNL năm 2025 của ĐHQG TP. HCM\nTổ hợp: Đang cập nhật\nTháng 9, năm 2025\nĐang cập nhật", "content": {"Bằng cấp": "Cử nhân", "Thời gian đào tạo": "Toàn thời gian: 4 năm", "Chương trình đào tạo": "Xem thông tin chi tiết về chương trình đào tạo", "Chuẩn đầu ra": "Xem thông tin chi tiết về chuẩn đầu ra", "Phương thức xét tuyển riêng": "Kết quả quá trình học tập THPT Kết quả bài thi ĐGNL năm 2025 của ĐHQG TP. HCM", "Xét tuyển theo điểm thi THPT": "Tổ hợp: Đang cập nhật", "Khai giảng": "Tháng 9, năm 2025", "Học phí": "Đang cập nhật"}, "name": "Kiểm toán (Chuyên ngành Kiểm toán và Phân tích dữ liệu)"}], "images": ["https://admission.tdtu.edu.vn/sites/admission23/files/Tuyen-sinh/Dai-hoc/Nganh/KT/1.jpg", "https://admission.tdtu.edu.vn/sites/admission23/files/Tuyen-sinh/Dai-hoc/Nganh/KT/2.jpg", "https://admission.tdtu.edu.vn/sites/admission23/files/Tuyen-sinh/Dai-hoc/Nganh/KT/3.jpg"]}
{"name": "Kiến trúc", "description": "Kiến trúc là ngành tích hợp kiến thức ở cả 2 lĩnh vực nghệ thuật và kỹ thuật, vận dụng tư duy logic và khả năng sáng tạo để thiết kế, tổ chức và sắp xếp không gian các công trình kiến trúc, cung cấp các giải pháp trong lĩnh vực xây dựng nhằm đáp ứng nhu cầu thực tế về nơi ở, sinh hoạt, vui chơi, làm việc,… của xã hội.\n\nKiến trúc sư tốt nghiệp tại Trường Đại học Tôn Đức Thắng hoàn toàn có thể tự tin ứng tuyển vào làm việc tại các công ty tư vấn thiết kế kiến trúc - xây dựng, viện nghiên cứu kiến trúc, ban quản lý các dự án, cơ quan quản lý kiến trúc và quy hoạch xây dựng đô thị hoặc tự thành lập doanh nghiệp để phát triển năng lực của bản thân. Ngoài ra, sinh viên sau khi tốt nghiệp còn có cơ hội trở thành giảng viên giảng dạy các môn học thuộc chuyên ngành Kiến trúc tại các trường đại học trên cả nước hoặc nước ngoài.", "reasons": ["Đội ngũ giảng viên giàu kinh nghiệm", "Liên tục cập nhật xu hướng", "Sáng tạo, thẩm mỹ và mang tính kỹ thuật cao"], "programs": [{"tab": "Tiêu chuẩn", "major_code": "7580101", "description": "Sinh viên được trang bị đầy đủ kiến thức cơ bản về nghệ thuật kiến trúc, kỹ thuật vẽ hình học, họa hình, bố cục tạo hình, lịch sử mỹ thuật đến các kiến thức chuyên ngành như nguyên lý thiết kế nhà ở, kỹ thuật thi công, công tác quy hoạch, thiết kế đô thị, phương pháp sáng tác kiến trúc, phương pháp vẽ 2D, 3D, các phần mềm đồ hoạ hiện đại và liên tục cập nhật như Revit, Autocad, Sketchup …\nKhông những cung cấp kiến thức nền tảng cho sinh viên, nội dung chương trình đào tạo còn tập trung phát triển các kỹ năng thực hành cho người học, giúp cho người học rèn luyện kỹ năng thiết kế kiến trúc, thiết kế nội thất và phát triển năng lực tư duy thẩm mỹ về không gian, nhận thức và tạo dựng cái đẹp nhằm đáp ứng nhu cầu thực tế của xã hội.\nSinh viên còn được tạo điều kiện để tham gia các buổi liên hoan nghệ thuật, chương trình triển lãm và các cuộc thi thiết kế lớn trong và ngoài nước để tích lũy kinh nghiệm thực tế, giao lưu văn hoá và nâng cao khả năng sáng tạo.\nThông qua mạng lưới đối tác doanh nghiệp thân hữu, sinh viên được hướng dẫn tham gia kiến tập tại các công ty trong và ngoài nước, qua đó giúp sinh viên sớm làm quen và tiếp cận với môi trường văn hoá doanh nghiệp, tạo cơ hội tìm kiếm cơ hội nghề nghiệp cho tương lai. Đặc biệt, đối với một số môn học chuyên ngành, Nhà trường sẽ kết hợp với các đối tác quốc tế, tổ chức các chương trình học tập trao đổi ngắn hạn nhằm tạo điều kiện cho sinh viên được tìm hiểu về lịch sử và các công trình kiến trúc của mỗi quốc gia và giao lưu văn hoá giữa các nền văn hóa trên thế giới.\nSinh viên sau khi tốt nghiệp được trang bị đầy đủ kiến thức và kỹ năng sử dụng thành thạo các phần mềm phục vụ thiết kế; phân tích, tổng hợp và ứng dụng khoa học công nghệ để thực hiện các đồ án thiết kế kiến trúc; vận dụng khả năng tư duy sáng tạo để phác thảo ý tưởng thiết kế ban đầu cho đến triển khai bản vẽ kỹ thuật thi công; hiểu biết căn bản về các giải pháp kết cấu công trình và sử dụng vật liệu xây dựng trong kiến trúc nội – ngoại thất công trình.\nCử nhân\nKiến trúc sư\nToàn thời gian: 4 năm\nToàn thời gian: 5 năm\nXem thông tin chi tiết về chương trình đào tạo\nXem thông tin chi tiết về chuẩn đầu ra\nKết quả quá trình học tập THPT\nKết quả bài thi ĐGNL năm 2025 của ĐHQG TP. HCM\nTổ hợp: Đang cập nhật\nĐiểm trúng tuyển 2024 (thang 40):29,80\nTháng 9, năm 2025\nKhoảng 31 đến 32 triệu đồng/năm (năm 2024)", "content": {"Bằng cấp": "Cử nhân Kiến trúc sư", "Thời gian đào tạo": "Toàn thời gian: 4 năm Toàn thời gian: 5 năm", "Chương trình đào tạo": "Xem thông tin chi tiết về chương trình đào tạo", "Chuẩn đầu ra": "Xem thông tin chi tiết về chuẩn đầu ra", "Phương thức xét tuyển riêng": "Kết quả quá trình học tập THPT Kết quả bài thi ĐGNL năm 2025 của ĐHQG TP. HCM", "Xét tuyển theo điểm thi THPT": "Tổ hợp: Đang cập nhật Điểm trúng tuyển 2024 (thang 40):29,80", "Khai giảng": "Tháng 9, năm 2025", "Học phí": "Khoảng 31 đến 32 triệu đồng/năm (năm 2024)"}, "name": "Kiến trúc"}, {"tab": "Tiên tiến", "major_code": "F7580101", "description": "Chương trình tiên tiến (giảng dạy và tài liệu học tập bằng tiếng anh đối với một số môn học chuyên ngành), sĩ số lớp học dưới 35 sinh viên. Do các giảng viên giàu kinh nghiệm trực tiếp giảng dạy. Ngoài kiến thức nền tảng và chuyên môn được thiết kế và cập nhật liên tục theo xu hướng của nền giáo dục chuẩn quốc tế, sinh viên theo học ngành Kiến trúc chương trình tiên tiến còn được trang bị thêm các kỹ năng nghề nghiệp trong cùng lĩnh vực nhằm đáp ứng yêu cầu của nền giáo dục khai phóng, đào tạo nguồn nhân lực chất lượng cao và vững tay nghề.\nBên cạnh đó, sinh viên còn được tham gia các học phần thực tế tại nước ngoài, tìm hiểu văn hóa và kiến trúc đặc trưng của các quốc gia có lịch sử lâu đời trên thế giới, qua đó nâng cao hiểu biết về văn hóa và kiến thức chuyên ngành, đồng thời giúp sinh viên phát triển tư duy thẩm mỹ và năng lực nghiên cứu, sáng tạo trong nghệ thuật.\nNgoài ra, sinh viên được hướng dẫn tham gia kiến tập tại các công ty trong và ngoài nước để làm quen và tiếp cận với môi trường văn hoá doanh nghiệp, tạo cơ hội tìm kiếm cơ hội nghề nghiệp cho tương lai. Nhà trường cũng đặc biệt hỗ trợ, giới thiệu việc làm cho sinh viên sau khi tốt nghiệp.\nCử nhân\nKiến trúc sư\nToàn thời gian: 4 năm\nToàn thời gian: 5 năm\nXem thông tin chi tiết về chương trình đào tạo\nXem thông tin chi tiết về chuẩn đầu ra\nKết quả quá trình học tập THPT\nKết quả bài thi ĐGNL năm 2025 của ĐHQG TP. HCM\nTổ hợp: Đang cập nhật\nĐiểm trúng tuyển 2024 (thang 40):28,50\nTháng 9, năm 2025\nKhoảng 53 đến 54 triệu đồng/năm (năm 2024)", "content": {"Bằng cấp": "Cử nhân Kiến trúc sư", "Thời gian đào tạo": "Toàn thời gian: 4 năm Toàn thời gian: 5 năm", "Chương trình đào tạo": "Xem thông tin chi tiết về chương trình đào tạo", "Chuẩn đầu ra": "Xem thông tin chi tiết về chuẩn đầu ra", "Phương thức xét tuyển riêng": "Kết quả quá trình học tập THPT Kết quả bài thi ĐGNL năm 2025 của ĐHQG TP. HCM", "Xét tuyển theo điểm thi THPT": "Tổ hợp: Đang cập nhật Điểm trúng tuyển 2024 (thang 40):28,50", "Khai giảng": "Tháng 9, năm 2025", "Học phí": "Khoảng 53 đến 54 triệu đồng/năm (năm 2024)"}, "name": "Kiến trúc"}], "images": ["https://admission.tdtu.edu.vn/sites/admission23/files/Tuyen-sinh/Dai-hoc/Nganh/Kien-truc/1.JPG", "https://admission.tdtu.edu.vn/sites/admission23/files/Tuyen-sinh/Dai-hoc/Nganh/Kien-truc/2.jpg", "https://admission.tdtu.edu.vn/sites/admission23/files/Tuyen-sinh/Dai-hoc/Nganh/Kien-truc/3.jpg"]}
{"name": "Kinh doanh quốc tế", "description": "Kinh doanh quốc tế đang là một ngành nhận được nhiều sự quan tâm hiện nay trong bối cảnh Việt Nam tham gia nhiều tổ chức thương mại - liên minh kinh tế thế giới và khu vực. Đây là một lĩnh vực thuộc nhóm ngành kinh doanh, ứng dụng kiến thức về thương mại quốc tế, logistics,tài chính và đầu tư, marketing toàn cầu … để thực hiện các giao dịch hàng hóa giữa thương nhân đến từ các quốc gia trên thế giới trong giai đoạn toàn cầu hoá.\n\nCử nhân kinh doanh quốc tế có đầy đủ năng lực để làm việc tại các tập đoàn đa quốc gia, các tổ chức nghiên cứu thị trường, hiệp hội ngành nghề, trung tâm xúc tiến thương mại,... ở những vị trí như chuyên viên xuất nhập khẩu, chuyên viên quản trị logistics, chuyên viên giao nhận vận tải, chuyên viên thanh toán quốc tế, chuyên viên quản trị tài chính, chuyên viên đầu tư quốc tế, chuyên viên marketing quốc tế và các vị trí chức năng quan trọng khác trong môi trường kinh doanh quốc tế.", "reasons": ["Chương trình đào tạo trình độ đại học được trao chứng nhận kiểm định theo tiêu chuẩn FIBAA", "Mức học phí hợp lý với chương trình đào tạo chuẩn quốc tế", "100% sinh viên ra trường có việc làm trong vòng 12 tháng kể từ khi tốt nghiệp"], "programs": [{"tab": "Tiêu chuẩn", "major_code": "7340120", "description": "Cử nhân kinh doanh quốc tế chương trình tiêu chuẩn có đầy đủ năng lực để làm việc tại các tập đoàn đa quốc gia, các tổ chức nghiên cứu thị trường, hiệp hội ngành nghề, trung tâm xúc tiến thương mại,... ở những vị trí như chuyên viên xuất nhập khẩu, chuyên viên quản trị logistics, chuyên viên giao nhận vận tải, chuyên viên thanh toán quốc tế, chuyên viên quản trị tài chính, chuyên viên đầu tư quốc tế, chuyên viên marketing quốc tế và các vị trí chức năng quan trọng khác trong môi trường kinh doanh quốc tế.\nCử nhân\nToàn thời gian: 4 năm\nXem thông tin chi tiết về chương trình đào tạo\nXem thông tin chi tiết về chuẩn đầu ra\nKết quả quá trình học tập THPT\nKết quả bài thi ĐGNL năm 2025 của ĐHQG TP. HCM\nTổ hợp: Đang cập nhật\nĐiểm trúng tuyển 2024 (thang 40):33,80\nTháng 9, năm 2025\nKhoảng 27 đến 28 triệu đồng/năm (năm 2024)", "content": {"Bằng cấp": "Cử nhân", "Thời gian đào tạo": "Toàn thời gian: 4 năm", "Chương trình đào tạo": "Xem thông tin chi tiết về chương trình đào tạo", "Chuẩn đầu ra": "Xem thông tin chi tiết về chuẩn đầu ra", "Phương thức xét tuyển riêng": "Kết quả quá trình học tập THPT Kết quả bài thi ĐGNL năm 2025 của ĐHQG TP. HCM", "Xét tuyển theo điểm thi THPT": "Tổ hợp: Đang cập nhật Điểm trúng tuyển 2024 (thang 40):33,80", "Khai giảng": "Tháng 9, năm 2025", "Học phí": "Khoảng 27 đến 28 triệu đồng/năm (năm 2024)"}, "name": "Kinh doanh quốc tế"}, {"tab": "Tiên tiến", "major_code": "F7340120", "description": "Cử nhân kinh doanh quốc tế chương trình tiên tiến của TDTU  được thiết kế có các điểm nổi bật như ứng dụng các công nghệ hệ thống ERP, thực tế ảo VR-QR vào giảng dạy, quy mô lớp học hợp lý, môi trường học tập năng động với cơ sở vật chất hiện đại, tăng cường học tập thực tế tại doanh nghiệp theo phương châm học đi đôi với hành.\nSinh viên tốt nghiệp đạt chuẩn đầu ra với yêu cầu cao về chuyên môn nghiệp vụ, kỹ năng tin học, ngoại ngữ và kỹ năng mềm nhằm đáp ứng được nhu cầu ngày càng đa dạng của doanh nghiệp trong và ngoài nước.\nĐội ngũ giảng viên tham gia giảng dạy chương trình tiên tiến giàu kinh nghiệm thực tiễn và nghiên cứu. Các học phần cốt lõi ngành của chương trình được giảng dạy bởi chuyên gia có kinh nghiệm làm việc thực tế hoặc đến từ doanh nghiệp có uy tín tại Việt Nam hoặc các công ty đa quốc gia.\nCử nhân\nToàn thời gian: 4 năm\nXem thông tin chi tiết về chương trình đào tạo\nXem thông tin chi tiết về chuẩn đầu ra\nKết quả quá trình học tập THPT\nKết quả bài thi ĐGNL năm 2025 của ĐHQG TP. HCM\nTổ hợp: Đang cập nhật\nĐiểm trúng tuyển 2024 (thang 40):30,80\nTháng 9, năm 2025\nKhoảng 62 đến 64 triệu đồng/năm (năm 2024)", "content": {"Bằng cấp": "Cử nhân", "Thời gian đào tạo": "Toàn thời gian: 4 năm", "Chương trình đào tạo": "Xem thông tin chi tiết về chương trình đào tạo", "Chuẩn đầu ra": "Xem thông tin chi tiết về chuẩn đầu ra", "Phương thức xét tuyển riêng": "Kết quả quá trình học tập THPT Kết quả bài thi ĐGNL năm 2025 của ĐHQG TP. HCM", "Xét tuyển theo điểm thi THPT": "Tổ hợp: Đang cập nhật Điểm trúng tuyển 2024 (thang 40):30,80", "Khai giảng": "Tháng 9, năm 2025", "Học phí": "Khoảng 62 đến 64 triệu đồng/năm (năm 2024)"}, "name": "Kinh doanh quốc tế"}, {"tab": "Đại học bằng tiếng Anh", "major_code": "FA7340120", "description": "Cử nhân kinh doanh quốc tế chương trình đại học bằng tiếng Anh của TDTU được thiết kế có các điểm nổi bật như ứng dụng các công nghệ hệ thống ERP, thực tế ảo VR-QR vào giảng dạy, quy mô lớp học hợp lý, môi trường học tập năng động với cơ sở vật chất hiện đại, tăng cường học tập thực tế tại doanh nghiệp theo phương châm học đi đôi với hành. Chương trình giảng dạy hoàn toàn bằng tiếng Anh.\nSinh viên tốt nghiệp đạt chuẩn đầu ra với yêu cầu cao về chuyên môn nghiệp vụ, kỹ năng tin học, đặc biệt là ngoại ngữ và kỹ năng mềm nhằm đáp ứng yêu cầu của thị trường lao động hội nhập quốc tế.\nNgoài ra, sinh viên tham gia chương trình này có cơ hội được tham gia học kỳ tại nước ngoài với các trường đối tác thân hữu, uy tín và có hợp tác với TDTU. Từ đây, sinh viên có thêm nhiều lựa chọn định hướng nghề nghiệp tốt hơn và rộng mở hơn.\nCử nhân\nToàn thời gian: 4 năm\nXem thông tin chi tiết về chương trình đào tạo\nXem thông tin chi tiết về chuẩn đầu ra\nKết quả quá trình học tập THPT\nKết quả bài thi ĐGNL năm 2025 của ĐHQG TP. HCM\nTổ hợp: Đang cập nhật\nĐiểm trúng tuyển 2024 (thang 40):28,00\nTháng 9, năm 2025\nKhoảng 83 đến 84 triệu đồng/năm (năm 2024)", "content": {"Bằng cấp": "Cử nhân", "Thời gian đào tạo": "Toàn thời gian: 4 năm", "Chương trình đào tạo": "Xem thông tin chi tiết về chương trình đào tạo", "Chuẩn đầu ra": "Xem thông tin chi tiết về chuẩn đầu ra", "Phương thức xét tuyển riêng": "Kết quả quá trình học tập THPT Kết quả bài thi ĐGNL năm 2025 của ĐHQG TP. HCM", "Xét tuyển theo điểm thi THPT": "Tổ hợp: Đang cập nhật Điểm trúng tuyển 2024 (thang 40):28,00", "Khai giảng": "Tháng 9, năm 2025", "Học phí": "Khoảng 83 đến 84 triệu đồng/năm (năm 2024)"}, "name": "Kinh doanh quốc tế"}, {"tab": "Liên kết quốc tế - K7340120L", "major_code": "K7340120L", "description": "Cử nhân (song bằng)\n4 năm (3 năm đầu học tại TDTU, 1 năm sau học tại Trường liên kết)\nXem thông tin chi tiết về chương trình đào tạo\nXem thông tin chi tiết về chuẩn đầu ra\nKết quả quá trình học tập THPT\nKết quả bài thi ĐGNL năm 2025 của ĐHQG TP. HCM\nTổ hợp: Đang cập nhật\nĐiểm trúng tuyển 2024 (thang 40):28,00\nTháng 9, năm 2025\nGiai đoạn 1: khoảng 82 đến 83 triệu đồng/năm (năm 2024)", "content": {"Bằng cấp": "Cử nhân (song bằng)", "Thời gian đào tạo": "4 năm (3 năm đầu học tại TDTU, 1 năm sau học tại Trường liên kết)", "Chương trình đào tạo": "Xem thông tin chi tiết về chương trình đào tạo", "Chuẩn đầu ra": "Xem thông tin chi tiết về chuẩn đầu ra", "Phương thức xét tuyển riêng": "Kết quả quá trình học tập THPT Kết quả bài thi ĐGNL năm 2025 của ĐHQG TP. HCM", "Xét tuyển theo điểm thi THPT": "Tổ hợp: Đang cập nhật Điểm trúng tuyển 2024 (thang 40):28,00", "Khai giảng": "Tháng 9, năm 2025", "Học phí": "Giai đoạn 1: khoảng 82 đến 83 triệu đồng/năm (năm 2024)"}, "name": "Kinh doanh quốc tế liên kết Đại học La Trobe, Úc"}], "images": ["https://admission.tdtu.edu.vn/sites/admission23/files/Tuyen-sinh/Dai-hoc/Nganh/KDQT/1.jpg", "https://admission.tdtu.edu.vn/sites/admission23/files/Tuyen-sinh/Dai-hoc/Nganh/KDQT/2.jpg", "https://admission.tdtu.edu.vn/sites/admission23/files/Tuyen-sinh/Dai-hoc/Nganh/KDQT/3.jpg"]}
{"name": "Kỹ thuật cơ điện tử", "description": "Kỹ thuật cơ điện tử là ngành học kết hợp giữa khoa học máy tính, kỹ thuật điện-điện tử và kỹ thuật cơ khí để thiết kế, chế tạo và vận hành máy móc, thiết bị thông minh nhằm phục vụ cho công cuộc tạo ra các sản phẩm mới có nhiều tính năng vượt trội, phục vụ cho nhu cầu công nghiệp hoá - hiện đại hoá hoặc phát triển bền vững của mỗi quốc gia.\nSinh viên ngành Kỹ thuật cơ điện tử khi ra trường có các cơ hội làm việc ở các vị trí như kỹ sư thiết kế, chế tạo máy móc tự động hóa; kỹ sư vận hành, bảo trì các thống điện tử công nghiệp, robot công nghiệp trong các dây chuyền sản xuất lắp ráp thông minh; chuyên viên tư vấn, thiết kế, phân tích mô phỏng nhằm cung cấp giải pháp công nghệ theo yêu cầu của khách hàng là các đơn vị sản xuất kinh doanh hoặc hành chính sự nghiệp; nhân viên hỗ trợ kỹ thuật hoặc giới thiệu sản phẩm cho các tập đoàn sản xuất thiết bị cơ khí – cơ điện tử. Ngoài ra, kỹ sư Kỹ thuật cơ điện tử còn có khả năng tiếp tục theo học tại các chương trình sau đại học trong nước hoặc quốc tế hoặc tham gia giảng dạy, nghiên cứu các môn chuyên ngành tại các trường cao đẳng và đại học trên cả nước.", "reasons": ["Học phí phù hợp", "Liên tục cập nhật xu hướng", "100% sinh viên ra trường có việc làm trong vòng 12 tháng kể từ khi tốt nghiệp"], "programs": [{"tab": "Tiêu chuẩn", "major_code": "7520114", "description": "Chương trình đào tạo ngành Kỹ thuật cơ điện tử tại TDTU mang tính sáng tạo và ứng dụng cao, giúp người học am hiểu các kỹ thuật cơ khí chế tạo, điện tử điều khiển tự động, công nghệ thông tin và các công nghệ hiện đại liên quan để đáp ứng nhu cầu nhân lực cho đất nước trong cách mạng công nghiệp 4.0 như các nguyên tắc điều khiển công nghiệp, hệ thống điều khiển cơ điện tử và bộ điều khiển logic lập trình, thiết kế máy và động học, sản xuất tích hợp máy vi tính, chế tạo và điều khiển sản phẩm cơ điện tử, kỹ thuật điều khiển tự động, … Đặc biệt, ngành học đào tạo phương pháp thiết kế đặc trưng cơ điện tử trong đó các thành phần cơ khí, điện tử và công nghệ thông tin của robot, được thiết kế và chế tạo song song để bổ trợ lẫn nhau nhằm tạo nên chất lượng và tính năng vượt trội mà phương pháp truyền thống không đạt được.\nBên cạnh đó, chương trình đào tạo còn được xây dựng theo hướng mang tính ứng dụng cao, kết hợp chặt chẽ giữa lý thuyết và thực hành với các phòng thí nghiệm đa dạng, phong phú, đặc biệt sinh viên được tiếp cận với trang thiết bị thí nghiệm hiện đại được hỗ trợ bởi các tập đoàn lớn trong nước và quốc tế. Sinh viên tiếp cận sớm với môi trường và văn hoá doanh nghiệp thông qua các chuyến tham quan thực tế và kiến tập tại doanh nghiệp để học hỏi và cập nhật xu hướng mới trong ngành đào tạo, vận dụng kiến thức và kỹ năng đã được trang bị để giải quyết các vấn đề thực tiễn tại công ty.\nMột số học phần chuyên môn và các chương trình nghiên cứu đều có sự đóng góp của nhiều chuyên gia có tay nghề cao kết hợp với giảng viên trực tiếp giảng dạy và hướng dẫn thực hiện các dự án nghiên cứu khoa học ngay tại doanh nghiệp, mở ra nhiều cơ hội phát triển toàn diện cả về kiến thức lẫn kỹ năng chuyên ngành cho sinh viên.\nSinh viên sau tốt nghiệp ngành Kỹ thuật cơ điện tử sẽ tích lũy được kiến thức cơ sở để phân tích lý thuyết cơ điện tử và thiết kế hệ thống cơ điện tử cơ bản; áp dụng kiến thức chuyên môn vào quy trình thường xuyên trong kỹ thuật cơ điện tử; phân tích các vấn đề thực tế có thể xảy ra trong kỹ thuật cơ điện tử và chọn phương pháp thích hợp để giải quyết các vấn đề bất thường; cải thiện và nâng cấp các hệ thống cơ điện tử; thiết kế, thực hiện và vận hành hệ thống cơ điện tử; tư vấn, lập kế hoạch, quản lý và triển khai các dự án liên quan đến cơ điện tử Kỹ năng giao tiếp hiệu quả, bao gồm cả kỹ năng giao tiếp làm việc nhóm, quản lý thời gian và tài nguyên hiệu quả.\nCử nhân\nKỹ sư\nToàn thời gian: 4 năm\nToàn thời gian: 5 năm\nXem thông tin chi tiết về chương trình đào tạo\nXem thông tin chi tiết về chuẩn đầu ra\nKết quả quá trình học tập THPT\nKết quả bài thi ĐGNL năm 2025 của ĐHQG TP. HCM\nTổ hợp: Đang cập nhật\nĐiểm trúng tuyển 2024 (thang 40):31,30\nTháng 9, năm 2025\nKhoảng 31 đến 32 triệu đồng/năm (năm 2024)", "content": {"Bằng cấp": "Cử nhân Kỹ sư", "Thời gian đào tạo": "Toàn thời gian: 4 năm Toàn thời gian: 5 năm", "Chương trình đào tạo": "Xem thông tin chi tiết về chương trình đào tạo", "Chuẩn đầu ra": "Xem thông tin chi tiết về chuẩn đầu ra", "Phương thức xét tuyển riêng": "Kết quả quá trình học tập THPT Kết quả bài thi ĐGNL năm 2025 của ĐHQG TP. HCM", "Xét tuyển theo điểm thi THPT": "Tổ hợp: Đang cập nhật Điểm trúng tuyển 2024 (thang 40):31,30", "Khai giảng": "Tháng 9, năm 2025", "Học phí": "Khoảng 31 đến 32 triệu đồng/năm (năm 2024)"}, "name": "Kỹ thuật cơ điện tử"}], "images": ["https://admission.tdtu.edu.vn", "https://admission.tdtu.edu.vn/sites/admission23/files/Tuyen-sinh/Dai-hoc/Nganh/CDT/1.jpg", "https://admission.tdtu.edu.vn/sites/admission23/files/Tuyen-sinh/Dai-hoc/Nganh/CDT/2.jpg", "https://admission.tdtu.edu.vn/sites/admission23/files/Tuyen-sinh/Dai-hoc/Nganh/CDT/3.jpg"]}
{"name": "Kỹ thuật điện tử - viễn thông (Chuyên ngành Kỹ thuật thiết kế vi mạch bán dẫn)", "description": "Năm 2025, Trường Đại học Tôn Đức Thắng tuyển sinh đào tạo chuyên ngành Kỹ thuật thiết kế vi mạch bán dẫn là một trong các ngành mũi nhọn theo Chiến lược phát triển công nghiệp bán dẫn của Việt Nam.\nChương trình đào tạo đại học chuyên ngành Kỹ thuật Thiết kế vi mạch bán dẫn được xây dựng trên cơ sở chương trình đang đào tạo ngành Kỹ thuật Điện tử - viễn thông. Chương trình cung cấp kiến thức và kỹ năng toàn diện chuyên sâu về ngành vi mạch bán dẫn, giúp người học hiểu toàn bộ quy trình thiết kế, chế tạo, đóng gói và kiểm thử vi mạch; đồng thời tích hợp thực hành chuyên sâu trong kỹ thuật thiết kế vi mạch và giúp sinh viên có thể chọn hướng nghề nghiệp phù hợp trong công nghiệp vi mạch bán dẫn, giải quyết các thách thức công nghệ trong thời đại internet vạn vật (IoT) và trí tuệ thông minh nhân tạo (AI).\nSinh viên tốt nghiệp có thể làm việc ở các vị trí kỹ sư thiết kế, kiểm thử vi mạch, phát triển ứng dụng, tư vấn kỹ thuật, giảng dạy và nghiên cứu hay khởi nghiệp trong lĩnh vực vi mạch bán dẫn, tại các công ty công nghệ hàng đầu trong lĩnh vực vi mạch bán dẫn tại Việt Nam và quốc tế, hoặc tham gia các dự án nghiên cứu và triển khai công nghệ vi mạch bán dẫn tại các trung tâm/ viện nghiên cứu.", "reasons": ["Chương trình đạt chuẩn quốc tế", "Đội ngũ giảng viên đẳng cấp quốc tế", "Cơ sở vật chất hiện đại"], "programs": [{"tab": "Tiêu chuẩn", "major_code": "7520207T", "description": "Chương trình được thiết kế theo tiêu chuẩn kiểm định quốc tế, được đối sánh với các chương trình đại học uy tín trên thế giới và chuẩn đầu ra tin học đạt chứng chỉ MOS (Microsoft Office Specialist) tối thiểu 750/1000 điểm hoặc chứng chỉ ICDL (International Certification of Digital Literacy) đạt 75% trở lên và kỹ năng ngoại ngữ đạt chứng chỉ tiếng Anh tối thiểu IELTS 5.0 hoặc chứng chỉ khác tương đương.\nTrong năm đầu, sinh viên học các học phần kiến thức đại cương kết hợp với một phần kiến thức cơ sở ngành, tạo điều kiện cho sinh viên tiếp cận nghề nghiệp ngay từ đầu để hiểu rõ ngành nghề của mình.\nSinh viên được tiếp cận sớm với các doanh nghiệp trong lĩnh vực thiết kế vi mạch bán dẫn thông qua các đợt kiến tập được tổ chức ít nhất 1 lần/ 1 học kỳ, các buổi seminar định hướng nghề nghiệp, các bài giảng chuyên đề do giáo sư/chuyên gia trong và ngoài nước trình bày, ...\nCó ít nhất 10% môn chuyên ngành được dạy bằng tiếng Anh. Số lượng môn tự chọn được chia theo nhóm, giúp sinh viên có phương án định hướng nghề nghiệp cho bản thân.\nCó tính liên thông với các chương trình Sau Đại học của Khoa, đặc biệt là chương trình Thạc sĩ ngành Kỹ thuật viễn thông.\nCử nhân\nKỹ sư\nToàn thời gian: 4 năm\nToàn thời gian: 5 năm\nXem thông tin chi tiết về chương trình đào tạo\nXem thông tin chi tiết về chuẩn đầu ra\nKết quả quá trình học tập THPT\nKết quả bài thi ĐGNL năm 2025 của ĐHQG TP. HCM\nTổ hợp: Đang cập nhật\nTháng 9, năm 2025\nĐang cập nhật", "content": {"Bằng cấp": "Cử nhân Kỹ sư", "Thời gian đào tạo": "Toàn thời gian: 4 năm Toàn thời gian: 5 năm", "Chương trình đào tạo": "Xem thông tin chi tiết về chương trình đào tạo", "Chuẩn đầu ra": "Xem thông tin chi tiết về chuẩn đầu ra", "Phương thức xét tuyển riêng": "Kết quả quá trình học tập THPT Kết quả bài thi ĐGNL năm 2025 của ĐHQG TP. HCM", "Xét tuyển theo điểm thi THPT": "Tổ hợp: Đang cập nhật", "Khai giảng": "Tháng 9, năm 2025", "Học phí": "Đang cập nhật"}, "name": "Kỹ thuật điện tử - viễn thông (Chuyên ngành Kỹ thuật thiết kế vi mạch bán dẫn)"}], "images": ["https://admission.tdtu.edu.vn", "https://admission.tdtu.edu.vn/sites/admission23/files/Tuyen-sinh/Dai-hoc/Nganh/TKVM/1.png", "https://admission.tdtu.edu.vn/sites/admission23/files/Tuyen-sinh/Dai-hoc/Nganh/TKVM/2.jpg", "https://admission.tdtu.edu.vn/sites/admission23/files/Tuyen-sinh/Dai-hoc/Nganh/DT-VT/1.jpg"]}
{"name": "Kỹ thuật điện tử - viễn thông", "description": "Ngành Kỹ thuật điện tử - viễn thông là ngành của sự sáng tạo và đam mê công nghệ. Bằng việc sử dụng các hệ thống thiết bị mạng viễn thông hay các thiết bị điện tử đã tạo nên hệ thống trao đổi thông tin đầy thú vị đi kèm với các thiết bị tiên tiến được cung cấp bởi các tập đoàn lớn đến từ Mỹ, Canada,...\nTại Việt Nam, lĩnh vực công nghệ thông tin và truyền thông (ICT) đang phát triển một cách mạnh mẽ và đóng vai trò quan trọng đối với sự phát triển kinh tế xã hội. Trong đó, ngành Kỹ thuật điện tử – viễn thông là một ngành năng động, với các ứng dụng liên quan trực tiếp đến nhiều lĩnh vực trong cuộc sống, đặc biệt trong thời đại cách mạng công nghiệp 4.0.\nVới chương trình đào tạo cử nhân và kỹ sư cho hai hệ đào tạo tiêu chuẩn và tiên tiến (chương trình giảng dạy các môn chuyên ngành bằng tiếng anh) giúp cho sinh viên học được các kiến thức cần thiết khi bước vào thị trường lao động đầy thử thách. Bên cạnh đó, sinh viên có nhiều cơ hội làm việc tại các cơ quan nhà nước, các trung tâm nghiên cứu, các tập đoàn, công ty viễn thông nước ngoài,...\nNgành Kỹ thuật điện tử - viễn thông đang giảng dạy, nghiên cứu các lĩnh vực theo xu hướng hiện nay: mạng di động 5G, IoT, thiết kế vi mạch hay các mạch điện tử thông minh,... luôn đem lại sự thích thú và cơ hội phát triển nghề nghiệp cho mỗi sinh viên.", "reasons": ["Học phí phù hợp", "Liên tục cập nhật xu hướng", "100% sinh viên ra trường có việc làm trong vòng 12 tháng kể từ khi tốt nghiệp"], "programs": [{"tab": "Tiêu chuẩn", "major_code": "7520207", "description": "Chương trình được thiết kế theo tiêu chuẩn kiểm định quốc tế, được đối sánh với các chương trình đại học uy tín trên thế giới và chuẩn đầu ra tin học đạt chứng chỉ tin học Microsoft Office Specialist tối thiểu 750/1000 điểm hoặc chứng chỉ ICDL (International Certification of Digital Literacy) đạt 75% trở lên và kỹ năng ngoại ngữ đạt chứng chỉ tiếng Anh tối thiểu IELTS 5.0 hoặc chứng chỉ khác tương đương. Ngoài các kiến thức cơ bản về lý thuyết mạch điện - điện tử, kỹ thuật đo lường điện-điện tử, kỹ thuật mô phỏng bằng phần mềm, ngành học còn cung cấp cho sinh viên kiến thức về chuyên ngành như các mạng truyền thông di động thế hệ mới, công nghệ internet kết nối vạn vật, thiết kế vi mạch, mạch điện tử thông minh ứng dụng trong dân dụng và công nghiệp, …\nChương trình đào tạo chú trọng kết hợp chặt chẽ giữa lý thuyết và thực hành. Sinh viên được thực hành trên các hệ thống trang thiết bị hiện đại, đa số được tài trợ bởi các tập đoàn, doanh nghiệp lớn trong ngành như Siemens, Altera, Mitsubishi, Keysight… Ngoài ra, thông qua các đồ án môn học và đồ án tốt nghiệp, sinh viên được tiếp cận và thực hiện các đề tài đang là vấn đề cấp bách trong thực tế như mạng thông tin di động 5G, công nghệ internet kết nối vạn vật, xe tự hành, nông-lâm-ngư nghiệp-nhà thông minh, thiết kế vi mạch bán dẫn, …\nNgoài chuyên môn, sinh viên còn tham gia nhiều các hoạt động ngoại khóa khác nhau. Sinh viên được tiếp cận sớm với môi trường và văn hoá doanh nghiệp thông qua các chuyến tham quan thực tế, kiến tập và thực tập tại doanh nghiệp. Khoa còn thường xuyên tổ chức các buổi sinh hoạt học thuật, workshop, ngày hội việc làm, … với các diễn giả là những chuyên gia hàng đầu đến từ các công ty viễn thông trong nước và quốc tế … nhằm định hướng nghề nghiệp cho sinh viên, tăng thêm cơ hội việc làm trong tương lai. Thêm vào đó, trong một số học phần chuyên môn và các chương trình nghiên cứu đều có sự đóng góp của nhiều chuyên gia có tay nghề cao kết hợp với giảng viên trực tiếp giảng dạy và hướng dẫn thực hiện các dự án nghiên cứu khoa học ngay tại doanh nghiệp, mở ra nhiều cơ hội phát triển toàn diện cả về kiến thức lẫn kỹ năng chuyên ngành cho sinh viên.\nSinh viên sau tốt nghiệp ngành Kỹ thuật điện tử - viễn thông có khả năng khảo sát, lựa chọn, vận hành, bảo trì, sửa chữa các hệ thống truyền dẫn dữ liệu trong dân dụng hay công nghiệp; thiết kế giao diện giám sát, quản lí và lập trình điều khiển hệ thống; xây dựng hệ thống mạng thu thập và quản lý cơ sở dữ liệu cho các cơ quan, doanh nghiệp; tham gia cải tiến nâng cấp hệ thống, đề xuất dự toán kinh phí, kỹ thuật, thiết bị và nhân lực, thời gian thực hiện cho các dự án liên quan đến điện tử viễn thông; có khả năng tự học, tự nghiên cứu để cập nhật kỹ thuật, công nghệ mới và học lên trình độ cao hơn.\nCử nhân\nKỹ sư\nToàn thời gian: 4 năm\nToàn thời gian: 5 năm\nXem thông tin chi tiết về chương trình đào tạo\nXem thông tin chi tiết về chuẩn đầu ra\nKết quả quá trình học tập THPT\nKết quả bài thi ĐGNL năm 2025 của ĐHQG TP. HCM\nTổ hợp: Đang cập nhật\nĐiểm trúng tuyển 2024 (thang 40):31,20\nTháng 9, năm 2025\nKhoảng 31 đến 32 triệu đồng/năm (năm 2024)", "content": {"Bằng cấp": "Cử nhân Kỹ sư", "Thời gian đào tạo": "Toàn thời gian: 4 năm Toàn thời gian: 5 năm", "Chương trình đào tạo": "Xem thông tin chi tiết về chương trình đào tạo", "Chuẩn đầu ra": "Xem thông tin chi tiết về chuẩn đầu ra", "Phương thức xét tuyển riêng": "Kết quả quá trình học tập THPT Kết quả bài thi ĐGNL năm 2025 của ĐHQG TP. HCM", "Xét tuyển theo điểm thi THPT": "Tổ hợp: Đang cập nhật Điểm trúng tuyển 2024 (thang 40):31,20", "Khai giảng": "Tháng 9, năm 2025", "Học phí": "Khoảng 31 đến 32 triệu đồng/năm (năm 2024)"}, "name": "Kỹ thuật điện tử - viễn thông"}, {"tab": "Tiên tiến", "major_code": "F7520207", "description": "Chương trình được thiết kế theo tiêu chuẩn kiểm định quốc tế, được đối sánh với các chương trình đại học uy tín trên thế giới và chuẩn đầu ra tin học đạt chứng chỉ tin học Microsoft Office Specialist tối thiểu 750/1000 điểm hoặc chứng chỉ ICDL (International Certification of Digital Literacy) đạt 75% trở lên và kỹ năng ngoại ngữ đạt chứng chỉ tiếng Anh tối thiểu IELTS 5.5 hoặc chứng chỉ khác tương đương. Điểm đặc biệt của chương trình này là hơn 50% các môn chuyên ngành được giảng dạy bằng Tiếng Anh.\nĐối với chương trình đại học tiên tiến, sinh viên có cơ hội thực hiện đồ án tốt nghiệp theo các đề tài do doanh nghiệp đặt hàng; được tiếp cận sớm với môi trường và văn hoá doanh nghiệp thông qua các chuyến tham quan thực tế, kiến tập và thực tập.\nKhoa còn thường xuyên tổ chức các buổi sinh hoạt học thuật, workshop, ngày hội việc làm, … với các diễn giả là những chuyên gia hàng đầu đến từ các công ty tự động hoá trong nước và quốc tế … nhằm định hướng nghề nghiệp cho sinh viên, tăng thêm cơ hội việc làm trong tương lai. Thêm vào đó, trong một số học phần chuyên môn và các chương trình nghiên cứu đều có sự đóng góp của nhiều chuyên gia có tay nghề cao kết hợp với giảng viên trực tiếp giảng dạy và hướng dẫn thực hiện các dự án nghiên cứu khoa học hay khởi nghiệp ngay tại doanh nghiệp, mở ra nhiều cơ hội phát triển toàn diện cả về kiến thức lẫn kỹ năng chuyên ngành cho sinh viên.\nNhà trường còn tạo cơ hội để các sinh viên có năng lực học tập tốt được tham gia các khóa học trao đổi ngắn hạn cũng như thực hiện đồ án tốt nghiệp tại các trường đại học lớn trên thế giới như Anh, Hàn Quốc, Cộng hoà Czech, …  để học tập và giao lưu văn hoá, cập nhật thêm các xu hướng và kỹ thuật mới thuộc lĩnh vực chuyên môn của ngành học.\nVới năng lực ngoại ngữ và cơ hội tiếp cận với các trường đại học nước ngoài, sinh viên tốt nghiệp ngành Kỹ thuật điện tử viễn thông chương trình đại học tiên tiến có nhiều cơ hội xin được các học bổng bán phần hoặc toàn phần để tiếp tục học tập nâng cao trình độ sau đại học.\nCử nhân\nKỹ sư\nToàn thời gian: 4 năm\nToàn thời gian: 5 năm\nXem thông tin chi tiết về chương trình đào tạo\nXem thông tin chi tiết về chuẩn đầu ra\nKết quả quá trình học tập THPT\nKết quả bài thi ĐGNL năm 2025 của ĐHQG TP. HCM\nTổ hợp: Đang cập nhật\nĐiểm trúng tuyển 2024 (thang 40):26,00\nTháng 9, năm 2025\nKhoảng 53 đến 54 triệu đồng/năm (năm 2024)", "content": {"Bằng cấp": "Cử nhân Kỹ sư", "Thời gian đào tạo": "Toàn thời gian: 4 năm Toàn thời gian: 5 năm", "Chương trình đào tạo": "Xem thông tin chi tiết về chương trình đào tạo", "Chuẩn đầu ra": "Xem thông tin chi tiết về chuẩn đầu ra", "Phương thức xét tuyển riêng": "Kết quả quá trình học tập THPT Kết quả bài thi ĐGNL năm 2025 của ĐHQG TP. HCM", "Xét tuyển theo điểm thi THPT": "Tổ hợp: Đang cập nhật Điểm trúng tuyển 2024 (thang 40):26,00", "Khai giảng": "Tháng 9, năm 2025", "Học phí": "Khoảng 53 đến 54 triệu đồng/năm (năm 2024)"}, "name": "Kỹ thuật điện tử - viễn thông"}], "images": ["https://admission.tdtu.edu.vn", "https://admission.tdtu.edu.vn/sites/admission23/files/Tuyen-sinh/Dai-hoc/Nganh/DT-VT/1.jpg", "https://admission.tdtu.edu.vn/sites/admission23/files/Tuyen-sinh/Dai-hoc/Nganh/DT-VT/2.jpg", "https://admission.tdtu.edu.vn/sites/admission23/files/Tuyen-sinh/Dai-hoc/Nganh/DT-VT/3.jpg"]}
{"name": "Kỹ thuật điện", "description": "Kỹ thuật điện là ngành học cốt lõi, ứng dụng kiến thức điện - điện tử để thiết kế, lắp đặt, vận hành và tối ưu hóa các hệ thống cung cấp điện; từ quy mô nhỏ như tòa nhà, khu dân cư đến các nhà máy công nghiệp, trạm biến áp (TBA) và lưới truyền tải điện quốc gia nhằm đảm bảo nguồn điện luôn ổn định và bền vững, phục vụ cho nhu cầu đời sống sinh hoạt của người dân ở mỗi quốc gia. Với xu thế công nghiệp hóa gắn liền chuyển đổi số, ngành Kỹ thuật điện ngày càng ứng dụng các công nghệ tiên tiến như Trí tuệ nhân tạo (AI), Internet vạn vật (IoT) và các thuật toán tối ưu để quản lý, vận hành hệ thống điện hiệu quả, đáp ứng linh hoạt nhu cầu công nghiệp và đời sống.", "reasons": ["Cơ hội trải nghiệm các học phần nghề nghiệp, tập sự nghề nghiệp tại các doanh nghiệp, định chế tài chính trong và ngoài nước", "Cơ hội tham gia chương trình trao đổi ngắn hạn, dài hạn với các đại học uy tín trên thế giới", "100% sinh viên ra trường có việc làm trong vòng 12 tháng kể từ khi tốt nghiệp"], "programs": [{"tab": "Tiêu chuẩn", "major_code": "7520201", "description": "Ngoài các kiến thức cơ sở về xác suất thống kê, lý thuyết mạch điện, mạch điện tử và hệ thống tự động hóa trong công nghiệp, sinh viên còn được trang bị kiến thức và kỹ năng chuyên ngành tích hợp ở cả 3 lĩnh vực hệ thống điện, cung cấp điện và năng lượng tái tạo như các nguồn năng lượng tái tạo, máy điện trong thiết bị tự động và điều khiển, điều khiển logic và PLC, nhà máy điện và trạm biến áp, hệ thống BMS cho tòa nhà, kỹ thuật điện cao áp, chiếu sáng công nghiệp và dân dụng,… với các phòng thí nghiệm đa dạng, phong phú, hiện đại và liên tục được cập nhật.\nChương trình đào tạo của ngành đạt chuẩn kiểm định ASIIN với hệ thống tín chỉ quy đổi tương đương khung trình độ của Châu Âu. Với sự phát triển mạnh mẽ của năng lượng tái tạo và năng lượng xanh (điện gió, điện mặt trời), sinh viên tốt nghiệp có nhiều cơ hội tham gia các dự án tiên tiến, đáp ứng nhu cầu cấp thiết của thị trường lao động trong và ngoài nước. Ứng dụng các phần mềm chuyên dụng như AutoCAD, BIM, Revit, Ecodial, Etap, Power World,... trong thiết kế, tính toán, mô phỏng và mô hình hóa 3D công trình thực tế ảo.\nSinh viên được hướng dẫn tham gia các khóa đào tạo ngắn hạn, các chuyến tham quan thực tế và kiến tập tại doanh nghiệp để học hỏi và cập nhật xu hướng mới trong ngành đào tạo, vận dụng kiến thức và kỹ năng đã được trang bị để giải quyết các vấn đề thực tiễn tại công ty, đồng thời sớm làm quen với môi trường và văn hoá doanh nghiệp. Trong một số học phần chuyên môn và các chương trình nghiên cứu đều có sự đóng góp của nhiều chuyên gia có tay nghề cao đến từ các công ty điện lực, nhà máy công nghiệp và công ty xây dựng trong việc kết hợp với giảng viên trực tiếp giảng dạy và hướng dẫn thực hiện các dự án nghiên cứu khoa học ngay tại doanh nghiệp.\nCử nhân\nKỹ sư\nToàn thời gian: 4 năm\nToàn thời gian: 5 năm\nXem thông tin chi tiết về chương trình đào tạo\nXem thông tin chi tiết về chuẩn đầu ra\nKết quả quá trình học tập THPT\nKết quả bài thi ĐGNL năm 2025 của ĐHQG TP. HCM\nTổ hợp: Đang cập nhật\nĐiểm trúng tuyển 2024 (thang 40):30,00\nTháng 9, năm 2025\nKhoảng 31 đến 32 triệu đồng/năm (năm 2024)", "content": {"Bằng cấp": "Cử nhân Kỹ sư", "Thời gian đào tạo": "Toàn thời gian: 4 năm Toàn thời gian: 5 năm", "Chương trình đào tạo": "Xem thông tin chi tiết về chương trình đào tạo", "Chuẩn đầu ra": "Xem thông tin chi tiết về chuẩn đầu ra", "Phương thức xét tuyển riêng": "Kết quả quá trình học tập THPT Kết quả bài thi ĐGNL năm 2025 của ĐHQG TP. HCM", "Xét tuyển theo điểm thi THPT": "Tổ hợp: Đang cập nhật Điểm trúng tuyển 2024 (thang 40):30,00", "Khai giảng": "Tháng 9, năm 2025", "Học phí": "Khoảng 31 đến 32 triệu đồng/năm (năm 2024)"}, "name": "Kỹ thuật điện"}, {"tab": "Tiên tiến", "major_code": "F7520201", "description": "Ngành Kỹ thuật điện có khả năng: thiết kế, thi công, giám sát, vận hành và bảo dưỡng các hệ thống điện quốc gia, các hệ thống điện vừa và nhỏ; thiết kế và lắp đặt các công trình điện dân dụng và công nghiệp theo tiêu chuẩn quốc tế; nghiên cứu ứng dụng, thiết kế, vận hành các nguồn năng lượng tái tạo (VD: năng lượng mặt trời, gió, sóng biển); ứng dụng IoT cho các dự án nông nghiệp công nghệ cao, quản lý năng lượng cho tòa nhà, lưới điện thông minh; nghiên cứu giải pháp tiết kiệm điện và sử dụng năng lượng hiệu quả.\nChương trình tiên tiến có phương pháp giáo dục hiện đại, ứng dụng công nghệ số trong giảng dạy, ngôn ngữ giảng dạy bằng tiếng Việt và tiếng Anh.\nHọc các môn chuyên ngành bằng tiếng Anh: Trên 50% các môn học chuyên ngành được giảng dạy bằng tiếng Anh bởi đội ngũ giảng viên có chuyên môn cao. Điều này không chỉ giúp sinh viên mở rộng vốn từ vựng chuyên ngành mà còn nâng cao kỹ năng ngoại ngữ trong lĩnh vực đào tạo, tạo lợi thế khi ứng tuyển vào các công ty đa quốc gia.\nCơ sở vật chất: Phòng học đầy đủ tiện nghi với trang thiết bị dạy học hiện đại nhất. Được học trong các phòng học đặc thù riêng của Khoa; được ưu tiên tiếp cận sớm với các thiết bị thí nghiệm mới, được hỗ trợ một số linh kiện chuyên dụng trong quá trình làm đồ án tốt nghiệp.\nSinh viên có cơ hội tham gia các khóa đào tạo, trao đổi ngắn hạn hoặc thực hiện đồ án tốt nghiệp ở các trường đại học hàng đầu về kỹ thuật như Đài Loan, Cộng Hòa Séc,… Sinh viên sau khi tốt nghiệp có cơ hội nhận học bổng cao học tại Trường Đại học Tôn Đức Thắng, hoặc được ưu tiên giới thiệu xin học bổng toàn phần ở các trường đại học trên thế giới có liên kết với Trường Đại học Tôn Đức Thắng.\nCử nhân\nKỹ sư\nToàn thời gian: 4 năm\nToàn thời gian: 5 năm\nXem thông tin chi tiết về chương trình đào tạo\nXem thông tin chi tiết về chuẩn đầu ra\nKết quả quá trình học tập THPT\nKết quả bài thi ĐGNL năm 2025 của ĐHQG TP. HCM\nTổ hợp: Đang cập nhật\nĐiểm trúng tuyển 2024 (thang 40):23,00\nTháng 9, năm 2025\nKhoảng 53 đến 54 triệu đồng/năm (năm 2024)", "content": {"Bằng cấp": "Cử nhân Kỹ sư", "Thời gian đào tạo": "Toàn thời gian: 4 năm Toàn thời gian: 5 năm", "Chương trình đào tạo": "Xem thông tin chi tiết về chương trình đào tạo", "Chuẩn đầu ra": "Xem thông tin chi tiết về chuẩn đầu ra", "Phương thức xét tuyển riêng": "Kết quả quá trình học tập THPT Kết quả bài thi ĐGNL năm 2025 của ĐHQG TP. HCM", "Xét tuyển theo điểm thi THPT": "Tổ hợp: Đang cập nhật Điểm trúng tuyển 2024 (thang 40):23,00", "Khai giảng": "Tháng 9, năm 2025", "Học phí": "Khoảng 53 đến 54 triệu đồng/năm (năm 2024)"}, "name": "Kỹ thuật điện"}, {"tab": "Liên kết quốc tế", "major_code": "K7520201", "description": "Cử nhân (song bằng)\n4 năm (2,5 năm đầu học tại TDTU, 1,5 năm sau học tại Trường liên kết)\nXem thông tin chi tiết về chương trình đào tạo\nXem thông tin chi tiết về chuẩn đầu ra\nKết quả quá trình học tập THPT\nKết quả bài thi ĐGNL năm 2025 của ĐHQG TP. HCM\nTổ hợp: Đang cập nhật\nĐiểm trúng tuyển 2024 (thang 40):24,00\nTháng 9, năm 2025\nGiai đoạn 1: khoảng 78 đến 80 triệu đồng/năm (năm 2024)", "content": {"Bằng cấp": "Cử nhân (song bằng)", "Thời gian đào tạo": "4 năm (2,5 năm đầu học tại TDTU, 1,5 năm sau học tại Trường liên kết)", "Chương trình đào tạo": "Xem thông tin chi tiết về chương trình đào tạo", "Chuẩn đầu ra": "Xem thông tin chi tiết về chuẩn đầu ra", "Phương thức xét tuyển riêng": "Kết quả quá trình học tập THPT Kết quả bài thi ĐGNL năm 2025 của ĐHQG TP. HCM", "Xét tuyển theo điểm thi THPT": "Tổ hợp: Đang cập nhật Điểm trúng tuyển 2024 (thang 40):24,00", "Khai giảng": "Tháng 9, năm 2025", "Học phí": "Giai đoạn 1: khoảng 78 đến 80 triệu đồng/năm (năm 2024)"}, "name": "Kỹ thuật điện - điện tử liên kết Đại học khoa học ứng dụng Saxion, Hà Lan"}], "images": ["https://admission.tdtu.edu.vn", "https://admission.tdtu.edu.vn/sites/admission23/files/Tuyen-sinh/Dai-hoc/Nganh/KTD/1.jpg", "https://admission.tdtu.edu.vn/sites/admission23/files/Tuyen-sinh/Dai-hoc/Nganh/KTD/2.jpg", "https://admission.tdtu.edu.vn/sites/admission23/files/Tuyen-sinh/Dai-hoc/Nganh/KTD/3.jpg"]}
{"name": "Kỹ thuật điều khiển và tự động hóa", "description": "Kỹ thuật điều khiển và tự động hóa không chỉ là trụ cột của các ngành sản xuất hiện đại mà còn là mắt xích quan trọng trong các xu hướng công nghệ toàn cầu như trí tuệ nhân tạo (AI), Internet vạn vật (IoT), chuyển đổi số, kinh tế tuần hoàn và các giải pháp giảm phát thải carbon. Đây là ngành học đi đầu trong việc thiết kế và triển khai các hệ thống tự động thông minh, giúp tối ưu hóa hiệu suất, tiết kiệm tài nguyên, và giảm thiểu tác động đến môi trường.\nSinh viên ngành Kỹ thuật điều khiển và tự động hoá sau khi ra trường có các cơ hội làm việc ở các vị trí như kỹ sư thiết kế, vận hành và bảo trì hệ thống thông minh tại các nhà máy tự động hóa, trung tâm điều khiển năng lượng tái tạo, và dây chuyền sản xuất công nghệ cao, chuyên gia tư vấn chuyển đổi số và giải pháp công nghệ xanh, nhà phát triển công nghệ AI và IoT. Ngoài ra, sinh viên còn có thể trở thành những nhà nghiên cứu và giảng dạy chuyên sâu, đóng góp vào sự phát triển công nghệ tự động hóa trong nước và quốc tế.", "reasons": ["Chương trình đào tạo được chứng nhận đạt chuẩn quốc tế ASIIN", "Chất lượng đào tạo chuẩn quốc tế với mức học phí phù hợp", "100% sinh viên ra trường có việc làm trong vòng 12 tháng kể từ khi tốt nghiệp"], "programs": [{"tab": "Tiêu chuẩn", "major_code": "7520216", "description": "Ngành Kỹ thuật điều khiển và tự động hóa của TDTU đạt chứng nhận kiểm định quốc tế ASIIN, có hiệu lực từ 30/9/2024 đến 30/9/2029, khẳng định chất lượng đào tạo theo các tiêu chuẩn hàng đầu thế giới. Chương trình được đối sánh với các chương trình đại học uy tín toàn cầu, đảm bảo sinh viên được tiếp cận nền giáo dục hiện đại, hội nhập quốc tế. Chương trình cung cấp nền tảng vững chắc về lý thuyết và thực hành trong các lĩnh vực như lý thuyết mạch điện - điện tử, kỹ thuật đo lường điện - điện tử, kỹ thuật mô phỏng bằng phần mềm và phân tích dữ liệu, các phương pháp điều khiển kinh điển và hiện đại, mạng truyền thông công nghiệp, công nghệ Internet kết nối vạn vật (IoT), công nghệ robot, và tự động hóa quá trình sản xuất. Ngoài ra, sinh viên được trang bị kiến thức thực tế thông qua việc thực hiện các đồ án môn học, đồ án tốt nghiệp với đề tài được giao nhằm giải quyết các vấn đề cấp bách như chuyển đổi số trong công nghiệp, ứng dụng IoT trong xe tự hành, nông nghiệp thông minh, và nhà thông minh, năng lượng tái tạo và các hệ thống tự động hóa thân thiện với môi trường.\nVới môi trường học tập hiện đại cùng với chương trình kết hợp chặt chẽ giữa lý thuyết và thực hành trên các trang thiết bị tiên tiến, phần lớn được tài trợ bởi các tập đoàn lớn như Siemens, ABB, Mitsubishi, Endress+Hauser. Sinh viên sẽ tham gia các đồ án môn học và đồ án tốt nghiệp, tiếp cận các dự án thực tế và công nghệ mới nhất. Ngoài chuyên môn, sinh viên còn được tham gia nhiều hoạt động ngoại khóa khác nhau. Được tham quan thực tế, kiến tập và thực tập tại các doanh nghiệp hàng đầu trong lĩnh vực tự động hóa. Học tập dưới sự hướng dẫn của giảng viên giàu kinh nghiệm và các chuyên gia tay nghề cao, thực hiện các dự án nghiên cứu khoa học ngay tại doanh nghiệp.\nSau khi tốt nghiệp, sinh viên sẽ được trang bị đầy đủ các kỹ năng chuyên môn để vận hành, bảo trì, sửa chữa các hệ thống tự động hóa và dây chuyền sản xuất hiện đại, thiết kế giao diện giám sát, lập trình điều khiển, và xây dựng hệ thống quản lý cơ sở dữ liệu cho nhà máy, xí nghiệp, cải tiến, nâng cấp hệ thống tự động hóa và tham gia lập kế hoạch kỹ thuật, tài chính cho các dự án, làm việc trong các lĩnh vực mới như quản lý năng lượng tái tạo, phát triển các giải pháp IoT, và chuyển đổi số.\nCử nhân\nKỹ sư\nToàn thời gian: 4 năm\nToàn thời gian: 5 năm\nXem thông tin chi tiết về chương trình đào tạo\nXem thông tin chi tiết về chuẩn đầu ra\nKết quả quá trình học tập THPT\nKết quả bài thi ĐGNL năm 2025 của ĐHQG TP. HCM\nTổ hợp: Đang cập nhật\nĐiểm trúng tuyển 2024 (thang 40):31,85\nTháng 9, năm 2025\nKhoảng 31 đến 32 triệu đồng/năm (năm 2024)", "content": {"Bằng cấp": "Cử nhân Kỹ sư", "Thời gian đào tạo": "Toàn thời gian: 4 năm Toàn thời gian: 5 năm", "Chương trình đào tạo": "Xem thông tin chi tiết về chương trình đào tạo", "Chuẩn đầu ra": "Xem thông tin chi tiết về chuẩn đầu ra", "Phương thức xét tuyển riêng": "Kết quả quá trình học tập THPT Kết quả bài thi ĐGNL năm 2025 của ĐHQG TP. HCM", "Xét tuyển theo điểm thi THPT": "Tổ hợp: Đang cập nhật Điểm trúng tuyển 2024 (thang 40):31,85", "Khai giảng": "Tháng 9, năm 2025", "Học phí": "Khoảng 31 đến 32 triệu đồng/năm (năm 2024)"}, "name": "Kỹ thuật điều khiển và tự động hóa"}, {"tab": "Tiên tiến", "major_code": "F7520216", "description": "Chương trình tiên tiến ngành Kỹ thuật điều khiển và tự động hóa đạt chứng nhận kiểm định quốc tế ASIIN (có hiệu lực từ 30/9/2024 đến 30/9/2029), khẳng định chất lượng đào tạo đạt tiêu chuẩn quốc tế, sánh ngang với các chương trình uy tín toàn cầu.\nVới hơn 50% các môn chuyên ngành được giảng dạy bằng tiếng Anh, giúp sinh viên nâng cao năng lực ngoại ngữ, sẵn sàng làm việc trong môi trường quốc tế. Sinh viên có cơ hội thực hiện đồ án tốt nghiệp theo các đề tài do doanh nghiệp đặt hàng, trực tiếp giải quyết các vấn đề thực tiễn và áp dụng công nghệ hiện đại. Được tham gia các khóa học trao đổi ngắn hạn và thực hiện đồ án tốt nghiệp tại các trường đại học hàng đầu thế giới như Anh, Hàn Quốc, Cộng hòa Czech…, mở rộng cơ hội học tập, giao lưu văn hóa và cập nhật những xu hướng kỹ thuật mới nhất.\nChương trình kết hợp chặt chẽ giữa lý thuyết và thực hành, với sự đồng hành của các giảng viên giàu kinh nghiệm và chuyên gia hàng đầu từ các doanh nghiệp lớn trong lĩnh vực tự động hóa. Sinh viên được tham gia vào các chuyến tham quan thực tế, kiến tập và thực tập tại doanh nghiệp, làm việc với các chuyên gia đến từ các tập đoàn quốc tế, sớm tiếp cận môi trường làm việc chuyên nghiệp và văn hóa doanh nghiệp giúp định hướng nghề nghiệp và mở rộng mạng lưới quan hệ. Tham gia vào các dự án nghiên cứu khoa học và đồ án môn học liên quan đến các xu hướng công nghệ như chuyển đổi số, IoT, năng lượng tái tạo, và các giải pháp tự động hóa thông minh.\nVới nội dung đào tạo hiện đại, theo sát xu hướng công nghệ, sinh viên được trang bị kiến thức và kỹ năng tiên tiến, đề tài của các đồ án môn học và đồ án tốt nghiệp bám trong các lĩnh vực như: IoT và trí tuệ nhân tạo (AI) trong điều khiển và giám sát hệ thống, chuyển đổi số và tối ưu hóa quy trình sản xuất, công nghệ robot và ứng dụng trong công nghiệp thông minh, năng lượng tái tạo và phát triển bền vững, góp phần giảm phát thải carbon và xây dựng kinh tế tuần hoàn.\nSinh viên tốt nghiệp chương trình tiên tiến có thể đảm nhận các vai trò như vận hành, bảo trì, và cải tiến hệ thống tự động hóa, dây chuyền sản xuất trong công nghiệp, thiết kế giao diện giám sát, lập trình điều khiển, và xây dựng hệ thống cơ sở dữ liệu cho nhà máy, làm việc trong các dự án chuyển đổi số, ứng dụng IoT và AI, phát triển năng lượng tái tạo,tham gia vào các chương trình nghiên cứu và học bổng sau đại học tại các trường đại học danh tiếng trên thế giới.\nCử nhân\nKỹ sư\nToàn thời gian: 4 năm\nToàn thời gian: 5 năm\nXem thông tin chi tiết về chương trình đào tạo\nXem thông tin chi tiết về chuẩn đầu ra\nKết quả quá trình học tập THPT\nKết quả bài thi ĐGNL năm 2025 của ĐHQG TP. HCM\nTổ hợp: Đang cập nhật\nĐiểm trúng tuyển 2024 (thang 40):26,70\nTháng 9, năm 2025\nKhoảng 53 đến 54 triệu đồng/năm (năm 2024)", "content": {"Bằng cấp": "Cử nhân Kỹ sư", "Thời gian đào tạo": "Toàn thời gian: 4 năm Toàn thời gian: 5 năm", "Chương trình đào tạo": "Xem thông tin chi tiết về chương trình đào tạo", "Chuẩn đầu ra": "Xem thông tin chi tiết về chuẩn đầu ra", "Phương thức xét tuyển riêng": "Kết quả quá trình học tập THPT Kết quả bài thi ĐGNL năm 2025 của ĐHQG TP. HCM", "Xét tuyển theo điểm thi THPT": "Tổ hợp: Đang cập nhật Điểm trúng tuyển 2024 (thang 40):26,70", "Khai giảng": "Tháng 9, năm 2025", "Học phí": "Khoảng 53 đến 54 triệu đồng/năm (năm 2024)"}, "name": "Kỹ thuật điều khiển và tự động hóa"}, {"tab": "Đại học bằng tiếng Anh", "major_code": "FA7520216", "description": "Chương trình đại học Tiếng Anh ngành Kỹ thuật Điều khiển và Tự động hóa được thiết kế nhằm trang bị cho sinh viên nền tảng kiến thức chuyên môn và kỹ năng ngoại ngữ vượt trội, đáp ứng yêu cầu ngày càng cao của thị trường lao động quốc tế. Chương trình đã đạt chứng nhận kiểm định ASIIN (hiệu lực từ 30/9/2024 đến 30/9/2029), khẳng định chất lượng đào tạo đạt tiêu chuẩn quốc tế.\nToàn bộ các môn chuyên ngành được giảng dạy bằng tiếng Anh, bởi đội ngũ giảng viên là các giáo sư, tiến sĩ, và chuyên gia giàu kinh nghiệm, tốt nghiệp từ các trường đại học danh tiếng trên thế giới.\nSinh viên có cơ hội tham gia các chương trình trao đổi quốc tế, thực hiện đồ án tốt nghiệp tại các trường đại học uy tín như Anh, Hàn Quốc, Cộng hòa Czech, Đài Loan, Hà Lan… để học hỏi, giao lưu văn hóa và cập nhật các xu hướng công nghệ mới nhất.\nVới môi trường học tập hiện đại và cơ hội thực tiễn, sinh viên được trải nghiệm một môi trường học tập năng động, kết hợp lý thuyết với thực tiễn thông qua các buổi workshop, hội thảo học thuật và ngày hội việc làm, với sự tham gia của các chuyên gia từ các tập đoàn công nghệ hàng đầu trong và ngoài nước như Siemens, ABB, Mitsubishi… Ngoài ra, sinh viên còn được tham gia các dự án nghiên cứu khoa học và thực tập tại doanh nghiệp, giúp sinh viên áp dụng kiến thức vào thực tế, giải quyết các vấn đề kỹ thuật liên quan đến IoT, AI, năng lượng tái tạo, chuyển đổi số, và tự động hóa thông minh. Với sự hướng dẫn chuyên môn từ các chuyên gia trong ngành, tạo điều kiện cho sinh viên phát triển toàn diện cả về kiến thức lẫn kỹ năng làm việc nhóm, quản lý dự án, và giải quyết vấn đề.\nChương trình học bám sát các xu hướng công nghệ tiên tiến trong đào tạo thông qua các đề tài của các đồ án môn học và đồ án tốt nghiệp bám theo xu hướng các lĩnh vực công nghệ mới nhất, bao gồm Trí tuệ nhân tạo (AI) và Internet vạn vật (IoT) trong giám sát và điều khiển hệ thống tự động, năng lượng tái tạo, giải pháp giảm phát thải carbon, và ứng dụng kinh tế tuần hoàn, tự động hóa thông minh trong sản xuất và vận hành dây chuyền công nghiệp.\nSau khi tốt nghiệp, sinh viên chương trình Hội nhập Quốc tế có thể đảm nhận các vị trí như: Kỹ sư thiết kế, vận hành, bảo trì và tối ưu hóa hệ thống tự động hóa tại các nhà máy, xí nghiệp trong nước và quốc tế. Chuyên gia tư vấn, quản lý dự án chuyển đổi số và ứng dụng công nghệ mới.Nhân sự tại các tập đoàn đa quốc gia hoặc các doanh nghiệp nước ngoài hoạt động tại Việt Nam hoặc ứng viên tiềm năng cho các học bổng sau đại học tại các trường danh tiếng trên toàn cầu.\nCử nhân\nKỹ sư\nToàn thời gian: 4 năm\nToàn thời gian: 5 năm\nXem thông tin chi tiết về chương trình đào tạo\nXem thông tin chi tiết về chuẩn đầu ra\nKết quả quá trình học tập THPT\nKết quả bài thi ĐGNL năm 2025 của ĐHQG TP. HCM\nTổ hợp: Đang cập nhật\nĐiểm trúng tuyển 2024 (thang 40):24,00\nTháng 9, năm 2025\nKhoảng 81 đến 83 triệu đồng/năm (năm 2024)", "content": {"Bằng cấp": "Cử nhân Kỹ sư", "Thời gian đào tạo": "Toàn thời gian: 4 năm Toàn thời gian: 5 năm", "Chương trình đào tạo": "Xem thông tin chi tiết về chương trình đào tạo", "Chuẩn đầu ra": "Xem thông tin chi tiết về chuẩn đầu ra", "Phương thức xét tuyển riêng": "Kết quả quá trình học tập THPT Kết quả bài thi ĐGNL năm 2025 của ĐHQG TP. HCM", "Xét tuyển theo điểm thi THPT": "Tổ hợp: Đang cập nhật Điểm trúng tuyển 2024 (thang 40):24,00", "Khai giảng": "Tháng 9, năm 2025", "Học phí": "Khoảng 81 đến 83 triệu đồng/năm (năm 2024)"}, "name": "Kỹ thuật điều khiển và tự động hóa"}], "images": ["https://admission.tdtu.edu.vn", "https://admission.tdtu.edu.vn/sites/admission23/files/Tuyen-sinh/Dai-hoc/Nganh/KTDK-TDH/1.jpg", "https://admission.tdtu.edu.vn/sites/admission23/files/Tuyen-sinh/Dai-hoc/Nganh/KTDK-TDH/2.JPG", "https://admission.tdtu.edu.vn/sites/admission23/files/Tuyen-sinh/Dai-hoc/Nganh/KTDK-TDH/3.jpg"]}
{"name": "Kỹ thuật hóa học", "description": "Kỹ thuật hoá học là ngành học giao thoa giữa khoa học và kỹ thuật, ứng dụng kiến thức về hoá lý, vật liệu vô cơ, vật liệu hữu cơ, tách chiết hợp chất,… vào sản xuất để phát triển và vận hành các quy trình công nghệ có liên quan đến hóa chất và công nghệ.\nSinh viên sau khi tốt nghiệp ngành Kỹ thuật hoá học có thể đảm nhiệm các vị trí như: chuyên viên vận hành và quản lý sản xuất; chuyên viên nghiên cứu phát triển sản phẩm; chuyên viên tư vấn quản lí và chuyển giao công nghệ; nhân viên kinh doanh hóa chất; nhân viên kiểm soát chất lượng sản phẩm tại các công ty, nhà máy sản xuất dược phẩm, mỹ phẩm, hương liệu, phân bón, vật liệu xây dựng, gốm sứ silicat, vật liệu polymer, vật liệu nano, vật liệu bán dẫn, hóa chất, cao su, vải, thuốc nhuộm, chất tẩy rửa,… Ngoài ra, kỹ sư Kỹ thuật hoá học còn có thể tham gia nghiên cứu, giảng dạy tại các trung tâm, viện nghiên cứu, các trường đại học cao đẳng hoặc tiếp tục học lên cao hơn ở các chương trình sau đại học.", "reasons": ["Đội ngũ giảng viên giàu kinh nghiệm", "Số tiết học thực tế chiếm gần 50% chương trình đào tạo", "100% sinh viên ra trường có việc làm trong vòng 12 tháng kể từ khi tốt nghiệp"], "programs": [{"tab": "Tiêu chuẩn", "major_code": "7520301", "description": "Sinh viên được trang bị kiến thức về hóa lý, vật liệu vô cơ, vật liệu hữu cơ, tách chiết hợp chất, … để ứng dụng thực tế vào sản xuất nhằm phát triển và vận hành các quy trình công nghệ có liên quan đến hóa chất và công nghệ.\nNgoài kiến thức chuyên môn được trang bị theo chương trình đào tạo quốc tế, sinh viên còn được thực hành trong các trung tâm thí nghiệm với thiết bị hiện đại và liên tục cập nhật. Ngoài ra, Nhà trường còn chú trọng đầu tư xây dựng các phòng thí nghiệm hóa phân tích, hóa vô cơ, hóa hữu cơ và các phòng thí nghiệm chuyên đề về nhuộm in, các hợp chất tự nhiên, cao su, polymer, gốm sứ, … nhằm phục vụ nhu cầu học tập và nghiên cứu của sinh viên.\nSố tiết học thực hành chiếm khoảng 50% trong chương trình đào tạo, giúp sinh viên được trải nghiệm thực tế, góp phần nâng cao tay nghề bên cạnh việc tiếp thu kiến thức chuyên môn. Trong suốt quá trình học, sinh viên được hướng dẫn ôn tập và ứng dụng kiến thức đã học vào thực tiễn thông qua mạng lưới kết nối doanh nghiệp dưới hình thức tham quan, trải nghiệm thực tế quy trình sản xuất, quá trình vận hành thiết bị, … qua đó nâng cao khả năng tư duy logic để phân tích tình huống, lập luận và giải quyết vấn đề kỹ thuật một cách thực tiễn và tối ưu. Trong một số môn học chuyên sâu, giảng viên sẽ đồng hành cùng với các chuyên gia dày dặn kinh nghiệm đến từ doanh nghiệp trực tiếp giảng dạy và hướng dẫn sinh viên thực hiện các dự án nghiên cứu, từ đó nâng cao khả năng thực hành nghề nghiệp cho sinh viên ngay khi còn ngồi trên ghế Nhà trường.\nHiểu được nhu cầu của xã hội về nguồn nhân lực có tay nghề cao, Nhà trường luôn tạo điều kiện để sinh viên tham gia vào các dự án nghiên cứu khoa học và các cuộc thi học thuật thuộc lĩnh vực chuyên môn, giúp sinh viên trau dồi và phát huy năng lực tìm tòi, sáng tạo và vận dụng thuần thục các kỹ năng đã được trang bị trong quá trình học tập.\nCử nhân\nKỹ sư\nToàn thời gian: 4 năm\nToàn thời gian: 5 năm\nXem thông tin chi tiết về chương trình đào tạo\nXem thông tin chi tiết về chuẩn đầu ra\nKết quả quá trình học tập THPT\nKết quả bài thi ĐGNL năm 2025 của ĐHQG TP. HCM\nTổ hợp: Đang cập nhật\nĐiểm trúng tuyển 2024 (thang 40):27,80\nTháng 9, năm 2025\nKhoảng 31 đến 32 triệu đồng (năm 2024)", "content": {"Bằng cấp": "Cử nhân Kỹ sư", "Thời gian đào tạo": "Toàn thời gian: 4 năm Toàn thời gian: 5 năm", "Chương trình đào tạo": "Xem thông tin chi tiết về chương trình đào tạo", "Chuẩn đầu ra": "Xem thông tin chi tiết về chuẩn đầu ra", "Phương thức xét tuyển riêng": "Kết quả quá trình học tập THPT Kết quả bài thi ĐGNL năm 2025 của ĐHQG TP. HCM", "Xét tuyển theo điểm thi THPT": "Tổ hợp: Đang cập nhật Điểm trúng tuyển 2024 (thang 40):27,80", "Khai giảng": "Tháng 9, năm 2025", "Học phí": "Khoảng 31 đến 32 triệu đồng (năm 2024)"}, "name": "Kỹ thuật hóa học"}, {"tab": "Tiên tiến", "major_code": "F7520301", "description": "Sinh viên được trang bị các kiến thức về hoá lý, vật liệu vô cơ, vật liệu hữu cơ, tách chiết hợp chất... Lý thuyết chuyên ngành hiện đại giúp sinh viên tốt nghiệp có thể đáp ứng các yêu cầu công việc tại Việt Nam, cũng như tại các nước tiên tiến; hoặc học tập các bậc học cao hơn ở nước ngoài.\nTrong quá trình học tập, sinh viên được thực hành tại phòng thí nghiệm, tham gia các đợt học tập ngoài thực địa, tại doanh nghiệp; được tham gia cùng thực hiện các đề tài, dự án cùng với giảng viên và doanh nghiệp. Do đặc điểm chương trình được giảng dạy bằng tiếng Anh ngay từ năm đầu tiên, sinh viên có nhiều cơ hội tiếp cận, giao lưu  và được tham gia tất cả các sự kiện quốc tế diễn ra tại Khoa, Trường; tham gia học tập cùng với các đoàn sinh viên quốc tế cùng nhiều hoạt động học thuật khác, giúp sinh viên nâng cao kiến thức, năng lực ngoại ngữ và kỹ năng thực hành chuyên môn.\nCử nhân\nKỹ sư\nToàn thời gian: 4 năm\nToàn thời gian: 5 năm\nXem thông tin chi tiết về chương trình đào tạo\nXem thông tin chi tiết về chuẩn đầu ra\nTổ hợp: Toán, Anh, Hóa*2\nKQ ĐGNL của ĐHQG TP. HCM\nƯu tiên xét tuyển theo TDTU\nTổ hợp: A00; B00; D07\nĐiểm trúng tuyển 2024 (thang 40):23,00\nTháng 9, năm 2025\nKhoảng 53 đến 54 triệu đồng/năm (năm 2024)", "content": {"Bằng cấp": "Cử nhân Kỹ sư", "Thời gian đào tạo": "Toàn thời gian: 4 năm Toàn thời gian: 5 năm", "Chương trình đào tạo": "Xem thông tin chi tiết về chương trình đào tạo", "Chuẩn đầu ra": "Xem thông tin chi tiết về chuẩn đầu ra", "Phương thức xét tuyển riêng": "Tổ hợp: Toán, Anh, Hóa*2 KQ ĐGNL của ĐHQG TP. HCM Ưu tiên xét tuyển theo TDTU", "Xét tuyển theo điểm thi THPT": "Tổ hợp: A00; B00; D07 Điểm trúng tuyển 2024 (thang 40):23,00", "Khai giảng": "Tháng 9, năm 2025", "Học phí": "Khoảng 53 đến 54 triệu đồng/năm (năm 2024)"}, "name": "Kỹ thuật hóa học"}], "images": ["https://admission.tdtu.edu.vn/sites/admission23/files/Tuyen-sinh/Dai-hoc/Nganh/Ky-thuat-hoa-hoc/1.jpg", "https://admission.tdtu.edu.vn/sites/admission23/files/Tuyen-sinh/Dai-hoc/Nganh/Ky-thuat-hoa-hoc/2.JPG", "https://admission.tdtu.edu.vn/sites/admission23/files/Tuyen-sinh/Dai-hoc/Nganh/Ky-thuat-hoa-hoc/3.JPG"]}
{"name": "Kỹ thuật phần mềm", "description": "Kỹ thuật phần mềm là ngành ứng dụng kiến thức về lập trình, thiết kế phần mềm, quy trình vận hành và phát triển phần mềm, phân tích yêu cầu hệ thống, trí tuệ nhân tạo… để tạo ra sản phẩm phần mềm đạt chất lượng cao, đáp ứng xu hướng phát triển mạnh mẽ của công nghệ và nhu cầu nghiệp vụ cụ thể trong nền sản xuất của xã hội.\n\nCử nhân Kỹ thuật phần mềm có thể tự tin khởi nghiệp hoặc ứng tuyển vào các doanh nghiệp trong và ngoài nước, các cơ quan, ban ngành ở những vị trí: Chuyên viên phân tích yêu cầu (BA), Kiến trúc sư phần mềm (SA), Lập trình viên (Developer), Chuyên viên thử nghiệm phần mềm (Tester), chuyên viên cầu nối (BrSE), chuyên viên nghiên cứu và phát triển ứng dụng (R&D), giảng viên giảng dạy các môn học về ngành kỹ thuật phần mềm hoặc có thể tiếp tục nghiên cứu và học lên cao học.", "reasons": ["Liên tục cập nhật xu hướng", "Số tiết học thực tế chiếm gần 50% chương trình đào tạo", "100% sinh viên ra trường có việc làm trong vòng 12 tháng kể từ khi tốt nghiệp"], "programs": [{"tab": "Tiêu chuẩn", "major_code": "7480103", "description": "Sinh viên sẽ ngành Kỹ thuật phần mềm được đào tạo từ những kiến thức cơ bản đến những xu hướng hiện đại như: phát triển ứng dụng trên nền tảng số và thiết bị thông minh; thiết kế giao diện người dùng trực quan, thân thiện; phân tích hệ thống; đảm bảo an toàn thông tin; và quản lý dự án công nghệ thông tin một cách hiệu quả.\nChương trình chú trọng cân bằng giữa lý thuyết và thực hành, với các buổi học tại phòng lab hiện đại, liên tục cập nhật công nghệ mới nhất. Sinh viên không chỉ nắm vững kiến thức mà còn có cơ hội áp dụng chúng vào thực tế thông qua các dự án thực hành. Các học phần được thiết kế theo lộ trình tăng dần mức độ, giúp sinh viên từng bước làm chủ quy trình phát triển phần mềm từ thu thập yêu cầu, phân tích, thiết kế, lập trình, kiểm thử, cho đến vận hành và bảo trì hệ thống.\nSau khi tốt nghiệp, sinh viên ngành Kỹ thuật Phần mềm sẽ sở hữu những kỹ năng toàn diện như: phân tích, thiết kế, lập trình và kiểm thử phần mềm; quản lý và triển khai dự án công nghệ thông tin; sử dụng thành thạo các công cụ phần mềm để phân tích dữ liệu doanh nghiệp; và tư vấn giải pháp xây dựng hệ thống phần mềm hiện đại. Chương trình không chỉ trang bị kiến thức mà còn mở ra cơ hội nghề nghiệp rộng lớn, giúp sinh viên tự tin bước vào thị trường lao động đầy tiềm năng.\nCử nhân\nToàn thời gian: 4 năm\nXem thông tin chi tiết về chương trình đào tạo\nXem thông tin chi tiết về chuẩn đầu ra\nKết quả quá trình học tập THPT\nKết quả bài thi ĐGNL năm 2025 của ĐHQG TP. HCM\nTổ hợp: Đang cập nhật\nĐiểm trúng tuyển 2024 (thang 40):33,30\nTháng 9, năm 2025\nKhoảng 31 đến 32 triệu đồng/năm (năm 2024)", "content": {"Bằng cấp": "Cử nhân", "Thời gian đào tạo": "Toàn thời gian: 4 năm", "Chương trình đào tạo": "Xem thông tin chi tiết về chương trình đào tạo", "Chuẩn đầu ra": "Xem thông tin chi tiết về chuẩn đầu ra", "Phương thức xét tuyển riêng": "Kết quả quá trình học tập THPT Kết quả bài thi ĐGNL năm 2025 của ĐHQG TP. HCM", "Xét tuyển theo điểm thi THPT": "Tổ hợp: Đang cập nhật Điểm trúng tuyển 2024 (thang 40):33,30", "Khai giảng": "Tháng 9, năm 2025", "Học phí": "Khoảng 31 đến 32 triệu đồng/năm (năm 2024)"}, "name": "Kỹ thuật phần mềm"}, {"tab": "Tiên tiến", "major_code": "F7480103", "description": "Chương trình tiên tiến ngành Kỹ thuật phần mềm cung cấp kiến thức chuyên môn và chuyên ngành và rèn luyện kỹ năng thực hành, phát triển kỹ năng mềm, và tạo cơ hội thực tập thực tế tại các doanh nghiệp. Sinh viên sẽ được trang bị kiến thức sâu rộng về công nghiệp phần mềm, bao gồm:Quy trình phát triển phần mềm chuyên nghiệp;Kỹ năng sử dụng các công cụ hỗ trợ phát triển phần mềm hiệu quả;Kiến thức toàn diện về từng giai đoạn trong dự án phần mềm, từ thu thập yêu cầu, phân tích, thiết kế, lập trình, kiểm thử, đến vận hành và bảo trì.\nChương trình tiên tiến ngành Kỹ thuật phần mềm mang những đặc điểm nổi bật, tạo điều kiện tốt nhất để sinh viên phát triển toàn diện và hội nhập quốc tế:Đội ngũ giảng viên giàu kinh nghiệm: Các môn học được đảm nhiệm bởi những giảng viên giỏi chuyên môn, giàu kinh nghiệm giảng dạy, và có năng lực nghiên cứu khoa học;Tăng cường năng lực ngoại ngữ: 50% các môn học cơ sở ngành và chuyên ngành được giảng dạy hoàn toàn bằng tiếng Anh, giúp sinh viên nâng cao khả năng ngoại ngữ và sẵn sàng làm việc trong môi trường quốc tế;Hợp tác với doanh nghiệp: Sinh viên được tham gia các khóa đào tạo chuyên môn thực tế do các doanh nghiệp tổ chức và cấp chứng chỉ, đảm bảo năng lực thực tiễn ngay từ khi còn trên ghế nhà trường;Cơ hội học tập quốc tế: Những sinh viên có đủ điều kiện tài chính và học thuật có thể đăng ký tham gia chương trình trao đổi một học kỳ hoặc thực tập tốt nghiệp tại các trường đại học ở nước ngoài, như tại Đài Loan hoặc Cộng hòa Séc.\nNhững đặc điểm này không chỉ giúp sinh viên nắm vững kiến thức chuyên môn mà còn mở rộng cơ hội giao lưu, học hỏi, và chuẩn bị hành trang để cạnh tranh trên thị trường lao động toàn cầu.\nCử nhân\nToàn thời gian: 4 năm\nXem thông tin chi tiết về chương trình đào tạo\nXem thông tin chi tiết về chuẩn đầu ra\nKết quả quá trình học tập THPT\nKết quả bài thi ĐGNL năm 2025 của ĐHQG TP. HCM\nTổ hợp: Đang cập nhật\nĐiểm trúng tuyển 2024 (thang 40):33,90\nTháng 9, năm 2025\nKhoảng 53 đến 54 triệu đồng/năm (năm 2024)", "content": {"Bằng cấp": "Cử nhân", "Thời gian đào tạo": "Toàn thời gian: 4 năm", "Chương trình đào tạo": "Xem thông tin chi tiết về chương trình đào tạo", "Chuẩn đầu ra": "Xem thông tin chi tiết về chuẩn đầu ra", "Phương thức xét tuyển riêng": "Kết quả quá trình học tập THPT Kết quả bài thi ĐGNL năm 2025 của ĐHQG TP. HCM", "Xét tuyển theo điểm thi THPT": "Tổ hợp: Đang cập nhật Điểm trúng tuyển 2024 (thang 40):33,90", "Khai giảng": "Tháng 9, năm 2025", "Học phí": "Khoảng 53 đến 54 triệu đồng/năm (năm 2024)"}, "name": "Kỹ thuật phần mềm"}, {"tab": "Đại học bằng tiếng Anh", "major_code": "FA7480103", "description": "Chương trình đào tạo đại học bằng tiếng Anh ngành Kỹ thuật phần mềm được xây dựng nhằm đào tạo ra các kỹ sư phần mềm không chỉ có kiến thức sâu rộng về các lĩnh vực chuyên môn mà còn rèn luyện khả năng nghiên cứu, tìm hiểu tài liệu, và làm việc bằng tiếng Anh một cách chuyên nghiệp và hiệu quả.\nĐặc điểm nổi bật của chương trình- Môi trường học tập hiện đại và chuyên nghiệp: Quy mô lớp học nhỏ (20-25 sinh viên/lớp), tạo điều kiện để giảng viên theo sát từng cá nhân, tăng cường tương tác và hiệu quả học tập. Cơ sở vật chất hiện đại, tiện nghi, cùng môi trường học tập năng động, thúc đẩy sự sáng tạo và phát triển các kỹ năng chuyên môn lẫn kỹ năng mềm. Sinh viên được hỗ trợ tối đa từ trợ giảng, tổ tư vấn học đường, và giảng viên cố vấn, đảm bảo định hướng học tập rõ ràng và hiệu quả.- Đội ngũ giảng viên giàu kinh nghiệm:Các môn học được giảng dạy bởi đội ngũ giảng viên trong và ngoài nước có trình độ chuyên môn cao, kinh nghiệm thực tiễn, và kỹ năng giảng dạy xuất sắc. Chất lượng đào tạo được giám sát chặt chẽ nhằm đáp ứng các tiêu chuẩn quốc tế và nhu cầu của thị trường lao động.- Đào tạo chuyên sâu bằng tiếng Anh: 100% các môn học cơ sở ngành và chuyên ngành được giảng dạy bằng tiếng Anh, giúp sinh viên nâng cao khả năng ngoại ngữ, tư duy logic, và sẵn sàng làm việc trong môi trường toàn cầu.- Kết nối doanh nghiệp và hội nhập quốc tế: Sinh viên có cơ hội tham gia các khóa đào tạo thực tế tại doanh nghiệp và nhận chứng chỉ chuyên môn, tăng cường kỹ năng thực hành và năng lực đáp ứng công việc. Chương trình mang đến cơ hội học tập và thực tập tại các trường đại học quốc tế ví dụ như Đài Loan, Cộng hòa Séc.Chương trình không chỉ tập trung cung cấp kiến thức chuyên môn sâu rộng về các lĩnh vực của Kỹ thuật phần mềm, từ phát triển ứng dụng, thiết kế hệ thống, kiểm thử, đến bảo trì phần mềm, mà còn rèn luyện kỹ năng ngoại ngữ và kỹ năng làm việc thực tế, giúp sinh viên sẵn sàng đáp ứng mọi thách thức trong môi trường làm việc hiện đại và hội nhập toàn cầu.\nCử nhân\nToàn thời gian: 4 năm\nXem thông tin chi tiết về chương trình đào tạo\nXem thông tin chi tiết về chuẩn đầu ra\nKết quả quá trình học tập THPT\nKết quả bài thi ĐGNL năm 2025 của ĐHQG TP. HCM\nTổ hợp: Đang cập nhật\nĐiểm trúng tuyển 2024 (thang 40):28,00\nTháng 9, năm 2025\nKhoảng 81 đến 83 triệu đồng/năm (năm 2024)", "content": {"Bằng cấp": "Cử nhân", "Thời gian đào tạo": "Toàn thời gian: 4 năm", "Chương trình đào tạo": "Xem thông tin chi tiết về chương trình đào tạo", "Chuẩn đầu ra": "Xem thông tin chi tiết về chuẩn đầu ra", "Phương thức xét tuyển riêng": "Kết quả quá trình học tập THPT Kết quả bài thi ĐGNL năm 2025 của ĐHQG TP. HCM", "Xét tuyển theo điểm thi THPT": "Tổ hợp: Đang cập nhật Điểm trúng tuyển 2024 (thang 40):28,00", "Khai giảng": "Tháng 9, năm 2025", "Học phí": "Khoảng 81 đến 83 triệu đồng/năm (năm 2024)"}, "name": "Kỹ thuật phần mềm"}], "images": ["https://admission.tdtu.edu.vn/sites/admission23/files/Tuyen-sinh/Dai-hoc/Nganh/KTPM/3.jpg", "https://admission.tdtu.edu.vn/sites/admission23/files/Tuyen-sinh/Dai-hoc/Nganh/KTPM/1.JPG", "https://admission.tdtu.edu.vn/sites/admission23/files/Tuyen-sinh/Dai-hoc/Nganh/KTPM/2.jpg"]}
{"name": "Kỹ thuật xây dựng công trình giao thông", "description": "\nNgành Kỹ thuật xây dựng công trình giao thông của Trường Đại học Tôn Đức Thắng đào tạo kỹ sư với kiến thức tổng hợp, đủ khả năng đảm nhận các công việc như thiết kế, thi công, giám sát, lập dự án, và lập dự toán cho các công trình như cầu đường bộ, hầm, cầu vượt, nút giao thông, đường sân bay và hạ tầng kỹ thuật. Sinh viên tốt nghiệp có đủ kiến thức chuyên môn và khả năng tin học, ngoại ngữ để làm việc trong và ngoài nước, cũng như tiếp tục học tập ở các bậc cao hơn.", "reasons": ["Chương trình được kiểm định bởi tổ chức ASIIN", "Đội ngũ giảng viên có trình độ chuyên môn cao, giàu kinh nghiệm thực tế", "Cơ hội thực tập và việc làm cao"], "programs": [{"tab": "Tiêu chuẩn", "major_code": "7580205", "description": "Sinh viên được trang bị vững chắc về kiến thức nền tảng như cơ học đất, cơ học kết cấu, sức bền liệu, kết cấu bê tông cốt thép, kết cấu thép, trắc địa, thủy lực, thủy văn,... Ngoài ra, sinh viên còn được hướng dẫn chuyên sâu về kiến thức chuyên ngành như thiết kế đường, thiết kế cầu, đồ án kết cấu bê tông, đồ án kết cấu thép, đồ án nền móng, đồ án thiết kế cầu, đồ án thiết kế đường, kinh tế xây dựng và dự toán, thi công xây dựng cầu đường, thí nghiệm kiểm định vật liệu xây dựng, quản lý và khai thác cầu đường, các phần mềm và công cụ hỗ trợ thiết kế như Civil 3D, Midas, AndDesign,…\nChương trình đào tạo được xây dựng theo hướng gắn liền với thực tế và mang tính ứng dụng cao. Tất cả các môn học được thiết kế lồng ghép giữa lý thuyết, đồ án và thực hành thí nghiệm mô phỏng, được thiết kế giống 100% như các công trình thực tế, qua đó giúp sinh viên củng cố kiến thức chuyên môn, nâng cao tay nghề và rèn luyện phản xạ, tư duy nhạy bén trước khi bước chân vào thị trường lao động đầy cạnh tranh.\nThông qua mạng lưới đối tác thân hữu của Nhà trường, sinh viên được hướng dẫn tham gia trải nghiệm và kiến tập tại các công ty xây dựng công trình giao thông trong và ngoài nước ngay từ những năm đầu tiên học tập, qua đó góp phần nâng cao năng lực chuyên môn, giúp sinh viên thích nghi nhanh với môi trường và văn hoá doanh nghiệp, đáp ứng nhanh chóng các yêu cầu trong xây dựng và thiết kế công trình giao thông.\nNhà trường còn tạo điều kiện cho những sinh viên giỏi có cơ hội trải nghiệm ít nhất một học kỳ ở nước ngoài trước khi tốt nghiệp để trao đổi và giao lưu văn hoá, tìm hiểu về kiến trúc, cơ sở hạ tầng, xu hướng xây dựng và phát triển các công trình giao thông trên thế giới.\nCử nhân\nkỹ sư\nToàn thời gian: 4 năm\nToàn thời gian: 5 năm\nXem thông tin chi tiết về chương trình đào tạo\nXem thông tin chi tiết về chuẩn đầu ra\nKết quả quá trình học tập THPT\nKết quả bài thi ĐGNL năm 2025 của ĐHQG TP. HCM\nTổ hợp: Đang cập nhật\nĐiểm trúng tuyển 2024 (thang 40):22,00\nTháng 9, năm 2025\nKhoảng 31 đến 32 triệu đồng/năm (năm 2024)", "content": {"Bằng cấp": "Cử nhân kỹ sư", "Thời gian đào tạo": "Toàn thời gian: 4 năm Toàn thời gian: 5 năm", "Chương trình đào tạo": "Xem thông tin chi tiết về chương trình đào tạo", "Chuẩn đầu ra": "Xem thông tin chi tiết về chuẩn đầu ra", "Phương thức xét tuyển riêng": "Kết quả quá trình học tập THPT Kết quả bài thi ĐGNL năm 2025 của ĐHQG TP. HCM", "Xét tuyển theo điểm thi THPT": "Tổ hợp: Đang cập nhật Điểm trúng tuyển 2024 (thang 40):22,00", "Khai giảng": "Tháng 9, năm 2025", "Học phí": "Khoảng 31 đến 32 triệu đồng/năm (năm 2024)"}, "name": "Kỹ thuật xây dựng công trình giao thông"}], "images": ["https://admission.tdtu.edu.vn/sites/admission23/files/Tuyen-sinh/Dai-hoc/Nganh/KTXDCTGiaothong/1.jpg", "https://admission.tdtu.edu.vn/sites/admission23/files/Tuyen-sinh/Dai-hoc/Nganh/KTXDCTGiaothong/2.jpg", "https://admission.tdtu.edu.vn/sites/admission23/files/Tuyen-sinh/Dai-hoc/Nganh/KTXDCTGiaothong/3.jpg"]}
{"name": "Kỹ thuật xây dựng", "description": "Xây dựng là ngành truyền thống có từ lâu đời, luôn quan trọng và cần thiết ở mọi thời đại, có ảnh hưởng đến sự phát triển kinh tế xã hội của mỗi quốc gia, góp phần nâng cao năng lực sản xuất và thúc đẩy sự phát triển của các ngành kinh tế khác. Do vậy, nhu cầu về nguồn nhân lực chất lượng cao trong ngành luôn ở mức cao, được quan tâm và mở ra nhiều cơ hội việc làm cho sinh viên lựa chọn theo học ngành Kỹ thuật xây dựng.\n\nKỹ sư tốt nghiệp ngành Kỹ thuật xây dựng có thể tự tin ứng tuyển vào các vị trí như kỹ sư thiết kế, giám sát và quản lý thi công các công trình xây dựng trong và ngoài nước; làm việc tại các cơ quan quản lý nhà nước trong lĩnh vực xây dựng hay các doanh nghiệp có ngành nghề liên quan như bất động sản, ngân hàng, nhà máy xí nghiệp sản xuất công nghiệp…; tự thành lập các công ty tư vấn thiết kế, thi công công trình; giảng viên giảng dạy các ngành học liên quan đến lĩnh vực xây dựng hoặc tiếp tục học tập lên các bậc học cao hơn.", "reasons": ["Đội ngũ giảng viên giàu kinh nghiệm", "Học phí phù hợp", "Liên tục cập nhật xu hướng"], "programs": [{"tab": "Tiêu chuẩn", "major_code": "7580201", "description": "Sinh viên được đào tạo và tiếp cận với tất cả các kiến thức liên quan đến tư vấn, tính toán thiết kế, tổ chức thi công, quản lý, giám sát và nghiệm thu các công trình xây dựng nhằm phục vụ đời sống và nhu cầu của con người. Thông qua các kiến thức cơ bản và kỹ năng chuyên môn, sinh viên còn được trang bị thêm kiến thức về các phần mềm trong thiết kế xây dựng, phần mềm tính toán ứng dụng; kết cấu bê tông, kết cấu thép; phương pháp nghiên cứu trắc địa, thuỷ lực; kiểm tra chất lượng vật liệu và chất lượng công trình; xử lý nền móng và gia cố công trình,…\nSinh viên được hướng dẫn tham gia trải nghiệm và kiến tập tại các công ty xây dựng trong và ngoài nước thông qua mạng lưới đối tác thân hữu của Nhà trường ngay từ những năm đầu tiên học tập.\nÁp dụng chương trình đào tạo tiên tiến đạt chuẩn châu Âu, được kiểm định bỡi ASIIN. Đội ngũ giảng viên giỏi về chuyên môn, dày dạn kinh nghiệm giảng dạy, tốt nghiệp sau đại học từ các trường đại học tiên tiến nước ngoài. Sinh viên ngành Kỹ thuật xây dựng của Trường Đại học Tôn Đức Thắng được trang bị kiến thức cơ bản và kiến thức chuyên môn vững vàng để có thể thực hiện công việc tư vấn, giám sát và quản lý dự án trên các công trường xây dựng nhà ở, nhà xưởng và các công trình công cộng một cách chuyên nghiệp đáp ứng nhu cầu đa dạng của sự nghiệp phát triển kinh tế - xã hội, theo kịp sự tiến bộ khoa học kỹ thuật.\nCử nhân\nKỹ sư\nToàn thời gian: 4 năm\nToàn thời gian: 5 năm\nXem thông tin chi tiết về chương trình đào tạo\nXem thông tin chi tiết về chuẩn đầu ra\nKết quả quá trình học tập THPT\nKết quả bài thi ĐGNL năm 2025 của ĐHQG TP. HCM\nTổ hợp: Đang cập nhật\nĐiểm trúng tuyển 2024 (thang 40):24,00\nTháng 9, năm 2025\nKhoảng 31 đến 32 triệu đồng/năm (năm 2024)", "content": {"Bằng cấp": "Cử nhân Kỹ sư", "Thời gian đào tạo": "Toàn thời gian: 4 năm Toàn thời gian: 5 năm", "Chương trình đào tạo": "Xem thông tin chi tiết về chương trình đào tạo", "Chuẩn đầu ra": "Xem thông tin chi tiết về chuẩn đầu ra", "Phương thức xét tuyển riêng": "Kết quả quá trình học tập THPT Kết quả bài thi ĐGNL năm 2025 của ĐHQG TP. HCM", "Xét tuyển theo điểm thi THPT": "Tổ hợp: Đang cập nhật Điểm trúng tuyển 2024 (thang 40):24,00", "Khai giảng": "Tháng 9, năm 2025", "Học phí": "Khoảng 31 đến 32 triệu đồng/năm (năm 2024)"}, "name": "Kỹ thuật xây dựng"}, {"tab": "Tiên tiến", "major_code": "F7580201", "description": "Chương trình tiên tiến ngành Kỹ thuật xây dựng tuyển sinh với các điểm khác biệt so với chương trình tiêu chuẩn như sau:\n- Chương trình đào tạo hiện đại giúp sinh viên tốt nghiệp có thể đáp ứng các yêu cầu công việc tại Việt Nam, cũng như tại các nước tiên tiến; hoặc học tập các bậc học cao hơn ở nước ngoài;\n- Kỹ năng thực hành chuyên môn được chú trọng, sinh viên sau tốt nghiệp có đủ kinh nghiệm thực tế để bắt đầu công việc một cách tự tin;\n- Phương pháp đào tạo theo chuẩn quốc tế, sĩ số lớp học dưới 35 sinh viên;\n- Học tập lý thuyết tại trường kết hợp với thực hành thực tập tại doanh nghiệp ở các môn học chuyên ngành, giúp sinh viên tốt nghiệp có đủ kiến thức và kỹ năng để làm việc một cách chuyên nghiệp;\n- Rèn luyện tác phong chuyên nghiệp, khả năng làm việc nhóm, tư duy phản biện, giúp đáp ứng yêu cầu tuyển dụng của các nhà tuyển dụng khó tính nhất;\n- Được cam kết đảm bảo việc làm đúng chuyên môn sau tốt nghiệp;\n- Sinh viên được hỗ trợ và giới thiệu thực tập trong hoặc ngoài nước tùy theo nguyện vọng;\n- Đội ngũ giảng viên được tuyển chọn là những giảng viên uy tín, tốt nghiệp từ các nước tiên tiến hoặc các chuyên gia nổi tiếng đến từ các doanh nghiệp;\n- Được học tập bổ sung để nhận các chứng chỉ, chứng nhận về giám sát công trình, phân tích và tính toán kết cấu công trình dùng phần mềm Etabs, thể hiện bản vẽ xây dựng dùng phần mềm chuyên dụng Autocad, Autodesk Revit, Chứng chỉ an toàn lao động …;\n- Được giảng dạy bằng tiếng anh đối với các môn học chuyên ngành, cũng như được làm đồ án tốt nghiệp bằng tiếng anh, giúp sinh viên có đủ khả năng ngoại ngữ để làm việc trong môi trường quốc tế.\nCử nhân\nKỹ sư\nToàn thời gian: 4 năm\nToàn thời gian: 5 năm\nXem thông tin chi tiết về chương trình đào tạo\nXem thông tin chi tiết về chuẩn đầu ra\nKết quả quá trình học tập THPT\nKết quả bài thi ĐGNL năm 2025 của ĐHQG TP. HCM\nTổ hợp: Đang cập nhật\nĐiểm trúng tuyển 2024 (thang 40):22,00\nTháng 9, năm 2025\nKhoảng 53 đến 54 triệu đồng/năm (năm 2024)", "content": {"Bằng cấp": "Cử nhân Kỹ sư", "Thời gian đào tạo": "Toàn thời gian: 4 năm Toàn thời gian: 5 năm", "Chương trình đào tạo": "Xem thông tin chi tiết về chương trình đào tạo", "Chuẩn đầu ra": "Xem thông tin chi tiết về chuẩn đầu ra", "Phương thức xét tuyển riêng": "Kết quả quá trình học tập THPT Kết quả bài thi ĐGNL năm 2025 của ĐHQG TP. HCM", "Xét tuyển theo điểm thi THPT": "Tổ hợp: Đang cập nhật Điểm trúng tuyển 2024 (thang 40):22,00", "Khai giảng": "Tháng 9, năm 2025", "Học phí": "Khoảng 53 đến 54 triệu đồng/năm (năm 2024)"}, "name": "Kỹ thuật xây dựng"}, {"tab": "Đại học bằng tiếng Anh", "major_code": "FA7580201", "description": "Ngoài các chương trình tiêu chuẩn, tiên tiến, khoa còn tuyển sinh chương trình đại học bằng tiếng Anh cho ngành Kỹ thuật xây dựng để góp phần đào tạo kỹ sư xây dựng đáp ứng nhu cầu nhân lực chất lượng cao cho khu vực Đông Nam Á và quốc tế. Sinh viên được hướng dẫn tham gia trải nghiệm và kiến tập tại các công ty xây dựng trong và ngoài nước thông qua mạng lưới đối tác thân hữu của Nhà trường ngay từ những năm đầu tiên học tập.\nCử nhân\nKỹ sư\nToàn thời gian: 4 năm\nToàn thời gian: 5 năm\nXem thông tin chi tiết về chương trình đào tạo\nXem thông tin chi tiết về chuẩn đầu ra\nKết quả quá trình học tập THPT\nKết quả bài thi ĐGNL năm 2025 của ĐHQG TP. HCM\nTổ hợp: Đang cập nhật\nĐiểm trúng tuyển 2024 (thang 40):24,00\nTháng 9, năm 2025\nKhoảng 81 đến 83 triệu đồng/năm (năm 2024)", "content": {"Bằng cấp": "Cử nhân Kỹ sư", "Thời gian đào tạo": "Toàn thời gian: 4 năm Toàn thời gian: 5 năm", "Chương trình đào tạo": "Xem thông tin chi tiết về chương trình đào tạo", "Chuẩn đầu ra": "Xem thông tin chi tiết về chuẩn đầu ra", "Phương thức xét tuyển riêng": "Kết quả quá trình học tập THPT Kết quả bài thi ĐGNL năm 2025 của ĐHQG TP. HCM", "Xét tuyển theo điểm thi THPT": "Tổ hợp: Đang cập nhật Điểm trúng tuyển 2024 (thang 40):24,00", "Khai giảng": "Tháng 9, năm 2025", "Học phí": "Khoảng 81 đến 83 triệu đồng/năm (năm 2024)"}, "name": "Kỹ thuật xây dựng"}, {"tab": "Liên kết quốc tế", "major_code": "K7580201", "description": "Cử nhân (song bằng)\n4 năm (2 năm đầu học tại TDTU, 2 năm sau học tại Trường liên kết)\nXem thông tin chi tiết về chương trình đào tạo\nXem thông tin chi tiết về chuẩn đầu ra\nKết quả quá trình học tập THPT\nKết quả bài thi ĐGNL năm 2025 của ĐHQG TP. HCM\nTổ hợp: Đang cập nhật\nĐiểm trúng tuyển 2024 (thang 40):24,00\nTháng 9, năm 2025\nGiai đoạn 1: khoảng 76 đến 77 triệu đồng/năm (năm 2024)", "content": {"Bằng cấp": "Cử nhân (song bằng)", "Thời gian đào tạo": "4 năm (2 năm đầu học tại TDTU, 2 năm sau học tại Trường liên kết)", "Chương trình đào tạo": "Xem thông tin chi tiết về chương trình đào tạo", "Chuẩn đầu ra": "Xem thông tin chi tiết về chuẩn đầu ra", "Phương thức xét tuyển riêng": "Kết quả quá trình học tập THPT Kết quả bài thi ĐGNL năm 2025 của ĐHQG TP. HCM", "Xét tuyển theo điểm thi THPT": "Tổ hợp: Đang cập nhật Điểm trúng tuyển 2024 (thang 40):24,00", "Khai giảng": "Tháng 9, năm 2025", "Học phí": "Giai đoạn 1: khoảng 76 đến 77 triệu đồng/năm (năm 2024)"}, "name": "Kỹ thuật xây dựng liên kết Đại học La Trobe, Úc"}], "images": ["https://admission.tdtu.edu.vn/sites/admission23/files/Tuyen-sinh/Dai-hoc/Nganh/Ky-thuat-xay-dung/1.jpg", "https://admission.tdtu.edu.vn/sites/admission23/files/Tuyen-sinh/Dai-hoc/Nganh/Ky-thuat-xay-dung/2.jpg", "https://admission.tdtu.edu.vn/sites/admission23/files/Tuyen-sinh/Dai-hoc/Nganh/Ky-thuat-xay-dung/3.jpg"]}
{"name": "Luật", "description": "Chương trình đào tạo ngành Luật của Trường Đại học Tôn Đức Thắng được xây dựngtheo quy định giáo dục đại học Việt Nam vàcập nhật liên tục dựa trên khung chương trình tiêu chuẩn quốc tế nhằm mang lại giá trị cao và sự khác biệt cho sinh viên ở cả năm lĩnh vực: kiến thức, tư duy, kỹ năng, hành vi và thái độ. Chương trình đã được kiểm định bởi tổ chức FIBAA.\n\nSinh viên được trang bị kiến thức luật bao quát ở hầu hết các lĩnh vực pháp lý. Chương trình đào tạo đảm bảo người học được trang bị kiến thức chung về Triết học, Kinh tế vi mô, logic học…; khối kiến thức cơ sở ngành như Lý luận về nhà nước và pháp luật, Hiến pháp Việt Nam…; khối thức chuyên ngành như luật dân sự, luật thương mại, luật hành chính, luật hình sự, luật quốc tế, luật tố tụng… Người học còn được rèn luyện các kỹ năng pháp lý cần thiết như soạn thảo văn bản hành chính, nghiệp vụ thư ký toà án, thực hành nghề luật, soạn thảo hợp đồng, tư vấn thành lập doanh nghiệp…", "reasons": ["Chương trình đào tạo hiện đại và thực tiễn", "Đội ngũ giảng viên chất lượng cao", "Mở rộng mạng lưới hợp tác quốc tế, hợp tác doanh nghiệp"], "programs": [{"tab": "Tiêu chuẩn", "major_code": "7380101", "description": "Chương trình đào tạo ngành Luật của Trường Đại học Tôn Đức Thắng được xây dựng dựa trên đặc thù của giáo dục Việt Nam và cập nhật liên tục dựa trên khung chương trình tiêu chuẩn quốc tế nhằm mang lại giá trị cao và sự khác biệt cho sinh viên ở cả năm lĩnh vực: kiến thức, tư duy, kỹ năng, hành vi và thái độ.\nSinh viên được trang bị kiến thức luật bao quát ở hầu hết các lĩnh vực. Không chỉ riêng kiến thức về luật tài chính, luật thương mại, luật kinh tế, luật dân sự; Nhà trường còn cung cấp kiến thức về luật hôn nhân gia đình, quy định chung về tài sản, quyền thừa kế, luật hình sự - hành chính, luật môi trường, tội phạm học, bồi thường hợp đồng, tranh chấp thương mại, khiếu nại, tố cáo, quyền con người, quyền công dân, ...\nSố tiết học thực hành được thiết kế để cân bằng với lượng kiến thức lý thuyết, giúp sinh viên được trải nghiệm thực tế. Thông qua các hình thức tổ chức các phiên tòa giả định với những tình huống xảy ra thực tế, sinh viên được tạo cơ hội để nghiên cứu, phân tích và giải quyết vấn đề như một chuyên viên luật thực thụ, góp phần nâng cao kỹ năng tư duy và phản biện bên cạnh việc tiếp thu kiến thức chuyên môn.\nVới mạng lưới doanh nghiệp thân hữu và các chuyên gia quốc tế có nhiều kinh nghiệm trong cùng lĩnh vực, sinh viên được hướng dẫn tham gia các khóa đào tạo ngắn hạn để cập nhật kiến thức luật trong nước và quốc tế; trải nghiệm văn hóa và kiến tập tại doanh nghiệp để tích lũy kinh nghiệm.\nNgoài ra, trong một số môn học chuyên sâu, các chuyên gia và luật sư có uy tín sẽ cùng với giảng viên trực tiếp giảng dạy và hướng dẫn sinh viên thực hiện các dự án nghiên cứu ngay tại doanh nghiệp, nâng cao tính ứng dụng trong chương trình học và kỹ năng thực hành nghề nghiệp cho sinh viên.\nCử nhân\nToàn thời gian: 4 năm\nXem thông tin chi tiết về chương trình đào tạo\nXem thông tin chi tiết về chuẩn đầu ra\nKết quả quá trình học tập THPT\nKết quả bài thi ĐGNL năm 2025 của ĐHQG TP. HCM\nTổ hợp: Đang cập nhật\nĐiểm trúng tuyển 2024 (thang 40):33,45\nTháng 9, năm 2025\nKhoảng 27 đến 28 triệu đồng/năm (năm 2024)", "content": {"Bằng cấp": "Cử nhân", "Thời gian đào tạo": "Toàn thời gian: 4 năm", "Chương trình đào tạo": "Xem thông tin chi tiết về chương trình đào tạo", "Chuẩn đầu ra": "Xem thông tin chi tiết về chuẩn đầu ra", "Phương thức xét tuyển riêng": "Kết quả quá trình học tập THPT Kết quả bài thi ĐGNL năm 2025 của ĐHQG TP. HCM", "Xét tuyển theo điểm thi THPT": "Tổ hợp: Đang cập nhật Điểm trúng tuyển 2024 (thang 40):33,45", "Khai giảng": "Tháng 9, năm 2025", "Học phí": "Khoảng 27 đến 28 triệu đồng/năm (năm 2024)"}, "name": "Luật"}, {"tab": "Tiên tiến: Luật (Chuyên ngành Luật kinh tế)", "major_code": "F7380101", "description": "Chương trình đào tạo đại học ngành Luật được xây dựng trên cơ sở đảm bảo chương trình khung do Bộ Giáo dục và Đào tạo ban hành, có đối sánh Chương trình đào tạo của một số trường đại học đào tạo Luật trong nước và quốc tế uy tín trên thế giới đảm bảo có đặc thù riêng của TDTU và được thiết kế một cách có hệ thống.\nToàn bộ nội dung chương trình cho đào tạo trình độ cử nhân được xây dựng được cấu trúc hợp lý, linh hoạt, thông qua các môn tự chọn, người học có thể chọn môn theo nguyện vọng, bổ sung thêm những học phần thiết yếu để trang bị kiến thức, kỹ năng theo yêu cầu cũng như để đáp ứng yêu cầu của thị trường lao động.\nMục tiêu của chương trình là trang bị cho sinh viên các kiến thức và kỹ năng cần thiết để ứng tuyển vào các vị trí như chuyên gia tư vấn; quản lý doanh nghiệp; chuyên gia đàm phán, soạn thảo và ký kết các hợp đồng thương mại; luật sư đảm nhiệm công tác pháp lý ở các doanh nghiệp thuộc các thành phần kinh tế; làm việc trong các cơ quan nhà nước, các tổ chức chính trị – xã hội; tham gia các hoạt động tố tụng liên quan đến thương mại, dân sự, lao động, hành chính; đảm đương công tác pháp chế ở các tổ chức phi chính phủ, các tổ chức quốc tế tại Việt Nam; nghiên cứu, đề ra các giải pháp mang tính pháp lý ở các doanh nghiệp cũng như ở các cơ quan quản lý Nhà nước. Ngoài ra, cử nhân Luật còn có thể học lên cao học để bổ sung, cập nhật và nâng cao kiến thức ngành luật.\nCử nhân\nToàn thời gian: 4 năm\nXem thông tin chi tiết về chương trình đào tạo\nXem thông tin chi tiết về chuẩn đầu ra\nTổ hợp: Văn*2, Anh, Sử\nKQ ĐGNL của ĐHQG TP. HCM\nƯu tiên xét tuyển theo TDTU\nTổ hợp: A00; A01; C00; D01\nTháng 9, năm 2025\nĐang cập nhật", "content": {"Bằng cấp": "Cử nhân", "Thời gian đào tạo": "Toàn thời gian: 4 năm", "Chương trình đào tạo": "Xem thông tin chi tiết về chương trình đào tạo", "Chuẩn đầu ra": "Xem thông tin chi tiết về chuẩn đầu ra", "Phương thức xét tuyển riêng": "Tổ hợp: Văn*2, Anh, Sử KQ ĐGNL của ĐHQG TP. HCM Ưu tiên xét tuyển theo TDTU", "Xét tuyển theo điểm thi THPT": "Tổ hợp: A00; A01; C00; D01", "Khai giảng": "Tháng 9, năm 2025", "Học phí": "Đang cập nhật"}, "name": "Luật(Chuyên ngành Luật kinh tế)"}, {"tab": "Tiên tiến: Luật (Chuyên ngành Luật thương mại quốc tế)", "major_code": "F7380101T", "description": "Chương trình đào tạo đại học ngành Luật được xây dựng trên cơ sở đảm bảo chương trình khung do Bộ Giáo dục và Đào tạo ban hành, có đối sánh Chương trình đào tạo của một số trường đại học đào tạo Luật trong nước và quốc tế uy tín trên thế giới đảm bảo có đặc thù riêng của TDTU và được thiết kế một cách có hệ thống.\nToàn bộ nội dung chương trình cho đào tạo trình độ cử nhân được xây dựng được cấu trúc hợp lý, linh hoạt, thông qua các môn tự chọn, người học có thể chọn môn theo nguyện vọng, bổ sung thêm những học phần thiết yếu để trang bị kiến thức, kỹ năng theo yêu cầu cũng như để đáp ứng yêu cầu của thị trường lao động.\nMục tiêu của chương trình là trang bị cho sinh viên các kiến thức và kỹ năng cần thiết để ứng tuyển vào các vị trí như chuyên gia tư vấn; quản lý doanh nghiệp; chuyên gia đàm phán, soạn thảo và ký kết các hợp đồng thương mại; luật sư đảm nhiệm công tác pháp lý ở các doanh nghiệp thuộc các thành phần kinh tế; làm việc trong các cơ quan nhà nước, các tổ chức chính trị – xã hội; tham gia các hoạt động tố tụng liên quan đến thương mại, dân sự, lao động, hành chính; đảm đương công tác pháp chế ở các tổ chức phi chính phủ, các tổ chức quốc tế tại Việt Nam; nghiên cứu, đề ra các giải pháp mang tính pháp lý ở các doanh nghiệp cũng như ở các cơ quan quản lý Nhà nước. Ngoài ra, cử nhân Luật còn có thể học lên cao học để bổ sung, cập nhật và nâng cao kiến thức ngành luật.\nCử nhân\nToàn thời gian: 4 năm\nXem thông tin chi tiết về chương trình đào tạo\nXem thông tin chi tiết về chuẩn đầu ra\nTổ hợp: Văn*2, Anh, Sử\nKQ ĐGNL của ĐHQG TP. HCM\nƯu tiên xét tuyển theo TDTU\nTổ hợp: A00; A01; C00; D01\nTháng 9, năm 2025\nĐang cập nhật", "content": {"Bằng cấp": "Cử nhân", "Thời gian đào tạo": "Toàn thời gian: 4 năm", "Chương trình đào tạo": "Xem thông tin chi tiết về chương trình đào tạo", "Chuẩn đầu ra": "Xem thông tin chi tiết về chuẩn đầu ra", "Phương thức xét tuyển riêng": "Tổ hợp: Văn*2, Anh, Sử KQ ĐGNL của ĐHQG TP. HCM Ưu tiên xét tuyển theo TDTU", "Xét tuyển theo điểm thi THPT": "Tổ hợp: A00; A01; C00; D01", "Khai giảng": "Tháng 9, năm 2025", "Học phí": "Đang cập nhật"}, "name": "Luật (Chuyên ngành Luật thương mại quốc tế)"}], "images": ["https://admission.tdtu.edu.vn/sites/admission23/files/Tuyen-sinh/Dai-hoc/Nganh/Luat/1.png", "https://admission.tdtu.edu.vn/sites/admission23/files/Tuyen-sinh/Dai-hoc/Nganh/Luat/2.jpg", "https://admission.tdtu.edu.vn/sites/admission23/files/Tuyen-sinh/Dai-hoc/Nganh/Luat/3.jpg"]}
{"name": "Mạng máy tính và truyền thông dữ liệu", "description": "Trong kỷ nguyên công nghệ số, Mạng máy tính và Truyền thông dữ liệu đã trở thành nền tảng không thể thiếu để kết nối thế giới và mở ra vô số cơ hội sáng tạo. Đây là ngành học không chỉ trang bị kiến thức từ cơ bản đến chuyên sâu về lĩnh vực được đào tạo, mà còn giúp sinh viên tiếp thu các thành tựu khoa học công nghệ tiên tiến, hiện đại để phát triển các kỹ năng thiết thực trong một lĩnh vực đầy tiềm năng này.\nNgành học này tập trung vào việc xây dựng, quản lý, và bảo mật các hệ thống mạng, từ mạng nội bộ đến mạng diện rộng kết nối toàn cầu. Sinh viên sẽ được học cách thiết kế hệ thống mạng hiện đại, triển khai các công nghệ tiên tiến như điện toán đám mây, trí tuệ nhân tạo (AI) trong mạng, và phát triển ứng dụng IoT trên nền tảng di động lẫn không dây. Các nguyên tắc trao đổi dữ liệu, truyền thông, và giải pháp ứng dụng công nghệ mạng vào cuộc sống sẽ là trọng tâm đào tạo, tạo tiền đề cho sự phát triển của các ngành khác.\nSau khi tốt nghiệp, sinh viên ngành Mạng máy tính và Truyền thông dữ liệu tại Trường Đại học Tôn Đức Thắng tự tin đảm nhận nhiều vai trò , vị trí quan trọng:Chuyên viên quản trị hệ thống mạng tại các tổ chức lớn;Tư vấn và thiết kế hệ thống mạng cho doanh nghiệp;Lập trình viên phát triển ứng dụng trên thiết bị di động và nền tảng mạng không dây;Chuyên viên bảo mật và vận hành trung tâm dữ liệu;Nghiên cứu viên và học tiếp bậc cao học trong các lĩnh vực công nghệ tiên tiến.", "reasons": ["Số tiết học thực tế chiếm gần 50% chương trình đào tạo", "Cơ hội trải nghiệm các học phần nghề nghiệp, tập sự nghề nghiệp tại các doanh nghiệp", "100% sinh viên ra trường có việc làm trong vòng 12 tháng kể từ khi tốt nghiệp"], "programs": [{"tab": "Tiêu chuẩn", "major_code": "7480102", "description": "Chương trình học tiêu chuẩn Mạng máy tính và Truyền thông dữ liệu đào tạo theo chuẩn quốc tế, cân bằng giữa lý thuyết nền tảng và ứng dụng thực tế. Sinh viên sẽ trải qua các học phần từ cơ bản đến chuyên sâu, từ việc phân tích nhu cầu thực tế đến thiết kế và triển khai các giải pháp mạng phù hợp cho cá nhân hoặc tổ chức. Đặc biệt, sinh viên sẽ được tiếp cận các công nghệ mới nhất như AI trong mạng, tính toán di động, và an toàn thông tin.Trường chú trọng đầu tư mạnh mẽ vào hệ thống phòng thí nghiệm thực hành với trang thiết bị tiên tiến, tạo điều kiện tối ưu cho sinh viên học tập và nghiên cứu. Đồng thời, nhà trường liên kết với các tập đoàn công nghệ hàng đầu, mang đến cơ hội thực tập và trải nghiệm thực tế, giúp sinh viên sẵn sàng gia nhập thị trường lao động ngay khi tốt nghiệp.\nCử nhân\nToàn thời gian: 4 năm\nXem thông tin chi tiết về chương trình đào tạo\nXem thông tin chi tiết về chuẩn đầu ra\nKết quả quá trình học tập THPT\nKết quả bài thi ĐGNL năm 2025 của ĐHQG TP. HCM\nTổ hợp: Đang cập nhật\nĐiểm trúng tuyển 2024 (thang 40):31,20\nTháng 9, năm 2025\nKhoảng 31 đến 32 triệu đồng/năm (năm 2024)", "content": {"Bằng cấp": "Cử nhân", "Thời gian đào tạo": "Toàn thời gian: 4 năm", "Chương trình đào tạo": "Xem thông tin chi tiết về chương trình đào tạo", "Chuẩn đầu ra": "Xem thông tin chi tiết về chuẩn đầu ra", "Phương thức xét tuyển riêng": "Kết quả quá trình học tập THPT Kết quả bài thi ĐGNL năm 2025 của ĐHQG TP. HCM", "Xét tuyển theo điểm thi THPT": "Tổ hợp: Đang cập nhật Điểm trúng tuyển 2024 (thang 40):31,20", "Khai giảng": "Tháng 9, năm 2025", "Học phí": "Khoảng 31 đến 32 triệu đồng/năm (năm 2024)"}, "name": "Mạng máy tính và truyền thông dữ liệu"}], "images": ["https://admission.tdtu.edu.vn/sites/admission23/files/Tuyen-sinh/Dai-hoc/Nganh/MMT-TTDL/1.JPG", "https://admission.tdtu.edu.vn/sites/admission23/files/Tuyen-sinh/Dai-hoc/Nganh/MMT-TTDL/2.jpg", "https://admission.tdtu.edu.vn/sites/admission23/files/Tuyen-sinh/Dai-hoc/Nganh/MMT-TTDL/3.jpg"]}
{"name": "Marketing", "description": "Trong bối cảnh hiện nay, Marketing đã không còn quá xa lạ với mọi người và có tầm quan trọng đặc biệt đối với các doanh nghiệp, xã hội đang phát triển và hội nhập quốc tế như Việt Nam. Đây cũng được xem là một trong số những ngành “hot”; thu hút sự quan tâm đông đảo của học sinh, sinh viên trên cả nước.\nSinh viên ngành Marketing được cung cấp các kiến thức nền tảng về Marketing và các kỹ năng chuyên môn cần thiết để vận dụng linh hoạt, sáng tạo vào các hoạt động Marketing online và offline tại các tổ chức và doanh nghiệp. Sinh viên sẽ tích lũy kinh nghiệm thực tiễn thông qua các đợt thực tập tại doanh nghiệp, tham gia các đề án thực tế và các buổi hội thảo chuyên ngành. Bên cạnh đó, sinh viên còn được rèn luyện kỹ năng nghề nghiệp ngay tại trường thông qua các câu lạc bộ, hoạt động truyền thông và PR do Nhà trường tổ chức.\nCử nhân Marketing sau khi ra trường có thể tự tin ứng tuyển vào các vị trí như chuyên viên tại các công ty hoạt động trong lĩnh vực Marketing; chuyên viên nghiên cứu thị trường, tổ chức sự kiện; chuyên viên chăm sóc khách hàng; chuyên viên truyền thông và quan hệ công chúng; chuyên viên phát triển nội dung; chuyên viên phát triển và quản trị thương hiệu. Ngoài ra, cử nhân Marketing còn có thể tham gia giảng dạy, nghiên cứu về lĩnh vực tiếp thị và quảng cáo hoặc tiếp tục nghiên cứu và học tập các bậc học cao hơn ở các chương trình sau đại học.", "reasons": ["Môn học cập nhật theo xu hướng thực tế", "Chương trình học đạt tiêu chuẩn kiểm định quốc tế FIBAA", "Đội ngũ giảng viên tận tâm"], "programs": [{"tab": "Tiêu chuẩn", "major_code": "7340115", "description": "Sinh viên ngành Marketing tại trường Đại học Tôn Đức Thắng, được trang bị hệ thống kiến thức nền tảng về Marketing hiện đại; cung cấp nhiều kiến thức về tiếp thị kỹ thuật số, nghiên cứu thị trường, hành vi khách hàng, quản lý bán hàng, truyền thông tích hợp quảng cáo và tổ chức sự kiện, xây dựng và phát triển các mối quan hệ khách hàng, tiếp thị quốc tế, tiếp thị xã hội, quản lý sản phẩm và bán hàng chuyên nghiệp, …\nVới mục tiêu đào tạo sinh viên trở thành một Marketer toàn diện về cả năng lực chuyên môn lẫn kỹ năng nghề nghiệp, chương trình học được nghiên cứu và xây dựng theo hướng kết hợp hài hoà giữa lý thuyết và thực tiễn thông qua các bài giảng trên lớp và kinh nghiệm thực tế từ các đợt thực tập, kiến tập tại doanh nghiệp, các buổi hội thảo chuyên ngành hiện đại. Ngoài ra, sinh viên còn được học thông qua các bài tập mô phỏng, vận dụng kiến thức, tổng hợp thông tin và đưa ra giải pháp cụ thể.\nTrong các môn học chuyên sâu, các chuyên gia hàng đầu trong lĩnh vực Marketing  và giảng viên sẽ trực tiếp giảng dạy và hướng dẫn sinh viên thực hiện các dự án thực tế ngay tại doanh nghiệp. Tính ứng dụng của các học phần được thiết kế theo hướng tăng dần từ cấp độ kiến thức cơ bản cho đến cấp độ sinh viên có khả năng tự tiếp nhận tình huống, phân tích mục tiêu và đối tượng khách hàng, lên ý triển khai một dự án tiếp thị hoàn chỉnh.\nSinh viên tốt nghiệp ngành Marketing tại Trường Đại học Tôn Đức Thắng được cung cấp đầy đủ kiến thức và kỹ năng chuyên môn để tham gia vào gần như tất cả các khía cạnh của hoạt động kinh doanh, bắt đầu bằng việc xác định sứ mệnh của công ty, đánh giá mong muốn và nhu cầu của người tiêu dùng, xây dựng chiến lược, thiết kế sản phẩm và dịch vụ, thực hiện các chương trình khuyến mãi và giám sát sự hài lòng của người tiêu dùng với sản phẩm của công ty.\nCử nhân\nToàn thời gian: 4 năm\nXem thông tin chi tiết về chương trình đào tạo\nXem thông tin chi tiết về chuẩn đầu ra\nKết quả quá trình học tập THPT\nKết quả bài thi ĐGNL năm 2025 của ĐHQG TP. HCM\nTổ hợp: Đang cập nhật\nĐiểm trúng tuyển 2024 (thang 40):34,25\nTháng 9, năm 2025\nKhoảng 27 đến 28 triệu đồng/năm (năm 2024)", "content": {"Bằng cấp": "Cử nhân", "Thời gian đào tạo": "Toàn thời gian: 4 năm", "Chương trình đào tạo": "Xem thông tin chi tiết về chương trình đào tạo", "Chuẩn đầu ra": "Xem thông tin chi tiết về chuẩn đầu ra", "Phương thức xét tuyển riêng": "Kết quả quá trình học tập THPT Kết quả bài thi ĐGNL năm 2025 của ĐHQG TP. HCM", "Xét tuyển theo điểm thi THPT": "Tổ hợp: Đang cập nhật Điểm trúng tuyển 2024 (thang 40):34,25", "Khai giảng": "Tháng 9, năm 2025", "Học phí": "Khoảng 27 đến 28 triệu đồng/năm (năm 2024)"}, "name": "Marketing"}, {"tab": "Tiên tiến", "major_code": "F7340115", "description": "Chương trình tiên tiến, Cử nhân ngành Marketing cung cấp các kiến thức nền tảng về Marketing và các kỹ năng chuyên môn cần thiết để vận dụng linh hoạt, sáng tạo vào một hoạt động Marketing online và offline tại các tổ chức và doanh nghiệp. Sinh viên sẽ có được kinh nghiệm thực tiễn thông qua các đợt thực tập tại doanh nghiệp, các đề án và các buổi hội thảo chuyên ngành đồng thời thực hành nghề nghiệp tại Trường thông qua các câu lạc bộ và hoạt động truyền thông, PR của Nhà trường.\nChương trình có sự kết hợp giữa giảng viên có kinh nghiệm trong lĩnh vực nghiên cứu và giảng viên tại doanh nghiệp, đặc biệt sinh viên được tham gia chương trình thực tập tại doanh nghiệp sớm từ năm thứ 2 nhằm cọ xát thực tế và định hướng nghề nghiệp cụ thể. Song song đó, sinh viên được tiếp xúc và định hướng làm việc tại các tập đoàn đa quốc gia, tập đoàn hàng đầu Việt Nam và các công ty trong lĩnh vực Marketing đầu ngành.\nSinh viên tốt nghiệp chương trình tiên tiến, Cử nhân ngành Marketing có kỹ năng tiếng Anh tương đương với chứng chỉ IELTS 5.5.\nCử nhân\nToàn thời gian: 4 năm\nXem thông tin chi tiết về chương trình đào tạo\nXem thông tin chi tiết về chuẩn đầu ra\nKết quả quá trình học tập THPT\nKết quả bài thi ĐGNL năm 2025 của ĐHQG TP. HCM\nTổ hợp: Đang cập nhật\nĐiểm trúng tuyển 2024 (thang 40):31,30\nTháng 9, năm 2025\nKhoảng 62 đến 64 triệu đồng/năm (năm 2024)", "content": {"Bằng cấp": "Cử nhân", "Thời gian đào tạo": "Toàn thời gian: 4 năm", "Chương trình đào tạo": "Xem thông tin chi tiết về chương trình đào tạo", "Chuẩn đầu ra": "Xem thông tin chi tiết về chuẩn đầu ra", "Phương thức xét tuyển riêng": "Kết quả quá trình học tập THPT Kết quả bài thi ĐGNL năm 2025 của ĐHQG TP. HCM", "Xét tuyển theo điểm thi THPT": "Tổ hợp: Đang cập nhật Điểm trúng tuyển 2024 (thang 40):31,30", "Khai giảng": "Tháng 9, năm 2025", "Học phí": "Khoảng 62 đến 64 triệu đồng/năm (năm 2024)"}, "name": "Marketing"}, {"tab": "Đại học bằng tiếng Anh", "major_code": "FA7340115", "description": "Chương trình cử nhân Marketing đại  học bằng tiếng Anh được xây dựng theo các chuẩn chương trình đào tạo quốc tế, được đối sánh với chương trình của các trường đại học TOP 100 thế giới theo THE.\nTham gia chương trình học, sinh viên được tạo điều kiện kiến tập tại các công ty hàng đầu Việt Nam và công ty lớn trong lĩnh vực Marketing, từ đó hiểu rõ về môi trường làm việc và được định hướng phát triển con đường sự nghiệp trong tương lai. Các môn học được giảng dạy hầu hết bằng tiếng Anh, sinh viên có cơ hội trau dồi vốn ngoại ngữ, kỹ năng làm việc chuyên nghiệp và thái độ cầu thị.\nChương trình đại học bằng tiếng Anh của Khoa Quản trị Kinh doanh là một chương trình đào tạo với các ưu điểm về giáo trình – giảng dạy, quy mô lớp học, đội ngũ giảng viên và cả sự trải nghiệm thực tế. Sinh viên được tiếp xúc và định hướng làm việc tại các công ty tư vấn, agency, nghiên cứu thị trường hàng đầu thế giới như các công ty hàng đầu thế giới như: PricewaterhouseCoopers (PwC), Deloitte (Deloitte), Ernst and Young (EY), KPMG, BCG, Mc Kinsey, Nielsen, Kantar, Ogilvy and Mather...\nCử nhân\nToàn thời gian: 4 năm\nXem thông tin chi tiết về chương trình đào tạo\nXem thông tin chi tiết về chuẩn đầu ra\nKết quả quá trình học tập THPT\nKết quả bài thi ĐGNL năm 2025 của ĐHQG TP. HCM\nTổ hợp: Đang cập nhật\nĐiểm trúng tuyển 2024 (thang 40):28,00\nTháng 9, năm 2025\nKhoảng 83 đến 84 triệu đồng/năm (năm 2024)", "content": {"Bằng cấp": "Cử nhân", "Thời gian đào tạo": "Toàn thời gian: 4 năm", "Chương trình đào tạo": "Xem thông tin chi tiết về chương trình đào tạo", "Chuẩn đầu ra": "Xem thông tin chi tiết về chuẩn đầu ra", "Phương thức xét tuyển riêng": "Kết quả quá trình học tập THPT Kết quả bài thi ĐGNL năm 2025 của ĐHQG TP. HCM", "Xét tuyển theo điểm thi THPT": "Tổ hợp: Đang cập nhật Điểm trúng tuyển 2024 (thang 40):28,00", "Khai giảng": "Tháng 9, năm 2025", "Học phí": "Khoảng 83 đến 84 triệu đồng/năm (năm 2024)"}, "name": "Marketing"}], "images": ["https://admission.tdtu.edu.vn/sites/admission23/files/Tuyen-sinh/Dai-hoc/Nganh/Marketing/1.jpg", "https://admission.tdtu.edu.vn/sites/admission23/files/Tuyen-sinh/Dai-hoc/Nganh/Marketing/2.JPG", "https://admission.tdtu.edu.vn/sites/admission23/files/Tuyen-sinh/Dai-hoc/Nganh/Marketing/3.jpg"]}
{"name": "Ngôn ngữ Anh", "description": "Ngôn ngữ Anh là ngành học về ngôn ngữ, văn hóa và văn học Anh – Mỹ, thông qua việc sử dụng thành thạo các kỹ năng nghe, nói, đọc, viết, dịch thuật, … để hòa nhập với cộng đồng và đáp ứng nhu cầu phát triển của xã hội.\nCử nhân ngành Ngôn ngữ Anh Trường Đại học Tôn Đức Thắng sau khi tốt nghiệp có đầy đủ năng lực để đáp ứng được yêu cầu của thị trường lao động hiện nay ở các vị trí như: giáo viên tiếng Anh, nhân viên văn phòng hành chính, nhân viên tư vấn quốc tế của các cơ quan, công ty trong và ngoài nước, biên - phiên dịch viên, nhân viên Đại sứ quán, cơ quan ngoại giao, các tổ chức quốc tế, tổ chức chính phủ và phi chính phủ có sử dụng tiếng Anh, ... Ngoài ra, cử nhân Ngôn ngữ Anh còn có khả năng tiếp tục nghiên cứu và học tập để nâng cao trình độ ở các bậc cao học, tiến sĩ ngành giảng dạy Tiếng Anh, ngôn ngữ học ứng dụng, …", "reasons": ["Đội ngũ giảng viên giàu kinh nghiệm", "Mức học phí phù hợp", "100% sinh viên ra trường có việc làm trong vòng 12 tháng kể từ khi tốt nghiệp"], "programs": [{"tab": "Tiêu chuẩn", "major_code": "7220201", "description": "Ngoài các môn học nền tảng với các kỹ năng cần thiết, sinh viên còn được học chuyên sâu vào ngôn ngữ thông qua các môn học như ngữ âm – âm vị, hình thái học, cú pháp học, ngữ nghĩa học, … hay các môn văn học, văn hóa xã hội để hiểu và cảm nhận rõ nét về quy luật vận động của ngôn ngữ Anh trong lịch sử phát triển, đặc điểm của nền văn hóa, phong cách sống và thói quen sinh hoạt của người bản xứ thông qua cách sử dụng ngôn ngữ trong học thuật, làm việc và giao tiếp thường ngày.\nNgoài ngôn ngữ chính được đào tạo, sinh viên còn được tự chọn thêm tiếng Hoa hoặc tiếng Pháp để trau dồi song song trong suốt 4 năm học, giúp cho sinh viên có thêm phương tiện để tương tác và ứng dụng vào nghề nghiệp trong tương lai, đáp ứng nhu cầu về nguồn lao động chất lượng cao của xã hội.\nThông qua chương trình đào tạo được thiết kế mang tính thực tiễn và theo hướng kết nối, sinh viên ngành Ngôn ngữ Anh Trường Đại học Tôn Đức Thắng còn được tiếp cận sớm với môi trường và văn hoá doanh nghiệp ngay từ năm học thứ 2 qua hình thức tiếp cận, học hỏi và kiến tập tại các công ty trong và ngoài nước để vận dụng thành thạo các kỹ năng tiếng Anh trong công việc và tích luỹ kinh nghiệm thực tế. Ngoài ra, sinh viên còn được tạo đào tạo và huấn luyện kỹ năng chuyên môn bởi các chuyên gia có nhiều kinh nghiệm thông qua các khoá học ngắn hạn, hội thảo khoa học và các cuộc thi học thuật, …\nSau khi tốt nghiệp, cử nhân ngành Ngôn ngữ Anh có thể phân tích và vận dụng thuần thục các kiến thức thực tế vững chắc, lý thuyết sâu rộng về ngôn ngữ và văn hoá vào giao tiếp trong môi trường quốc tế; đặc biệt là trong lĩnh vực sư phạm, kinh tế, thương mại; đáp ứng được yêu cầu của thị trường lao động hiện nay\nCử nhân\nToàn thời gian: 4 năm\nXem thông tin chi tiết về chương trình đào tạo\nXem thông tin chi tiết về chuẩn đầu ra\nKết quả quá trình học tập THPT\nKết quả bài thi ĐGNL năm 2025 của ĐHQG TP. HCM\nTổ hợp: Đang cập nhật\nĐiểm trúng tuyển 2024 (thang 40):33,80\nTháng 9, năm 2025\nKhoảng 27 đến 28 triệu đồng/năm (năm 2024)", "content": {"Bằng cấp": "Cử nhân", "Thời gian đào tạo": "Toàn thời gian: 4 năm", "Chương trình đào tạo": "Xem thông tin chi tiết về chương trình đào tạo", "Chuẩn đầu ra": "Xem thông tin chi tiết về chuẩn đầu ra", "Phương thức xét tuyển riêng": "Kết quả quá trình học tập THPT Kết quả bài thi ĐGNL năm 2025 của ĐHQG TP. HCM", "Xét tuyển theo điểm thi THPT": "Tổ hợp: Đang cập nhật Điểm trúng tuyển 2024 (thang 40):33,80", "Khai giảng": "Tháng 9, năm 2025", "Học phí": "Khoảng 27 đến 28 triệu đồng/năm (năm 2024)"}, "name": "Ngôn ngữ Anh"}, {"tab": "Tiên tiến", "major_code": "F7220201", "description": "Ngành Ngôn ngữ Anh chương trình tiên tiến với mục tiêu không bỏ sót nhân tài và mong muốn đào tạo thêm những Cử nhân Ngôn ngữ Anh có phẩm chất và năng lực vượt trội nhằm đóng góp cho sự phát triển kinh tế đất nước. Chương trình Ngôn ngữ Anh Chất lượng cao chú trọng tính thực tiễn và trang bị cho sinh viên những kĩ năng, phản xạ cả về ngôn ngữ lẫn tác phong làm việc rất phù hợp cho việc cạnh tranh trong môi trường Quốc tế sau này.\nSinh viên được học thêm một số chứng chỉ giúp nâng cao trình độ ngoại ngữ và chuyên ngành.\nCử nhân\nToàn thời gian: 4 năm\nXem thông tin chi tiết về chương trình đào tạo\nXem thông tin chi tiết về chuẩn đầu ra\nKết quả quá trình học tập THPT\nKết quả bài thi ĐGNL năm 2025 của ĐHQG TP. HCM\nTổ hợp: Đang cập nhật\nĐiểm trúng tuyển 2024 (thang 40):30,30\nTháng 9, năm 2025\nKhoảng 62 đến 64 triệu đồng/năm (năm 2024)", "content": {"Bằng cấp": "Cử nhân", "Thời gian đào tạo": "Toàn thời gian: 4 năm", "Chương trình đào tạo": "Xem thông tin chi tiết về chương trình đào tạo", "Chuẩn đầu ra": "Xem thông tin chi tiết về chuẩn đầu ra", "Phương thức xét tuyển riêng": "Kết quả quá trình học tập THPT Kết quả bài thi ĐGNL năm 2025 của ĐHQG TP. HCM", "Xét tuyển theo điểm thi THPT": "Tổ hợp: Đang cập nhật Điểm trúng tuyển 2024 (thang 40):30,30", "Khai giảng": "Tháng 9, năm 2025", "Học phí": "Khoảng 62 đến 64 triệu đồng/năm (năm 2024)"}, "name": "Ngôn ngữ Anh"}, {"tab": "Đại học bằng tiếng Anh", "major_code": "FA7220201", "description": "Chương trình cung cấp cho sinh viên kiến thức cơ bản và chuyên sâu về âm – âm vị, hình thái học, cú pháp học, ngữ nghĩa học, … hay các môn văn học, văn hóa xã hội của ngôn ngữ Anh trong lịch sử phát triển, đặc điểm của nền văn hóa, phong cách sống và thói quen sinh hoạt của người bản xứ thông qua giáo trình và phương pháp giảng dạy hoàn toàn bằng tiếng Anh.\nKhi lựa chọn chương trình này, sinh viên ngành được tiếp cận sớm với môi trường và văn hoá doanh nghiệp ngay từ năm học đầu tiên qua hình thức học hỏi và kiến tập tại các công ty trong và ngoài nước để vận dụng thành thạo các kỹ năng tiếng Anh trong công việc và tích luỹ kinh nghiệm thực tế. Đồng thời, vào năm học thứ 3, sinh viên được hướng dẫn tham gia chương trình học phần nghề nghiệp hoặc tập sự nghề nghiệp ít nhất 1 học kỳ ở nước ngoài.\nBên cạnh đó, sinh viên được sử dụng các tiện ích học tập và sinh hoạt tại Trường; được hưởng các tiện ích hỗ trợ học, tự học tại Thư viện, hệ thống trợ giảng hỗ trợ học tập hoàn toàn miễn phí.\nCử nhân\nToàn thời gian: 4 năm\nXem thông tin chi tiết về chương trình đào tạo\nXem thông tin chi tiết về chuẩn đầu ra\nKết quả quá trình học tập THPT\nKết quả bài thi ĐGNL năm 2025 của ĐHQG TP. HCM\nTổ hợp: Đang cập nhật\nĐiểm trúng tuyển 2024 (thang 40):25,00\nTháng 9, năm 2025\nKhoảng 76 đến 80 triệu đồng/năm (năm 2024)", "content": {"Bằng cấp": "Cử nhân", "Thời gian đào tạo": "Toàn thời gian: 4 năm", "Chương trình đào tạo": "Xem thông tin chi tiết về chương trình đào tạo", "Chuẩn đầu ra": "Xem thông tin chi tiết về chuẩn đầu ra", "Phương thức xét tuyển riêng": "Kết quả quá trình học tập THPT Kết quả bài thi ĐGNL năm 2025 của ĐHQG TP. HCM", "Xét tuyển theo điểm thi THPT": "Tổ hợp: Đang cập nhật Điểm trúng tuyển 2024 (thang 40):25,00", "Khai giảng": "Tháng 9, năm 2025", "Học phí": "Khoảng 76 đến 80 triệu đồng/năm (năm 2024)"}, "name": "Ngôn ngữ Anh"}], "images": ["https://admission.tdtu.edu.vn/sites/admission23/files/Tuyen-sinh/Dai-hoc/Nganh/Ngon-ngu-anh/1.jpg", "https://admission.tdtu.edu.vn/sites/admission23/files/Tuyen-sinh/Dai-hoc/Nganh/Ngon-ngu-anh/2.jpg", "https://admission.tdtu.edu.vn/sites/admission23/files/Tuyen-sinh/Dai-hoc/Nganh/Ngon-ngu-anh/3.jpg", "https://admission.tdtu.edu.vn"]}
{"name": "Ngôn ngữ Trung Quốc", "description": "Ngôn ngữ Trung Quốc là ngành học cung cấp những kiến thức chuyên sâu về tiếng Trung và kỹ năng sử dụng thành thạo ngôn ngữ này để ứng dụng trong các lĩnh vực kinh tế, thương mại, văn hoá, giáo dục, công nghệ, …\nVới lượng kiến thức và kỹ năng được đào tạo và trau dồi trong quá trình học tập, cử nhân ngôn ngữ Trung còn có thể tham gia vào môi trường lao động cạnh tranh với những vị trí như: biên - phiên dịch viên tiếng Trung tại các công ty liên doanh, thư ký, trợ lý lãnh đạo, tiếp viên hàng không, nhân viên kinh doanh, nhân viên xuất nhập khẩu tại các công ty thương mại, chuyên viên tư vấn du học, nhân viên Đại sứ quán, giảng viên dạy tiếng Trung, hướng dẫn viên du lịch, … Sinh viên tốt nghiệp ngành Ngôn ngữ Trung Quốc còn có khả năng tiếp tục học tập nâng cao trình độ ở các bậc cao hơn như thạc sĩ, tiến sĩ ngành Giảng dạy Hán ngữ quốc tế; thạc sĩ, tiến sĩ các ngành Văn tự - Văn học - Ngôn ngữ Hán; thạc sĩ, tiến sĩ các ngành thương mại, du lịch, sư phạm ở Trung Quốc, Đài Loan, …", "reasons": ["Đội ngũ giảng viên giàu kinh nghiệm", "Mức học phí phù hợp", "100% sinh viên ra trường có việc làm trong vòng 12 tháng kể từ khi tốt nghiệp"], "programs": [{"tab": "Tiêu chuẩn", "major_code": "7220204", "description": "Ngoài những môn học đại cương, sinh viên theo học ngành Ngôn ngữ Trung tại Đại học Tôn Đức Thắng còn được cung cấp những nền tảng kiến thức chuyên sâu về ngôn ngữ và văn hoá Trung Quốc như ngữ pháp, Hán tự, văn học Trung Hoa, … giúp sinh viên hiểu rõ hơn về lịch sử, văn hoá, đất nước và con người Trung Quốc.\nChương trình đào tạo ngành Ngôn ngữ Trung còn chú trọng trang bị cho sinh viên các kỹ năng và kiến thức về biên phiên dịch, tiếng Trung thương mại, kỹ năng soạn thảo văn bản bằng tiếng Trung, … đủ để sinh viên hoạt động và công tác hiệu quả trong các lĩnh vực chuyên môn liên quan đến đất nước và con người Trung Quốc.\nĐiểm nổi bật của ngành học này tại Đại học Tôn Đức Thắng là chương trình đào tạo luôn chú trọng tính thực tiễn và cập nhật liên tục nhằm đáp ứng nhu cầu về nguồn lực chất lượng cao của thị trường lao động. Sinh viên được hướng dẫn tham gia các khoá đào tạo ngắn hạn, các buổi học thuật và chia sẻ định hướng đến từ các chuyên gia hàng đầu về ngôn ngữ. Bên cạnh đó, Nhà trường còn tăng cường đưa sinh viên đến tham quan và kiến tập ở các công ty, xí nghiệp hàng đầu Trung Quốc từ năm học thứ 2 để tìm hiểu môi trường làm việc và hội nhập văn hoá, từ đó thúc đẩy quá trình học tập tốt hơn.\nHoạt động nghiên cứu khoa học cũng được đặc biệt chú trọng trong quá trình sinh viên học tập và sinh hoạt tại TDTU. Nhà trường thường xuyên tạo điều kiện cho sinh viên tham gia vào các đề tài nghiên cứu khoa học, góp phần nâng cao kiến thức, năng lực chuyên môn, hình thành tư duy và khả năng phân tích ngôn ngữ, văn hoá và các vấn đề trong lĩnh vực thương mại bằng tiếng Trung Quốc, tạo tiền đề cho sinh viên tiếp tục học cao hơn với các chương trình sau đại học.\nCử nhân\nToàn thời gian: 4 năm\nXem thông tin chi tiết về chương trình đào tạo\nXem thông tin chi tiết về chuẩn đầu ra\nKết quả quá trình học tập THPT\nKết quả bài thi ĐGNL năm 2025 của ĐHQG TP. HCM\nTổ hợp: Đang cập nhật\nĐiểm trúng tuyển 2024 (thang 40):32,50\nTháng 9, năm 2025\nKhoảng 27 đến 28 triệu đồng/năm (năm 2024)", "content": {"Bằng cấp": "Cử nhân", "Thời gian đào tạo": "Toàn thời gian: 4 năm", "Chương trình đào tạo": "Xem thông tin chi tiết về chương trình đào tạo", "Chuẩn đầu ra": "Xem thông tin chi tiết về chuẩn đầu ra", "Phương thức xét tuyển riêng": "Kết quả quá trình học tập THPT Kết quả bài thi ĐGNL năm 2025 của ĐHQG TP. HCM", "Xét tuyển theo điểm thi THPT": "Tổ hợp: Đang cập nhật Điểm trúng tuyển 2024 (thang 40):32,50", "Khai giảng": "Tháng 9, năm 2025", "Học phí": "Khoảng 27 đến 28 triệu đồng/năm (năm 2024)"}, "name": "Ngôn ngữ Trung Quốc"}], "images": ["https://admission.tdtu.edu.vn/sites/admission23/files/Tuyen-sinh/Dai-hoc/Nganh/Ngon-ngu-TQ/1.jpg", "https://admission.tdtu.edu.vn/sites/admission23/files/Tuyen-sinh/Dai-hoc/Nganh/Ngon-ngu-TQ/4.jpg", "https://admission.tdtu.edu.vn/sites/admission23/files/Tuyen-sinh/Dai-hoc/Nganh/Ngon-ngu-TQ/3.JPG", "https://admission.tdtu.edu.vn"]}
{"name": "Quan hệ lao động", "description": "Quan hệ lao động là một trong những ngành mới được đào tạo trong những năm gần đây nhằm đón đầu xu thế phát triển và nhu cầu của xã hội về nguồn lao động. Đây là ngành học ứng dụng các kiến thức và kỹ năng về luật lao động, nguyên lý quan hệ lao động, thương lượng tập thể, hợp đồng lao động và thỏa ước lao động để xử lý tốt các quan hệ xã hội, quan hệ quần chúng; giải quyết tranh chấp lao động; quản trị nguồn nhân lực, hành vi tổ chức, thù lao và phúc lợi cho người lao động và đoàn thể.\nCử nhân quan hệ lao động có thể tham gia vào các công ty, tổ chức ở những vị trí như: nhân viên hành chính nhân sự; nhân viên đảm bảo phúc lợi; chuyên viên truyền thông nội bộ; chuyên viên phát triển thương hiệu tuyển dụng; chuyên viên tư vấn nghiên cứu các dự án về quan hệ lao động; chuyên viên thương lượng, đàm phán và giải quyết tranh chấp lao động; chuyên viên phụ trách quan hệ lao động của công đoàn, các tổ chức phi chính phủ, cơ quan nhà nước, …", "reasons": ["Chương trình đã được FIBAA chứng nhận chương trình đạt chất lượng quốc tế", "Hơn 15 năm kinh nghiệm đào tạo về ngành học này, tỷ lệ sinh viên tốt nghiệp có việc làm luôn đạt trên 98%", "Sinh viên có nhiều cơ hội học tập cùng với sinh viên quốc tế tại trường, đi ra các nước phát triển trao đổi văn hóa, học tập ngắn hạn"], "programs": [{"tab": "Tiêu chuẩn", "major_code": "7340408", "description": "Chương trình cung cấp cho sinh viên nhiều kiến thức và kỹ năng trong lĩnh vực quản trị quan hệ lao động và hành vi tổ chức như quản lý nhân sự, tâm lý tổ chức, hành vi tổ chức, tổ chức hoạt động công đoàn, pháp luật lao động, quan hệ lao động, giải quyết tranh chấp lao động, quản trị sự thay đổi, văn hóa tổ chức, phát triển tổ chức, …\nNhà trường luôn chú trọng thiết kế chương trình đào tạo sát với thực tế và mang tính ứng dụng. Sinh viên được hướng dẫn tham gia các khóa đào tạo ngắn hạn, tập sự nghề nghiệp từ năm học thứ 2 tại các liên đoàn lao động, các công ty trong và ngoài nước, góp phần củng cố nền tảng kiến thức và tích lũy kinh nghiệm thực tế.\nTính ứng dụng của chương trình đào tạo còn được thể hiện thông qua các dự án nghiên cứu khoa học và các vấn đề thực tiễn trong lĩnh vực nhân sự, sinh viên sẽ được hướng dẫn trực tiếp bởi các chuyên gia hàng đầu trong ngành quan hệ lao động để tìm hiểu, phân tích và vận dụng kiến thức đã học để tìm ra giải pháp nhằm giải quyết các vấn đề về nguồn lực ngay tại doanh nghiệp, từ đó hình thành tư duy logic, khả năng lập luận và xử lý tình huống cho sinh viên.\nSinh viên tốt nghiệp ngành Quan hệ lao động có đầy đủ năng lực và kỹ năng để đưa ra chính sách về tiền lương, phúc lợi và an toàn sức khỏe cho người lao động; nghiên cứu và thiết kế các hoạt động tạo động lực làm việc, xây dựng văn hóa tổ chức, lãnh đạo nhân viên, quản trị sự thay đổi và các hoạt động quản lý nhân sự khác để tạo ra những hành vi tích cực tại nơi làm việc, từ đó gia tăng sự hài lòng với công việc, sự cam kết trung thành với tổ chức, đảm bảo kết quả và hiệu suất công việc được nâng cao.\nCử nhân\nToàn thời gian: 4 năm\nXem thông tin chi tiết về chương trình đào tạo\nXem thông tin chi tiết về chuẩn đầu ra\nKết quả quá trình học tập THPT\nKết quả bài thi ĐGNL năm 2025 của ĐHQG TP. HCM\nTổ hợp: Đang cập nhật\nĐiểm trúng tuyển 2024 (thang 40):25,00\nTháng 9, năm 2025\nKhoảng 27 đến 28 triệu đồng/năm (năm 2024)", "content": {"Bằng cấp": "Cử nhân", "Thời gian đào tạo": "Toàn thời gian: 4 năm", "Chương trình đào tạo": "Xem thông tin chi tiết về chương trình đào tạo", "Chuẩn đầu ra": "Xem thông tin chi tiết về chuẩn đầu ra", "Phương thức xét tuyển riêng": "Kết quả quá trình học tập THPT Kết quả bài thi ĐGNL năm 2025 của ĐHQG TP. HCM", "Xét tuyển theo điểm thi THPT": "Tổ hợp: Đang cập nhật Điểm trúng tuyển 2024 (thang 40):25,00", "Khai giảng": "Tháng 9, năm 2025", "Học phí": "Khoảng 27 đến 28 triệu đồng/năm (năm 2024)"}, "name": "Quan hệ lao động (Chuyên ngành Quản lý quan hệ lao động, Chuyên ngành Hành vi tổ chức)"}], "images": ["https://admission.tdtu.edu.vn/sites/admission23/files/Tuyen-sinh/Dai-hoc/Nganh/Quan-he-lao-dong/1.jpg", "https://admission.tdtu.edu.vn/sites/admission23/files/Tuyen-sinh/Dai-hoc/Nganh/Quan-he-lao-dong/2_0.jpg", "https://admission.tdtu.edu.vn/sites/admission23/files/Tuyen-sinh/Dai-hoc/Nganh/Quan-he-lao-dong/3_0.jpg"]}
{"name": "Quản lý thể dục thể thao - Chuyên ngành Golf", "description": "Quản lý thể dục thể thao - Chuyên ngành Golf là ngành học ứng dụng các kiến thức về kinh doanh cũng như kỹ năng thực hành đánh Golf để huấn luyện, quản lý, kinh doanh và tổ chức các sự kiện, giải đấu Golf, đáp ứng nhu cầu thực tế của con người và xã hội, đặc biệt là trong bối cảnh nền kinh tế hội nhập và phát triển như hiện nay.\n\nSinh viên tốt nghiệp có thể làm trong các sân Golf, các doanh nghiệp, tổ chức, hiệp hội Golf hay resort, khách sạn,… bao gồm: chuyên viên tổ chức sự kiện- giải đấu Golf, du lịch giải trí Golf; chuyên viên nghiên cứu thị trường và kinh doanh Golf, quản lý sân Golf, quản lý khu thể thao ở khách sạn và Resort; huấn luyện viên - giáo viên dạy Golf  ở trường quốc tế và trường đại học.", "reasons": ["Đội ngũ giảng viên và chương trình học quốc tế", "Thực tập thực tế, học bổng toàn phần", "Trao đổi sinh viên quốc tế, cơ sở vật chất quốc tế"], "programs": [{"tab": "Tiêu chuẩn", "major_code": "7810301G", "description": "Chương trình đào tạo chuyên ngành Golf được xây dựng và đối sánh với chương trình đào tạo của đại học Golf hàng đầu Hàn Quốc và đã được kiểm định theo chuẩn FIBAA (Foundation for International Business Administration Accreditation) là tổ chức đảm bảo chất lượng của chính phủ Thụy Sĩ. Với yêu cầu cao về các tiêu chí kiểm định như: chất lượng giảng viên, thiết kế chương trình, cơ sở vật chất, chất lượng dịch vụ, tính ứng dụng thực tiễn, chất lượng người học... nên kiểm định FIBAA là một trong những chứng nhận tốt nhất và được công nhận rộng rãi trên thế giới.\nVới chuyên ngành Golf tại Trường Đại học Tôn Đức Thắng, sinh viên được học tập và rèn luyện trong môi trường chuyên nghiệp, hệ thống sân - bãi tập ngoài trời quy mô lớn, hệ thống phòng tập thể lực cùng phòng mô phỏng - phân tích kỹ thuật 3D hiện đại của Golfzon Hàn Quốc.\nMối quan hệ hợp tác chặt chẽ với hơn 50 doanh nghiệp thân hữu trong và ngoài nước như Vinpearl Golf; Westlake Golf, Golf Group, Passio Golf, Hiệp hội Golf Việt Nam, Golf 72+ Academy,… cùng 4 học kỳ thực tập thực tế được tổ chức trong và ngoài nước, sinh viên có điều kiện ứng dụng kiến thức chuyên môn và kỹ năng đánh golf vào thực tế để trao dồi, học hỏi và tích lũy thêm những kỹ năng làm việc hiệu quả và hoàn toàn có thể đi làm ngay khi tốt nghiệp.\nCử nhân\nToàn thời gian: 4 năm\nXem thông tin chi tiết về chương trình đào tạo\nXem thông tin chi tiết về chuẩn đầu ra\nKết quả quá trình học tập THPT\nKết quả bài thi ĐGNL năm 2025 của ĐHQG TP. HCM\nTổ hợp: Đang cập nhật\nĐiểm trúng tuyển 2024:22,00\nTháng 9, năm 2025\nKhoảng 27 đến 28 triệu đồng/năm (năm 2024)", "content": {"Bằng cấp": "Cử nhân", "Thời gian đào tạo": "Toàn thời gian: 4 năm", "Chương trình đào tạo": "Xem thông tin chi tiết về chương trình đào tạo", "Chuẩn đầu ra": "Xem thông tin chi tiết về chuẩn đầu ra", "Phương thức xét tuyển riêng": "Kết quả quá trình học tập THPT Kết quả bài thi ĐGNL năm 2025 của ĐHQG TP. HCM", "Xét tuyển theo điểm thi THPT": "Tổ hợp: Đang cập nhật Điểm trúng tuyển 2024:22,00", "Khai giảng": "Tháng 9, năm 2025", "Học phí": "Khoảng 27 đến 28 triệu đồng/năm (năm 2024)"}, "name": "Quản lý thể dục thể thao (Chuyên ngành Golf)"}], "images": ["https://admission.tdtu.edu.vn/sites/admission23/files/Tuyen-sinh/Dai-hoc/Nganh/Golf/1.jpg", "https://admission.tdtu.edu.vn/sites/admission23/files/Tuyen-sinh/Dai-hoc/Nganh/Golf/2.jpg", "https://admission.tdtu.edu.vn/sites/admission23/files/Tuyen-sinh/Dai-hoc/Nganh/Golf/3.jpeg"]}
{"name": "Quản lý thể dục thể thao - Chuyên ngành Kinh doanh thể thao và tổ chức sự kiện", "description": "Khoa Khoa học thể thao - Trường Đại học Tôn Đức Thắng là đơn vị giáo dục đầu tiên tại Việt Nam đào tạo Ngành Quản lý thể dục thể thao với chuyên ngành Kinh doanh thể thao và tổ chức sự kiện.\nChuyên ngành Kinh doanh thể thao và tổ chức sự kiện là ngành học ứng dụng các kiến thức, xu hướng về quản trị-kinh doanh, truyền thông tiếp thị, kinh tế tài chính, quản trị nguồn nhân lực cũng như các kỹ năng về phương pháp tổ chức,… vào trong hai lĩnh vực Tổ chức các loại hình sự kiện (âm nhạc, lễ hội, vui chơi giải trí và sự kiện doanh nghiệp,…) cũng như lĩnh vực Kinh doanh thể thao (quản lý câu lạc thể thao từ nghiệp dư đến chuyên nghiệp; các tổ chức hiệp hội, doanh nghiệp,…).\n\nSinh viên tốt nghiệp có thể làm trong các agency sự kiện, truyền thông, marketing; các doanh nghiệp, tổ chức, hiệp hội thể thao các cấp hay resort, khách sạn, … bao gồm: chuyên viên tổ chức sự kiện, hội nghị, hội thảo, lễ hội du lịch thể thao, du lịch giải trí; chuyên viên nghiên cứu thị trường thể thao; chuyên viên đàm phán tài trợ; chuyên viên truyền thông, tiếp thị trong lĩnh vực thể thao; chuyên viên quản lý phòng GYM, quản lý thể thao giải trí; chuyên viên quản lý du lịch thể thao, quản lý khu thể thao ở khách sạn và Resort; chuyên viên quản lý bán hàng thể thao; cán bộ quản lý công trình thể thao, câu lạc bộ thể thao ở trường quốc tế và trường đại học; chuyên viên tổ chức hoạt động thể dục thể thao tại các cơ sở, câu lạc bộ cấp quận huyện trên cả nước, …", "reasons": ["Đội ngũ giảng viên và chương trình học quốc tế", "Thực tập thực tế và học bổng toàn phần", "Trao đổi sinh viên quốc tế, cơ sở vật chất quốc tế"], "programs": [{"tab": "Tiêu chuẩn", "major_code": "7810301", "description": "Chương trình đào tạoQuản lý thể dục thể thao(Chuyên ngành Kinh doanh thể thao và Tổ chức sự kiện) được xây dựng theo tiêu chuẩn của đại học TOP 100 thế giới và được kiểm định bởi FIBAA (Foundation for International Business Administration Accreditation) là tổ chức đảm bảo chất lượng của chính phủ Thụy Sĩ. Với yêu cầu cao về các tiêu chí kiểm định như: chất lượng giảng viên, thiết kế chương trình, cơ sở vật chất, chất lượng dịch vụ, tính ứng dụng thực tiễn, chất lượng người học... nên kiểm định FIBAA là một trong những chứng nhận tốt nhất và được công nhận rộng rãi trên thế giới.\nBên cạnh các kỹ năng chuyên môn trong lĩnh vực tổ chức sự kiện và kinh doanh thể thao, sinh viên còn được trang bị cáckỹ năng quản lý bán hàng trong, giao tiếp và đám trongkinh doanh, thiết kế đồ hoạ, thiết kế dựng phim, nhiếp ảnh, phương tiện truyền thông kỹ thuật số,…\nChương trình đào tạo được thiết kế theo hướng quốc tế hóa và mang tính ứng dụng cao, với hơn 30% môn học chuyên ngành được dạy bằng Tiếng Anh bởi các giảng viên, chuyên gia quốc tế, hơn 50% môn học chuyên ngành gắn liền với thực hành.\nVới cơ sở vật chất hiện đại, các trang thiết bị thể dục thể thao tiến tiến (Nhà thi đấu, Sân vận động, Phòng Golf 3D, Hội trường sự kiện,..) của Trường, sinh viên chuyên ngành Kinh doanh thể thao và tổ chức sự kiện được trực tiếp học tập, rèn luyện,  tham gia điều hành hoạt động các câu lạc bộ thể thao, tổ chức các sự kiện lễ hội và sự kiện thể thao lớn trong và ngoài trường.\nNgoài ra, chương trình đào tạo được gắn kết chặt chẽ với hơn 50 doanh nghiệp trong và ngoài nước, qua 4 học kỳ thực tập thực tế, sinh viên có điều kiện ứng dụng kiến thức vào thực tế và làm việc như một nhân viên thực thụ để trao dồi, học hỏi và tích lũy thêm những kỹ năng làm việc hiệu quả và hoàn toàn có thể đi làm ngay khi tốt nghiệp.\nCử nhân\nToàn thời gian: 4 năm\nXem thông tin chi tiết về chương trình đào tạo\nXem thông tin chi tiết về chuẩn đầu ra\nKết quả quá trình học tập THPT\nKết quả bài thi ĐGNL năm 2025 của ĐHQG TP. HCM\nTổ hợp: Đang cập nhật\nĐiểm trúng tuyển 2024:31.30\nTháng 9, năm 2025\nKhoảng 27 đến 28 triệu đồng/năm (năm 2024)", "content": {"Bằng cấp": "Cử nhân", "Thời gian đào tạo": "Toàn thời gian: 4 năm", "Chương trình đào tạo": "Xem thông tin chi tiết về chương trình đào tạo", "Chuẩn đầu ra": "Xem thông tin chi tiết về chuẩn đầu ra", "Phương thức xét tuyển riêng": "Kết quả quá trình học tập THPT Kết quả bài thi ĐGNL năm 2025 của ĐHQG TP. HCM", "Xét tuyển theo điểm thi THPT": "Tổ hợp: Đang cập nhật Điểm trúng tuyển 2024:31.30", "Khai giảng": "Tháng 9, năm 2025", "Học phí": "Khoảng 27 đến 28 triệu đồng/năm (năm 2024)"}, "name": "Quản lý thể dục thể thao (Chuyên ngành Kinh doanh thể thao và tổ chức sự kiện)"}], "images": ["https://admission.tdtu.edu.vn/sites/admission23/files/Tuyen-sinh/Dai-hoc/Nganh/KDTT-TCSK/1.png", "https://admission.tdtu.edu.vn/sites/admission23/files/Tuyen-sinh/Dai-hoc/Nganh/KDTT-TCSK/2.png", "https://admission.tdtu.edu.vn/sites/admission23/files/Tuyen-sinh/Dai-hoc/Nganh/KDTT-TCSK/3.JPG"]}
{"name": "Quản lý xây dựng", "description": "Quản lý xây dựng là ngành học vận dụng kiến thức chuyên môn để quản lý các dự án xây dựng, hoặc thực hiện nhiệm vụ tư vấn quản lý toàn bộ dự án, lập và thẩm định dự án đầu tư, lập hồ sơ thiết kế tổ chức thi công, tư vấn đấu thầu, quản lý thi công, nghiệm thu bàn giao công trình đưa vào sử dụng và thanh quyết toán công trình, kiểm định công trình xây dựng, v.v. Đối với một quốc gia đang phát triển nhanh như Việt Nam, nhu cầu về các chuyên gia quản lý xây dựng ngày càng cao, nhằm đảm bảo hiệu quả đầu tư dự án trong ngành xây dựng và sự phát triển bền vững của đất nước.\nSinh viên tốt nghiệp ngành Quản lý xây dựng có đủ năng lực và kỹ năng để ứng tuyển vào hầu hết các vị trí công việc liên quan đến công tác quản lý dự án tại doanh nghiệp xây dựng, đầu tư bất động sản như thiết kế, giám sát, thi công, đấu thầu, đầu tư, thanh quyết toán,…; làm việc tại các cơ quan quản lý Nhà nước và cơ quan chuyên môn của chủ đầu tư về xây dựng; trở thành giảng viên, nghiên cứu viên, hoặc tiếp tục bậc học cao hơn tại các cơ sở đào tạo trong và ngoài nước.", "reasons": ["Chương trình đào tạo theo tiêu chuẩn quốc tế", "Đội ngũ giảng viên có trình độ chuyên môn cao, giàu kinh nghiệm thực tế", "Cơ hội thực tập và việc làm cao"], "programs": [{"tab": "Tiêu chuẩn", "major_code": "7580302", "description": "Chương trình Quản lý xây dựng giảng dạy trong 4 năm học, chia thành 8 học kỳ. Từ học kỳ 2, sinh viên bắt đầu học các môn cơ sở ngành như: trắc địa công trình, cơ học kết cấu, nền móng, bê tông cốt thép, kết cấu thép công trình, kỹ thuật và tổ chức thi công, pháp luật trong quản lý dự án xây dựng.\nTừ học kỳ 4 sinh viên được trang bị kiến thức chuyên ngành như quản lý dự án theo tiêu chuẩn quốc tế (PMP), lập và thẩm định dự án đầu tư, lập tổng mức đầu tư và tổng dự toán công trình, quản lý hợp đồng, đấu thầu và mua sắm, giám sát dự án xây dựng, quản lý rủi ro, chất lượng, an toàn dự án, kiểm định công trình xây dựng, mô hình thông tin công trình BIM,…\nThời lượng thực hành thực tế chiếm hơn 30% tổng thời lượng đào tạo, sinh viên được trải nghiệm tại các dự án xây dựng, nhằm nhanh chóng tiếp cận kinh nghiệm giám sát và quản lý thực tiễn ngay từ những năm đầu tiên học tập.\nĐiểm nổi bật là chương trình đào tạo được thiết kế theo tiêu chuẩn quốc tế với 80% giáo trình, tài liệu bằng tiếng Anh cùng đội ngũ giảng viên có nhiều kinh nghiệm kinh nghiệm trong quản lý dự án chuyên nghiệp, là các Giáo sư, Tiến sĩ tốt nghiệp nước ngoài như Nhật Bản, Đài Loan, Úc, Hàn Quốc,... Đặc biệt, nội dung và phương pháp giảng dạy hiện đại, liên tục đổi mới nhằm khuyến khích và phát huy tính sáng tạo của người học.\nCử nhân\nToàn thời gian: 4 năm\nXem thông tin chi tiết về chương trình đào tạo\nXem thông tin chi tiết về chuẩn đầu ra\nKết quả quá trình học tập THPT\nKết quả bài thi ĐGNL năm 2025 của ĐHQG TP. HCM\nTổ hợp: Đang cập nhật\nĐiểm trúng tuyển năm 2024 (thang 40):23,00\nTháng 9, năm 2025\nKhoảng 31 đến 32 triệu đồng/năm (năm 2024)", "content": {"Bằng cấp": "Cử nhân", "Thời gian đào tạo": "Toàn thời gian: 4 năm", "Chương trình đào tạo": "Xem thông tin chi tiết về chương trình đào tạo", "Chuẩn đầu ra": "Xem thông tin chi tiết về chuẩn đầu ra", "Phương thức xét tuyển riêng": "Kết quả quá trình học tập THPT Kết quả bài thi ĐGNL năm 2025 của ĐHQG TP. HCM ", "Xét tuyển theo điểm thi THPT": "Tổ hợp: Đang cập nhật Điểm trúng tuyển năm 2024 (thang 40):23,00", "Khai giảng": "Tháng 9, năm 2025", "Học phí": "Khoảng 31 đến 32 triệu đồng/năm (năm 2024)"}, "name": "Quản lý xây dựng"}], "images": ["https://admission.tdtu.edu.vn/sites/admission23/files/Tuyen-sinh/Dai-hoc/Nganh/Quan-ly-xay-dung/1.jpg", "https://admission.tdtu.edu.vn/sites/admission23/files/Tuyen-sinh/Dai-hoc/Nganh/Quan-ly-xay-dung/2.JPG", "https://admission.tdtu.edu.vn/sites/admission23/files/Tuyen-sinh/Dai-hoc/Nganh/Quan-ly-xay-dung/3.jpg"]}
{"name": "Quản trị kinh doanh (Chuyên ngành Quản trị chuỗi cung ứng)", "description": "Việt Nam đang khẳng định vị thế là một mắt xích quan trọng trong chuỗi cung ứng toàn cầu. Với tốc độ tăng trưởng kinh tế vượt bậc, sự hội nhập quốc tế sâu rộng qua các hiệp định thương mại tự do như CPTPP và EVFTA, cùng làn sóng đầu tư nước ngoài không ngừng gia tăng, đất nước ta đang trở thành trung tâm sản xuất hàng đầu khu vực. Sự hiện diện của các tập đoàn lớn và dòng chảy thương mại mạnh mẽ tạo ra cơ hội phát triển vượt bậc, đồng thời đặt ra yêu cầu cấp thiết về quản trị chuỗi cung ứng hiệu quả để đảm bảo nguồn cung ổn định, giao hàng đúng hạn và chất lượng sản phẩm tối ưu. Đây không chỉ là yếu tố sống còn của doanh nghiệp mà còn là động lực thúc đẩy nền kinh tế Việt Nam phát triển bền vững trong môi trường cạnh tranh toàn cầu.\nChương trình Cử nhân ngành Quản trị Kinh doanh chuyên ngành Quản trị Chuỗi cung ứng tại Trường Đại học Tôn Đức Thắng được thiết kế để đáp ứng nhu cầu này. Chương trình cung cấp kiến thức chuyên sâu về quản lý vận tải, tồn kho, logistics và chuỗi cung ứng bền vững, đồng thời tích hợp các công nghệ hiện đại như IoT, Blockchain và Big Data. Sinh viên được đào tạo kỹ năng phân tích sắc bén, hoạch định chiến lược thông minh, và quản lý toàn diện, kết hợp hài hòa giữa học thuật và thực tiễn.\n\nNgoài ra, chương trình còn chú trọng phát triển kỹ năng lãnh đạo, tư duy sáng tạo và tinh thần trách nhiệm xã hội, giúp sinh viên sẵn sàng đối mặt với thách thức từ toàn cầu hóa và chuyển đổi số. Tốt nghiệp ngành này, sinh viên có thể tự tin đảm nhận nhiều vị trí đa dạng trong chuỗi cung ứng và mở rộng sự nghiệp trên thị trường quốc tế.", "reasons": ["Chương trình đào tạo toàn diện, bám sát nhu cầu thực tiễn", "Liên tục cập nhật xu hướng", "Đội ngũ giảng viên chuyên môn cao"], "programs": [{"tab": "Tiêu chuẩn", "major_code": "7340101", "description": "Chương trình cử nhân ngành Quản trị kinh doanh (Chuyên ngành Quản trị chuỗi cung ứng) tại Trường Đại học Tôn Đức Thắng (TDTU) không chỉ trang bị cho sinh viên một nền tảng kiến thức vững chắc mà còn mở ra cơ hội nghề nghiệp phong phú và đa dạng. Tốt nghiệp ngành này, người học có thể tự tin đảm nhận những vị trí quan trọng như quản lý logistics, điều phối chuỗi cung ứng, chuyên gia hoạch định nhu cầu hay quản lý rủi ro trong chuỗi cung ứng - những lĩnh vực đang ngày càng được săn đón trên thị trường lao động. Không dừng lại ở đó, chương trình còn giúp sinh viên phát triển sâu hơn trong các lĩnh vực hoạch định chiến lược, thiết kế chuỗi cung ứng, nghiên cứu thị trường, tư vấn quản trị hoặc tham gia vào môi trường học thuật với vai trò giảng dạy và nghiên cứu tại các tổ chức giáo dục hàng đầu.\nVới chương trình được thiết kế hiện đại, kết hợp giữa học thuật và thực tiễn, cử nhân ngành Quản trị kinh doanh (Chuyên ngành Quản trị chuỗi cung ứng) tại TDTU được trang bị đầy đủ các kỹ năng cần thiết để sẵn sàng đối mặt với thách thức từ toàn cầu hóa và chuyển đổi số. Đặc biệt, sinh viên tốt nghiệp có thể không chỉ tạo dựng sự nghiệp tại Việt Nam mà còn tự tin chinh phục thị trường quốc tế, khẳng định giá trị và bản lĩnh của mình trên bản đồ nhân lực toàn cầu.\nCử nhân\nToàn thời gian: 4 năm\nXem thông tin chi tiết về chương trình đào tạo\nXem thông tin chi tiết về chuẩn đầu ra\nKết quả quá trình học tập THPT\nKết quả bài thi ĐGNL năm 2025 của ĐHQG TP. HCM\nTổ hợp: Đang cập nhật\nTháng 9, năm 2025\nĐang cập nhật", "content": {"Bằng cấp": "Cử nhân", "Thời gian đào tạo": "Toàn thời gian: 4 năm", "Chương trình đào tạo": "Xem thông tin chi tiết về chương trình đào tạo", "Chuẩn đầu ra": "Xem thông tin chi tiết về chuẩn đầu ra", "Phương thức xét tuyển riêng": "Kết quả quá trình học tập THPT Kết quả bài thi ĐGNL năm 2025 của ĐHQG TP. HCM", "Xét tuyển theo điểm thi THPT": "Tổ hợp: Đang cập nhật", "Khai giảng": "Tháng 9, năm 2025", "Học phí": "Đang cập nhật"}, "name": "Quản trị kinh doanh (Chuyên ngành Quản trị chuỗi cung ứng)"}], "images": ["https://admission.tdtu.edu.vn/sites/admission23/files/Tuyen-sinh/Dai-hoc/Nganh/QTKD-QLCCU/1.JPG", "https://admission.tdtu.edu.vn/sites/admission23/files/Tuyen-sinh/Dai-hoc/Nganh/QTKD-QLCCU/2.jpg", "https://admission.tdtu.edu.vn/sites/admission23/files/Tuyen-sinh/Dai-hoc/Nganh/QTKD-QLCCU/3.jpg"]}
{"name": "Quản trị kinh doanh – Chuyên ngành Quản trị nguồn nhân lực", "description": "Quản trị kinh doanh – Chuyên ngành Quản trị nguồn nhân lực là một chương trình đào tạo xây dựng kiến thức nền tảng và kỹ năng quản lý nguồn nhân lực trong môi trường kinh doanh hiện đại cho người học. Sinh viên được trang bị các kiến thức về hoạch định chiến lược và kế hoạch nhân sự; tuyển dụng, đào tạo và phát triển, quan hệ lao động, đãi ngộ, đánh giá và quản lý hiệu quả công việc; duy trì và phát triển tổ chức. Thông qua việc kết hợp giữa lý thuyết và thực hành, sinh viên sẽ nắm bắt được các xu hướng mới nhất trong lĩnh vực nhân sự và có thể vận dụng linh hoạt trong công việc tương lai.\nNgoài ra, sinh viên có cơ hội tham gia vào các dự án thực tế, kiến tập tại doanh nghiệp, giúp phát triển các kỹ năng mềm quan trọng như lãnh đạo, giao tiếp, đàm phán, tư duy sáng tạo, và giải quyết vấn đề trong môi trường làm việc chuyên nghiệp. Qua đó, sinh viên hoàn thiện bộ khung năng lực của bản thân, bao gồm kiến thức – kỹ năng – thái độ, để sẵn sàng trở thành những nhà quản trị nhân sự tài năng, đáp ứng nhu cầu thị trường lao động hiện nay.", "reasons": ["Chương trình đào tạo tiên tiến, cập nhật xu hướng", "Đội ngũ giảng viên chuyên môn cao", "Hợp tác với các doanh nghiệp hàng đầu"], "programs": [{"tab": "Tiêu chuẩn", "major_code": "7340101", "description": "Chương trình Tiêu chuẩn, sinh viên ngành Quản trị nhân lực sẽ được học các kiến thức từ tổng quan đến chuyên ngành trong lĩnh vực quản trị nhân sự, bao gồm tuyển dụng và thu hút nhân tài, hoạch định nguồn nhân lực, đào tạo và phát triển, tiền lương và phúc lợi, phát triển tổ chức,... Ngoài ra, ngành học còn tạo điều kiện cho người học được phát triển các kỹ năng nghề nghiệp như kỹ năng lập kế hoạch, quản lý hành chính, xử lý tình huống trong quan hệ lao động; chăm sóc sức khỏe nhân viên; bảo hiểm và trí tuệ cảm xúc.\nTất cả những cơ hội được học tập và thực hành đó luôn được Nhà trường tạo điều kiện thông qua các dự án nghiên cứu thực tiễn thuộc về lĩnh vực quản trị nhân lực, như phân tích thị trường lao động, các vấn đề nhân sự tại một công ty,... Từ đó, sinh viên sẽ hình thành các năng lực tư duy, kỹ năng phản biện, khả năng phân tích, đánh giá và giải quyết tình huống như một nhà quản trị thực thụ.\nBên cạnh đó, thông qua mạng lưới đối tác doanh nghiệp thân hữu trong nước và quốc tế, Nhà trường thường xuyên tổ chức các chương trình đi tham quan, kiến tập tại doanh nghiệp với chủ trương đổi mới căn bản, toàn diện giáo dục và đào tạo. Qua đó, sinh viên có cơ hội tiếp cận với đa dạng môi trường và văn hóa làm việc, đồng thời cập nhật xu hướng mới nhất trong lĩnh vực chuyên môn để tích lũy kinh nghiệm bản thân, chuẩn bị cho hành trang sự nghiệp trong tương lai.\nCử nhân\nToàn thời gian: 4 năm\nXem thông tin chi tiết về chương trình đào tạo\nXem thông tin chi tiết về chuẩn đầu ra\nKết quả quá trình học tập THPT\nKết quả bài thi ĐGNL năm 2025 của ĐHQG TP. HCM\nTổ hợp: Đang cập nhật\nĐiểm trúng tuyển 2024 (thang 40):33,00\nTháng 9, năm 2025\nKhoảng 27 đến 28 triệu đồng/năm (năm 2024)", "content": {"Bằng cấp": "Cử nhân", "Thời gian đào tạo": "Toàn thời gian: 4 năm", "Chương trình đào tạo": "Xem thông tin chi tiết về chương trình đào tạo", "Chuẩn đầu ra": "Xem thông tin chi tiết về chuẩn đầu ra", "Phương thức xét tuyển riêng": "Kết quả quá trình học tập THPT Kết quả bài thi ĐGNL năm 2025 của ĐHQG TP. HCM", "Xét tuyển theo điểm thi THPT": "Tổ hợp: Đang cập nhật Điểm trúng tuyển 2024 (thang 40):33,00", "Khai giảng": "Tháng 9, năm 2025", "Học phí": "Khoảng 27 đến 28 triệu đồng/năm (năm 2024)"}, "name": "Quản trị kinh doanh – Chuyên ngành Quản trị nguồn nhân lực"}, {"tab": "Tiên tiến", "major_code": "F7340101", "description": "Chương trình Tiên tiến (tiền thân là Chương trình đại học Chất lượng cao), Cử nhân ngành Quản trị nhân lực được trang bị đầy đủ các kiến thức về pháp luật; quản lý nguồn nhân lực từ cấp chiến lược đến cấp vận hành; các kỹ năng triển khai công việc quản lý nhân sự như săn tìm tài năng, sàng lọc ứng viên, tổ chức hành chính, và tái cơ cấu tổ chức vì mục tiêu phát triển chung.\nNgoài ra, chương trình có những đặc điểm nổi bật như sau:\nTham gia các hoạt động thực tế nghề nghiệp thông qua các cuộc thi chuyên ngành, các lớp học chuyên đề, hội thảo, tọa đàm, các buổi kiến tập tại doanh nghiệp ngay từ năm nhất;\nChương trình trao đổi một học kỳ, trao đổi hè với các trường đại học nước ngoài;\nĐào tạo ngoại ngữ và các kỹ năng mềm, bao gồm các kỹ năng làm việc độc lập, giao tiếp Tiếng Anh, tư duy đổi mới và sáng tạo, kỹ năng lãnh đạo, kỹ năng phân tích và xử lý dữ liệu trong quản lý nhân sự;\nGiáo trình giảng dạy được đối sánh với chương trình của các trường Đại học Top 100 thế giới; 50% môn học chuyên ngành được giảng dạy bằng tiếng Anh.\nCử nhân\nToàn thời gian: 4 năm\nXem thông tin chi tiết về chương trình đào tạo\nXem thông tin chi tiết về chuẩn đầu ra\nKết quả quá trình học tập THPT\nKết quả bài thi ĐGNL năm 2025 của ĐHQG TP. HCM\nTổ hợp: Đang cập nhật\nĐiểm trúng tuyển 2024 (thang 40):30,00\nTháng 9, năm 2025\nKhoảng 62 đến 64 triệu đồng/năm (năm 2024)", "content": {"Bằng cấp": "Cử nhân", "Thời gian đào tạo": "Toàn thời gian: 4 năm", "Chương trình đào tạo": "Xem thông tin chi tiết về chương trình đào tạo", "Chuẩn đầu ra": "Xem thông tin chi tiết về chuẩn đầu ra", "Phương thức xét tuyển riêng": "Kết quả quá trình học tập THPT Kết quả bài thi ĐGNL năm 2025 của ĐHQG TP. HCM", "Xét tuyển theo điểm thi THPT": "Tổ hợp: Đang cập nhật Điểm trúng tuyển 2024 (thang 40):30,00", "Khai giảng": "Tháng 9, năm 2025", "Học phí": "Khoảng 62 đến 64 triệu đồng/năm (năm 2024)"}, "name": "Quản trị kinh doanh – Chuyên ngành Quản trị nguồn nhân lực"}], "images": ["https://admission.tdtu.edu.vn/sites/admission23/files/Tuyen-sinh/Dai-hoc/Nganh/QLNL/1.JPG", "https://admission.tdtu.edu.vn/sites/admission23/files/Tuyen-sinh/Dai-hoc/Nganh/QLNL/2.jpg", "https://admission.tdtu.edu.vn/sites/admission23/files/Tuyen-sinh/Dai-hoc/Nganh/QLNL/3.jpg"]}
{"name": "Quản trị kinh doanh – Chuyên ngành Quản trị nhà hàng khách sạn", "description": "Chương trình Cử nhân Quản trị Kinh doanh chuyên ngành Quản trị Nhà hàng - Khách sạn được thiết kế đạt chuẩn quốc tế, mang đến cho sinh viên nền tảng vững chắc để tự tin và thích nghi trong môi trường làm việc chuyên nghiệp. Với nội dung đào tạo toàn diện, chương trình không chỉ tập trung vào kiến thức lý thuyết mà còn chú trọng phát triển kỹ năng thực hành, xử lý tình huống, ra quyết định và kỹ thuật quản trị trong ngành dịch vụ.\nSinh viên sẽ được học từ đội ngũ giảng viên giàu kinh nghiệm cùng giáo trình giảng dạy tham khảo từ các trường đại học hàng đầu thế giới. Hệ thống tài liệu và giáo trình được trang bị đầy đủ tại Thư viện trường, hỗ trợ tối ưu cho việc học tập và nghiên cứu. Đồng thời, chương trình còn tạo cơ hội trải nghiệm thực tế tại các khách sạn, khu nghỉ dưỡng cao cấp, giúp sinh viên hiểu sâu hơn về môi trường làm việc chuyên nghiệp.\nKhi tốt nghiệp, cử nhân ngành này có thể đảm nhận nhiều vị trí quan trọng tại các tập đoàn khách sạn quốc tế và trong nước, khu nghỉ dưỡng, trung tâm hội nghị và sự kiện. Các vị trí tiềm năng bao gồm: nhân viên, giám sát, quản lý tại các bộ phận Lễ tân, Buồng phòng, Sales, Marketing và nhiều lĩnh vực liên quan.", "reasons": ["Chương trình đào tạo tiên tiến, cập nhật xu hướng", "Tham quan, kiến tập, thực tập tại các khách sạn lớn, uy tín trong và ngoài nước", "100% sinh viên ra trường có việc làm trong vòng 12 tháng kể từ khi tốt nghiệp"], "programs": [{"tab": "Tiêu chuẩn", "major_code": "7340101N", "description": "Chương trình Tiêu chuẩn, cử nhân ngành Quản trị Kinh doanh chuyên ngành Quản trị Nhà hàng - Khách sạn được thiết kế chuyên sâu, giúp sinh viên nắm bắt toàn diện cả lý thuyết lẫn thực tiễn. Sinh viên sẽ được trang bị kiến thức cơ bản về nghiệp vụ và quản trị Lễ tân, Buồng phòng, Ẩm thực, đồng thời khám phá các lĩnh vực chuyên sâu như Quản trị Resort, Quản trị MICE, Hành vi người tiêu dùng, Quản lý hệ thống phòng, Nhân sự, Giao tiếp khách hàng, Giải quyết rủi ro và Tổ chức sự kiện. Mục tiêu là giúp sinh viên thấu hiểu xu hướng khách hàng và xây dựng chiến lược hiệu quả để vận hành các cơ sở lưu trú hoặc chuỗi nhà hàng cao cấp đạt tiêu chuẩn 5 sao.\nChương trình kết hợp lý thuyết với thực hành tại các phòng mô phỏng hiện đại ngay trong trường và các kỳ thực tập thực tế tại các nhà hàng, khách sạn lớn ở Thành phố Hồ Chí Minh và cả nước. Sinh viên cũng tham gia các buổi tọa đàm, workshop chuyên ngành với sự dẫn dắt của các diễn giả uy tín, các chuyến tham quan thực tế và các cuộc thi chuyên ngành nhằm tăng cường kỹ năng chuyên môn và tích lũy kinh nghiệm thực tiễn.\nSau khi tốt nghiệp, cử nhân chuyên ngành này đủ khả năng đảm nhiệm các vị trí từ nhân viên đến quản lý tại các tập đoàn khách sạn, khu nghỉ dưỡng quốc tế, nhà hàng cao cấp. Về mảng lưu trú, sinh viên có thể làm việc trong bộ phận Lễ tân, Buồng phòng, Sales, Marketing hoặc Nhân sự tại các khách sạn 4-5 sao. Về mảng ẩm thực, cơ hội mở rộng đến các vị trí quản lý tại nhà hàng A la carte, buffet hay nhà hàng tiệc cưới.\nCử nhân\nToàn thời gian: 4 năm\nXem thông tin chi tiết về chương trình đào tạo\nXem thông tin chi tiết về chuẩn đầu ra\nKết quả quá trình học tập THPT\nKết quả bài thi ĐGNL năm 2025 của ĐHQG TP. HCM\nTổ hợp: Đang cập nhật\nĐiểm trúng tuyển 2024 (thang 40):32,00\nTháng 9, năm 2025\nKhoảng 27 đến 28 triệu đồng/năm (năm 2024)", "content": {"Bằng cấp": "Cử nhân", "Thời gian đào tạo": "Toàn thời gian: 4 năm", "Chương trình đào tạo": "Xem thông tin chi tiết về chương trình đào tạo", "Chuẩn đầu ra": "Xem thông tin chi tiết về chuẩn đầu ra", "Phương thức xét tuyển riêng": "Kết quả quá trình học tập THPT Kết quả bài thi ĐGNL năm 2025 của ĐHQG TP. HCM", "Xét tuyển theo điểm thi THPT": "Tổ hợp: Đang cập nhật Điểm trúng tuyển 2024 (thang 40):32,00", "Khai giảng": "Tháng 9, năm 2025", "Học phí": "Khoảng 27 đến 28 triệu đồng/năm (năm 2024)"}, "name": "Quản trị kinh doanh (Chuyên ngành Quản trị nhà hàng khách sạn)"}, {"tab": "Tiên tiến", "major_code": "F7340101N", "description": "Chương trình Tiên tiến, cử nhân ngành Quản trị Kinh doanh chuyên ngành Quản trị Nhà hàng - Khách sạn được thiết kế với nhiều ưu điểm vượt trội, đáp ứng nhu cầu đào tạo nguồn nhân lực chất lượng cao cho ngành dịch vụ, tạo điều kiện tối ưu cho sự tương tác giữa giảng viên và sinh viên, đảm bảo chất lượng học tập cao nhất.\nNgay từ năm đầu tiên, sinh viên được tham gia thực tập tại các khách sạn 4-5 sao chuẩn quốc tế, mang đến cơ hội trải nghiệm thực tế, giúp kết nối lý thuyết và thực hành theo phương châm \"học đi đôi với hành\". Chương trình trang bị cho sinh viên không chỉ kiến thức chuyên môn mà còn các kỹ năng quan trọng như xử lý tình huống, ra quyết định, quản trị, đàm phán và lãnh đạo trong lĩnh vực Nhà hàng - Khách sạn. Các cuộc thi chuyên ngành cũng được tổ chức thường xuyên để sinh viên củng cố kiến thức, gia tăng cọ xát và rèn luyện sự tự tin trong môi trường cạnh tranh.\nSinh viên tốt nghiệp có cơ hội làm việc tại các khách sạn, khu nghỉ dưỡng và chuỗi nhà hàng hàng đầu thế giới, đảm nhận các vị trí từ nhân viên đến quản lý ở bộ phận Lễ tân, Buồng phòng, Sales, Marketing, Nhân sự, hoặc quản lý nhà hàng A la carte, buffet, tiệc cưới. Sự phát triển của các khu nghỉ dưỡng tích hợp công viên giải trí và dịch vụ ẩm thực cũng mở ra nhiều cơ hội tại các resort cao cấp. Đây là lựa chọn lý tưởng cho những ai muốn phát triển sự nghiệp trong ngành Nhà hàng - Khách sạn đầy tiềm năng.\nCử nhân\nToàn thời gian: 4 năm\nXem thông tin chi tiết về chương trình đào tạo\nXem thông tin chi tiết về chuẩn đầu ra\nKết quả quá trình học tập THPT\nKết quả bài thi ĐGNL năm 2025 của ĐHQG TP. HCM\nTổ hợp: Đang cập nhật\nĐiểm trúng tuyển 2024 (thang 40):27,80\nTháng 9, năm 2025\nKhoảng 62 đến 64 triệu đồng/năm (năm 2024)", "content": {"Bằng cấp": "Cử nhân", "Thời gian đào tạo": "Toàn thời gian: 4 năm", "Chương trình đào tạo": "Xem thông tin chi tiết về chương trình đào tạo", "Chuẩn đầu ra": "Xem thông tin chi tiết về chuẩn đầu ra", "Phương thức xét tuyển riêng": "Kết quả quá trình học tập THPT Kết quả bài thi ĐGNL năm 2025 của ĐHQG TP. HCM", "Xét tuyển theo điểm thi THPT": "Tổ hợp: Đang cập nhật Điểm trúng tuyển 2024 (thang 40):27,80", "Khai giảng": "Tháng 9, năm 2025", "Học phí": "Khoảng 62 đến 64 triệu đồng/năm (năm 2024)"}, "name": "Quản trị kinh doanh (Chuyên ngành Quản trị nhà hàng khách sạn)"}, {"tab": "Đại học bằng tiếng Anh", "major_code": "FA7340101N", "description": "Chương trình đại học bằng tiếng Anh cử nhân Quản trị kinh doanh (Chuyên ngành Quản trị nhà hàng khách sạn) là chương trình đạt chuẩn quốc tế được giảng dạy và học tập bằng 100% tiếng Anh cung cấp cho người học các kiến thức chuyên ngành và trang bị đầy đủ kỹ năng chuyên môn để nắm bắt kịp thời xu hướng, tình hình phát triển và nhu cầu của ngành nhà hàng, khách sạn tại Việt Nam và thế giới.\nChương trình đại học bằng tiếng Anh có các ưu điểm cũng như khác biệt so với các chương trình khác như ngôn ngữ giảng dạy và học tập bằng tiếng Anh, quy mô lớp học nhỏ (30-40 sinh viên) tăng mức độ tương tác giữa người dạy và người học. Đặc biệt, sinh viên được ưu tiên tham gia các khóa học trao đổi 1 học kỳ hoặc khóa học ngắn hạn với các trường đại học quốc tế.\nBên cạnh đó, khi tham gia học tập theo chương trình đại học bằng tiếng Anh cử nhân Quản trị kinh doanh (Chuyên ngành Quản trị nhà hàng khách sạn), sinh viên được thực tập tại các khách sạn từ 4-5 sao chuẩn quốc tế ngay từ năm đầu tiên nhằm trải nghiệm thực tế tại doanh nghiệp theo phương châm học đi đôi với hành. Sinh viên được trang bị kiến thức, song song với những năng lực chuyên sâu về thực hành, phương pháp xử lý tình huống và ra quyết định, kỹ năng quản trị, kỹ năng đàm phán trong kinh doanh và quản lý Nhà hàng Khách sạn. Ngoài ra, các cuộc thi chuyên ngành cũng được tổ chức nhằm tăng cường sự cọ xát chuyên ngành cho sinh viên cũng như hỗ trợ sinh viên ôn tập các kiến thức cần có.\nSinh viên chương trình cử nhân Quản trị kinh doanh (Chuyên ngành Quản trị nhà hàng khách sạn) tại Trường Đại học Tôn Đức Thắng có triển vọng nghề nghiệp đa dạng sau khi tốt nghiệp. Người học sẽ có đủ khả năng để làm việc trong những khách sạn, khu nghỉ dưỡng của các tập đoàn hàng đầu thế giới tại các vị trí khác nhau từng phòng ban và bộ phận về cả 02 mảng lưu trú và ẩm thực. Về mảng lưu trú, có các chức vụ từ nhân viên đến giám sát, cấp quản lý của bộ phận Lễ tân, bộ phận Buồng phòng, các nhà hàng với phong cách đặc sắc khác nhau, bộ phận Sales, Marketing, Nhân sự tại các khách sạn và khu nghỉ dưỡng từ 4 đến 5 sao thuộc các tập đoàn hàng đầu thế giới. Về mảng ẩm thực, các em sinh viên có thể đảm nhiệm những vị trí lên đến cấp quản lý tại các nhà hàng A la carte, các chi nhánh nhà hàng tiệc cưới, nhà hàng buffet… Đặc biệt hơn nữa, với sự phát triển gần đây của các khu nghỉ dưỡng mang tính thư giãn, giải trí, sinh viên còn có cơ hội thực tập và làm việc tại các resort đi kèm với công viên chủ đề, khu vui chơi giải trí và ăn uống tại các tỉnh thành của Việt Nam.\nCử nhân\nToàn thời gian: 4 năm\nXem thông tin chi tiết về chương trình đào tạo\nXem thông tin chi tiết về chuẩn đầu ra\nKết quả quá trình học tập THPT\nKết quả bài thi ĐGNL năm 2025 của ĐHQG TP. HCM\nTổ hợp: Đang cập nhật\nĐiểm trúng tuyển 2024 (thang 40):27,00\nTháng 9, năm 2025\nKhoảng 83 đến 84 triệu đồng/năm (năm 2024)", "content": {"Bằng cấp": "Cử nhân", "Thời gian đào tạo": "Toàn thời gian: 4 năm", "Chương trình đào tạo": "Xem thông tin chi tiết về chương trình đào tạo", "Chuẩn đầu ra": "Xem thông tin chi tiết về chuẩn đầu ra", "Phương thức xét tuyển riêng": "Kết quả quá trình học tập THPT Kết quả bài thi ĐGNL năm 2025 của ĐHQG TP. HCM", "Xét tuyển theo điểm thi THPT": "Tổ hợp: Đang cập nhật Điểm trúng tuyển 2024 (thang 40):27,00", "Khai giảng": "Tháng 9, năm 2025", "Học phí": "Khoảng 83 đến 84 triệu đồng/năm (năm 2024)"}, "name": "Quản trị kinh doanh (Chuyên ngành Quản trị nhà hàng khách sạn)"}, {"tab": "Liên kết quốc tế", "major_code": "K7340101N", "description": "Cử nhân (song bằng)\n4 năm (2,5 năm đầu học tại TDTU, 1,5 năm sau học tại Trường liên kết)\nXem thông tin chi tiết về chương trình đào tạo\nXem thông tin chi tiết về chuẩn đầu ra\nKết quả quá trình học tập THPT\nKết quả bài thi ĐGNL năm 2025 của ĐHQG TP. HCM\nTổ hợp: Đang cập nhật\nĐiểm trúng tuyển 2024 (thang 40):28,00\nTháng 9, năm 2025\nGiai đoạn 1: khoảng 78 đến 79 triệu đồng/năm (năm 2024)", "content": {"Bằng cấp": "Cử nhân (song bằng)", "Thời gian đào tạo": "4 năm (2,5 năm đầu học tại TDTU, 1,5 năm sau học tại Trường liên kết)", "Chương trình đào tạo": "Xem thông tin chi tiết về chương trình đào tạo", "Chuẩn đầu ra": "Xem thông tin chi tiết về chuẩn đầu ra", "Phương thức xét tuyển riêng": "Kết quả quá trình học tập THPT Kết quả bài thi ĐGNL năm 2025 của ĐHQG TP. HCM", "Xét tuyển theo điểm thi THPT": "Tổ hợp: Đang cập nhật Điểm trúng tuyển 2024 (thang 40):28,00", "Khai giảng": "Tháng 9, năm 2025", "Học phí": "Giai đoạn 1: khoảng 78 đến 79 triệu đồng/năm (năm 2024)"}, "name": "Quản trị nhà hàng - Khách sạn liên kết Đại học Taylor’s, Malaysia"}], "images": ["https://admission.tdtu.edu.vn/sites/admission23/files/Tuyen-sinh/Dai-hoc/Nganh/NH-KS/1.JPG", "https://admission.tdtu.edu.vn/sites/admission23/files/Tuyen-sinh/Dai-hoc/Nganh/NH-KS/2.JPG", "https://admission.tdtu.edu.vn/sites/admission23/files/Tuyen-sinh/Dai-hoc/Nganh/NH-KS/3.JPG"]}
{"name": "Quy hoạch vùng và đô thị", "description": "Quy hoạch vùng và đô thị là ngành quan trọng hàng đầu trong việc xây dựng và phát triển đất nước. Đây là ngành học mới tại Việt Nam, chuyên đào tạo về quy hoạch đô thị và nông thôn nhằm định hướng bố trí không gian vùng, đô thị và điểm dân cư, các hệ thống công trình hạ tầng kỹ thuật, tạo môi trường sống tiện lợi cho người dân.\nKỹ sư Quy hoạch vùng và đô thị có thể làm việc tại các công ty tư vấn thiết kế quy hoạch, kiến trúc và xây dựng trong và ngoài nước; các cơ quan quản lý quy hoạch, kiến trúc và xây dựng; các Sở, Viện nghiên cứu về quy hoạch, kiến trúc và xây dựng; và các tổ chức phi chính phủ. Ngoài ra, kỹ sư ngành này có thể học tập lên các bậc học Thạc sĩ, Tiến sĩ ở các trường đại học hoặc viện nghiên cứu trong và ngoài nước.", "reasons": ["Liên tục cập nhật xu hướng", "Đội ngũ giảng viên có trình độ chuyên môn cao, giàu kinh nghiệm thực tế", "Cơ hội thực tập và việc làm cao"], "programs": [{"tab": "Tiêu chuẩn", "major_code": "7580105", "description": "Chương trình đào tạo Quy hoạch vùng và đô thị được xây dựng theo tiêu chuẩn kiểm định quốc tế FIBAA. Với nội dung chương trình hiện đại, linh hoạt và chú trọng rèn luyện khả năng quy hoạch tích hợp, quản lý đô thị, thiết kế đô thị đáp ứng nhu cầu thực tế của xã hội, các công ty trong nước và nước ngoài và các cơ quan quản lý nhà nước trong dài hạn. Quy hoạch vùng đô thị đào tạo ra những kỹ sư quy hoạch có tư duy và khả năng quy hoạch tích hợp.\nThế mạnh của ngành Quy hoạch vùng và đô thị là hợp tác quốc tế sâu - rộng thông qua trao đổi sinh viên, các đồ án, các seminar, workshop với các sinh viên, giáo sư, chuyên gia nước ngoài để có cái nhìn quốc tế đa chiều, cập nhật các xu hướng mới, xác định ra những điểm mạnh/ yếu từ đó có những hướng phát triển riêng cho mình. Đặc biệt, ngành Quy hoạch vùng và đô thị khuyến khích sinh viên tham gia các nghiên cứu khoa học tạo tiền đề cho sự say mê khoa học để làm nghiên cứu hoặc học lên cao hơn sau khi tốt nghiệp.\nCử nhân\nKỹ sư\nToàn thời gian: 4 năm\nToàn thời gian: 5 năm\nXem thông tin chi tiết về chương trình đào tạo\nXem thông tin chi tiết về chuẩn đầu ra\nKết quả quá trình học tập THPT\nKết quả bài thi ĐGNL năm 2025 của ĐHQG TP. HCM\nTổ hợp: Đang cập nhật\nĐiểm trúng tuyển 2024 (thang 40):23,00\nTháng 9, năm 2025\nKhoảng 31 đến 32 triệu đồng/năm (năm 2024)", "content": {"Bằng cấp": "Cử nhân Kỹ sư", "Thời gian đào tạo": "Toàn thời gian: 4 năm Toàn thời gian: 5 năm", "Chương trình đào tạo": "Xem thông tin chi tiết về chương trình đào tạo", "Chuẩn đầu ra": "Xem thông tin chi tiết về chuẩn đầu ra", "Phương thức xét tuyển riêng": "Kết quả quá trình học tập THPT Kết quả bài thi ĐGNL năm 2025 của ĐHQG TP. HCM", "Xét tuyển theo điểm thi THPT": "Tổ hợp: Đang cập nhật Điểm trúng tuyển 2024 (thang 40):23,00", "Khai giảng": "Tháng 9, năm 2025", "Học phí": "Khoảng 31 đến 32 triệu đồng/năm (năm 2024)"}, "name": "Quy hoạch vùng và đô thị"}], "images": ["https://admission.tdtu.edu.vn", "https://admission.tdtu.edu.vn/sites/admission23/files/Tuyen-sinh/Dai-hoc/Nganh/Quy-hoach-vung-do-thi/1.jpg", "https://admission.tdtu.edu.vn/sites/admission23/files/Tuyen-sinh/Dai-hoc/Nganh/Quy-hoach-vung-do-thi/2.JPG", "https://admission.tdtu.edu.vn/sites/admission23/files/Tuyen-sinh/Dai-hoc/Nganh/Quy-hoach-vung-do-thi/3.jpg"]}
{"name": "Tài chính - Ngân hàng (Chuyên ngành Tài chính quốc tế)", "description": "Tài chính - Ngân hàng là ngành có lĩnh vực làm việc khá rộng, bao quát toàn bộ các hoạt động liên quan đến giao dịch tiền tệ và kinh doanh thông qua hệ thống ngân hàng như tài chính thuế, tài chính doanh nghiệp, các công cụ tài chính dùng để thanh toán trong nước và quốc tế. Là một trong những ngành mũi nhọn và đóng vai trò quan trọng trong lĩnh vực giao thương, tiền tệ, kinh doanh, ngành Tài chính - Ngân hàng luôn có sức hút với rất nhiều sinh viên bởi những cơ hội nghề nghiệp vô cùng đa dạng trong nền kinh tế toàn cầu hiện nay.\nCử nhân ngành Tài chính - Ngân hàng sau khi tốt nghiệp có thể tự tin ứng tuyển vào các hệ thống ngân hàng, định chế tài chính, doanh nghiệp hay các cơ quan ban ngành với nhiều vị trí đa dạng như chuyên viên tín dụng; chuyên viên phân tích và quản trị rủi ro; chuyên viên quan hệ khách hàng; chuyên viên thẩm định giá; chuyên viên kinh doanh tài chính quốc tế; chuyên viên phân tích và quản lý quỹ đầu tư; chuyên viên quản trị và huy động vốn; chuyên viên tài chính; kế toán; kiểm toán tại các doanh nghiệp, tổ chức kinh tế - xã hội, các cơ quan như Bộ Tài chính, cơ quan Thuế, Hải quan, Kho bạc Nhà nước, biên tập viên kinh tế - tài chính tại các cơ quan thông tấn, báo chí, công ty truyền thông; nghiên cứu viên tại các viện, trung tâm nghiên cứu trong và ngoài nước, … Ngoài ra, cử nhân ngành Tài chính - ngân hàng còn có thể tiếp tục nghiên cứu và học lên ở những bậc học cao hơn.", "reasons": ["Cơ hội trải nghiệm các học phần nghề nghiệp tại các doanh nghiệp trong và ngoài nước", "Cơ hội tham gia chương trình trao đổi ngắn hạn, dài hạn với các đại học uy tín trên thế giới", "100% sinh viên ra trường có việc làm trong vòng 12 tháng kể từ khi tốt nghiệp"], "programs": [{"tab": "Tiêu chuẩn", "major_code": "7340201Q", "description": "Chương trình cử nhân tiêu chuẩn chuyên ngành Tài chính quốc tế trang bị cho sinh viên các kiến thức nền tảng, hiện đại và chuyên sâu về lĩnh vực tài chính quốc tế. Sinh viên có năng lực ứng dụng kiến thức để giải quyết các yêu cầu, xử lý, cung cấp thông tin và ra quyết định trong lĩnh vực tài chính quốc tế, đặc biệt là trong thương mại quốc tế, thị trường tài chính quốc tế, đầu tư trực tiếp nước ngoài, quản trị dự án đầu tư quốc tế, và quản trị tài chính công ty đa quốc gia.\nThông qua chương trình đào tạo được xây dựng theo chuẩn quốc tế và bám sát nhu cầu thực tiễn của xã hội, sinh viên được học tập và ứng dụng các kiến thức chuyên ngành trong suốt 4 năm học với các cơ hội trải nghiệm học phần nghề nghiệp, tập sự nghề nghiệp tại các doanh nghiệp, định chế tài chính trong và ngoài nước. Ngoài ra, bên cạnh những giờ học lý thuyết, sinh viên còn được thực hành  tại phòng thực hành mô phỏng Ngân hàng thương mại và Công ty chứng khoán, được Nhà trường đầu tư xây dựng và bố trí hệ thống máy tính, phần mềm, trang thiết bị hiện đại, qua đó giúp sinh viên sớm thích nghi với môi trường làm việc tại các doanh nghiệp trong và ngoài nước.\nBên cạnh đó, sinh viên còn được rèn luyện kỹ năng giao tiếp, làm việc nhóm, các kỹ năng mềm khác nhằm xử lý công việc, sử dụng thành thạo ngoại ngữ và các kỹ năng công nghệ thông tin trong bối cảnh hội nhập toàn cầu. Những hoạt động nghiên cứu khoa học sinh viên được tổ chức thường niên nhằm nâng cao kỹ năng nghiên cứu khoa học cho sinh viên, tạo điều kiện giúp sinh viên phát huy năng lực sáng tạo, tìm tòi và học hỏi các kiến thức chuyên sâu.\nNhà trường còn thường xuyên tổ chức các buổi workshop/seminar, cuộc thi học thuật  tạo môi trường cho sinh viên được giao lưu và trải nghiệm nghề nghiệp trong lĩnh vực tài chính - ngân hàng.\nCử nhân\nToàn thời gian: 4 năm\nXem thông tin chi tiết về chương trình đào tạo\nXem thông tin chi tiết về chuẩn đầu ra\nKết quả quá trình học tập THPT\nKết quả bài thi ĐGNL năm 2025 của ĐHQG TP. HCM\nTổ hợp: Đang cập nhật\nTháng 9, năm 2025\nĐang cập nhật", "content": {"Bằng cấp": "Cử nhân", "Thời gian đào tạo": "Toàn thời gian: 4 năm", "Chương trình đào tạo": "Xem thông tin chi tiết về chương trình đào tạo", "Chuẩn đầu ra": "Xem thông tin chi tiết về chuẩn đầu ra", "Phương thức xét tuyển riêng": "Kết quả quá trình học tập THPT Kết quả bài thi ĐGNL năm 2025 của ĐHQG TP. HCM", "Xét tuyển theo điểm thi THPT": "Tổ hợp: Đang cập nhật", "Khai giảng": "Tháng 9, năm 2025", "Học phí": "Đang cập nhật"}, "name": "Tài chính - Ngân hàng(Chuyên ngành Tài chính quốc tế)"}], "images": ["https://admission.tdtu.edu.vn", "https://admission.tdtu.edu.vn/sites/admission23/files/Tuyen-sinh/Dai-hoc/Nganh/TCNH/1_1.png", "https://admission.tdtu.edu.vn/sites/admission23/files/Tuyen-sinh/Dai-hoc/Nganh/TCNH/2_0.png", "https://admission.tdtu.edu.vn/sites/admission23/files/Tuyen-sinh/Dai-hoc/Nganh/TCNH/3.JPG"]}
{"name": "Tài chính - Ngân hàng", "description": "Tài chính - Ngân hàng là ngành có lĩnh vực làm việc khá rộng, bao quát toàn bộ các hoạt động liên quan đến giao dịch tiền tệ và kinh doanh thông qua hệ thống ngân hàng như tài chính thuế, tài chính doanh nghiệp, các công cụ tài chính dùng để thanh toán trong nước và quốc tế. Là một trong những ngành mũi nhọn và đóng vai trò quan trọng trong lĩnh vực giao thương, tiền tệ, kinh doanh, ngành Tài chính - Ngân hàng luôn có sức hút với rất nhiều sinh viên bởi những cơ hội nghề nghiệp vô cùng đa dạng trong nền kinh tế toàn cầu hiện nay.\nCử nhân ngành Tài chính - Ngân hàng sau khi tốt nghiệp có thể tự tin ứng tuyển vào các hệ thống ngân hàng, định chế tài chính, doanh nghiệp hay các cơ quan ban ngành với nhiều vị trí đa dạng như chuyên viên tín dụng; chuyên viên phân tích và quản trị rủi ro; chuyên viên quan hệ khách hàng; chuyên viên thẩm định giá; chuyên viên kinh doanh tài chính quốc tế; chuyên viên phân tích và quản lý quỹ đầu tư; chuyên viên quản trị và huy động vốn; chuyên viên tài chính; kế toán; kiểm toán tại các doanh nghiệp, tổ chức kinh tế - xã hội, các cơ quan như Bộ Tài chính, cơ quan Thuế, Hải quan, Kho bạc Nhà nước, biên tập viên kinh tế - tài chính tại các cơ quan thông tấn, báo chí, công ty truyền thông; nghiên cứu viên tại các viện, trung tâm nghiên cứu trong và ngoài nước, … Ngoài ra, cử nhân ngành Tài chính - ngân hàng còn có thể tiếp tục nghiên cứu và học lên ở những bậc học cao hơn.", "reasons": ["Cơ hội trải nghiệm các học phần nghề nghiệp tại các doanh nghiệp trong và ngoài nước", "Cơ hội tham gia chương trình trao đổi ngắn hạn, dài hạn với các đại học uy tín trên thế giới", "100% sinh viên ra trường có việc làm trong vòng 12 tháng kể từ khi tốt nghiệp"], "programs": [{"tab": "Tiêu chuẩn", "major_code": "7340201", "description": "Chương trình đào tạo ngành Tài chính - Ngân hàng sẽ trang bị cho sinh viên các khối kiến thức chung (ngoại ngữ, tin học, toán học, kiến thức xã hội), kiến thức cơ bản đến chuyên sâu trong lĩnh vực tài chính - ngân hàng như lập kế hoạch tài chính, định giá doanh nghiệp, phân tích tài chính doanh nghiệp, quản trị rủi ro tài chính, quản trị tín dụng, nghiệp vụ thanh toán, đầu tư tài chính, …\nChương trình còn chú trọng phát triển các kỹ năng chuyên dùng trong lĩnh vực tài chính - ngân hàng cho sinh viên như kỹ năng phân tích tài chính doanh nghiệp; kỹ năng lập kế hoạch tài chính; kỹ năng phát hiện và đưa ra các giải pháp quản trị rủi ro tài chính tại doanh nghiệp và tổ chức tín dụng; thẩm định giá trị tài sản, chứng khoán và các dự án đầu tư.\nThông qua chương trình đào tạo được xây dựng theo chuẩn quốc tế và bám sát nhu cầu thực tiễn của xã hội, sinh viên được học tập và ứng dụng các kiến thức chuyên ngành trong suốt 4 năm học với cơ hội trải nghiệm các học phần nghề nghiệp, tập sự nghề nghiệp tại các doanh nghiệp, định chế tài chính trong và ngoài nước. Ngoài ra, bên cạnh những giờ học lý thuyết, sinh viên còn được thực hành  tại phòng thực hành mô phỏng Ngân hàng thương mại và Công ty chứng khoán, được Nhà trường đầu tư xây dựng và bố trí hệ thống máy tính, phần mềm, trang thiết bị hiện đại, qua đó giúp sinh viên sớm thích nghi với môi trường làm việc tại các doanh nghiệp trong và ngoài nước.\nBên cạnh đó, sinh viên còn được rèn luyện kỹ năng giao tiếp, làm việc nhóm, các kỹ năng mềm khác nhằm xử lý công việc, sử dụng thành thạo ngoại ngữ và các kỹ năng công nghệ thông tin trong bối cảnh hội nhập toàn cầu. Những hoạt động nghiên cứu khoa học sinh viên được tổ chức thường niên nhằm nâng cao kỹ năng nghiên cứu khoa học cho sinh viên, tạo điều kiện giúp sinh viên phát huy năng lực sáng tạo, tìm tòi và học hỏi các kiến thức chuyên sâu.\nCử nhân\nToàn thời gian: 4 năm\nXem thông tin chi tiết về chương trình đào tạo\nXem thông tin chi tiết về chuẩn đầu ra\nKết quả quá trình học tập THPT\nKết quả bài thi ĐGNL năm 2025 của ĐHQG TP. HCM\nTổ hợp: Đang cập nhật\nĐiểm trúng tuyển 2024 (thang 40):33,00\nTháng 9, năm 2025\nKhoảng 27 đến 28 triệu đồng/năm (năm 2024)", "content": {"Bằng cấp": "Cử nhân", "Thời gian đào tạo": "Toàn thời gian: 4 năm", "Chương trình đào tạo": "Xem thông tin chi tiết về chương trình đào tạo", "Chuẩn đầu ra": "Xem thông tin chi tiết về chuẩn đầu ra", "Phương thức xét tuyển riêng": "Kết quả quá trình học tập THPT Kết quả bài thi ĐGNL năm 2025 của ĐHQG TP. HCM", "Xét tuyển theo điểm thi THPT": "Tổ hợp: Đang cập nhật Điểm trúng tuyển 2024 (thang 40):33,00", "Khai giảng": "Tháng 9, năm 2025", "Học phí": "Khoảng 27 đến 28 triệu đồng/năm (năm 2024)"}, "name": "Tài chính - Ngân hàng"}, {"tab": "Tiên tiến", "major_code": "F7340201", "description": "Chương trình cử nhân tiên tiến ngành Tài chính - Ngân hàng đào tạo cử nhân có phẩm chất đạo đức, chính trị và sức khỏe tốt. Nội dung chương trình cử nhân tiên tiến được xây dựng theo nhu cầu của thị trường lao động; gắn kết lý thuyết với thực tiễn; kết hợp kiến thức chuyên môn và chuyên ngành với rèn luyện kỹ năng thực hành; chú trọng đến các kỹ năng mềm và thực tập doanh nghiệp; xây dựng ý thức tự học, tự nghiên cứu giúp sinh viên rèn luyện và hoàn thiện các phẩm chất nghề nghiệp cần thiết, đáp ứng được nhu cầu làm việc đa dạng của thị trường lao động chất lượng cao trong và ngoài nước.\nTốt nghiệp cử nhân tiên tiến sinh viên có đủ năng lực chuyên môn, kỹ năng ngoại ngữ và kỹ năng mềm quản lý công việc, có thể đảm nhận được công việc liên quan tại các ngân hàng, tổ chức tín dụng phi ngân hàng, công ty chứng khoán, công ty bảo hiểm, các doanh nghiệp trong nước và ngoài nước, các tổ chức phi chính phủ, các Trung tâm/Viện/Phòng nghiên cứu và quản lý nghiên cứu về kinh tế; các trường đại học trong và ngoài nước; hoặc tiếp tục học lên cao học.\nCử nhân\nToàn thời gian: 4 năm\nXem thông tin chi tiết về chương trình đào tạo\nXem thông tin chi tiết về chuẩn đầu ra\nKết quả quá trình học tập THPT\nKết quả bài thi ĐGNL năm 2025 của ĐHQG TP. HCM\nTổ hợp: Đang cập nhật\nĐiểm trúng tuyển 2024 (thang 40):28,70\nTháng 9, năm 2025\nKhoảng 50 đến 52 triệu đồng/năm (năm 2024)", "content": {"Bằng cấp": "Cử nhân", "Thời gian đào tạo": "Toàn thời gian: 4 năm", "Chương trình đào tạo": "Xem thông tin chi tiết về chương trình đào tạo", "Chuẩn đầu ra": "Xem thông tin chi tiết về chuẩn đầu ra", "Phương thức xét tuyển riêng": "Kết quả quá trình học tập THPT Kết quả bài thi ĐGNL năm 2025 của ĐHQG TP. HCM", "Xét tuyển theo điểm thi THPT": "Tổ hợp: Đang cập nhật Điểm trúng tuyển 2024 (thang 40):28,70", "Khai giảng": "Tháng 9, năm 2025", "Học phí": "Khoảng 50 đến 52 triệu đồng/năm (năm 2024)"}, "name": "Tài chính - Ngân hàng"}, {"tab": "Đại học bằng tiếng Anh", "major_code": "FA7340201", "description": "Chương trình đại học bằng tiếng Anh ngành Tài chính - Ngân hàng được xây dựng dựa trên chương trình đào tạo của các trường đại học, viện đào tạo hàng đầu thế giới. Cùng với nhu cầu của thị trường lao động quốc tế hóa cao trong lĩnh vực tài chính, ngân hàng, chương trình được xây dựng gắn kết lý thuyết với thực tiễn; kết hợp kiến thức chuyên môn và chuyên ngành với rèn luyện kỹ năng thực hành; chú trọng đến các kỹ năng mềm và trải nghiệm doanh nghiệp; xây dựng ý thức tự học, tự nghiên cứu giúp sinh viên rèn luyện và hoàn thiện các phẩm chất nghề nghiệp cần thiết.\n100% các môn học trong chương trình được giảng dạy bằng tiếng Anh. Trong đó có một số môn học được các Giáo sư của những trường đại học từ các Quốc gia trên thế giới về giảng dạy.\nĐặc biệt, chương trình còn tích hợp các môn họcChứng chỉ CFA (Chartered Financial Analyst) giúp sinh viên trang bị kiến thức chuyên ngành, kỹ năng cần thiết để tham gia kỳ thi CFA level 1. Chứng chỉ CFA được công nhận rộng rãi trên khắp thế giới bởi tính thực tiễn cao và cung cấp nền tảng kiến thức và các nguyên tắc hoạt động của thị trường đầu tư toàn cầu do Viện CFA Hoa Kỳ cấp.\nCử nhân\nToàn thời gian: 4 năm\nXem thông tin chi tiết về chương trình đào tạo\nXem thông tin chi tiết về chuẩn đầu ra\nKết quả quá trình học tập THPT\nKết quả bài thi ĐGNL năm 2025 của ĐHQG TP. HCM\nTổ hợp: Đang cập nhật\nĐiểm trúng tuyển 2024 (thang 40):26,00\nTháng 9, năm 2025\nKhoảng 76 đến 80 triệu đồng/năm (năm 2024)", "content": {"Bằng cấp": "Cử nhân", "Thời gian đào tạo": "Toàn thời gian: 4 năm", "Chương trình đào tạo": "Xem thông tin chi tiết về chương trình đào tạo", "Chuẩn đầu ra": "Xem thông tin chi tiết về chuẩn đầu ra", "Phương thức xét tuyển riêng": "Kết quả quá trình học tập THPT Kết quả bài thi ĐGNL năm 2025 của ĐHQG TP. HCM", "Xét tuyển theo điểm thi THPT": "Tổ hợp: Đang cập nhật Điểm trúng tuyển 2024 (thang 40):26,00", "Khai giảng": "Tháng 9, năm 2025", "Học phí": "Khoảng 76 đến 80 triệu đồng/năm (năm 2024)"}, "name": "Tài chính - Ngân hàng"}, {"tab": "Liên kết quốc tế-K7340201X", "major_code": "K7340201X", "description": "Cử nhân (song bằng)\n4 năm (3 năm đầu học tại TDTU, 1 năm sau học tại Trường liên kết)\nXem thông tin chi tiết về chương trình đào tạo\nXem thông tin chi tiết về chuẩn đầu ra\nKết quả quá trình học tập THPT\nKết quả bài thi ĐGNL năm 2025 của ĐHQG TP. HCM\nTổ hợp: Đang cập nhật\nĐiểm trúng tuyển 2024 (thang 40):26,00\nTháng 9, năm 2025\nGiai đoạn 1: khoảng 78 đến 80 triệu đồng/năm (năm 2024)", "content": {"Bằng cấp": "Cử nhân (song bằng)", "Thời gian đào tạo": "4 năm (3 năm đầu học tại TDTU, 1 năm sau học tại Trường liên kết)", "Chương trình đào tạo": "Xem thông tin chi tiết về chương trình đào tạo", "Chuẩn đầu ra": "Xem thông tin chi tiết về chuẩn đầu ra", "Phương thức xét tuyển riêng": "Kết quả quá trình học tập THPT Kết quả bài thi ĐGNL năm 2025 của ĐHQG TP. HCM", "Xét tuyển theo điểm thi THPT": "Tổ hợp: Đang cập nhật Điểm trúng tuyển 2024 (thang 40):26,00", "Khai giảng": "Tháng 9, năm 2025", "Học phí": "Giai đoạn 1: khoảng 78 đến 80 triệu đồng/năm (năm 2024)"}, "name": "Tài chính và kiểm soát liên kết Đại học khoa học ứng dụng Saxion, Hà Lan"}, {"tab": "Liên kết quốc tế-K7340201M", "major_code": "K7340201M", "description": "Cử nhân (đơn bằng)\n3.5 năm (2 năm đầu học tại TDTU, 1.5 năm sau học tại Trường liên kết)\nXem thông tin chi tiết về chương trình đào tạo\nXem thông tin chi tiết về chuẩn đầu ra\nKết quả quá trình học tập THPT\nKết quả bài thi ĐGNL năm 2025 của ĐHQG TP. HCM\nTổ hợp: Đang cập nhật\nĐiểm trúng tuyển 2024 (thang 40):26,00\nTháng 9, năm 2025\nGiai đoạn 1: khoảng 82 đến 83 triệu đồng/năm (năm 2024)", "content": {"Bằng cấp": "Cử nhân (đơn bằng)", "Thời gian đào tạo": "3.5 năm (2 năm đầu học tại TDTU, 1.5 năm sau học tại Trường liên kết)", "Chương trình đào tạo": "Xem thông tin chi tiết về chương trình đào tạo", "Chuẩn đầu ra": "Xem thông tin chi tiết về chuẩn đầu ra", "Phương thức xét tuyển riêng": "Kết quả quá trình học tập THPT Kết quả bài thi ĐGNL năm 2025 của ĐHQG TP. HCM", "Xét tuyển theo điểm thi THPT": "Tổ hợp: Đang cập nhật Điểm trúng tuyển 2024 (thang 40):26,00", "Khai giảng": "Tháng 9, năm 2025", "Học phí": "Giai đoạn 1: khoảng 82 đến 83 triệu đồng/năm (năm 2024)"}, "name": "Khối ngành Kinh doanh liên kết Đại học Massey, New Zealand"}], "images": ["https://admission.tdtu.edu.vn", "https://admission.tdtu.edu.vn/sites/admission23/files/Tuyen-sinh/Dai-hoc/Nganh/TCNH/1_1.png", "https://admission.tdtu.edu.vn/sites/admission23/files/Tuyen-sinh/Dai-hoc/Nganh/TCNH/2_0.png", "https://admission.tdtu.edu.vn/sites/admission23/files/Tuyen-sinh/Dai-hoc/Nganh/TCNH/3.JPG"]}
{"name": "Thiết kế đồ họa", "description": "Thiết kế đồ họa là ngành học luôn mang tính hiện đại có sự ảnh hưởng đa chiều tới hầu hết các ngành nghề trong xã hội.\nThiết kế đồ họa tại Trường Đại học Tôn Đức Thắng sẽ bao gồm các lĩnh vực chính như: nghệ thuật chữ (typography), nhận diện thương hiệu (branding), thiết kế các ấn phẩm (publication design), quảng cáo (advertising), hình ảnh đồ họa (image making), thiết kế bao bì (packaging), thiết kế Web và ứng dụng (website & application design). Đây là những nhân tố đóng vai trò cùng quan trọng trong quảng cáo, các hoạt động văn hóa nghệ thuật để truyền tải thông điệp đến công chúng, phục vụ cho nhu cầu phát triển của xã hội.\nCử nhân Thiết kế đồ họa có thể tự tin ứng tuyển vào làm việc tại các công ty thiết kế, studio, agency, công ty truyền thông, nhà xuất bản,... trong nước và quốc tế ở các vị trí như: chuyên viên thiết kế đồ họa; giám đốc sáng tạo; chuyên viên chỉ đạo nghệ thuật, chụp ảnh, vẽ minh họa, quảng cáo; phụ trách in ấn, thiết kế tạp chí và xuất bản; chuyên viên thiết kế bao bì; chuyên viên truyền thông trong nước và quốc tế. Ngoài ra, sinh viên có thể tạo lập công ty hoặc thương hiệu riêng; lựa chọn giảng dạy tại các cơ sở giáo dục đại học, cao đẳng hoặc tham gia các chương trình đào tạo thạc sĩ thuộc nhóm ngành mỹ thuật, thiết kế trong và ngoài nước.", "reasons": ["Đội ngũ giảng viên giàu kinh nghiệm", "Liên tục cập nhật xu hướng", "100% sinh viên ra trường có việc làm trong vòng 12 tháng kể từ khi tốt nghiệp"], "programs": [{"tab": "Tiêu chuẩn", "major_code": "7210403", "description": "Chương trình học bao gồm 2 nhóm chính là cơ bản và chuyên ngành. Sinh viên được trang bị các kiến thức cơ bản gồm những môn hình họa giúp phát triển khả năng vẽ và nhìn nhận màu sắc trong thiết kế. Bên cạnh đó, Nhà trường còn cập nhật cho sinh viên các kiến thức chuyên môn về tư duy thiết kế, ngôn ngữ thiết kế đồ họa, các kỹ thuật về in ấn cơ bản, phương pháp chọn giấy và phát triển giải pháp thiết kế.\nNhà trường luôn chú trọng đầu tư cơ sở vật chất và trang thiết bị hiện đại nhằm mang lại cho sinh viên không gian học tập sáng tạo và đạt chuẩn quốc tế. Các học phần thực hành cũng đặc biệt được đẩy mạnh và nâng cao. Sinh viên được luyện tập thao tác sử dụng phần mềm đồ họa chuyên nghiệp và quá trình thiết kế thông qua các đồ án đa dạng chủ đề và mang tính thực tiễn cao.\nBên cạnh đào tạo kiến thức và kỹ năng chuyên môn, sinh viên còn được hướng dẫn tham gia các khóa học ngắn hạn, tham quan và kiến tập tại các công ty trong và ngoài nước thông qua mạng lưới doanh nghiệp hợp tác với TDTU. Đặc biệt, trong một số học phần chuyên sâu, các chuyên gia hàng đầu trong lĩnh vực thiết kế đồ họa kết hợp cùng với giảng viên trực tiếp giảng dạy và hướng dẫn cho sinh viên để thực hiện đồ án ngay tại doanh nghiệp hoặc các dự án dự thi các cuộc thi thiết kế trong nước và quốc tế.\nSinh viên tốt nghiệp ngành Thiết kế đồ họa có khả năng phân tích xu hướng thẩm mỹ, tìm kiếm và phát triển ý tưởng mới trong thiết kế đồ họa; sáng tác, hoàn thiện dự án đồ họa mang tính ứng dụng cao; phân tích dự án đồ họa, từ đó hoạch định quy trình thực hiện hiệu quả; tự cập nhật kiến thức để làm việc trong môi trường thiết kế chuyên nghiệp tại Việt Nam và trên thế giới; sử dụng thành thạo các phần mềm thiết kế 2D, 3D làm công cụ thể hiện và trình bày ý tưởng.\nCử nhân\nToàn thời gian: 4 năm\nXem thông tin chi tiết về chương trình đào tạo\nXem thông tin chi tiết về chuẩn đầu ra\nKết quả quá trình học tập THPT\nKết quả bài thi ĐGNL năm 2025 của ĐHQG TP. HCM\nTổ hợp: Đang cập nhật\nĐiểm trúng tuyển 2024 (thang 40):31,50\nTháng 9, năm 2025\nKhoảng 31 đến 32 triệu đồng/năm (năm 2024)", "content": {"Bằng cấp": "Cử nhân", "Thời gian đào tạo": "Toàn thời gian: 4 năm", "Chương trình đào tạo": "Xem thông tin chi tiết về chương trình đào tạo", "Chuẩn đầu ra": "Xem thông tin chi tiết về chuẩn đầu ra", "Phương thức xét tuyển riêng": "Kết quả quá trình học tập THPT Kết quả bài thi ĐGNL năm 2025 của ĐHQG TP. HCM", "Xét tuyển theo điểm thi THPT": "Tổ hợp: Đang cập nhật Điểm trúng tuyển 2024 (thang 40):31,50", "Khai giảng": "Tháng 9, năm 2025", "Học phí": "Khoảng 31 đến 32 triệu đồng/năm (năm 2024)"}, "name": "Thiết kế đồ họa"}, {"tab": "Tiên tiến", "major_code": "F7210403", "description": "Chương trình tiên tiến ngành Thiết kế đồ họa  được xây dựng dựa trên tham khảo cấu trúc khung chương trình đào tạo ngành tương đương từ Đại học New South Wales, Art Center College of Design, Đại học Boston và Rochester Institute of technology.Đội ngũ giảng viên là những chuyên gia thiết kế nhiều kinh nghiệm, trong đó giảng viên nước ngoài và giảng viên được đào tạo tại nước ngoài tham gia giảng dạy chiếm 70%.\nChương trình có một số học phần đào tạo sinh viên các kỹ năng chuyên biệt để tham gia các dự án thiết kế như: Motion Graphic Design; Story and Cinematography; Design Management; Tiếng Anh chuyên ngành đồ họa…\n50% số lượng môn học trong chương trình được giảng dạy bằng tiếng Anh.\nMột số học phần được giảng dạy, hỗ trợ từ các doanh nghiệp, công ty có uy tín tại Việt Nam và nước ngoài.\nHọc phần tốt nghiệp được thực hiện tại các trường Đại học nước ngoài có mối quan hệ hợp tác với trường Đại học Tôn Đức Thắng như: Đại học Ming Chi (Đài Loan), Đại học Shute (Đài Loan), Đại học Tomas Bata (Cộng hòa Séc).\nChương trình được xây dựng theo qui trình đánh giá của trường Đại học Tôn Đức Thắng, có sự tham khảo ý kiến phản hồi của người sử dụng lao động, của cựu sinh viên và ý kiến đóng góp của chuyên gia, các tổ chức kiểm định trên thế giới.\nTốt nghiệp ngành Thiết kế đồ họa chất lượng cao, sinh viên đạt được các kiến thức và kỹ năng như sau: Sinh viên được trang bị những kiến thức cơ bản về vẽ mỹ thuật, về thẩm mỹ, về bố cục thị giác và xử lí hình ảnh; hiểu về phương pháp nghiên cứu, phương pháp thiết kế, phương pháp lập kế hoạch để phát triển ý tưởng cho sản phẩm; các kĩ năng sử dụng phần mềm thiết kế làm công cụ thể hiện và trình bày ý tưởng.\nCử nhân\nToàn thời gian: 4 năm\nXem thông tin chi tiết về chương trình đào tạo\nXem thông tin chi tiết về chuẩn đầu ra\nKết quả quá trình học tập THPT\nKết quả bài thi ĐGNL năm 2025 của ĐHQG TP. HCM\nTổ hợp: Đang cập nhật\nĐiểm trúng tuyển 2024 (thang 40):31,00\nTháng 9, năm 2025\nKhoảng 53 đến 54 triệu đồng/năm (năm 2024)", "content": {"Bằng cấp": "Cử nhân", "Thời gian đào tạo": "Toàn thời gian: 4 năm", "Chương trình đào tạo": "Xem thông tin chi tiết về chương trình đào tạo", "Chuẩn đầu ra": "Xem thông tin chi tiết về chuẩn đầu ra", "Phương thức xét tuyển riêng": "Kết quả quá trình học tập THPT Kết quả bài thi ĐGNL năm 2025 của ĐHQG TP. HCM", "Xét tuyển theo điểm thi THPT": "Tổ hợp: Đang cập nhật Điểm trúng tuyển 2024 (thang 40):31,00", "Khai giảng": "Tháng 9, năm 2025", "Học phí": "Khoảng 53 đến 54 triệu đồng/năm (năm 2024)"}, "name": "Thiết kế đồ họa"}], "images": ["https://admission.tdtu.edu.vn/sites/admission23/files/Tuyen-sinh/Dai-hoc/Nganh/Thiet-ke-do-hoa/1.jpg", "https://admission.tdtu.edu.vn/sites/admission23/files/Tuyen-sinh/Dai-hoc/Nganh/Thiet-ke-do-hoa/2.jpg", "https://admission.tdtu.edu.vn/sites/admission23/files/Tuyen-sinh/Dai-hoc/Nganh/Thiet-ke-do-hoa/4.jpg"]}
{"name": "Thiết kế nội thất", "description": "Thiết kế nội thất là ngành học tổng hợp của nghệ thuật, mỹ thuật và kỹ thuật hội hoạ, dựa trên thẩm mỹ kiến trúc, ánh sáng, màu sắc,… để tạo nên các công trình nội thất hài hoà, tinh tế, thổi hồn vào không gian sống và đáp ứng nhu cầu của người sử dụng. Đây là ngành học rất quan trọng trong đời sống của con người và hiện đang là ngành học có nhu cầu về nguồn nhân lực tăng trưởng nhanh chóng, thu hút sự quan tâm và tìm hiểu của đông đảo học sinh, sinh viên.\nCử nhân Thiết kế nội thất có đầy đủ năng lực để bước chân vào thị trường lao động nhộn nhịp và tự tin ứng tuyển vào các vị trí như: nhà thiết kế; giám đốc sáng tạo tại các doanh nghiệp trong nước và quốc tế, biên tập viên các tạp chí nội thất, nhà ở; lập công ty riêng hoặc thiết kế tự do hoặc tham gia giảng dạy, nghiên cứu tại các cơ sở giáo dục đại học, cao đẳng và viện nghiên cứu liên quan. Ngoài ra, sinh viên còn có khả năng tiếp tục theo học các chương trình đào tạo thạc sĩ, tiến sĩ thuộc nhóm ngành mỹ thuật, thiết kế trong và ngoài nước.", "reasons": ["100% sinh viên được tham quan, kiến tập tại các doanh nghiệp uy tín đã ký kết hợp tác với Khoa", "Tổ chức thường xuyên Talkshow, Workshop với sự tham gia hướng dẫn của các giáo sư cố vấn, chuyên gia nước ngoài có uy tín", "100% sinh viên ra trường có việc làm trong vòng 12 tháng kể từ khi tốt nghiệp"], "programs": [{"tab": "Tiêu chuẩn", "major_code": "7580108", "description": "Ngoài các môn học cơ bản của ngành như lịch sử mỹ thuật, hình hoạ, vẽ phối cảnh,… chương trình còn cung cấp cho sinh viên những kiến thức trọng tâm về nguyên lý thiết kế, nguyên tắc tổ chức không gian, nghiên cứu ánh sáng, vật liệu và cách ứng dụng vật liệu vào thực tế như: thiết kế đồ nội thất, xây dựng và vật liệu trang trí nội thất. Bên cạnh đó, chương trình cũng chú trọng tới việc nâng cao các kỹ năng nghề nghiệp cần thiết cho sinh viên như thông qua các phương pháp thuyết trình, lập dự toán công trình và triển khai thi công.\nChương trình đào tạo ngành Thiết kế nội thất của Trường Đại học Tôn Đức Thắng còn chú trọng tính ứng dụng của ngành học và kỹ năng thực hành chuyên môn cho sinh viên. Nhà trường luôn tập trung xây dựng, đầu tư phòng học thực hành, các xưởng chế tác, đồng thời trang bị các hệ thống máy móc hiện đại và tiên tiến nhằm mang đến cho sinh viên môi trường học tập sáng tạo và đạt chuẩn quốc tế. Số tiết học thực hành được nghiên cứu để cân bằng với số buổi học lý thuyết, qua đó giúp sinh viên nâng cao tay nghề và rèn luyện tư duy thiết kế.\nTính ứng dụng của các học phần được thiết kế theo hướng tăng dần từ cấp độ cơ bản đến cấp độ sinh viên tự xây dựng ý tưởng, phác thảo và triển khai ý tưởng thành một sản phẩm hoặc công trình nội thất thực thụ trong quá trình thực hiện các đồ án chuyên ngành đa dạng.\nNgoài các chương trình học chính khóa, sinh viên ngành Thiết kế nội thất có cơ hội tham gia sinh hoạt tại Câu lạc bộ Nội thất như: CLB mô hình, CLB đồ gỗ,… và các hoạt động sôi nổi của trường. Nhà trường cũng thường xuyên kết hợp với các tổ chức: HAWA (Hiệp hội chế biến gỗ Việt nam), các công ty sản xuất phụ kiện nội thất: HAFELE, BLUM, VĨNH TƯỜNG, …các doanh nghiệp, công ty xây dựng, công ty trang trí nội thất để tổ chức các buổi tham quan, kiến tập cho sinh viên, tạo điều kiện cho sinh viên sớm tiếp cận với môi trường và văn hoá doanh nghiệp, tích luỹ kinh nghiệm thực tế và vận dụng các kiến thức, kỹ năng đã được học để tham gia trực tiếp vào dự án tại các công ty.\nNhà trường còn thường xuyên tổ chức các cuộc thi thiết kế bổ ích nhằm giúp sinh viên phát triển toàn diện về kiến thức và kỹ năng nghề nghiệp. Đặc biệt, các giảng viên chuyên ngành luôn hỗ trợ hết lòng về chuyên môn, khuyến khích sinh viên viên tự tin tham dự các cuộc thi thiết kế trong nước và quốc tế.\nSinh viên tốt nghiệp ngành Thiết kế nội thất có thể nắm vững các nguyên lý thiết kế và các quy trình thiết kế nội thất từ khâu đầu đến khâu cuối; có những hiểu biết về thị hiếu thẩm mỹ, về lịch sử mỹ thuật, lịch sử nội thất để từ đó tạo ra những thiết kế phù hợp với nhu cầu của người tiêu dùng; khả năng độc lập về tư vấn, thiết kế nội ngoại thất các công trình kiến trúc vừa và nhỏ; vận dụng tốt các kiến thức chuyên môn để thiết kế đồ đạc, nội – ngoại thất như nhà ở, công trình thương mại, công trình dịch vụ, công trình giáo dục, cảnh quan,…\nCử nhân\nToàn thời gian: 4 năm\nXem thông tin chi tiết về chương trình đào tạo\nXem thông tin chi tiết về chuẩn đầu ra\nKết quả quá trình học tập THPT\nKết quả bài thi ĐGNL năm 2025 của ĐHQG TP. HCM\nTổ hợp: Đang cập nhật\nĐiểm trúng tuyển 2024 (thang 40):29,70\nTháng 9, năm 2025\nKhoảng 31 đến 32 triệu đồng/năm (năm 2024)", "content": {"Bằng cấp": "Cử nhân", "Thời gian đào tạo": "Toàn thời gian: 4 năm", "Chương trình đào tạo": "Xem thông tin chi tiết về chương trình đào tạo", "Chuẩn đầu ra": "Xem thông tin chi tiết về chuẩn đầu ra", "Phương thức xét tuyển riêng": "Kết quả quá trình học tập THPT Kết quả bài thi ĐGNL năm 2025 của ĐHQG TP. HCM", "Xét tuyển theo điểm thi THPT": "Tổ hợp: Đang cập nhật Điểm trúng tuyển 2024 (thang 40):29,70", "Khai giảng": "Tháng 9, năm 2025", "Học phí": "Khoảng 31 đến 32 triệu đồng/năm (năm 2024)"}, "name": "Thiết kế nội thất"}], "images": ["https://admission.tdtu.edu.vn", "https://admission.tdtu.edu.vn/sites/admission23/files/Tuyen-sinh/Dai-hoc/Nganh/Thiet-ke-noi-that/1.jpg", "https://admission.tdtu.edu.vn/sites/admission23/files/Tuyen-sinh/Dai-hoc/Nganh/Thiet-ke-noi-that/2.jpg", "https://admission.tdtu.edu.vn/sites/admission23/files/Tuyen-sinh/Dai-hoc/Nganh/Thiet-ke-noi-that/3.jpg"]}
{"name": "Thiết kế thời trang", "description": "Thiết kế thời trang là ngành đào tạo nhân sự có khả năng thiết kế, sản xuất quần áo và phụ kiện phục vụ các nhu cầu của xã hội. Ngoài các kỹ năng thông thường như sáng tạo, phác hoạ và sử dụng các phần mềm đồ họa chuyên nghiệp để làm cho mẫu phục trang trở nên sống động, ngành học còn đào tạo các nhà thiết kế thời trang trở thành những người tiên phong, đi đầu và dự đoán trước những xu hướng mới về ngành thiết kế lẫn xu hướng thời trang trong những năm tiếp theo.\nSinh viên theo học ngành Thiết kế thời trang tại TDTU có đầy đủ năng lực để tự tin ứng tuyển vào các vị trí như: Nhà thiết kế (Fashion Designer), giám đốc sáng tạo (Creative Director) tại các doanh nghiệp trong nước và quốc tế; biên tập viên thời trang (Fashion Editor), người tạo phong cách (Stylist) trong các tạp chí thời trang, tạp chí mốt; tạo lập công ty hoặc thương hiệu riêng hoặc trở thành cán bộ giảng dạy, cán bộ nghiên cứu tại các cơ sở giáo dục đại học, cao đẳng và viện nghiên cứu liên quan.", "reasons": ["100% sinh viên được tham quan, kiến tập tại các doanh nghiệp uy tín đã ký kết hợp tác với Khoa", "Chương trình học sáng tạo không ngừng", "100% sinh viên ra trường có việc làm trong vòng 12 tháng kể từ khi tốt nghiệp"], "programs": [{"tab": "Tiêu chuẩn", "major_code": "7210404", "description": "Chương trình cung cấp cho sinh viên những kiến thức cơ bản về nguyên lý thiết kế, kiến thức về thẩm mỹ, lịch sử Mỹ thuật Việt Nam và thế giới, lịch sử thời trang, kiến thức cơ bản về các phương tiện tạo hình, màu sắc, các nguyên lý trong tạo hình, xu hướng thời trang, thời trang và ứng dụng,… Ngoài ra, chương trình còn cập nhật cho sinh viên kiến thức về chất liệu và xử lý chất liệu độc đáo như: Ribbon stitch (thêu ruy băng ), nhuộm Batik (nhuộm sáp ong), Knitting (đan), Smocking (khiếu vải), Shibori (nhuộm buộc), Marbling (vẽ hoa văn đá)...\nSinh viên còn được chú trọng tới việc nâng cao các kỹ năng nghề nghiệp cần thiết như: rèn luyện các phương pháp vẽ minh họa, vẽ kỹ thuật trong thiết kế thời trang, hướng dẫn các kỹ thuật cắt may từ đơn giản đến phức tạp. Số tiết học thực hành được thiết kế để cân bằng với số môn học lý thuyết và mang tính ứng dụng cao. Thông qua các đồ án chuyên ngành đa dạng và phong phú, sinh viên được học từ lý thuyết cơ bản đến khi có thể tự chuyển đổi ý tưởng thành sản phẩm hoàn thiện để trình diễn trước công chúng. Nhà trường còn tăng cường đầu tư phòng thực hành với không gian sáng tạo và các trang thiết bị chuyên dụng liên tục cập nhật, giúp sinh viên tiếp cận nhanh chóng với công nghệ và các xu hướng mới của ngành thời trang.\nĐiểm nổi bật của chương trình học là được xây dựng theo hướng kết nối với doanh nghiệp. Nhà trường thường xuyên kết hợp với các công ty trong và ngoài nước thuộc lĩnh vực thời trang để tổ chức các buổi tham quan, kiến tập, các cuộc thi thiết kế chuyên nghiệp nhằm giúp sinh viên phát triển toàn diện về kiến thức và kỹ năng nghề nghiệp. Ngoài các chương trình học chính khóa, sinh viên ngành Thiết kế thời trang có cơ hội tham gia sinh hoạt tại Câu lạc bộ thời trang của khoa và các hoạt động sôi nổi của trường.\nSinh viên tốt nghiệp ngành Thiết kế thời trang tại Trường Đại học Tôn Đức Thắng được trang bị đầy đủ kỹ năng về nguyên lý thiết kế và quy trình thiết kế một bộ sưu tập thời trang từ khâu đầu đến khâu cuối; vận dụng những hiểu biết về thị hiếu thẩm mỹ, về lịch sử mỹ thuật, lịch sử trang phục để từ đó có những thiết kế phù hợp với nhu cầu của người tiêu dùng; xây dựng, định hướng, thúc đẩy trình độ thẩm mỹ của người tiêu dùng thông qua các sản phẩm thời trang. Bên cạnh đó, sinh viên sau khi tốt nghiệp còn có khả năng tự cập nhật kiến thức, sử dụng thành thạo các phần mềm thiết kế 2D, 3D làm công cụ phân tích về trào lưu, xu hướng mốt, tìm kiếm và phát triển ý tưởng để thiết kế các loại hình trang phục đa dạng như: trang phục trẻ em, trang phục dạo phố, trang phục dạ hội, trang phục cưới,…\nCử nhân\nToàn thời gian: 4 năm\nXem thông tin chi tiết về chương trình đào tạo\nXem thông tin chi tiết về chuẩn đầu ra\nKết quả quá trình học tập THPT\nKết quả bài thi ĐGNL năm 2025 của ĐHQG TP. HCM\nTổ hợp: Đang cập nhật\nĐiểm trúng tuyển 2024 (thang 40): 30,60\nTháng 9, năm 2025\nKhoảng 31 đến 32 triệu đồng/năm (năm 2024)", "content": {"Bằng cấp": "Cử nhân", "Thời gian đào tạo": "Toàn thời gian: 4 năm", "Chương trình đào tạo": "Xem thông tin chi tiết về chương trình đào tạo", "Chuẩn đầu ra": "Xem thông tin chi tiết về chuẩn đầu ra", "Phương thức xét tuyển riêng": "Kết quả quá trình học tập THPT Kết quả bài thi ĐGNL năm 2025 của ĐHQG TP. HCM", "Xét tuyển theo điểm thi THPT": "Tổ hợp: Đang cập nhật Điểm trúng tuyển 2024 (thang 40): 30,60", "Khai giảng": "Tháng 9, năm 2025", "Học phí": "Khoảng 31 đến 32 triệu đồng/năm (năm 2024)"}, "name": "Thiết kế thời trang"}], "images": ["https://admission.tdtu.edu.vn/sites/admission23/files/Tuyen-sinh/Dai-hoc/Nganh/Thiet-ke-thoi-trang/1.png", "https://admission.tdtu.edu.vn/sites/admission23/files/Tuyen-sinh/Dai-hoc/Nganh/Thiet-ke-thoi-trang/2.JPG", "https://admission.tdtu.edu.vn/sites/admission23/files/Tuyen-sinh/Dai-hoc/Nganh/Thiet-ke-thoi-trang/3.jpg", "https://admission.tdtu.edu.vn"]}
{"name": "Thống kê", "description": "Thống kê là ngành học liên quan đến các vấn đề về dữ liệu như thu thập, tổng hợp, phân tích, giải thích, dự báo từ dữ liệu. Thống kê được ứng dụng trong rất nhiều lĩnh vực khoa học và đời sống như kinh tế, y học, môi trường, thời tiết, nông nghiệp. Thống kê là một trong những ngành học then chốt để tiếp cận với các lĩnh vực có rất nhiều sức hút hiện nay như khoa học dữ liệu, trí tuệ nhân tạo.\nCử nhân Thống kê có thể đảm nhận nhiều vị trí công việc như: Nghiệp vụ thống kê tại các đơn vị thống kê nhà nước ở Việt Nam, như Tổng cục thống kê Việt Nam, Cục thống kê cấp tỉnh, thành phố trực thuộc trung ương, Chi cục thống kê cấp quận, huyện, thị xã; Công tác tổng hợp, báo cáo, phân tích thống kê về các chỉ tiêu kinh tế - xã hội tại các sở, ban, ngành ở các cấp chính quyền từ trung ương đến địa phương; Chuyên viên phân tích dữ liệu tại các công ty nghiên cứu thị trường, bảo hiểm, chứng khoán, tài chính; Giảng dạy các học phần về thống kê và xác suất tại các trường đại học, cao đẳng, trung cấp chuyên nghiệp trong hệ thống giáo dục đào tạo Việt Nam. Ngoài ra, với các chuyên môn về thu thập, phân tích, báo cáo dữ liệu thống kê được học cho phép người tốt nghiệp ngành Thống kê có tính linh hoạt trong việc thích ứng làm các công việc khác trong nhiều lĩnh vực về kinh tế - xã hội.", "reasons": ["Đội ngũ giảng viên giàu kinh nghiệm", "Liên tục cập nhật xu hướng", "100% sinh viên ra trường có việc làm trong vòng 12 tháng kể từ khi tốt nghiệp"], "programs": [{"tab": "Tiêu chuẩn", "major_code": "7460201", "description": "Chương trình đào tạo không chỉ cung cấp cho sinh viên kiến thức và kỹ năng nghề nghiệp Thống kê mà còn rèn luyện tư duy logic, khả năng phân tích, giải quyết vấn đề thực tế nhanh nhẹn và hiệu quả trong công việc và các kỹ năng mềm khác.\nSinh viên được trải nghiệm với môi trường làm việc thực tế bên ngoài trường thông qua hoạt động tập sự nghề nghiệp Thống kê, được tham gia các workshop, seminar trong các lĩnh vực liên quan đến Thống kê. Sinh viên yêu thích nghiên cứu khoa học sẽ có cơ hội tham gia hoạt động nghiên cứu khoa học trong sinh viên dưới hướng dẫn, hỗ trợ của thầy cô giảng dạy trong ngành.\nChương trình đào tạo đã được kiểm định bởi tổ chức AUN (ASEAN University Network), một tổ chức bảo đảm chất lượng của mạng lưới các trường đại học thuộc cộng đồng ASEAN.\nCử nhân\nToàn thời gian: 4 năm\nXem thông tin chi tiết về chương trình đào tạo\nXem thông tin chi tiết về chuẩn đầu ra\nKết quả quá trình học tập THPT\nKết quả bài thi ĐGNL năm 2025 của ĐHQG TP. HCM\nTổ hợp: Đang cập nhật\nĐiểm trúng tuyển 2024 (thang 40):28,50\nTháng 9, năm 2025\nKhoảng 27 đến 28 triệu đồng/năm (năm 2024)", "content": {"Bằng cấp": "Cử nhân", "Thời gian đào tạo": "Toàn thời gian: 4 năm", "Chương trình đào tạo": "Xem thông tin chi tiết về chương trình đào tạo", "Chuẩn đầu ra": "Xem thông tin chi tiết về chuẩn đầu ra", "Phương thức xét tuyển riêng": "Kết quả quá trình học tập THPT Kết quả bài thi ĐGNL năm 2025 của ĐHQG TP. HCM", "Xét tuyển theo điểm thi THPT": "Tổ hợp: Đang cập nhật Điểm trúng tuyển 2024 (thang 40):28,50", "Khai giảng": "Tháng 9, năm 2025", "Học phí": "Khoảng 27 đến 28 triệu đồng/năm (năm 2024)"}, "name": "Thống kê"}], "images": ["https://admission.tdtu.edu.vn/sites/admission23/files/Tuyen-sinh/Dai-hoc/Nganh/TK/1.jpg", "https://admission.tdtu.edu.vn/sites/admission23/files/Tuyen-sinh/Dai-hoc/Nganh/TK/2.jpg", "https://admission.tdtu.edu.vn/sites/admission23/files/Tuyen-sinh/Dai-hoc/Nganh/TK/3.jpg"]}
{"name": "Toán ứng dụng", "description": "Ngành Toán ứng dụng là một ngành học rất phù hợp với những bạn trẻ yêu thích tìm hiểu về khoa học tính toán. Được đánh giá là ngành học mang tính ứng dụng cao và có ảnh hưởng đến nhiều ngành khoa học, có tiềm năng phát triển lớn trong tương lai. Các ứng dụng có thể bao gồm về giải tích số, toán học tính toán, mô hình toán học, tối ưu hoá, toán sinh học, lý thuyết trò chơi, toán tài chính,…\nTheo học ngành Toán ứng dụng tại Trường Đại học Tôn Đức Thắng, người học sẽ được đào tạo chuyên sâu về nhiều mảng của Toán học và Tin học như: Toán rời rạc, Đại số tuyến tính, Giải tích, Ngôn ngữ lập trình, Cơ sở dữ liệu,… Sau khi tốt nghiệp, sinh viên còn được trang bị thêm nhiều kỹ năng như:\nCử nhân Toán ứng dụng có thể đảm nhận nhiều vị trí công việc như: chuyên viên quản lý ngân sách, chuyên viên phân tích đầu tư, chuyên viên phân tích nghiên cứu hoạt động tại các công ty tài chính, các cơ quan chính phủ, phi chính phủ, tổ chức nghiên cứu, tổ chức học thuật; chuyên viên thiết kế và xây dựng thuật toán cho các phần mềm ứng dụng, truy vấn cơ sở dữ liệu, phát triển các thủ tục kiểm thử và khắc phục lỗi, tùy chỉnh phần mềm cho phù hợp với yêu cầu; giảng viên giảng dạy Toán ứng dụng hoặc giáo viên môn Toán tại các trường phổ thông, trung cấp, cao đẳng, đại học, …", "reasons": ["Đội ngũ giảng viên giàu kinh nghiệm", "Liên tục cập nhật xu hướng", "100% sinh viên ra trường có việc làm trong vòng 12 tháng kể từ khi tốt nghiệp"], "programs": [{"tab": "Tiêu chuẩn", "major_code": "7460112", "description": "Ngành Toán ứng dụng không chỉ cung cấp cho sinh viên kiến thức toán học hiện đại, mà còn trang bị cho sinh viên một số kỹ năng tính toán cơ bản, rèn luyện tư duy logic, khả năng phân tích, giải quyết vấn đề thực tế nhanh nhẹn và hiệu quả trong công việc và các kỹ năng mềm khác.\nSinh viên được trải nghiệm với môi trường làm việc thực tế bên ngoài trường thông qua học phần tập sự nghề nghiệp; được tham gia các workshop, seminar trong lĩnh vực liên quan đến ngành Toán ứng dụng. Các sinh viên giỏi và yêu thích nghiên cứu khoa học sẽ được hướng dẫn trong hoạt động nghiên cứu khoa học của sinh viên hoặc tham gia nghiên cứu và đăng kết quả nghiên cứu trên các tập san về Toán học ở trong nước và quốc tế.\nTối thiểu 10% môn học chuyên ngành trong chương trình đào tạo ngành Toán ứng dụng được giảng dạy bằng tiếng Anh. Chương trình đào tạo có tính liên thông với các chương trình Sau Đại học của Khoa.\nCử nhân\nToàn thời gian: 4 năm\nXem thông tin chi tiết về chương trình đào tạo\nXem thông tin chi tiết về chuẩn đầu ra\nKết quả quá trình học tập THPT\nKết quả bài thi ĐGNL năm 2025 của ĐHQG TP. HCM\nTổ hợp: Đang cập nhật\nĐiểm trúng tuyển 2024 (thang 40):31,00\nTháng 9, năm 2025\nKhoảng 27 đến 28 triệu đồng/năm (năm 2024)", "content": {"Bằng cấp": "Cử nhân", "Thời gian đào tạo": "Toàn thời gian: 4 năm", "Chương trình đào tạo": "Xem thông tin chi tiết về chương trình đào tạo", "Chuẩn đầu ra": "Xem thông tin chi tiết về chuẩn đầu ra", "Phương thức xét tuyển riêng": "Kết quả quá trình học tập THPT Kết quả bài thi ĐGNL năm 2025 của ĐHQG TP. HCM", "Xét tuyển theo điểm thi THPT": "Tổ hợp: Đang cập nhật Điểm trúng tuyển 2024 (thang 40):31,00", "Khai giảng": "Tháng 9, năm 2025", "Học phí": "Khoảng 27 đến 28 triệu đồng/năm (năm 2024)"}, "name": "Toán ứng dụng"}], "images": ["https://admission.tdtu.edu.vn/sites/admission23/files/Tuyen-sinh/Dai-hoc/Nganh/T-UD/1.jpg", "https://admission.tdtu.edu.vn/sites/admission23/files/Tuyen-sinh/Dai-hoc/Nganh/T-UD/2.jpg", "https://admission.tdtu.edu.vn/sites/admission23/files/Tuyen-sinh/Dai-hoc/Nganh/T-UD/3.jpg"]}
{"name": "Xã hội học", "description": "Xã hội học là ngành khoa học về hành vi con người và tổ chức xã hội, chuyên điều tra, khảo sát xã hội, phản biện xã hội, xác định nguyên nhân của các hiện tượng xã hội bất ổn và tìm ra giải pháp nhằm góp phần quản lý xã hội hiệu quả hơn trong giai đoạn hội nhập và phát triển. Một số hiện tượng xã hội mà ngành xã hội học nghiên cứu như hành vi lệch chuẩn trên xã hội thực và trên mạng xã hội, sự bất bình đẳng xã hội, nghèo đói, thất nghiệp, tham nhũng, lãng phí, vô cảm; ảnh hưởng tiêu cực của truyền thông đại chúng, mạng xã hội,… đến đời sống cá nhân, gia đình, và các nhóm xã hội, cộng đồng.\n\nCử nhân ngành Xã hội học được trang bị kiến thức và kỹ năng nghề nghiệp để tự tin ứng tuyển vào các tổ chức chính trị - xã hội, doanh nghiệp, trung tâm nghiên cứu, các tổ chức NGO; có thể làm việc ở các vị trí: hành chính, nhân sự, hỗ trợ và tư vấn kỹ thuật trong các cuộc khảo sát điều tra, viết đề xuất các dự án phát triển, hoạch định chính sách xã hội cho các tổ chức chính phủ và phi chính phủ; các bộ phận tiếp thị, quảng cáo, tư vấn khách hàng, quan hệ công chúng, quản lý hệ thống thông tin nội bộ, tổ chức sự kiện truyền thông doanh nghiệp hay tiếp tục học các chương trình sau đại học để tham gia giảng dạy tại các trường đại học.", "reasons": ["Chương trình được trao chứng nhận kiểm định theo tiêu chuẩn FIBAA với thời hạn công nhận là 05 năm (2021 - 2026)", "Đội ngũ giảng viên có chuyên môn cao, có kinh nghiệm nghiên cứu và hướng dẫn sinh viên thực hiện các dự án nghiên cứu khoa học", "100% sinh viên ra trường có việc làm trong vòng 12 tháng kể từ khi tốt nghiệp"], "programs": [{"tab": "Tiêu chuẩn", "major_code": "7310301", "description": "Chương trình đào tạo được xây dựng theo tiêu chuẩn quốc tế với hai định hướng: Quản lý xã hội và Truyền thông đại chúng. Đối với định hướng Quản lý xã hội, sinh viên được hướng dẫn tập trung vào việc ứng dụng các quan điểm lý thuyết và phương pháp nghiên cứu xã hội học, thiết kế nghiên cứu và công cụ thu thập thông tin, xử lý và phân tích thông tin vào khảo sát các vấn đề trong tất cả các lĩnh vực của đời sống xã hội theo nhu cầu của các tổ chức kinh tế, chính trị, xã hội, ...\nVới định hướng Truyền thông đại chúng, sinh viên được trang bị những kiến thức liên ngành khoa học xã hội, ứng dụng các quan điểm lý thuyết xã hội học, văn hóa, truyền thông và phương pháp nghiên cứu xã hội học để phân tích tác động & ảnh hưởng kinh tế, xã hội, văn hóa đến cá nhân, các nhóm xã hội, cộng đồng và xã hội nói chung trong bối cảnh thực hiện chuyển đổi số trong mọi lĩnh vực của đời sống kinh tế - xã hội hiện nay.\nCử nhân\nToàn thời gian: 4 năm\nXem thông tin chi tiết về chương trình đào tạo\nXem thông tin chi tiết về chuẩn đầu ra\nKết quả quá trình học tập THPT\nKết quả bài thi ĐGNL năm 2025 của ĐHQG TP. HCM\nTổ hợp: Đang cập nhật\nĐiểm trúng tuyển 2024 (thang 40):32,30\nTháng 9, năm 2025\nKhoảng 27 đến 28 triệu đồng/năm (năm 2024)", "content": {"Bằng cấp": "Cử nhân", "Thời gian đào tạo": "Toàn thời gian: 4 năm", "Chương trình đào tạo": "Xem thông tin chi tiết về chương trình đào tạo", "Chuẩn đầu ra": "Xem thông tin chi tiết về chuẩn đầu ra", "Phương thức xét tuyển riêng": "Kết quả quá trình học tập THPT Kết quả bài thi ĐGNL năm 2025 của ĐHQG TP. HCM", "Xét tuyển theo điểm thi THPT": "Tổ hợp: Đang cập nhật Điểm trúng tuyển 2024 (thang 40):32,30", "Khai giảng": "Tháng 9, năm 2025", "Học phí": "Khoảng 27 đến 28 triệu đồng/năm (năm 2024)"}, "name": "Xã hội học"}, {"tab": "Tiên tiến", "major_code": "F7310301", "description": "Chương trình đào tạo được thiết kế theo hướng hiện đại và hội nhập quốc tế nhằm đáp ứng nhu cầu của thị trường lao động trong bối cảnh cách mạng công nghiệp 4.0, phát triển phương tiện truyền thông mới. Đặc biệt nhấn mạnh kiến thức, kỹ năng công nghệ thông tin và công nghệ kỹ thuật số trong tổ chức và quản lý xã hội, phát triển kinh tế. Trong đó, gần 50% thời lượng chương trình được giảng dạy bằng tiếng Anh do giảng viên trong nước và quốc tế có kinh nghiệm và kiến thức chuyên môn cao thực hiện; Gần 30% thời lượng dành cho việc thực hành, thực tế nghề nghiệp, thực tập nghề nghiệp tại các cơ quan, doanh nghiệp trong các lĩnh vực về quản lý xã hội và truyền thông đại chúng. Phương pháp giảng dạy lấy người học làm trung tâm, kích thích sự sáng tạo, tư duy logic, phản biện của sinh viên.\nSinh viên có cơ hội tiếp cận các phương pháp nghiên cứu mới thông qua các hoạt động seminar, hội thảo quốc tế, hợp tác nghiên cứu khoa học sinh viên Việt Nam và quốc tế.\nNội dung chương trình đào tạo và phương pháp giảng dạy đáp ứng với tiêu chuẩn quốc tế đã giúp sinh viên xã hội học trở thành công dân toàn cầu, có thể tham gia vào thị trường lao động trong nước và Cộng đồng kinh tế ASEAN đặc biệt trong bối cảnh kiến thức và kỹ năng khảo sát (survey) – của ngành xã hội học, nằm trong 8 ngành nghề được tự do di chuyển trong thị trường lao động theo Hiệp định công nhận lẫn nhau (Mutual Recognition Agreements – MRAs).\nCử nhân\nToàn thời gian: 4 năm\nXem thông tin chi tiết về chương trình đào tạo\nXem thông tin chi tiết về chuẩn đầu ra\nTổ hợp: Văn*2, Anh, Sử\nKQ ĐGNL của ĐHQG TP. HCM\nƯu tiên xét tuyển theo TDTU\nTổ hợp: A01; C00; C01; D01\nTháng 9, năm 2025\nĐang cập nhật", "content": {"Bằng cấp": "Cử nhân", "Thời gian đào tạo": "Toàn thời gian: 4 năm", "Chương trình đào tạo": "Xem thông tin chi tiết về chương trình đào tạo", "Chuẩn đầu ra": "Xem thông tin chi tiết về chuẩn đầu ra", "Phương thức xét tuyển riêng": "Tổ hợp: Văn*2, Anh, Sử KQ ĐGNL của ĐHQG TP. HCM Ưu tiên xét tuyển theo TDTU", "Xét tuyển theo điểm thi THPT": "Tổ hợp: A01; C00; C01; D01", "Khai giảng": "Tháng 9, năm 2025", "Học phí": "Đang cập nhật"}, "name": "Xã hội học"}], "images": ["https://admission.tdtu.edu.vn/sites/admission23/files/Tuyen-sinh/Dai-hoc/Nganh/Xa-hoi-hoc/1.jpg", "https://admission.tdtu.edu.vn/sites/admission23/files/Tuyen-sinh/Dai-hoc/Nganh/Xa-hoi-hoc/2.jpg", "https://admission.tdtu.edu.vn/sites/admission23/files/Tuyen-sinh/Dai-hoc/Nganh/Xa-hoi-hoc/3.jpg"]}
