{
  "name": "Kế toán",
  "description": "Kế toán không chỉ là công cụ quản lý kinh tế – tài chính thuần túy, mà đã trở thành một lĩnh vực dịch vụ, một nghề nghiệp then chốt trong nền kinh tế thị trường. Đây là ngành quan trọng trong việc chuyển tải những thông tin kinh doanh đến các bên liên quan để làm nền tảng cho những quyết định chiến lược về những vấn đề tài chính doanh nghiệp và cá nhân, tuân thủ các quy định luật pháp, đáp ứng nhu cầu phát triển kinh tế của doanh nghiệp toàn cầu.",
  "reasons": [
    "Đội ngũ giảng viên tâm huyết với nghề",
    "Môi trường học tập hiện đại, chương trình đào tạo tích hợp chứng chỉ nghề nghiệp quốc tế",
    "Mạng lưới đối tác mạnh mẽ"
  ],
  "programs": [
    {
      "tab": "Tiêu chuẩn",
      "major_code": "7340301",
      "description": "Chương trình đào tạo ngành Kế toán sẽ trang bị cho sinh viên các khối kiến thức chung (ngoại ngữ, tin học, toán học, kiến thức xã hội), kiến thức cơ bản đến chuyên ngành về kế toán tài chính và quản trị, quản lý tài chính, thuế, kiểm toán, và luật thương mại, …\nBên cạnh đó, sinh viên còn được mở rộng kiến thức của mình trong nhiều lĩnh vực kinh doanh khác như marketing, kinh tế và tài chính, quản lý và khởi nghiệp, … Chương trình còn cung cấp thêm cho sinh viên một số phần mềm chuyên dụng được cập nhật liên tục theo xu hướng hiện đại của thế giới để làm công cụ hỗ trợ cho sự nghiệp trong tương lai.\nThông qua chương trình đào tạo được xây dựng theo chuẩn quốc tế và bám sát với nhu cầu thực tiễn của xã hội, Nhà trường luôn chú trọng hợp tác và mở rộng mạng lưới doanh nghiệp nhằm tạo điều kiện cho sinh viên có cơ hội học hỏi và tiếp xúc sớm với môi trường công việc thực tế ngay từ những năm đầu Đại học để phát triển khả năng tư duy, phân tích và đánh giá kinh tế thị trường.\nNhà trường còn thường xuyên tổ chức các buổi hội thảo, sinh hoạt học thuật hoặc các cuộc thi chuyên ngành về lĩnh vực kế toán - kiểm toán, tạo môi trường cho sinh viên được giao lưu và trải nghiệm nghề nghiệp trong cùng lĩnh vực. Sinh viên còn có cơ hội học tập thêm các chứng chỉ quốc tế về kế toán, kiểm toán để mở rộng cơ hội nghề nghiệp tại các doanh nghiệp nước ngoài và các tập đoàn đa quốc gia.\nCử nhân\nToàn thời gian: 4 năm\nXem thông tin chi tiết về chương trình đào tạo\nXem thông tin chi tiết về chuẩn đầu ra\nKết quả quá trình học tập THPT\nKết quả bài thi ĐGNL năm 2025 của ĐHQG TP. HCM\nTổ hợp: Đang cập nhật\nĐiểm trúng tuyển 2024 (thang 40):32.40\nTháng 9, năm 2025\n29.770.000 đồng/năm",
      "content": {
        "Bằng cấp": "Cử nhân",
        "Thời gian đào tạo": "Toàn thời gian: 4 năm",
        "Chương trình đào tạo": "Xem thông tin chi tiết về chương trình đào tạo",
        "Chuẩn đầu ra": "Xem thông tin chi tiết về chuẩn đầu ra",
        "Phương thức xét tuyển riêng": "Kết quả quá trình học tập THPT Kết quả bài thi ĐGNL năm 2025 của ĐHQG TP. HCM",
        "Xét tuyển theo điểm thi THPT": "Tổ hợp: Đang cập nhật Điểm trúng tuyển 2024 (thang 40):32.40",
        "Khai giảng": "Tháng 9, năm 2025",
        "Học phí": "29.770.000 đồng/năm"
      },
      "name": "Kế toán"
    },
    {
      "tab": "Tiên tiến",
      "major_code": "F7340301",
      "description": "Sinh viên được trang bị thêm các kỹ năng nghề nghiệp cần thiết cho tương lai cùng các cơ hội thực tập sớm, cơ hội giao lưu nghề nghiệp trong nước và quốc tế ngay trong quá trình học.\nTấm bằng cử nhân Kế toán - Chương trình tiên tiến tại TDTU sẽ là thẻ thông hành để bạn làm việc bất cứ nơi nào trên thế giới. Các vị trí nghề nghiệp về tài chính, kế toán, kiểm toán, tư vấn tài chính, tư vấn thuế, quản trị rủi ro, kiểm soát nội bộ… tại bất kỳ ngành nghề và lĩnh vực nào từ các cơ quan nhà nước, doanh nghiệp trong nước và quốc tế, công ty đa quốc gia, tổ chức tài chính (ngân hàng, chứng khoán, bảo hiểm, quỹ tài chính), tổ chức phi chính phủ cũng như quản lý doanh nghiệp gia đình.\nCử nhân\nToàn thời gian: 4 năm\nXem thông tin chi tiết về chương trình đào tạo\nXem thông tin chi tiết về chuẩn đầu ra\nKết quả quá trình học tập THPT\nKết quả bài thi ĐGNL năm 2025 của ĐHQG TP. HCM\nTổ hợp: Đang cập nhật\nĐiểm trúng tuyển 2024 (thang 40):27,00\nTháng 9, năm 2025\nTừ 54 đến 55 triệu đồng/năm",
      "content": {
        "Bằng cấp": "Cử nhân",
        "Thời gian đào tạo": "Toàn thời gian: 4 năm",
        "Chương trình đào tạo": "Xem thông tin chi tiết về chương trình đào tạo",
        "Chuẩn đầu ra": "Xem thông tin chi tiết về chuẩn đầu ra",
        "Phương thức xét tuyển riêng": "Kết quả quá trình học tập THPT Kết quả bài thi ĐGNL năm 2025 của ĐHQG TP. HCM",
        "Xét tuyển theo điểm thi THPT": "Tổ hợp: Đang cập nhật Điểm trúng tuyển 2024 (thang 40):27,00",
        "Khai giảng": "Tháng 9, năm 2025",
        "Học phí": "Từ 54 đến 55 triệu đồng/năm"
      },
      "name": "Kế toán"
    },
    {
      "tab": "Đại học bằng tiếng Anh",
      "major_code": "FA7340301",
      "description": "Kế toán - Chương trình đại học bằng tiếng Anh trang bị cho sinh viên các kiến thức và kỹ năng chuyên môn kế toán theo chuẩn mực và thông lệ quốc tế. Chương trình được thiết kế và giảng dạy hoàn toàn bằng tiếng Anh. Sinh viên được trang bị kiến thức và tiếp cận các mô hình thực hành theo chuẩn quốc tế. Một môi trường giáo dục chuyên nghiệp và hiện đại để sinh viên học hỏi và trau dồi tất cả các kĩ năng cần thiết làm nền tảng cho việc hội nhập vào lĩnh vực kế toán - kiểm toán quốc tế tại Việt Nam cũng như các nước trên thế giới.\nCử nhân\nToàn thời gian: 4 năm\nXem thông tin chi tiết về chương trình đào tạo\nXem thông tin chi tiết về chuẩn đầu ra\nKết quả quá trình học tập THPT\nKết quả bài thi ĐGNL năm 2025 của ĐHQG TP. HCM\nTổ hợp: Đang cập nhật\nĐiểm trúng tuyển 2024 (thang 40):24,00\nTháng 9, năm 2025\nTừ 79 đến 80 triệu đồng/năm",
      "content": {
        "Bằng cấp": "Cử nhân",
        "Thời gian đào tạo": "Toàn thời gian: 4 năm",
        "Chương trình đào tạo": "Xem thông tin chi tiết về chương trình đào tạo",
        "Chuẩn đầu ra": "Xem thông tin chi tiết về chuẩn đầu ra",
        "Phương thức xét tuyển riêng": "Kết quả quá trình học tập THPT Kết quả bài thi ĐGNL năm 2025 của ĐHQG TP. HCM",
        "Xét tuyển theo điểm thi THPT": "Tổ hợp: Đang cập nhật Điểm trúng tuyển 2024 (thang 40):24,00",
        "Khai giảng": "Tháng 9, năm 2025",
        "Học phí": "Từ 79 đến 80 triệu đồng/năm"
      },
      "name": "Kế toán"
    },
    {
      "tab": "Liên kết quốc tế",
      "major_code": "K7340301",
      "description": "Cử nhân (song bằng)\n4 năm (3 năm đầu học tại TDTU, 1 năm sau học tại Trường liên kết)\nXem thông tin chi tiết về chương trình đào tạo\nXem thông tin chi tiết\nKết quả quá trình học tập THPT\nKết quả bài thi ĐGNL năm 2025 của ĐHQG TP. HCM\nTổ hợp: Đang cập nhật\nĐiểm trúng tuyển 2024 (thang 40):24,00\nTháng 9, năm 2025\nGiai đoạn 1: Từ 77 đến 78 triệu đồng/năm",
      "content": {
        "Bằng cấp": "Cử nhân (song bằng)",
        "Thời gian đào tạo": "4 năm (3 năm đầu học tại TDTU, 1 năm sau học tại Trường liên kết)",
        "Chương trình đào tạo": "Xem thông tin chi tiết về chương trình đào tạo",
        "Thông tin chương trình": "Xem thông tin chi tiết",
        "Phương thức xét tuyển riêng": "Kết quả quá trình học tập THPT Kết quả bài thi ĐGNL năm 2025 của ĐHQG TP. HCM",
        "Xét tuyển theo điểm thi THPT": "Tổ hợp: Đang cập nhật Điểm trúng tuyển 2024 (thang 40):24,00",
        "Khai giảng": "Tháng 9, năm 2025",
        "Học phí": "Giai đoạn 1: Từ 77 đến 78 triệu đồng/năm"
      },
      "name": "Kế toán liên kết Đại học West of England, Bristol"
    }
  ],
  "images": [
    "https://admission.tdtu.edu.vn",
    "https://admission.tdtu.edu.vn/sites/admission23/files/Tuyen-sinh/Dai-hoc/Nganh/KT/1.jpg",
    "https://admission.tdtu.edu.vn/sites/admission23/files/Tuyen-sinh/Dai-hoc/Nganh/KT/2.jpg",
    "https://admission.tdtu.edu.vn/sites/admission23/files/Tuyen-sinh/Dai-hoc/Nganh/KT/3.jpg"
  ]
}