{
  "name": "Khoa học máy tính",
  "description": "Khoa học máy tính là ngành ứng dụng kiến thức về thuật toán, phương pháp tính toán, ngôn ngữ lập trình, phương pháp phân tích và xây dựng hệ thống thông tin, … để giải quyết các vấn đề thuộc lĩnh vực Khoa học máy tính; phát triển các hệ thống phần mềm máy tính, mô hình tính toán thông minh, các ứng dụng trên các nền tảng hiện đại để phục vụ cho nhiệm vụ công nghiệp hoá, hiện đại hoá đất nước trong lĩnh vực chuyển đổi số.\n\nSau khi tốt nghiệp, cử nhân Khoa học máy tính có thể tự tin đảm nhận tốt các vị trí như chuyên viên thiết kế và xây dựng các phần mềm máy tính, ứng dụng cho thiết bị di động, ứng dụng thương mại điện tử trên nền Web, các trò chơi trên máy tính và di động; chuyên viên quản trị và xây dựng các giải pháp đảm bảo an toàn cho các hệ thống máy tính và hệ thống mạng máy tính; chuyên viên lập trình; chuyên viên phát triển hệ thống thông minh; chuyên viên tư vấn, thẩm định và phát triển các dự án, giải pháp công nghệ thông tin; cán bộ chuyên trách tại các cơ quan nhà nước, … hoặc có thể tiếp tục học tập và nghiên cứu ở các bậc học cao hơn.",
  "reasons": [
    "Liên tục cập nhật xu hướng",
    "Số tiết học thực tế chiếm gần 50% chương trình đào tạo",
    "100% sinh viên ra trường có việc làm trong vòng 12 tháng kể từ khi tốt nghiệp"
  ],
  "programs": [
    {
      "tab": "Tiêu chuẩn",
      "major_code": "7480101",
      "description": "Chương trình cung cấp nền tảng vững chắc về Khoa học máy tính, tập trung vào các lĩnh vực hiện đại như: trí tuệ nhân tạo (AI), khai phá dữ liệu, khoa học dữ liệu, phát triển ứng dụng thông minh, ...\nKết hợp lý thuyết và thực hành, sinh viên áp dụng kiến thức qua các dự án thực tế liên quan đến AI, phân tích dữ liệu lớn, và xây dựng hệ thống thông minh.\nNgười học có hội tham quan và thực tập ở các doanh nghiệp từ năm thứ hai và học hỏi từ các chuyên gia đầu ngành trong lĩnh vực công nghệ tiên tiến.\nSau khi tốt nghiệp, sinh viên có kỹ năng phân tích dữ liệu, xây dựng mô hình AI, phát triển hệ thống hỗ trợ quyết định, và triển khai giải pháp công nghệ tiên tiến.\nCử nhân\nToàn thời gian: 4 năm\nXem thông tin chi tiết về chương trình đào tạo\nXem thông tin chi tiết về chuẩn đầu ra\nKết quả quá trình học tập THPT\nKết quả bài thi ĐGNL năm 2025 của ĐHQG TP. HCM\nTổ hợp: Đang cập nhật\nĐiểm trúng tuyển 2024 (thang 40):33,00\nTháng 9, năm 2025\n34.850.000 đồng/năm",
      "content": {
        "Bằng cấp": "Cử nhân",
        "Thời gian đào tạo": "Toàn thời gian: 4 năm",
        "Chương trình đào tạo": "Xem thông tin chi tiết về chương trình đào tạo",
        "Chuẩn đầu ra": "Xem thông tin chi tiết về chuẩn đầu ra",
        "Phương thức xét tuyển riêng": "Kết quả quá trình học tập THPT Kết quả bài thi ĐGNL năm 2025 của ĐHQG TP. HCM",
        "Xét tuyển theo điểm thi THPT": "Tổ hợp: Đang cập nhật Điểm trúng tuyển 2024 (thang 40):33,00",
        "Khai giảng": "Tháng 9, năm 2025",
        "Học phí": "34.850.000 đồng/năm"
      },
      "name": "Khoa học máy tính"
    },
    {
      "tab": "Tiên tiến",
      "major_code": "F7480101",
      "description": "Chương trình Tiên tiến chú trọng tính chuyên nghiệp và khả năng ứng dụng vào thực tiễn trong các lĩnh vực AI và khoa học dữ liệu. Chương trình được thiết kế mở rộng, nhằm đáp ứng nhu cầu ngày càng cao của xã hội, đồng thời kết hợp chặt chẽ giữa lý thuyết và ứng dụng. Không chỉ cung cấp kiến thức chuyên môn sâu rộng, chương trình còn rèn luyện kỹ năng thực hành, phát triển kỹ năng mềm, và tạo cơ hội thực tập thực tế tại các doanh nghiệp. Sinh viên sẽ được trang bị kiến thức toàn diện về công nghệ hiện đại trong trí tuệ nhân tạo và khoa học dữ liệu.\nĐặc điểm nổi bật:\n- Đội ngũ giảng viên: Giỏi chuyên môn, giàu kinh nghiệm trong lĩnh AI và phân tích dữ liệu.\n- Giảng dạy bằng tiếng Anh: 50% các môn học chuyên ngành.\n- Có cơ hội trao đổi hoặc thực tập tại các trường ở Mỹ, Hàn Quốc, Đài Loan, Cộng hòa Séc, …\nCử nhân\nToàn thời gian: 4 năm\nXem thông tin chi tiết về chương trình đào tạo\nXem thông tin chi tiết về chuẩn đầu ra\nKết quả quá trình học tập THPT\nKết quả bài thi ĐGNL năm 2025 của ĐHQG TP. HCM\nTổ hợp: Đang cập nhật\nĐiểm trúng tuyển 2024 (thang 40):30,80\nTháng 9, năm 2025\nTừ 55 đến 57 triệu đồng/năm",
      "content": {
        "Bằng cấp": "Cử nhân",
        "Thời gian đào tạo": "Toàn thời gian: 4 năm",
        "Chương trình đào tạo": "Xem thông tin chi tiết về chương trình đào tạo",
        "Chuẩn đầu ra": "Xem thông tin chi tiết về chuẩn đầu ra",
        "Phương thức xét tuyển riêng": "Kết quả quá trình học tập THPT Kết quả bài thi ĐGNL năm 2025 của ĐHQG TP. HCM",
        "Xét tuyển theo điểm thi THPT": "Tổ hợp: Đang cập nhật Điểm trúng tuyển 2024 (thang 40):30,80",
        "Khai giảng": "Tháng 9, năm 2025",
        "Học phí": "Từ 55 đến 57 triệu đồng/năm"
      },
      "name": "Khoa học máy tính"
    },
    {
      "tab": "Đại học bằng tiếng Anh",
      "major_code": "FA7480101",
      "description": "Chương trình được mở rộng toàn diện nhất, quốc tế hóa với các đặc điểm:\n- 100% bằng tiếng Anh:Từ các môn cơ sở đến chuyên ngành, tập trung vào trí tuệ nhân tạo, học máy, và khai phá dữ liệu, rèn luyện ngoại ngữ và tư duy toàn cầu.\n- Hợp tác quốc tế:Kết nối với doanh nghiệp và cơ hội học tập tại nước ngoài.\n- Cơ sở vật chất:Môi trường học tập hiện đại, lớp học nhỏ có quy mô 20-25 sinh viên, tăng cường tương tác.\nCử nhân\nToàn thời gian: 4 năm\nXem thông tin chi tiết về chương trình đào tạo\nXem thông tin chi tiết về chuẩn đầu ra\nKết quả quá trình học tập THPT\nKết quả bài thi ĐGNL năm 2025 của ĐHQG TP. HCM\nTổ hợp: Đang cập nhật\nĐiểm trúng tuyển 2024 (thang 40):28,00\nTháng 9, năm 2025\nTừ 81 đến 83 triệu đồng/năm",
      "content": {
        "Bằng cấp": "Cử nhân",
        "Thời gian đào tạo": "Toàn thời gian: 4 năm",
        "Chương trình đào tạo": "Xem thông tin chi tiết về chương trình đào tạo",
        "Chuẩn đầu ra": "Xem thông tin chi tiết về chuẩn đầu ra",
        "Phương thức xét tuyển riêng": "Kết quả quá trình học tập THPT Kết quả bài thi ĐGNL năm 2025 của ĐHQG TP. HCM",
        "Xét tuyển theo điểm thi THPT": "Tổ hợp: Đang cập nhật Điểm trúng tuyển 2024 (thang 40):28,00",
        "Khai giảng": "Tháng 9, năm 2025",
        "Học phí": "Từ 81 đến 83 triệu đồng/năm"
      },
      "name": "Khoa học máy tính"
    },
    {
      "tab": "Liên kết quốc tế - K7480101T",
      "major_code": "K7480101",
      "description": "Cử nhân (đơn bằng)\n4 năm (2 năm đầu học tại TDTU, 2 năm sau học tại Trường liên kết)\nXem thông tin chi tiết về chương trình đào tạo\nXem thông tin chi tiết\nKết quả quá trình học tập THPT\nKết quả bài thi ĐGNL năm 2025 của ĐHQG TP. HCM\nTổ hợp: Đang cập nhật\nĐiểm trúng tuyển 2024 (thang 40):28,00\nTháng 9, năm 2025\nGiai đoạn 1: Từ 76 đến 77 triệu đồng/năm",
      "content": {
        "Bằng cấp": "Cử nhân (đơn bằng)",
        "Thời gian đào tạo": "4 năm (2 năm đầu học tại TDTU, 2 năm sau học tại Trường liên kết)",
        "Chương trình đào tạo": "Xem thông tin chi tiết về chương trình đào tạo",
        "Thông tin chương trình": "Xem thông tin chi tiết",
        "Phương thức xét tuyển riêng": "Kết quả quá trình học tập THPT Kết quả bài thi ĐGNL năm 2025 của ĐHQG TP. HCM",
        "Xét tuyển theo điểm thi THPT": "Tổ hợp: Đang cập nhật Điểm trúng tuyển 2024 (thang 40):28,00",
        "Khai giảng": "Tháng 9, năm 2025",
        "Học phí": "Giai đoạn 1: Từ 76 đến 77 triệu đồng/năm"
      },
      "name": "Khoa học máy tính liên kết Đại học Kỹ thuật Ostrava, Cộng hòa Séc"
    },
    {
      "tab": "Liên kết quốc tế - K7480101L",
      "major_code": "K7480101",
      "description": "Cử nhân (song bằng)\n4 năm (2 năm đầu học tại TDTU, 2 năm sau học tại Trường liên kết)\nXem thông tin chi tiết về chương trình đào tạo\nXem thông tin chi tiết\nKết quả quá trình học tập THPT\nKết quả bài thi ĐGNL năm 2025 của ĐHQG TP. HCM\nTổ hợp: Đang cập nhật\nĐiểm trúng tuyển 2024 (thang 40):28,00\nTháng 9, năm 2025\nGiai đoạn 1: Từ 76 đến 77 triệu đồng/năm",
      "content": {
        "Bằng cấp": "Cử nhân (song bằng)",
        "Thời gian đào tạo": "4 năm (2 năm đầu học tại TDTU, 2 năm sau học tại Trường liên kết)",
        "Chương trình đào tạo": "Xem thông tin chi tiết về chương trình đào tạo",
        "Thông tin chương trình": "Xem thông tin chi tiết",
        "Phương thức xét tuyển riêng": "Kết quả quá trình học tập THPT Kết quả bài thi ĐGNL năm 2025 của ĐHQG TP. HCM",
        "Xét tuyển theo điểm thi THPT": "Tổ hợp: Đang cập nhật Điểm trúng tuyển 2024 (thang 40):28,00",
        "Khai giảng": "Tháng 9, năm 2025",
        "Học phí": "Giai đoạn 1: Từ 76 đến 77 triệu đồng/năm"
      },
      "name": "Công nghệ thông tin liên kết Đại học La Trobe, Úc"
    }
  ],
  "images": [
    "https://admission.tdtu.edu.vn/sites/admission23/files/Tuyen-sinh/Dai-hoc/Nganh/KHMTinh/3.JPG",
    "https://admission.tdtu.edu.vn/sites/admission23/files/Tuyen-sinh/Dai-hoc/Nganh/KHMTinh/1.jpg",
    "https://admission.tdtu.edu.vn/sites/admission23/files/Tuyen-sinh/Dai-hoc/Nganh/KHMTinh/2.jpg"
  ]
}