{
  "name": "Kiến trúc",
  "description": "Kiến trúc là ngành tích hợp kiến thức ở cả 2 lĩnh vực nghệ thuật và kỹ thuật, vận dụng tư duy logic và khả năng sáng tạo để thiết kế, tổ chức và sắp xếp không gian các công trình kiến trúc, cung cấp các giải pháp trong lĩnh vực xây dựng nhằm đáp ứng nhu cầu thực tế về nơi ở, sinh hoạt, vui chơi, làm việc,… của xã hội.\n\nKiến trúc sư tốt nghiệp tại Trường Đại học Tôn Đức Thắng hoàn toàn có thể tự tin ứng tuyển vào làm việc tại các công ty tư vấn thiết kế kiến trúc - xây dựng, viện nghiên cứu kiến trúc, ban quản lý các dự án, cơ quan quản lý kiến trúc và quy hoạch xây dựng đô thị hoặc tự thành lập doanh nghiệp để phát triển năng lực của bản thân. Ngoài ra, sinh viên sau khi tốt nghiệp còn có cơ hội trở thành giảng viên giảng dạy các môn học thuộc chuyên ngành Kiến trúc tại các trường đại học trên cả nước hoặc nước ngoài.",
  "reasons": [
    "Đội ngũ giảng viên giàu kinh nghiệm",
    "Liên tục cập nhật xu hướng",
    "Sáng tạo, thẩm mỹ và mang tính kỹ thuật cao"
  ],
  "programs": [
    {
      "tab": "Tiêu chuẩn",
      "major_code": "7580101",
      "description": "Sinh viên được trang bị đầy đủ kiến thức cơ bản về nghệ thuật kiến trúc, kỹ thuật vẽ hình học, họa hình, bố cục tạo hình, lịch sử mỹ thuật đến các kiến thức chuyên ngành như nguyên lý thiết kế nhà ở, kỹ thuật thi công, công tác quy hoạch, thiết kế đô thị, phương pháp sáng tác kiến trúc, phương pháp vẽ 2D, 3D, các phần mềm đồ hoạ hiện đại và liên tục cập nhật như Revit, Autocad, Sketchup …\nKhông những cung cấp kiến thức nền tảng cho sinh viên, nội dung chương trình đào tạo còn tập trung phát triển các kỹ năng thực hành cho người học, giúp cho người học rèn luyện kỹ năng thiết kế kiến trúc, thiết kế nội thất và phát triển năng lực tư duy thẩm mỹ về không gian, nhận thức và tạo dựng cái đẹp nhằm đáp ứng nhu cầu thực tế của xã hội.\nSinh viên còn được tạo điều kiện để tham gia các buổi liên hoan nghệ thuật, chương trình triển lãm và các cuộc thi thiết kế lớn trong và ngoài nước để tích lũy kinh nghiệm thực tế, giao lưu văn hoá và nâng cao khả năng sáng tạo.\nThông qua mạng lưới đối tác doanh nghiệp thân hữu, sinh viên được hướng dẫn tham gia kiến tập tại các công ty trong và ngoài nước, qua đó giúp sinh viên sớm làm quen và tiếp cận với môi trường văn hoá doanh nghiệp, tạo cơ hội tìm kiếm cơ hội nghề nghiệp cho tương lai. Đặc biệt, đối với một số môn học chuyên ngành, Nhà trường sẽ kết hợp với các đối tác quốc tế, tổ chức các chương trình học tập trao đổi ngắn hạn nhằm tạo điều kiện cho sinh viên được tìm hiểu về lịch sử và các công trình kiến trúc của mỗi quốc gia và giao lưu văn hoá giữa các nền văn hóa trên thế giới.\nSinh viên sau khi tốt nghiệp được trang bị đầy đủ kiến thức và kỹ năng sử dụng thành thạo các phần mềm phục vụ thiết kế; phân tích, tổng hợp và ứng dụng khoa học công nghệ để thực hiện các đồ án thiết kế kiến trúc; vận dụng khả năng tư duy sáng tạo để phác thảo ý tưởng thiết kế ban đầu cho đến triển khai bản vẽ kỹ thuật thi công; hiểu biết căn bản về các giải pháp kết cấu công trình và sử dụng vật liệu xây dựng trong kiến trúc nội – ngoại thất công trình.\nCử nhân\nKiến trúc sư\nToàn thời gian: 4 năm\nToàn thời gian: 5 năm\nXem thông tin chi tiết về chương trình đào tạo\nXem thông tin chi tiết về chuẩn đầu ra\nKết quả quá trình học tập THPT\nKết quả bài thi ĐGNL năm 2025 của ĐHQG TP. HCM\nTổ hợp: Đang cập nhật\nĐiểm trúng tuyển 2024 (thang 40):29,80\nTháng 9, năm 2025\n34.850.000 đồng/năm",
      "content": {
        "Bằng cấp": "Cử nhân Kiến trúc sư",
        "Thời gian đào tạo": "Toàn thời gian: 4 năm Toàn thời gian: 5 năm",
        "Chương trình đào tạo": "Xem thông tin chi tiết về chương trình đào tạo",
        "Chuẩn đầu ra": "Xem thông tin chi tiết về chuẩn đầu ra",
        "Phương thức xét tuyển riêng": "Kết quả quá trình học tập THPT Kết quả bài thi ĐGNL năm 2025 của ĐHQG TP. HCM",
        "Xét tuyển theo điểm thi THPT": "Tổ hợp: Đang cập nhật Điểm trúng tuyển 2024 (thang 40):29,80",
        "Khai giảng": "Tháng 9, năm 2025",
        "Học phí": "34.850.000 đồng/năm"
      },
      "name": "Kiến trúc"
    },
    {
      "tab": "Tiên tiến",
      "major_code": "F7580101",
      "description": "Chương trình tiên tiến (giảng dạy và tài liệu học tập bằng tiếng anh đối với một số môn học chuyên ngành), sĩ số lớp học dưới 35 sinh viên. Do các giảng viên giàu kinh nghiệm trực tiếp giảng dạy. Ngoài kiến thức nền tảng và chuyên môn được thiết kế và cập nhật liên tục theo xu hướng của nền giáo dục chuẩn quốc tế, sinh viên theo học ngành Kiến trúc chương trình tiên tiến còn được trang bị thêm các kỹ năng nghề nghiệp trong cùng lĩnh vực nhằm đáp ứng yêu cầu của nền giáo dục khai phóng, đào tạo nguồn nhân lực chất lượng cao và vững tay nghề.\nBên cạnh đó, sinh viên còn được tham gia các học phần thực tế tại nước ngoài, tìm hiểu văn hóa và kiến trúc đặc trưng của các quốc gia có lịch sử lâu đời trên thế giới, qua đó nâng cao hiểu biết về văn hóa và kiến thức chuyên ngành, đồng thời giúp sinh viên phát triển tư duy thẩm mỹ và năng lực nghiên cứu, sáng tạo trong nghệ thuật.\nNgoài ra, sinh viên được hướng dẫn tham gia kiến tập tại các công ty trong và ngoài nước để làm quen và tiếp cận với môi trường văn hoá doanh nghiệp, tạo cơ hội tìm kiếm cơ hội nghề nghiệp cho tương lai. Nhà trường cũng đặc biệt hỗ trợ, giới thiệu việc làm cho sinh viên sau khi tốt nghiệp.\nCử nhân\nKiến trúc sư\nToàn thời gian: 4 năm\nToàn thời gian: 5 năm\nXem thông tin chi tiết về chương trình đào tạo\nXem thông tin chi tiết về chuẩn đầu ra\nKết quả quá trình học tập THPT\nKết quả bài thi ĐGNL năm 2025 của ĐHQG TP. HCM\nTổ hợp: Đang cập nhật\nĐiểm trúng tuyển 2024 (thang 40):28,50\nTháng 9, năm 2025\nTừ 55 đến 57 triệu đồng/năm",
      "content": {
        "Bằng cấp": "Cử nhân Kiến trúc sư",
        "Thời gian đào tạo": "Toàn thời gian: 4 năm Toàn thời gian: 5 năm",
        "Chương trình đào tạo": "Xem thông tin chi tiết về chương trình đào tạo",
        "Chuẩn đầu ra": "Xem thông tin chi tiết về chuẩn đầu ra",
        "Phương thức xét tuyển riêng": "Kết quả quá trình học tập THPT Kết quả bài thi ĐGNL năm 2025 của ĐHQG TP. HCM",
        "Xét tuyển theo điểm thi THPT": "Tổ hợp: Đang cập nhật Điểm trúng tuyển 2024 (thang 40):28,50",
        "Khai giảng": "Tháng 9, năm 2025",
        "Học phí": "Từ 55 đến 57 triệu đồng/năm"
      },
      "name": "Kiến trúc"
    }
  ],
  "images": [
    "https://admission.tdtu.edu.vn/sites/admission23/files/Tuyen-sinh/Dai-hoc/Nganh/Kien-truc/1.JPG",
    "https://admission.tdtu.edu.vn/sites/admission23/files/Tuyen-sinh/Dai-hoc/Nganh/Kien-truc/2.jpg",
    "https://admission.tdtu.edu.vn/sites/admission23/files/Tuyen-sinh/Dai-hoc/Nganh/Kien-truc/3.jpg"
  ]
}