{
  "name": "Kinh doanh quốc tế",
  "description": "Kinh doanh quốc tế đang là một ngành nhận được nhiều sự quan tâm hiện nay trong bối cảnh Việt Nam tham gia nhiều tổ chức thương mại - liên minh kinh tế thế giới và khu vực. Đây là một lĩnh vực thuộc nhóm ngành kinh doanh, ứng dụng kiến thức về thương mại quốc tế, logistics,tài chính và đầu tư, marketing toàn cầu … để thực hiện các giao dịch hàng hóa giữa thương nhân đến từ các quốc gia trên thế giới trong giai đoạn toàn cầu hoá.\n\nCử nhân kinh doanh quốc tế có đầy đủ năng lực để làm việc tại các tập đoàn đa quốc gia, các tổ chức nghiên cứu thị trường, hiệp hội ngành nghề, trung tâm xúc tiến thương mại,... ở những vị trí như chuyên viên xuất nhập khẩu, chuyên viên quản trị logistics, chuyên viên giao nhận vận tải, chuyên viên thanh toán quốc tế, chuyên viên quản trị tài chính, chuyên viên đầu tư quốc tế, chuyên viên marketing quốc tế và các vị trí chức năng quan trọng khác trong môi trường kinh doanh quốc tế.",
  "reasons": [
    "Chương trình đào tạo trình độ đại học được trao chứng nhận kiểm định theo tiêu chuẩn FIBAA",
    "Mức học phí hợp lý với chương trình đào tạo chuẩn quốc tế",
    "100% sinh viên ra trường có việc làm trong vòng 12 tháng kể từ khi tốt nghiệp"
  ],
  "programs": [
    {
      "tab": "Tiêu chuẩn",
      "major_code": "7340120",
      "description": "Cử nhân kinh doanh quốc tế chương trình tiêu chuẩn có đầy đủ năng lực để làm việc tại các tập đoàn đa quốc gia, các tổ chức nghiên cứu thị trường, hiệp hội ngành nghề, trung tâm xúc tiến thương mại,... ở những vị trí như chuyên viên xuất nhập khẩu, chuyên viên quản trị logistics, chuyên viên giao nhận vận tải, chuyên viên thanh toán quốc tế, chuyên viên quản trị tài chính, chuyên viên đầu tư quốc tế, chuyên viên marketing quốc tế và các vị trí chức năng quan trọng khác trong môi trường kinh doanh quốc tế.\nCử nhân\nToàn thời gian: 4 năm\nXem thông tin chi tiết về chương trình đào tạo\nXem thông tin chi tiết về chuẩn đầu ra\nKết quả quá trình học tập THPT\nKết quả bài thi ĐGNL năm 2025 của ĐHQG TP. HCM\nTổ hợp: Đang cập nhật\nĐiểm trúng tuyển 2024 (thang 40):33,80\nTháng 9, năm 2025\n29.770.000 đồng/năm",
      "content": {
        "Bằng cấp": "Cử nhân",
        "Thời gian đào tạo": "Toàn thời gian: 4 năm",
        "Chương trình đào tạo": "Xem thông tin chi tiết về chương trình đào tạo",
        "Chuẩn đầu ra": "Xem thông tin chi tiết về chuẩn đầu ra",
        "Phương thức xét tuyển riêng": "Kết quả quá trình học tập THPT Kết quả bài thi ĐGNL năm 2025 của ĐHQG TP. HCM",
        "Xét tuyển theo điểm thi THPT": "Tổ hợp: Đang cập nhật Điểm trúng tuyển 2024 (thang 40):33,80",
        "Khai giảng": "Tháng 9, năm 2025",
        "Học phí": "29.770.000 đồng/năm"
      },
      "name": "Kinh doanh quốc tế"
    },
    {
      "tab": "Tiên tiến",
      "major_code": "F7340120",
      "description": "Cử nhân kinh doanh quốc tế chương trình tiên tiến của TDTU  được thiết kế có các điểm nổi bật như ứng dụng các công nghệ hệ thống ERP, thực tế ảo VR-QR vào giảng dạy, quy mô lớp học hợp lý, môi trường học tập năng động với cơ sở vật chất hiện đại, tăng cường học tập thực tế tại doanh nghiệp theo phương châm học đi đôi với hành.\nSinh viên tốt nghiệp đạt chuẩn đầu ra với yêu cầu cao về chuyên môn nghiệp vụ, kỹ năng tin học, ngoại ngữ và kỹ năng mềm nhằm đáp ứng được nhu cầu ngày càng đa dạng của doanh nghiệp trong và ngoài nước.\nĐội ngũ giảng viên tham gia giảng dạy chương trình tiên tiến giàu kinh nghiệm thực tiễn và nghiên cứu. Các học phần cốt lõi ngành của chương trình được giảng dạy bởi chuyên gia có kinh nghiệm làm việc thực tế hoặc đến từ doanh nghiệp có uy tín tại Việt Nam hoặc các công ty đa quốc gia.\nCử nhân\nToàn thời gian: 4 năm\nXem thông tin chi tiết về chương trình đào tạo\nXem thông tin chi tiết về chuẩn đầu ra\nKết quả quá trình học tập THPT\nKết quả bài thi ĐGNL năm 2025 của ĐHQG TP. HCM\nTổ hợp: Đang cập nhật\nĐiểm trúng tuyển 2024 (thang 40):30,80\nTháng 9, năm 2025\nTừ 62 đến 64 triệu đồng/năm",
      "content": {
        "Bằng cấp": "Cử nhân",
        "Thời gian đào tạo": "Toàn thời gian: 4 năm",
        "Chương trình đào tạo": "Xem thông tin chi tiết về chương trình đào tạo",
        "Chuẩn đầu ra": "Xem thông tin chi tiết về chuẩn đầu ra",
        "Phương thức xét tuyển riêng": "Kết quả quá trình học tập THPT Kết quả bài thi ĐGNL năm 2025 của ĐHQG TP. HCM",
        "Xét tuyển theo điểm thi THPT": "Tổ hợp: Đang cập nhật Điểm trúng tuyển 2024 (thang 40):30,80",
        "Khai giảng": "Tháng 9, năm 2025",
        "Học phí": "Từ 62 đến 64 triệu đồng/năm"
      },
      "name": "Kinh doanh quốc tế"
    },
    {
      "tab": "Đại học bằng tiếng Anh",
      "major_code": "FA7340120",
      "description": "Cử nhân kinh doanh quốc tế chương trình đại học bằng tiếng Anh của TDTU được thiết kế có các điểm nổi bật như ứng dụng các công nghệ hệ thống ERP, thực tế ảo VR-QR vào giảng dạy, quy mô lớp học hợp lý, môi trường học tập năng động với cơ sở vật chất hiện đại, tăng cường học tập thực tế tại doanh nghiệp theo phương châm học đi đôi với hành. Chương trình giảng dạy hoàn toàn bằng tiếng Anh.\nSinh viên tốt nghiệp đạt chuẩn đầu ra với yêu cầu cao về chuyên môn nghiệp vụ, kỹ năng tin học, đặc biệt là ngoại ngữ và kỹ năng mềm nhằm đáp ứng yêu cầu của thị trường lao động hội nhập quốc tế.\nNgoài ra, sinh viên tham gia chương trình này có cơ hội được tham gia học kỳ tại nước ngoài với các trường đối tác thân hữu, uy tín và có hợp tác với TDTU. Từ đây, sinh viên có thêm nhiều lựa chọn định hướng nghề nghiệp tốt hơn và rộng mở hơn.\nCử nhân\nToàn thời gian: 4 năm\nXem thông tin chi tiết về chương trình đào tạo\nXem thông tin chi tiết về chuẩn đầu ra\nKết quả quá trình học tập THPT\nKết quả bài thi ĐGNL năm 2025 của ĐHQG TP. HCM\nTổ hợp: Đang cập nhật\nĐiểm trúng tuyển 2024 (thang 40):28,00\nTháng 9, năm 2025\nTừ 83 đến 84 triệu đồng/năm",
      "content": {
        "Bằng cấp": "Cử nhân",
        "Thời gian đào tạo": "Toàn thời gian: 4 năm",
        "Chương trình đào tạo": "Xem thông tin chi tiết về chương trình đào tạo",
        "Chuẩn đầu ra": "Xem thông tin chi tiết về chuẩn đầu ra",
        "Phương thức xét tuyển riêng": "Kết quả quá trình học tập THPT Kết quả bài thi ĐGNL năm 2025 của ĐHQG TP. HCM",
        "Xét tuyển theo điểm thi THPT": "Tổ hợp: Đang cập nhật Điểm trúng tuyển 2024 (thang 40):28,00",
        "Khai giảng": "Tháng 9, năm 2025",
        "Học phí": "Từ 83 đến 84 triệu đồng/năm"
      },
      "name": "Kinh doanh quốc tế"
    },
    {
      "tab": "Liên kết quốc tế - K7340120L",
      "major_code": "K7340120",
      "description": "Cử nhân (song bằng)\n4 năm (3 năm đầu học tại TDTU, 1 năm sau học tại Trường liên kết)\nXem thông tin chi tiết về chương trình đào tạo\nXem thông tin chi tiết\nKết quả quá trình học tập THPT\nKết quả bài thi ĐGNL năm 2025 của ĐHQG TP. HCM\nTổ hợp: Đang cập nhật\nĐiểm trúng tuyển 2024 (thang 40):28,00\nTháng 9, năm 2025\nGiai đoạn 1: Từ 82 đến 83 triệu đồng/năm",
      "content": {
        "Bằng cấp": "Cử nhân (song bằng)",
        "Thời gian đào tạo": "4 năm (3 năm đầu học tại TDTU, 1 năm sau học tại Trường liên kết)",
        "Chương trình đào tạo": "Xem thông tin chi tiết về chương trình đào tạo",
        "Thông tin chương trình": "Xem thông tin chi tiết",
        "Phương thức xét tuyển riêng": "Kết quả quá trình học tập THPT Kết quả bài thi ĐGNL năm 2025 của ĐHQG TP. HCM",
        "Xét tuyển theo điểm thi THPT": "Tổ hợp: Đang cập nhật Điểm trúng tuyển 2024 (thang 40):28,00",
        "Khai giảng": "Tháng 9, năm 2025",
        "Học phí": "Giai đoạn 1: Từ 82 đến 83 triệu đồng/năm"
      },
      "name": "Kinh doanh quốc tế liên kết Đại học La Trobe, Úc"
    }
  ],
  "images": [
    "https://admission.tdtu.edu.vn/sites/admission23/files/Tuyen-sinh/Dai-hoc/Nganh/KDQT/1.jpg",
    "https://admission.tdtu.edu.vn/sites/admission23/files/Tuyen-sinh/Dai-hoc/Nganh/KDQT/2.jpg",
    "https://admission.tdtu.edu.vn/sites/admission23/files/Tuyen-sinh/Dai-hoc/Nganh/KDQT/3.jpg"
  ]
}