{
  "name": "Kỹ thuật điện",
  "description": "Kỹ thuật điện là ngành học cốt lõi, ứng dụng kiến thức điện - điện tử để thiết kế, lắp đặt, vận hành và tối ưu hóa các hệ thống cung cấp điện; từ quy mô nhỏ như tòa nhà, khu dân cư đến các nhà máy công nghiệp, trạm biến áp (TBA) và lưới truyền tải điện quốc gia nhằm đảm bảo nguồn điện luôn ổn định và bền vững, phục vụ cho nhu cầu đời sống sinh hoạt của người dân ở mỗi quốc gia. Với xu thế công nghiệp hóa gắn liền chuyển đổi số, ngành Kỹ thuật điện ngày càng ứng dụng các công nghệ tiên tiến như Trí tuệ nhân tạo (AI), Internet vạn vật (IoT) và các thuật toán tối ưu để quản lý, vận hành hệ thống điện hiệu quả, đáp ứng linh hoạt nhu cầu công nghiệp và đời sống.",
  "reasons": [
    "Cơ hội trải nghiệm các học phần nghề nghiệp, tập sự nghề nghiệp tại các doanh nghiệp, định chế tài chính trong và ngoài nước",
    "Cơ hội tham gia chương trình trao đổi ngắn hạn, dài hạn với các đại học uy tín trên thế giới",
    "100% sinh viên ra trường có việc làm trong vòng 12 tháng kể từ khi tốt nghiệp"
  ],
  "programs": [
    {
      "tab": "Tiêu chuẩn",
      "major_code": "7520201",
      "description": "Ngoài các kiến thức cơ sở về xác suất thống kê, lý thuyết mạch điện, mạch điện tử và hệ thống tự động hóa trong công nghiệp, sinh viên còn được trang bị kiến thức và kỹ năng chuyên ngành tích hợp ở cả 3 lĩnh vực hệ thống điện, cung cấp điện và năng lượng tái tạo như các nguồn năng lượng tái tạo, máy điện trong thiết bị tự động và điều khiển, điều khiển logic và PLC, nhà máy điện và trạm biến áp, hệ thống BMS cho tòa nhà, kỹ thuật điện cao áp, chiếu sáng công nghiệp và dân dụng,… với các phòng thí nghiệm đa dạng, phong phú, hiện đại và liên tục được cập nhật.\nChương trình đào tạo của ngành đạt chuẩn kiểm định ASIIN với hệ thống tín chỉ quy đổi tương đương khung trình độ của Châu Âu. Với sự phát triển mạnh mẽ của năng lượng tái tạo và năng lượng xanh (điện gió, điện mặt trời), sinh viên tốt nghiệp có nhiều cơ hội tham gia các dự án tiên tiến, đáp ứng nhu cầu cấp thiết của thị trường lao động trong và ngoài nước. Ứng dụng các phần mềm chuyên dụng như AutoCAD, BIM, Revit, Ecodial, Etap, Power World,... trong thiết kế, tính toán, mô phỏng và mô hình hóa 3D công trình thực tế ảo.\nSinh viên được hướng dẫn tham gia các khóa đào tạo ngắn hạn, các chuyến tham quan thực tế và kiến tập tại doanh nghiệp để học hỏi và cập nhật xu hướng mới trong ngành đào tạo, vận dụng kiến thức và kỹ năng đã được trang bị để giải quyết các vấn đề thực tiễn tại công ty, đồng thời sớm làm quen với môi trường và văn hoá doanh nghiệp. Trong một số học phần chuyên môn và các chương trình nghiên cứu đều có sự đóng góp của nhiều chuyên gia có tay nghề cao đến từ các công ty điện lực, nhà máy công nghiệp và công ty xây dựng trong việc kết hợp với giảng viên trực tiếp giảng dạy và hướng dẫn thực hiện các dự án nghiên cứu khoa học ngay tại doanh nghiệp.\nCử nhân\nKỹ sư\nToàn thời gian: 4 năm\nToàn thời gian: 5 năm\nXem thông tin chi tiết về chương trình đào tạo\nXem thông tin chi tiết về chuẩn đầu ra\nKết quả quá trình học tập THPT\nKết quả bài thi ĐGNL năm 2025 của ĐHQG TP. HCM\nTổ hợp: Đang cập nhật\nĐiểm trúng tuyển 2024 (thang 40):30,00\nTháng 9, năm 2025\n34.850.000 đồng/năm",
      "content": {
        "Bằng cấp": "Cử nhân Kỹ sư",
        "Thời gian đào tạo": "Toàn thời gian: 4 năm Toàn thời gian: 5 năm",
        "Chương trình đào tạo": "Xem thông tin chi tiết về chương trình đào tạo",
        "Chuẩn đầu ra": "Xem thông tin chi tiết về chuẩn đầu ra",
        "Phương thức xét tuyển riêng": "Kết quả quá trình học tập THPT Kết quả bài thi ĐGNL năm 2025 của ĐHQG TP. HCM",
        "Xét tuyển theo điểm thi THPT": "Tổ hợp: Đang cập nhật Điểm trúng tuyển 2024 (thang 40):30,00",
        "Khai giảng": "Tháng 9, năm 2025",
        "Học phí": "34.850.000 đồng/năm"
      },
      "name": "Kỹ thuật điện"
    },
    {
      "tab": "Tiên tiến",
      "major_code": "F7520201",
      "description": "Ngành Kỹ thuật điện có khả năng: thiết kế, thi công, giám sát, vận hành và bảo dưỡng các hệ thống điện quốc gia, các hệ thống điện vừa và nhỏ; thiết kế và lắp đặt các công trình điện dân dụng và công nghiệp theo tiêu chuẩn quốc tế; nghiên cứu ứng dụng, thiết kế, vận hành các nguồn năng lượng tái tạo (VD: năng lượng mặt trời, gió, sóng biển); ứng dụng IoT cho các dự án nông nghiệp công nghệ cao, quản lý năng lượng cho tòa nhà, lưới điện thông minh; nghiên cứu giải pháp tiết kiệm điện và sử dụng năng lượng hiệu quả.\nChương trình tiên tiến có phương pháp giáo dục hiện đại, ứng dụng công nghệ số trong giảng dạy, ngôn ngữ giảng dạy bằng tiếng Việt và tiếng Anh.\nHọc các môn chuyên ngành bằng tiếng Anh: Trên 50% các môn học chuyên ngành được giảng dạy bằng tiếng Anh bởi đội ngũ giảng viên có chuyên môn cao. Điều này không chỉ giúp sinh viên mở rộng vốn từ vựng chuyên ngành mà còn nâng cao kỹ năng ngoại ngữ trong lĩnh vực đào tạo, tạo lợi thế khi ứng tuyển vào các công ty đa quốc gia.\nCơ sở vật chất: Phòng học đầy đủ tiện nghi với trang thiết bị dạy học hiện đại nhất. Được học trong các phòng học đặc thù riêng của Khoa; được ưu tiên tiếp cận sớm với các thiết bị thí nghiệm mới, được hỗ trợ một số linh kiện chuyên dụng trong quá trình làm đồ án tốt nghiệp.\nSinh viên có cơ hội tham gia các khóa đào tạo, trao đổi ngắn hạn hoặc thực hiện đồ án tốt nghiệp ở các trường đại học hàng đầu về kỹ thuật như Đài Loan, Cộng Hòa Séc,… Sinh viên sau khi tốt nghiệp có cơ hội nhận học bổng cao học tại Trường Đại học Tôn Đức Thắng, hoặc được ưu tiên giới thiệu xin học bổng toàn phần ở các trường đại học trên thế giới có liên kết với Trường Đại học Tôn Đức Thắng.\nCử nhân\nKỹ sư\nToàn thời gian: 4 năm\nToàn thời gian: 5 năm\nXem thông tin chi tiết về chương trình đào tạo\nXem thông tin chi tiết về chuẩn đầu ra\nKết quả quá trình học tập THPT\nKết quả bài thi ĐGNL năm 2025 của ĐHQG TP. HCM\nTổ hợp: Đang cập nhật\nĐiểm trúng tuyển 2024 (thang 40):23,00\nTháng 9, năm 2025\nTừ 55 đến 57 triệu đồng/năm",
      "content": {
        "Bằng cấp": "Cử nhân Kỹ sư",
        "Thời gian đào tạo": "Toàn thời gian: 4 năm Toàn thời gian: 5 năm",
        "Chương trình đào tạo": "Xem thông tin chi tiết về chương trình đào tạo",
        "Chuẩn đầu ra": "Xem thông tin chi tiết về chuẩn đầu ra",
        "Phương thức xét tuyển riêng": "Kết quả quá trình học tập THPT Kết quả bài thi ĐGNL năm 2025 của ĐHQG TP. HCM",
        "Xét tuyển theo điểm thi THPT": "Tổ hợp: Đang cập nhật Điểm trúng tuyển 2024 (thang 40):23,00",
        "Khai giảng": "Tháng 9, năm 2025",
        "Học phí": "Từ 55 đến 57 triệu đồng/năm"
      },
      "name": "Kỹ thuật điện"
    },
    {
      "tab": "Liên kết quốc tế",
      "major_code": "K7520201",
      "description": "Cử nhân (song bằng)\n4 năm (2,5 năm đầu học tại TDTU, 1,5 năm sau học tại Trường liên kết)\nXem thông tin chi tiết về chương trình đào tạo\nXem thông tin chi tiết\nKết quả quá trình học tập THPT\nKết quả bài thi ĐGNL năm 2025 của ĐHQG TP. HCM\nTổ hợp: Đang cập nhật\nĐiểm trúng tuyển 2024 (thang 40):24,00\nTháng 9, năm 2025\nGiai đoạn 1: Từ 78 đến 79 triệu đồng/năm",
      "content": {
        "Bằng cấp": "Cử nhân (song bằng)",
        "Thời gian đào tạo": "4 năm (2,5 năm đầu học tại TDTU, 1,5 năm sau học tại Trường liên kết)",
        "Chương trình đào tạo": "Xem thông tin chi tiết về chương trình đào tạo",
        "Thông tin chương trình": "Xem thông tin chi tiết",
        "Phương thức xét tuyển riêng": "Kết quả quá trình học tập THPT Kết quả bài thi ĐGNL năm 2025 của ĐHQG TP. HCM",
        "Xét tuyển theo điểm thi THPT": "Tổ hợp: Đang cập nhật Điểm trúng tuyển 2024 (thang 40):24,00",
        "Khai giảng": "Tháng 9, năm 2025",
        "Học phí": "Giai đoạn 1: Từ 78 đến 79 triệu đồng/năm"
      },
      "name": "Kỹ thuật điện - điện tử liên kết Đại học khoa học ứng dụng Saxion, Hà Lan"
    }
  ],
  "images": [
    "https://admission.tdtu.edu.vn",
    "https://admission.tdtu.edu.vn/sites/admission23/files/Tuyen-sinh/Dai-hoc/Nganh/KTD/1.jpg",
    "https://admission.tdtu.edu.vn/sites/admission23/files/Tuyen-sinh/Dai-hoc/Nganh/KTD/2.jpg",
    "https://admission.tdtu.edu.vn/sites/admission23/files/Tuyen-sinh/Dai-hoc/Nganh/KTD/3.jpg"
  ]
}