{
  "name": "Kỹ thuật xây dựng",
  "description": "Xây dựng là ngành truyền thống có từ lâu đời, luôn quan trọng và cần thiết ở mọi thời đại, có ảnh hưởng đến sự phát triển kinh tế xã hội của mỗi quốc gia, góp phần nâng cao năng lực sản xuất và thúc đẩy sự phát triển của các ngành kinh tế khác. Do vậy, nhu cầu về nguồn nhân lực chất lượng cao trong ngành luôn ở mức cao, được quan tâm và mở ra nhiều cơ hội việc làm cho sinh viên lựa chọn theo học ngành Kỹ thuật xây dựng.\n\nKỹ sư tốt nghiệp ngành Kỹ thuật xây dựng có thể tự tin ứng tuyển vào các vị trí như kỹ sư thiết kế, giám sát và quản lý thi công các công trình xây dựng trong và ngoài nước; làm việc tại các cơ quan quản lý nhà nước trong lĩnh vực xây dựng hay các doanh nghiệp có ngành nghề liên quan như bất động sản, ngân hàng, nhà máy xí nghiệp sản xuất công nghiệp…; tự thành lập các công ty tư vấn thiết kế, thi công công trình; giảng viên giảng dạy các ngành học liên quan đến lĩnh vực xây dựng hoặc tiếp tục học tập lên các bậc học cao hơn.",
  "reasons": [
    "Đội ngũ giảng viên giàu kinh nghiệm",
    "Học phí phù hợp",
    "Liên tục cập nhật xu hướng"
  ],
  "programs": [
    {
      "tab": "Tiêu chuẩn",
      "major_code": "7580201",
      "description": "Sinh viên được đào tạo và tiếp cận với tất cả các kiến thức liên quan đến tư vấn, tính toán thiết kế, tổ chức thi công, quản lý, giám sát và nghiệm thu các công trình xây dựng nhằm phục vụ đời sống và nhu cầu của con người. Thông qua các kiến thức cơ bản và kỹ năng chuyên môn, sinh viên còn được trang bị thêm kiến thức về các phần mềm trong thiết kế xây dựng, phần mềm tính toán ứng dụng; kết cấu bê tông, kết cấu thép; phương pháp nghiên cứu trắc địa, thuỷ lực; kiểm tra chất lượng vật liệu và chất lượng công trình; xử lý nền móng và gia cố công trình,…\nSinh viên được hướng dẫn tham gia trải nghiệm và kiến tập tại các công ty xây dựng trong và ngoài nước thông qua mạng lưới đối tác thân hữu của Nhà trường ngay từ những năm đầu tiên học tập.\nÁp dụng chương trình đào tạo tiên tiến đạt chuẩn châu Âu, được kiểm định bỡi ASIIN. Đội ngũ giảng viên giỏi về chuyên môn, dày dạn kinh nghiệm giảng dạy, tốt nghiệp sau đại học từ các trường đại học tiên tiến nước ngoài. Sinh viên ngành Kỹ thuật xây dựng của Trường Đại học Tôn Đức Thắng được trang bị kiến thức cơ bản và kiến thức chuyên môn vững vàng để có thể thực hiện công việc tư vấn, giám sát và quản lý dự án trên các công trường xây dựng nhà ở, nhà xưởng và các công trình công cộng một cách chuyên nghiệp đáp ứng nhu cầu đa dạng của sự nghiệp phát triển kinh tế - xã hội, theo kịp sự tiến bộ khoa học kỹ thuật.\nCử nhân\nKỹ sư\nToàn thời gian: 4 năm\nToàn thời gian: 5 năm\nXem thông tin chi tiết về chương trình đào tạo\nXem thông tin chi tiết về chuẩn đầu ra\nKết quả quá trình học tập THPT\nKết quả bài thi ĐGNL năm 2025 của ĐHQG TP. HCM\nTổ hợp: Đang cập nhật\nĐiểm trúng tuyển 2024 (thang 40):24,00\nTháng 9, năm 2025\n34.850.000 đồng/năm",
      "content": {
        "Bằng cấp": "Cử nhân Kỹ sư",
        "Thời gian đào tạo": "Toàn thời gian: 4 năm Toàn thời gian: 5 năm",
        "Chương trình đào tạo": "Xem thông tin chi tiết về chương trình đào tạo",
        "Chuẩn đầu ra": "Xem thông tin chi tiết về chuẩn đầu ra",
        "Phương thức xét tuyển riêng": "Kết quả quá trình học tập THPT Kết quả bài thi ĐGNL năm 2025 của ĐHQG TP. HCM",
        "Xét tuyển theo điểm thi THPT": "Tổ hợp: Đang cập nhật Điểm trúng tuyển 2024 (thang 40):24,00",
        "Khai giảng": "Tháng 9, năm 2025",
        "Học phí": "34.850.000 đồng/năm"
      },
      "name": "Kỹ thuật xây dựng"
    },
    {
      "tab": "Tiên tiến",
      "major_code": "F7580201",
      "description": "Chương trình tiên tiến ngành Kỹ thuật xây dựng tuyển sinh với các điểm khác biệt so với chương trình tiêu chuẩn như sau:\n- Chương trình đào tạo hiện đại giúp sinh viên tốt nghiệp có thể đáp ứng các yêu cầu công việc tại Việt Nam, cũng như tại các nước tiên tiến; hoặc học tập các bậc học cao hơn ở nước ngoài;\n- Kỹ năng thực hành chuyên môn được chú trọng, sinh viên sau tốt nghiệp có đủ kinh nghiệm thực tế để bắt đầu công việc một cách tự tin;\n- Phương pháp đào tạo theo chuẩn quốc tế, sĩ số lớp học dưới 35 sinh viên;\n- Học tập lý thuyết tại trường kết hợp với thực hành thực tập tại doanh nghiệp ở các môn học chuyên ngành, giúp sinh viên tốt nghiệp có đủ kiến thức và kỹ năng để làm việc một cách chuyên nghiệp;\n- Rèn luyện tác phong chuyên nghiệp, khả năng làm việc nhóm, tư duy phản biện, giúp đáp ứng yêu cầu tuyển dụng của các nhà tuyển dụng khó tính nhất;\n- Được cam kết đảm bảo việc làm đúng chuyên môn sau tốt nghiệp;\n- Sinh viên được hỗ trợ và giới thiệu thực tập trong hoặc ngoài nước tùy theo nguyện vọng;\n- Đội ngũ giảng viên được tuyển chọn là những giảng viên uy tín, tốt nghiệp từ các nước tiên tiến hoặc các chuyên gia nổi tiếng đến từ các doanh nghiệp;\n- Được học tập bổ sung để nhận các chứng chỉ, chứng nhận về giám sát công trình, phân tích và tính toán kết cấu công trình dùng phần mềm Etabs, thể hiện bản vẽ xây dựng dùng phần mềm chuyên dụng Autocad, Autodesk Revit, Chứng chỉ an toàn lao động …;\n- Được giảng dạy bằng tiếng anh đối với các môn học chuyên ngành, cũng như được làm đồ án tốt nghiệp bằng tiếng anh, giúp sinh viên có đủ khả năng ngoại ngữ để làm việc trong môi trường quốc tế.\nCử nhân\nKỹ sư\nToàn thời gian: 4 năm\nToàn thời gian: 5 năm\nXem thông tin chi tiết về chương trình đào tạo\nXem thông tin chi tiết về chuẩn đầu ra\nKết quả quá trình học tập THPT\nKết quả bài thi ĐGNL năm 2025 của ĐHQG TP. HCM\nTổ hợp: Đang cập nhật\nĐiểm trúng tuyển 2024 (thang 40):22,00\nTháng 9, năm 2025\nTừ 55 đến 57 triệu đồng/năm",
      "content": {
        "Bằng cấp": "Cử nhân Kỹ sư",
        "Thời gian đào tạo": "Toàn thời gian: 4 năm Toàn thời gian: 5 năm",
        "Chương trình đào tạo": "Xem thông tin chi tiết về chương trình đào tạo",
        "Chuẩn đầu ra": "Xem thông tin chi tiết về chuẩn đầu ra",
        "Phương thức xét tuyển riêng": "Kết quả quá trình học tập THPT Kết quả bài thi ĐGNL năm 2025 của ĐHQG TP. HCM",
        "Xét tuyển theo điểm thi THPT": "Tổ hợp: Đang cập nhật Điểm trúng tuyển 2024 (thang 40):22,00",
        "Khai giảng": "Tháng 9, năm 2025",
        "Học phí": "Từ 55 đến 57 triệu đồng/năm"
      },
      "name": "Kỹ thuật xây dựng"
    },
    {
      "tab": "Đại học bằng tiếng Anh",
      "major_code": "FA7580201",
      "description": "Ngoài các chương trình tiêu chuẩn, tiên tiến, khoa còn tuyển sinh chương trình đại học bằng tiếng Anh cho ngành Kỹ thuật xây dựng để góp phần đào tạo kỹ sư xây dựng đáp ứng nhu cầu nhân lực chất lượng cao cho khu vực Đông Nam Á và quốc tế. Sinh viên được hướng dẫn tham gia trải nghiệm và kiến tập tại các công ty xây dựng trong và ngoài nước thông qua mạng lưới đối tác thân hữu của Nhà trường ngay từ những năm đầu tiên học tập.\nCử nhân\nKỹ sư\nToàn thời gian: 4 năm\nToàn thời gian: 5 năm\nXem thông tin chi tiết về chương trình đào tạo\nXem thông tin chi tiết về chuẩn đầu ra\nKết quả quá trình học tập THPT\nKết quả bài thi ĐGNL năm 2025 của ĐHQG TP. HCM\nTổ hợp: Đang cập nhật\nĐiểm trúng tuyển 2024 (thang 40):24,00\nTháng 9, năm 2025\nTừ 81 đến 83 triệu đồng/năm",
      "content": {
        "Bằng cấp": "Cử nhân Kỹ sư",
        "Thời gian đào tạo": "Toàn thời gian: 4 năm Toàn thời gian: 5 năm",
        "Chương trình đào tạo": "Xem thông tin chi tiết về chương trình đào tạo",
        "Chuẩn đầu ra": "Xem thông tin chi tiết về chuẩn đầu ra",
        "Phương thức xét tuyển riêng": "Kết quả quá trình học tập THPT Kết quả bài thi ĐGNL năm 2025 của ĐHQG TP. HCM",
        "Xét tuyển theo điểm thi THPT": "Tổ hợp: Đang cập nhật Điểm trúng tuyển 2024 (thang 40):24,00",
        "Khai giảng": "Tháng 9, năm 2025",
        "Học phí": "Từ 81 đến 83 triệu đồng/năm"
      },
      "name": "Kỹ thuật xây dựng"
    },
    {
      "tab": "Liên kết quốc tế",
      "major_code": "K7580201",
      "description": "Cử nhân (song bằng)\n4 năm (2 năm đầu học tại TDTU, 2 năm sau học tại Trường liên kết)\nXem thông tin chi tiết về chương trình đào tạo\nXem thông tin chi tiết\nKết quả quá trình học tập THPT\nKết quả bài thi ĐGNL năm 2025 của ĐHQG TP. HCM\nTổ hợp: Đang cập nhật\nĐiểm trúng tuyển 2024 (thang 40):24,00\nTháng 9, năm 2025\nGiai đoạn 1: Từ 76 đến 77 triệu đồng/năm",
      "content": {
        "Bằng cấp": "Cử nhân (song bằng)",
        "Thời gian đào tạo": "4 năm (2 năm đầu học tại TDTU, 2 năm sau học tại Trường liên kết)",
        "Chương trình đào tạo": "Xem thông tin chi tiết về chương trình đào tạo",
        "Thông tin chương trình": "Xem thông tin chi tiết",
        "Phương thức xét tuyển riêng": "Kết quả quá trình học tập THPT Kết quả bài thi ĐGNL năm 2025 của ĐHQG TP. HCM",
        "Xét tuyển theo điểm thi THPT": "Tổ hợp: Đang cập nhật Điểm trúng tuyển 2024 (thang 40):24,00",
        "Khai giảng": "Tháng 9, năm 2025",
        "Học phí": "Giai đoạn 1: Từ 76 đến 77 triệu đồng/năm"
      },
      "name": "Kỹ thuật xây dựng liên kết Đại học La Trobe, Úc"
    }
  ],
  "images": [
    "https://admission.tdtu.edu.vn/sites/admission23/files/Tuyen-sinh/Dai-hoc/Nganh/Ky-thuat-xay-dung/1.jpg",
    "https://admission.tdtu.edu.vn/sites/admission23/files/Tuyen-sinh/Dai-hoc/Nganh/Ky-thuat-xay-dung/2.jpg",
    "https://admission.tdtu.edu.vn/sites/admission23/files/Tuyen-sinh/Dai-hoc/Nganh/Ky-thuat-xay-dung/3.jpg"
  ]
}