{
  "name": "Kỹ thuật điều khiển và tự động hóa",
  "description": "Kỹ thuật điều khiển và tự động hóa không chỉ là trụ cột của các ngành sản xuất hiện đại mà còn là mắt xích quan trọng trong các xu hướng công nghệ toàn cầu như trí tuệ nhân tạo (AI), Internet vạn vật (IoT), chuyển đổi số, kinh tế tuần hoàn và các giải pháp giảm phát thải carbon. Đây là ngành học đi đầu trong việc thiết kế và triển khai các hệ thống tự động thông minh, giúp tối ưu hóa hiệu suất, tiết kiệm tài nguyên, và giảm thiểu tác động đến môi trường.\nSinh viên ngành Kỹ thuật điều khiển và tự động hoá sau khi ra trường có các cơ hội làm việc ở các vị trí như kỹ sư thiết kế, vận hành và bảo trì hệ thống thông minh tại các nhà máy tự động hóa, trung tâm điều khiển năng lượng tái tạo, và dây chuyền sản xuất công nghệ cao, chuyên gia tư vấn chuyển đổi số và giải pháp công nghệ xanh, nhà phát triển công nghệ AI và IoT. Ngoài ra, sinh viên còn có thể trở thành những nhà nghiên cứu và giảng dạy chuyên sâu, đóng góp vào sự phát triển công nghệ tự động hóa trong nước và quốc tế.",
  "reasons": [
    "Chương trình đào tạo được chứng nhận đạt chuẩn quốc tế ASIIN",
    "Chất lượng đào tạo chuẩn quốc tế với mức học phí phù hợp",
    "100% sinh viên ra trường có việc làm trong vòng 12 tháng kể từ khi tốt nghiệp"
  ],
  "programs": [
    {
      "tab": "Tiêu chuẩn",
      "major_code": "7520216",
      "description": "Ngành Kỹ thuật điều khiển và tự động hóa của TDTU đạt chứng nhận kiểm định quốc tế ASIIN, có hiệu lực từ 30/9/2024 đến 30/9/2029, khẳng định chất lượng đào tạo theo các tiêu chuẩn hàng đầu thế giới. Chương trình được đối sánh với các chương trình đại học uy tín toàn cầu, đảm bảo sinh viên được tiếp cận nền giáo dục hiện đại, hội nhập quốc tế. Chương trình cung cấp nền tảng vững chắc về lý thuyết và thực hành trong các lĩnh vực như lý thuyết mạch điện - điện tử, kỹ thuật đo lường điện - điện tử, kỹ thuật mô phỏng bằng phần mềm và phân tích dữ liệu, các phương pháp điều khiển kinh điển và hiện đại, mạng truyền thông công nghiệp, công nghệ Internet kết nối vạn vật (IoT), công nghệ robot, và tự động hóa quá trình sản xuất. Ngoài ra, sinh viên được trang bị kiến thức thực tế thông qua việc thực hiện các đồ án môn học, đồ án tốt nghiệp với đề tài được giao nhằm giải quyết các vấn đề cấp bách như chuyển đổi số trong công nghiệp, ứng dụng IoT trong xe tự hành, nông nghiệp thông minh, và nhà thông minh, năng lượng tái tạo và các hệ thống tự động hóa thân thiện với môi trường.\nVới môi trường học tập hiện đại cùng với chương trình kết hợp chặt chẽ giữa lý thuyết và thực hành trên các trang thiết bị tiên tiến, phần lớn được tài trợ bởi các tập đoàn lớn như Siemens, ABB, Mitsubishi, Endress+Hauser. Sinh viên sẽ tham gia các đồ án môn học và đồ án tốt nghiệp, tiếp cận các dự án thực tế và công nghệ mới nhất. Ngoài chuyên môn, sinh viên còn được tham gia nhiều hoạt động ngoại khóa khác nhau. Được tham quan thực tế, kiến tập và thực tập tại các doanh nghiệp hàng đầu trong lĩnh vực tự động hóa. Học tập dưới sự hướng dẫn của giảng viên giàu kinh nghiệm và các chuyên gia tay nghề cao, thực hiện các dự án nghiên cứu khoa học ngay tại doanh nghiệp.\nSau khi tốt nghiệp, sinh viên sẽ được trang bị đầy đủ các kỹ năng chuyên môn để vận hành, bảo trì, sửa chữa các hệ thống tự động hóa và dây chuyền sản xuất hiện đại, thiết kế giao diện giám sát, lập trình điều khiển, và xây dựng hệ thống quản lý cơ sở dữ liệu cho nhà máy, xí nghiệp, cải tiến, nâng cấp hệ thống tự động hóa và tham gia lập kế hoạch kỹ thuật, tài chính cho các dự án, làm việc trong các lĩnh vực mới như quản lý năng lượng tái tạo, phát triển các giải pháp IoT, và chuyển đổi số.\nCử nhân\nKỹ sư\nToàn thời gian: 4 năm\nToàn thời gian: 5 năm\nXem thông tin chi tiết về chương trình đào tạo\nXem thông tin chi tiết về chuẩn đầu ra\nKết quả quá trình học tập THPT\nKết quả bài thi ĐGNL năm 2025 của ĐHQG TP. HCM\nTổ hợp: Đang cập nhật\nĐiểm trúng tuyển 2024 (thang 40):31,85\nTháng 9, năm 2025\n34.850.000 đồng/năm",
      "content": {
        "Bằng cấp": "Cử nhân Kỹ sư",
        "Thời gian đào tạo": "Toàn thời gian: 4 năm Toàn thời gian: 5 năm",
        "Chương trình đào tạo": "Xem thông tin chi tiết về chương trình đào tạo",
        "Chuẩn đầu ra": "Xem thông tin chi tiết về chuẩn đầu ra",
        "Phương thức xét tuyển riêng": "Kết quả quá trình học tập THPT Kết quả bài thi ĐGNL năm 2025 của ĐHQG TP. HCM",
        "Xét tuyển theo điểm thi THPT": "Tổ hợp: Đang cập nhật Điểm trúng tuyển 2024 (thang 40):31,85",
        "Khai giảng": "Tháng 9, năm 2025",
        "Học phí": "34.850.000 đồng/năm"
      },
      "name": "Kỹ thuật điều khiển và tự động hóa"
    },
    {
      "tab": "Tiên tiến",
      "major_code": "F7520216",
      "description": "Chương trình tiên tiến ngành Kỹ thuật điều khiển và tự động hóa đạt chứng nhận kiểm định quốc tế ASIIN (có hiệu lực từ 30/9/2024 đến 30/9/2029), khẳng định chất lượng đào tạo đạt tiêu chuẩn quốc tế, sánh ngang với các chương trình uy tín toàn cầu.\nVới hơn 50% các môn chuyên ngành được giảng dạy bằng tiếng Anh, giúp sinh viên nâng cao năng lực ngoại ngữ, sẵn sàng làm việc trong môi trường quốc tế. Sinh viên có cơ hội thực hiện đồ án tốt nghiệp theo các đề tài do doanh nghiệp đặt hàng, trực tiếp giải quyết các vấn đề thực tiễn và áp dụng công nghệ hiện đại. Được tham gia các khóa học trao đổi ngắn hạn và thực hiện đồ án tốt nghiệp tại các trường đại học hàng đầu thế giới như Anh, Hàn Quốc, Cộng hòa Czech…, mở rộng cơ hội học tập, giao lưu văn hóa và cập nhật những xu hướng kỹ thuật mới nhất.\nChương trình kết hợp chặt chẽ giữa lý thuyết và thực hành, với sự đồng hành của các giảng viên giàu kinh nghiệm và chuyên gia hàng đầu từ các doanh nghiệp lớn trong lĩnh vực tự động hóa. Sinh viên được tham gia vào các chuyến tham quan thực tế, kiến tập và thực tập tại doanh nghiệp, làm việc với các chuyên gia đến từ các tập đoàn quốc tế, sớm tiếp cận môi trường làm việc chuyên nghiệp và văn hóa doanh nghiệp giúp định hướng nghề nghiệp và mở rộng mạng lưới quan hệ. Tham gia vào các dự án nghiên cứu khoa học và đồ án môn học liên quan đến các xu hướng công nghệ như chuyển đổi số, IoT, năng lượng tái tạo, và các giải pháp tự động hóa thông minh.\nVới nội dung đào tạo hiện đại, theo sát xu hướng công nghệ, sinh viên được trang bị kiến thức và kỹ năng tiên tiến, đề tài của các đồ án môn học và đồ án tốt nghiệp bám trong các lĩnh vực như: IoT và trí tuệ nhân tạo (AI) trong điều khiển và giám sát hệ thống, chuyển đổi số và tối ưu hóa quy trình sản xuất, công nghệ robot và ứng dụng trong công nghiệp thông minh, năng lượng tái tạo và phát triển bền vững, góp phần giảm phát thải carbon và xây dựng kinh tế tuần hoàn.\nSinh viên tốt nghiệp chương trình tiên tiến có thể đảm nhận các vai trò như vận hành, bảo trì, và cải tiến hệ thống tự động hóa, dây chuyền sản xuất trong công nghiệp, thiết kế giao diện giám sát, lập trình điều khiển, và xây dựng hệ thống cơ sở dữ liệu cho nhà máy, làm việc trong các dự án chuyển đổi số, ứng dụng IoT và AI, phát triển năng lượng tái tạo,tham gia vào các chương trình nghiên cứu và học bổng sau đại học tại các trường đại học danh tiếng trên thế giới.\nCử nhân\nKỹ sư\nToàn thời gian: 4 năm\nToàn thời gian: 5 năm\nXem thông tin chi tiết về chương trình đào tạo\nXem thông tin chi tiết về chuẩn đầu ra\nKết quả quá trình học tập THPT\nKết quả bài thi ĐGNL năm 2025 của ĐHQG TP. HCM\nTổ hợp: Đang cập nhật\nĐiểm trúng tuyển 2024 (thang 40):26,70\nTháng 9, năm 2025\nTừ 55 đến 57 triệu đồng/năm",
      "content": {
        "Bằng cấp": "Cử nhân Kỹ sư",
        "Thời gian đào tạo": "Toàn thời gian: 4 năm Toàn thời gian: 5 năm",
        "Chương trình đào tạo": "Xem thông tin chi tiết về chương trình đào tạo",
        "Chuẩn đầu ra": "Xem thông tin chi tiết về chuẩn đầu ra",
        "Phương thức xét tuyển riêng": "Kết quả quá trình học tập THPT Kết quả bài thi ĐGNL năm 2025 của ĐHQG TP. HCM",
        "Xét tuyển theo điểm thi THPT": "Tổ hợp: Đang cập nhật Điểm trúng tuyển 2024 (thang 40):26,70",
        "Khai giảng": "Tháng 9, năm 2025",
        "Học phí": "Từ 55 đến 57 triệu đồng/năm"
      },
      "name": "Kỹ thuật điều khiển và tự động hóa"
    },
    {
      "tab": "Đại học bằng tiếng Anh",
      "major_code": "FA7520216",
      "description": "Chương trình đại học Tiếng Anh ngành Kỹ thuật Điều khiển và Tự động hóa được thiết kế nhằm trang bị cho sinh viên nền tảng kiến thức chuyên môn và kỹ năng ngoại ngữ vượt trội, đáp ứng yêu cầu ngày càng cao của thị trường lao động quốc tế. Chương trình đã đạt chứng nhận kiểm định ASIIN (hiệu lực từ 30/9/2024 đến 30/9/2029), khẳng định chất lượng đào tạo đạt tiêu chuẩn quốc tế.\nToàn bộ các môn chuyên ngành được giảng dạy bằng tiếng Anh, bởi đội ngũ giảng viên là các giáo sư, tiến sĩ, và chuyên gia giàu kinh nghiệm, tốt nghiệp từ các trường đại học danh tiếng trên thế giới.\nSinh viên có cơ hội tham gia các chương trình trao đổi quốc tế, thực hiện đồ án tốt nghiệp tại các trường đại học uy tín như Anh, Hàn Quốc, Cộng hòa Czech, Đài Loan, Hà Lan… để học hỏi, giao lưu văn hóa và cập nhật các xu hướng công nghệ mới nhất.\nVới môi trường học tập hiện đại và cơ hội thực tiễn, sinh viên được trải nghiệm một môi trường học tập năng động, kết hợp lý thuyết với thực tiễn thông qua các buổi workshop, hội thảo học thuật và ngày hội việc làm, với sự tham gia của các chuyên gia từ các tập đoàn công nghệ hàng đầu trong và ngoài nước như Siemens, ABB, Mitsubishi… Ngoài ra, sinh viên còn được tham gia các dự án nghiên cứu khoa học và thực tập tại doanh nghiệp, giúp sinh viên áp dụng kiến thức vào thực tế, giải quyết các vấn đề kỹ thuật liên quan đến IoT, AI, năng lượng tái tạo, chuyển đổi số, và tự động hóa thông minh. Với sự hướng dẫn chuyên môn từ các chuyên gia trong ngành, tạo điều kiện cho sinh viên phát triển toàn diện cả về kiến thức lẫn kỹ năng làm việc nhóm, quản lý dự án, và giải quyết vấn đề.\nChương trình học bám sát các xu hướng công nghệ tiên tiến trong đào tạo thông qua các đề tài của các đồ án môn học và đồ án tốt nghiệp bám theo xu hướng các lĩnh vực công nghệ mới nhất, bao gồm Trí tuệ nhân tạo (AI) và Internet vạn vật (IoT) trong giám sát và điều khiển hệ thống tự động, năng lượng tái tạo, giải pháp giảm phát thải carbon, và ứng dụng kinh tế tuần hoàn, tự động hóa thông minh trong sản xuất và vận hành dây chuyền công nghiệp.\nSau khi tốt nghiệp, sinh viên chương trình Hội nhập Quốc tế có thể đảm nhận các vị trí như: Kỹ sư thiết kế, vận hành, bảo trì và tối ưu hóa hệ thống tự động hóa tại các nhà máy, xí nghiệp trong nước và quốc tế. Chuyên gia tư vấn, quản lý dự án chuyển đổi số và ứng dụng công nghệ mới.Nhân sự tại các tập đoàn đa quốc gia hoặc các doanh nghiệp nước ngoài hoạt động tại Việt Nam hoặc ứng viên tiềm năng cho các học bổng sau đại học tại các trường danh tiếng trên toàn cầu.\nCử nhân\nKỹ sư\nToàn thời gian: 4 năm\nToàn thời gian: 5 năm\nXem thông tin chi tiết về chương trình đào tạo\nXem thông tin chi tiết về chuẩn đầu ra\nKết quả quá trình học tập THPT\nKết quả bài thi ĐGNL năm 2025 của ĐHQG TP. HCM\nTổ hợp: Đang cập nhật\nĐiểm trúng tuyển 2024 (thang 40):24,00\nTháng 9, năm 2025\nTừ 81 đến 83 triệu đồng/năm",
      "content": {
        "Bằng cấp": "Cử nhân Kỹ sư",
        "Thời gian đào tạo": "Toàn thời gian: 4 năm Toàn thời gian: 5 năm",
        "Chương trình đào tạo": "Xem thông tin chi tiết về chương trình đào tạo",
        "Chuẩn đầu ra": "Xem thông tin chi tiết về chuẩn đầu ra",
        "Phương thức xét tuyển riêng": "Kết quả quá trình học tập THPT Kết quả bài thi ĐGNL năm 2025 của ĐHQG TP. HCM",
        "Xét tuyển theo điểm thi THPT": "Tổ hợp: Đang cập nhật Điểm trúng tuyển 2024 (thang 40):24,00",
        "Khai giảng": "Tháng 9, năm 2025",
        "Học phí": "Từ 81 đến 83 triệu đồng/năm"
      },
      "name": "Kỹ thuật điều khiển và tự động hóa"
    }
  ],
  "images": [
    "https://admission.tdtu.edu.vn",
    "https://admission.tdtu.edu.vn/sites/admission23/files/Tuyen-sinh/Dai-hoc/Nganh/KTDK-TDH/1.jpg",
    "https://admission.tdtu.edu.vn/sites/admission23/files/Tuyen-sinh/Dai-hoc/Nganh/KTDK-TDH/2.JPG",
    "https://admission.tdtu.edu.vn/sites/admission23/files/Tuyen-sinh/Dai-hoc/Nganh/KTDK-TDH/3.jpg"
  ]
}