{
  "name": "Kỹ thuật điện tử - viễn thông",
  "description": "Ngành Kỹ thuật điện tử - viễn thông là ngành của sự sáng tạo và đam mê công nghệ. Bằng việc sử dụng các hệ thống thiết bị mạng viễn thông hay các thiết bị điện tử đã tạo nên hệ thống trao đổi thông tin đầy thú vị đi kèm với các thiết bị tiên tiến được cung cấp bởi các tập đoàn lớn đến từ Mỹ, Canada,...\nTại Việt Nam, lĩnh vực công nghệ thông tin và truyền thông (ICT) đang phát triển một cách mạnh mẽ và đóng vai trò quan trọng đối với sự phát triển kinh tế xã hội. Trong đó, ngành Kỹ thuật điện tử – viễn thông là một ngành năng động, với các ứng dụng liên quan trực tiếp đến nhiều lĩnh vực trong cuộc sống, đặc biệt trong thời đại cách mạng công nghiệp 4.0.\nVới chương trình đào tạo cử nhân và kỹ sư cho hai hệ đào tạo tiêu chuẩn và tiên tiến (chương trình giảng dạy các môn chuyên ngành bằng tiếng anh) giúp cho sinh viên học được các kiến thức cần thiết khi bước vào thị trường lao động đầy thử thách. Bên cạnh đó, sinh viên có nhiều cơ hội làm việc tại các cơ quan nhà nước, các trung tâm nghiên cứu, các tập đoàn, công ty viễn thông nước ngoài,...\nNgành Kỹ thuật điện tử - viễn thông đang giảng dạy, nghiên cứu các lĩnh vực theo xu hướng hiện nay: mạng di động 5G, IoT, thiết kế vi mạch hay các mạch điện tử thông minh,... luôn đem lại sự thích thú và cơ hội phát triển nghề nghiệp cho mỗi sinh viên.",
  "reasons": [
    "Học phí phù hợp",
    "Liên tục cập nhật xu hướng",
    "100% sinh viên ra trường có việc làm trong vòng 12 tháng kể từ khi tốt nghiệp"
  ],
  "programs": [
    {
      "tab": "Tiêu chuẩn",
      "major_code": "7520207",
      "description": "Chương trình được thiết kế theo tiêu chuẩn kiểm định quốc tế, được đối sánh với các chương trình đại học uy tín trên thế giới và chuẩn đầu ra tin học đạt chứng chỉ tin học Microsoft Office Specialist tối thiểu 750/1000 điểm hoặc chứng chỉ ICDL (International Certification of Digital Literacy) đạt 75% trở lên và kỹ năng ngoại ngữ đạt chứng chỉ tiếng Anh tối thiểu IELTS 5.0 hoặc chứng chỉ khác tương đương. Ngoài các kiến thức cơ bản về lý thuyết mạch điện - điện tử, kỹ thuật đo lường điện-điện tử, kỹ thuật mô phỏng bằng phần mềm, ngành học còn cung cấp cho sinh viên kiến thức về chuyên ngành như các mạng truyền thông di động thế hệ mới, công nghệ internet kết nối vạn vật, thiết kế vi mạch, mạch điện tử thông minh ứng dụng trong dân dụng và công nghiệp, …\nChương trình đào tạo chú trọng kết hợp chặt chẽ giữa lý thuyết và thực hành. Sinh viên được thực hành trên các hệ thống trang thiết bị hiện đại, đa số được tài trợ bởi các tập đoàn, doanh nghiệp lớn trong ngành như Siemens, Altera, Mitsubishi, Keysight… Ngoài ra, thông qua các đồ án môn học và đồ án tốt nghiệp, sinh viên được tiếp cận và thực hiện các đề tài đang là vấn đề cấp bách trong thực tế như mạng thông tin di động 5G, công nghệ internet kết nối vạn vật, xe tự hành, nông-lâm-ngư nghiệp-nhà thông minh, thiết kế vi mạch bán dẫn, …\nNgoài chuyên môn, sinh viên còn tham gia nhiều các hoạt động ngoại khóa khác nhau. Sinh viên được tiếp cận sớm với môi trường và văn hoá doanh nghiệp thông qua các chuyến tham quan thực tế, kiến tập và thực tập tại doanh nghiệp. Khoa còn thường xuyên tổ chức các buổi sinh hoạt học thuật, workshop, ngày hội việc làm, … với các diễn giả là những chuyên gia hàng đầu đến từ các công ty viễn thông trong nước và quốc tế … nhằm định hướng nghề nghiệp cho sinh viên, tăng thêm cơ hội việc làm trong tương lai. Thêm vào đó, trong một số học phần chuyên môn và các chương trình nghiên cứu đều có sự đóng góp của nhiều chuyên gia có tay nghề cao kết hợp với giảng viên trực tiếp giảng dạy và hướng dẫn thực hiện các dự án nghiên cứu khoa học ngay tại doanh nghiệp, mở ra nhiều cơ hội phát triển toàn diện cả về kiến thức lẫn kỹ năng chuyên ngành cho sinh viên.\nSinh viên sau tốt nghiệp ngành Kỹ thuật điện tử - viễn thông có khả năng khảo sát, lựa chọn, vận hành, bảo trì, sửa chữa các hệ thống truyền dẫn dữ liệu trong dân dụng hay công nghiệp; thiết kế giao diện giám sát, quản lí và lập trình điều khiển hệ thống; xây dựng hệ thống mạng thu thập và quản lý cơ sở dữ liệu cho các cơ quan, doanh nghiệp; tham gia cải tiến nâng cấp hệ thống, đề xuất dự toán kinh phí, kỹ thuật, thiết bị và nhân lực, thời gian thực hiện cho các dự án liên quan đến điện tử viễn thông; có khả năng tự học, tự nghiên cứu để cập nhật kỹ thuật, công nghệ mới và học lên trình độ cao hơn.\nCử nhân\nKỹ sư\nToàn thời gian: 4 năm\nToàn thời gian: 5 năm\nXem thông tin chi tiết về chương trình đào tạo\nXem thông tin chi tiết về chuẩn đầu ra\nKết quả quá trình học tập THPT\nKết quả bài thi ĐGNL năm 2025 của ĐHQG TP. HCM\nTổ hợp: Đang cập nhật\nĐiểm trúng tuyển 2024 (thang 40):31,20\nTháng 9, năm 2025\n34.850.000 đồng/năm",
      "content": {
        "Bằng cấp": "Cử nhân Kỹ sư",
        "Thời gian đào tạo": "Toàn thời gian: 4 năm Toàn thời gian: 5 năm",
        "Chương trình đào tạo": "Xem thông tin chi tiết về chương trình đào tạo",
        "Chuẩn đầu ra": "Xem thông tin chi tiết về chuẩn đầu ra",
        "Phương thức xét tuyển riêng": "Kết quả quá trình học tập THPT Kết quả bài thi ĐGNL năm 2025 của ĐHQG TP. HCM",
        "Xét tuyển theo điểm thi THPT": "Tổ hợp: Đang cập nhật Điểm trúng tuyển 2024 (thang 40):31,20",
        "Khai giảng": "Tháng 9, năm 2025",
        "Học phí": "34.850.000 đồng/năm"
      },
      "name": "Kỹ thuật điện tử - viễn thông"
    },
    {
      "tab": "Tiên tiến",
      "major_code": "F7520207",
      "description": "Chương trình được thiết kế theo tiêu chuẩn kiểm định quốc tế, được đối sánh với các chương trình đại học uy tín trên thế giới và chuẩn đầu ra tin học đạt chứng chỉ tin học Microsoft Office Specialist tối thiểu 750/1000 điểm hoặc chứng chỉ ICDL (International Certification of Digital Literacy) đạt 75% trở lên và kỹ năng ngoại ngữ đạt chứng chỉ tiếng Anh tối thiểu IELTS 5.5 hoặc chứng chỉ khác tương đương. Điểm đặc biệt của chương trình này là hơn 50% các môn chuyên ngành được giảng dạy bằng Tiếng Anh.\nĐối với chương trình đại học tiên tiến, sinh viên có cơ hội thực hiện đồ án tốt nghiệp theo các đề tài do doanh nghiệp đặt hàng; được tiếp cận sớm với môi trường và văn hoá doanh nghiệp thông qua các chuyến tham quan thực tế, kiến tập và thực tập.\nKhoa còn thường xuyên tổ chức các buổi sinh hoạt học thuật, workshop, ngày hội việc làm, … với các diễn giả là những chuyên gia hàng đầu đến từ các công ty tự động hoá trong nước và quốc tế … nhằm định hướng nghề nghiệp cho sinh viên, tăng thêm cơ hội việc làm trong tương lai. Thêm vào đó, trong một số học phần chuyên môn và các chương trình nghiên cứu đều có sự đóng góp của nhiều chuyên gia có tay nghề cao kết hợp với giảng viên trực tiếp giảng dạy và hướng dẫn thực hiện các dự án nghiên cứu khoa học hay khởi nghiệp ngay tại doanh nghiệp, mở ra nhiều cơ hội phát triển toàn diện cả về kiến thức lẫn kỹ năng chuyên ngành cho sinh viên.\nNhà trường còn tạo cơ hội để các sinh viên có năng lực học tập tốt được tham gia các khóa học trao đổi ngắn hạn cũng như thực hiện đồ án tốt nghiệp tại các trường đại học lớn trên thế giới như Anh, Hàn Quốc, Cộng hoà Czech, …  để học tập và giao lưu văn hoá, cập nhật thêm các xu hướng và kỹ thuật mới thuộc lĩnh vực chuyên môn của ngành học.\nVới năng lực ngoại ngữ và cơ hội tiếp cận với các trường đại học nước ngoài, sinh viên tốt nghiệp ngành Kỹ thuật điện tử viễn thông chương trình đại học tiên tiến có nhiều cơ hội xin được các học bổng bán phần hoặc toàn phần để tiếp tục học tập nâng cao trình độ sau đại học.\nCử nhân\nKỹ sư\nToàn thời gian: 4 năm\nToàn thời gian: 5 năm\nXem thông tin chi tiết về chương trình đào tạo\nXem thông tin chi tiết về chuẩn đầu ra\nKết quả quá trình học tập THPT\nKết quả bài thi ĐGNL năm 2025 của ĐHQG TP. HCM\nTổ hợp: Đang cập nhật\nĐiểm trúng tuyển 2024 (thang 40):26,00\nTháng 9, năm 2025\nTừ 55 đến 57 triệu đồng/năm",
      "content": {
        "Bằng cấp": "Cử nhân Kỹ sư",
        "Thời gian đào tạo": "Toàn thời gian: 4 năm Toàn thời gian: 5 năm",
        "Chương trình đào tạo": "Xem thông tin chi tiết về chương trình đào tạo",
        "Chuẩn đầu ra": "Xem thông tin chi tiết về chuẩn đầu ra",
        "Phương thức xét tuyển riêng": "Kết quả quá trình học tập THPT Kết quả bài thi ĐGNL năm 2025 của ĐHQG TP. HCM",
        "Xét tuyển theo điểm thi THPT": "Tổ hợp: Đang cập nhật Điểm trúng tuyển 2024 (thang 40):26,00",
        "Khai giảng": "Tháng 9, năm 2025",
        "Học phí": "Từ 55 đến 57 triệu đồng/năm"
      },
      "name": "Kỹ thuật điện tử - viễn thông"
    }
  ],
  "images": [
    "https://admission.tdtu.edu.vn",
    "https://admission.tdtu.edu.vn/sites/admission23/files/Tuyen-sinh/Dai-hoc/Nganh/DT-VT/1.jpg",
    "https://admission.tdtu.edu.vn/sites/admission23/files/Tuyen-sinh/Dai-hoc/Nganh/DT-VT/2.jpg",
    "https://admission.tdtu.edu.vn/sites/admission23/files/Tuyen-sinh/Dai-hoc/Nganh/DT-VT/3.jpg"
  ]
}