{
  "name": "Kỹ thuật phần mềm",
  "description": "Kỹ thuật phần mềm là ngành ứng dụng kiến thức về lập trình, thiết kế phần mềm, quy trình vận hành và phát triển phần mềm, phân tích yêu cầu hệ thống, trí tuệ nhân tạo… để tạo ra sản phẩm phần mềm đạt chất lượng cao, đáp ứng xu hướng phát triển mạnh mẽ của công nghệ và nhu cầu nghiệp vụ cụ thể trong nền sản xuất của xã hội.\n\nCử nhân Kỹ thuật phần mềm có thể tự tin khởi nghiệp hoặc ứng tuyển vào các doanh nghiệp trong và ngoài nước, các cơ quan, ban ngành ở những vị trí: Chuyên viên phân tích yêu cầu (BA), Kiến trúc sư phần mềm (SA), Lập trình viên (Developer), Chuyên viên thử nghiệm phần mềm (Tester), chuyên viên cầu nối (BrSE), chuyên viên nghiên cứu và phát triển ứng dụng (R&D), giảng viên giảng dạy các môn học về ngành kỹ thuật phần mềm hoặc có thể tiếp tục nghiên cứu và học lên cao học.",
  "reasons": [
    "Liên tục cập nhật xu hướng",
    "Số tiết học thực tế chiếm gần 50% chương trình đào tạo",
    "100% sinh viên ra trường có việc làm trong vòng 12 tháng kể từ khi tốt nghiệp"
  ],
  "programs": [
    {
      "tab": "Tiêu chuẩn",
      "major_code": "7480103",
      "description": "Sinh viên sẽ ngành Kỹ thuật phần mềm được đào tạo từ những kiến thức cơ bản đến những xu hướng hiện đại như: phát triển ứng dụng trên nền tảng số và thiết bị thông minh; thiết kế giao diện người dùng trực quan, thân thiện; phân tích hệ thống; đảm bảo an toàn thông tin; và quản lý dự án công nghệ thông tin một cách hiệu quả.\nChương trình chú trọng cân bằng giữa lý thuyết và thực hành, với các buổi học tại phòng lab hiện đại, liên tục cập nhật công nghệ mới nhất. Sinh viên không chỉ nắm vững kiến thức mà còn có cơ hội áp dụng chúng vào thực tế thông qua các dự án thực hành. Các học phần được thiết kế theo lộ trình tăng dần mức độ, giúp sinh viên từng bước làm chủ quy trình phát triển phần mềm từ thu thập yêu cầu, phân tích, thiết kế, lập trình, kiểm thử, cho đến vận hành và bảo trì hệ thống.\nSau khi tốt nghiệp, sinh viên ngành Kỹ thuật Phần mềm sẽ sở hữu những kỹ năng toàn diện như: phân tích, thiết kế, lập trình và kiểm thử phần mềm; quản lý và triển khai dự án công nghệ thông tin; sử dụng thành thạo các công cụ phần mềm để phân tích dữ liệu doanh nghiệp; và tư vấn giải pháp xây dựng hệ thống phần mềm hiện đại. Chương trình không chỉ trang bị kiến thức mà còn mở ra cơ hội nghề nghiệp rộng lớn, giúp sinh viên tự tin bước vào thị trường lao động đầy tiềm năng.\nCử nhân\nToàn thời gian: 4 năm\nXem thông tin chi tiết về chương trình đào tạo\nXem thông tin chi tiết về chuẩn đầu ra\nKết quả quá trình học tập THPT\nKết quả bài thi ĐGNL năm 2025 của ĐHQG TP. HCM\nTổ hợp: Đang cập nhật\nĐiểm trúng tuyển 2024 (thang 40):33,30\nTháng 9, năm 2025\n34.850.000 đồng/năm",
      "content": {
        "Bằng cấp": "Cử nhân",
        "Thời gian đào tạo": "Toàn thời gian: 4 năm",
        "Chương trình đào tạo": "Xem thông tin chi tiết về chương trình đào tạo",
        "Chuẩn đầu ra": "Xem thông tin chi tiết về chuẩn đầu ra",
        "Phương thức xét tuyển riêng": "Kết quả quá trình học tập THPT Kết quả bài thi ĐGNL năm 2025 của ĐHQG TP. HCM",
        "Xét tuyển theo điểm thi THPT": "Tổ hợp: Đang cập nhật Điểm trúng tuyển 2024 (thang 40):33,30",
        "Khai giảng": "Tháng 9, năm 2025",
        "Học phí": "34.850.000 đồng/năm"
      },
      "name": "Kỹ thuật phần mềm"
    },
    {
      "tab": "Tiên tiến",
      "major_code": "F7480103",
      "description": "Chương trình tiên tiến ngành Kỹ thuật phần mềm cung cấp kiến thức chuyên môn và chuyên ngành và rèn luyện kỹ năng thực hành, phát triển kỹ năng mềm, và tạo cơ hội thực tập thực tế tại các doanh nghiệp. Sinh viên sẽ được trang bị kiến thức sâu rộng về công nghiệp phần mềm, bao gồm:Quy trình phát triển phần mềm chuyên nghiệp;Kỹ năng sử dụng các công cụ hỗ trợ phát triển phần mềm hiệu quả;Kiến thức toàn diện về từng giai đoạn trong dự án phần mềm, từ thu thập yêu cầu, phân tích, thiết kế, lập trình, kiểm thử, đến vận hành và bảo trì.\nChương trình tiên tiến ngành Kỹ thuật phần mềm mang những đặc điểm nổi bật, tạo điều kiện tốt nhất để sinh viên phát triển toàn diện và hội nhập quốc tế:Đội ngũ giảng viên giàu kinh nghiệm: Các môn học được đảm nhiệm bởi những giảng viên giỏi chuyên môn, giàu kinh nghiệm giảng dạy, và có năng lực nghiên cứu khoa học;Tăng cường năng lực ngoại ngữ: 50% các môn học cơ sở ngành và chuyên ngành được giảng dạy hoàn toàn bằng tiếng Anh, giúp sinh viên nâng cao khả năng ngoại ngữ và sẵn sàng làm việc trong môi trường quốc tế;Hợp tác với doanh nghiệp: Sinh viên được tham gia các khóa đào tạo chuyên môn thực tế do các doanh nghiệp tổ chức và cấp chứng chỉ, đảm bảo năng lực thực tiễn ngay từ khi còn trên ghế nhà trường;Cơ hội học tập quốc tế: Những sinh viên có đủ điều kiện tài chính và học thuật có thể đăng ký tham gia chương trình trao đổi một học kỳ hoặc thực tập tốt nghiệp tại các trường đại học ở nước ngoài, như tại Đài Loan hoặc Cộng hòa Séc.\nNhững đặc điểm này không chỉ giúp sinh viên nắm vững kiến thức chuyên môn mà còn mở rộng cơ hội giao lưu, học hỏi, và chuẩn bị hành trang để cạnh tranh trên thị trường lao động toàn cầu.\nCử nhân\nToàn thời gian: 4 năm\nXem thông tin chi tiết về chương trình đào tạo\nXem thông tin chi tiết về chuẩn đầu ra\nKết quả quá trình học tập THPT\nKết quả bài thi ĐGNL năm 2025 của ĐHQG TP. HCM\nTổ hợp: Đang cập nhật\nĐiểm trúng tuyển 2024 (thang 40):33,90\nTháng 9, năm 2025\nTừ 55 đến 57 triệu đồng/năm",
      "content": {
        "Bằng cấp": "Cử nhân",
        "Thời gian đào tạo": "Toàn thời gian: 4 năm",
        "Chương trình đào tạo": "Xem thông tin chi tiết về chương trình đào tạo",
        "Chuẩn đầu ra": "Xem thông tin chi tiết về chuẩn đầu ra",
        "Phương thức xét tuyển riêng": "Kết quả quá trình học tập THPT Kết quả bài thi ĐGNL năm 2025 của ĐHQG TP. HCM",
        "Xét tuyển theo điểm thi THPT": "Tổ hợp: Đang cập nhật Điểm trúng tuyển 2024 (thang 40):33,90",
        "Khai giảng": "Tháng 9, năm 2025",
        "Học phí": "Từ 55 đến 57 triệu đồng/năm"
      },
      "name": "Kỹ thuật phần mềm"
    },
    {
      "tab": "Đại học bằng tiếng Anh",
      "major_code": "FA7480103",
      "description": "Chương trình đào tạo đại học bằng tiếng Anh ngành Kỹ thuật phần mềm được xây dựng nhằm đào tạo ra các kỹ sư phần mềm không chỉ có kiến thức sâu rộng về các lĩnh vực chuyên môn mà còn rèn luyện khả năng nghiên cứu, tìm hiểu tài liệu, và làm việc bằng tiếng Anh một cách chuyên nghiệp và hiệu quả.\nĐặc điểm nổi bật của chương trình- Môi trường học tập hiện đại và chuyên nghiệp: Quy mô lớp học nhỏ (20-25 sinh viên/lớp), tạo điều kiện để giảng viên theo sát từng cá nhân, tăng cường tương tác và hiệu quả học tập. Cơ sở vật chất hiện đại, tiện nghi, cùng môi trường học tập năng động, thúc đẩy sự sáng tạo và phát triển các kỹ năng chuyên môn lẫn kỹ năng mềm. Sinh viên được hỗ trợ tối đa từ trợ giảng, tổ tư vấn học đường, và giảng viên cố vấn, đảm bảo định hướng học tập rõ ràng và hiệu quả.- Đội ngũ giảng viên giàu kinh nghiệm:Các môn học được giảng dạy bởi đội ngũ giảng viên trong và ngoài nước có trình độ chuyên môn cao, kinh nghiệm thực tiễn, và kỹ năng giảng dạy xuất sắc. Chất lượng đào tạo được giám sát chặt chẽ nhằm đáp ứng các tiêu chuẩn quốc tế và nhu cầu của thị trường lao động.- Đào tạo chuyên sâu bằng tiếng Anh: 100% các môn học cơ sở ngành và chuyên ngành được giảng dạy bằng tiếng Anh, giúp sinh viên nâng cao khả năng ngoại ngữ, tư duy logic, và sẵn sàng làm việc trong môi trường toàn cầu.- Kết nối doanh nghiệp và hội nhập quốc tế: Sinh viên có cơ hội tham gia các khóa đào tạo thực tế tại doanh nghiệp và nhận chứng chỉ chuyên môn, tăng cường kỹ năng thực hành và năng lực đáp ứng công việc. Chương trình mang đến cơ hội học tập và thực tập tại các trường đại học quốc tế ví dụ như Đài Loan, Cộng hòa Séc.Chương trình không chỉ tập trung cung cấp kiến thức chuyên môn sâu rộng về các lĩnh vực của Kỹ thuật phần mềm, từ phát triển ứng dụng, thiết kế hệ thống, kiểm thử, đến bảo trì phần mềm, mà còn rèn luyện kỹ năng ngoại ngữ và kỹ năng làm việc thực tế, giúp sinh viên sẵn sàng đáp ứng mọi thách thức trong môi trường làm việc hiện đại và hội nhập toàn cầu.\nCử nhân\nToàn thời gian: 4 năm\nXem thông tin chi tiết về chương trình đào tạo\nXem thông tin chi tiết về chuẩn đầu ra\nKết quả quá trình học tập THPT\nKết quả bài thi ĐGNL năm 2025 của ĐHQG TP. HCM\nTổ hợp: Đang cập nhật\nĐiểm trúng tuyển 2024 (thang 40):28,00\nTháng 9, năm 2025\nTừ 81 đến 83 triệu đồng/năm",
      "content": {
        "Bằng cấp": "Cử nhân",
        "Thời gian đào tạo": "Toàn thời gian: 4 năm",
        "Chương trình đào tạo": "Xem thông tin chi tiết về chương trình đào tạo",
        "Chuẩn đầu ra": "Xem thông tin chi tiết về chuẩn đầu ra",
        "Phương thức xét tuyển riêng": "Kết quả quá trình học tập THPT Kết quả bài thi ĐGNL năm 2025 của ĐHQG TP. HCM",
        "Xét tuyển theo điểm thi THPT": "Tổ hợp: Đang cập nhật Điểm trúng tuyển 2024 (thang 40):28,00",
        "Khai giảng": "Tháng 9, năm 2025",
        "Học phí": "Từ 81 đến 83 triệu đồng/năm"
      },
      "name": "Kỹ thuật phần mềm"
    }
  ],
  "images": [
    "https://admission.tdtu.edu.vn/sites/admission23/files/Tuyen-sinh/Dai-hoc/Nganh/KTPM/3.jpg",
    "https://admission.tdtu.edu.vn/sites/admission23/files/Tuyen-sinh/Dai-hoc/Nganh/KTPM/1.JPG",
    "https://admission.tdtu.edu.vn/sites/admission23/files/Tuyen-sinh/Dai-hoc/Nganh/KTPM/2.jpg"
  ]
}