{
  "name": "Luật",
  "description": "Chương trình đào tạo ngành Luật của Trường Đại học Tôn Đức Thắng được xây dựngtheo quy định giáo dục đại học Việt Nam vàcập nhật liên tục dựa trên khung chương trình tiêu chuẩn quốc tế nhằm mang lại giá trị cao và sự khác biệt cho sinh viên ở cả năm lĩnh vực: kiến thức, tư duy, kỹ năng, hành vi và thái độ. Chương trình đã được kiểm định bởi tổ chức FIBAA.\n\nSinh viên được trang bị kiến thức luật bao quát ở hầu hết các lĩnh vực pháp lý. Chương trình đào tạo đảm bảo người học được trang bị kiến thức chung về Triết học, Kinh tế vi mô, logic học…; khối kiến thức cơ sở ngành như Lý luận về nhà nước và pháp luật, Hiến pháp Việt Nam…; khối thức chuyên ngành như luật dân sự, luật thương mại, luật hành chính, luật hình sự, luật quốc tế, luật tố tụng… Người học còn được rèn luyện các kỹ năng pháp lý cần thiết như soạn thảo văn bản hành chính, nghiệp vụ thư ký toà án, thực hành nghề luật, soạn thảo hợp đồng, tư vấn thành lập doanh nghiệp…",
  "reasons": [
    "Chương trình đào tạo hiện đại và thực tiễn",
    "Đội ngũ giảng viên chất lượng cao",
    "Mở rộng mạng lưới hợp tác quốc tế, hợp tác doanh nghiệp"
  ],
  "programs": [
    {
      "tab": "Tiêu chuẩn",
      "major_code": "7380101",
      "description": "Chương trình đào tạo ngành Luật của Trường Đại học Tôn Đức Thắng được xây dựng dựa trên đặc thù của giáo dục Việt Nam và cập nhật liên tục dựa trên khung chương trình tiêu chuẩn quốc tế nhằm mang lại giá trị cao và sự khác biệt cho sinh viên ở cả năm lĩnh vực: kiến thức, tư duy, kỹ năng, hành vi và thái độ.\nSinh viên được trang bị kiến thức luật bao quát ở hầu hết các lĩnh vực. Không chỉ riêng kiến thức về luật tài chính, luật thương mại, luật kinh tế, luật dân sự; Nhà trường còn cung cấp kiến thức về luật hôn nhân gia đình, quy định chung về tài sản, quyền thừa kế, luật hình sự - hành chính, luật môi trường, tội phạm học, bồi thường hợp đồng, tranh chấp thương mại, khiếu nại, tố cáo, quyền con người, quyền công dân, ...\nSố tiết học thực hành được thiết kế để cân bằng với lượng kiến thức lý thuyết, giúp sinh viên được trải nghiệm thực tế. Thông qua các hình thức tổ chức các phiên tòa giả định với những tình huống xảy ra thực tế, sinh viên được tạo cơ hội để nghiên cứu, phân tích và giải quyết vấn đề như một chuyên viên luật thực thụ, góp phần nâng cao kỹ năng tư duy và phản biện bên cạnh việc tiếp thu kiến thức chuyên môn.\nVới mạng lưới doanh nghiệp thân hữu và các chuyên gia quốc tế có nhiều kinh nghiệm trong cùng lĩnh vực, sinh viên được hướng dẫn tham gia các khóa đào tạo ngắn hạn để cập nhật kiến thức luật trong nước và quốc tế; trải nghiệm văn hóa và kiến tập tại doanh nghiệp để tích lũy kinh nghiệm.\nNgoài ra, trong một số môn học chuyên sâu, các chuyên gia và luật sư có uy tín sẽ cùng với giảng viên trực tiếp giảng dạy và hướng dẫn sinh viên thực hiện các dự án nghiên cứu ngay tại doanh nghiệp, nâng cao tính ứng dụng trong chương trình học và kỹ năng thực hành nghề nghiệp cho sinh viên.\nCử nhân\nToàn thời gian: 4 năm\nXem thông tin chi tiết về chương trình đào tạo\nXem thông tin chi tiết về chuẩn đầu ra\nKết quả quá trình học tập THPT\nKết quả bài thi ĐGNL năm 2025 của ĐHQG TP. HCM\nTổ hợp: Đang cập nhật\nĐiểm trúng tuyển 2024 (thang 40):33,45\nTháng 9, năm 2025\n29.770.000 đồng/năm",
      "content": {
        "Bằng cấp": "Cử nhân",
        "Thời gian đào tạo": "Toàn thời gian: 4 năm",
        "Chương trình đào tạo": "Xem thông tin chi tiết về chương trình đào tạo",
        "Chuẩn đầu ra": "Xem thông tin chi tiết về chuẩn đầu ra",
        "Phương thức xét tuyển riêng": "Kết quả quá trình học tập THPT Kết quả bài thi ĐGNL năm 2025 của ĐHQG TP. HCM",
        "Xét tuyển theo điểm thi THPT": "Tổ hợp: Đang cập nhật Điểm trúng tuyển 2024 (thang 40):33,45",
        "Khai giảng": "Tháng 9, năm 2025",
        "Học phí": "29.770.000 đồng/năm"
      },
      "name": "Luật"
    },
    {
      "tab": "Tiên tiến: Luật (Chuyên ngành Luật kinh tế)",
      "major_code": "F7380101",
      "description": "Chương trình đào tạo đại học ngành Luật được xây dựng trên cơ sở đảm bảo chương trình khung do Bộ Giáo dục và Đào tạo ban hành, có đối sánh Chương trình đào tạo của một số trường đại học đào tạo Luật trong nước và quốc tế uy tín trên thế giới đảm bảo có đặc thù riêng của TDTU và được thiết kế một cách có hệ thống.\nToàn bộ nội dung chương trình cho đào tạo trình độ cử nhân được xây dựng được cấu trúc hợp lý, linh hoạt, thông qua các môn tự chọn, người học có thể chọn môn theo nguyện vọng, bổ sung thêm những học phần thiết yếu để trang bị kiến thức, kỹ năng theo yêu cầu cũng như để đáp ứng yêu cầu của thị trường lao động.\nMục tiêu của chương trình là trang bị cho sinh viên các kiến thức và kỹ năng cần thiết để ứng tuyển vào các vị trí như chuyên gia tư vấn; quản lý doanh nghiệp; chuyên gia đàm phán, soạn thảo và ký kết các hợp đồng thương mại; luật sư đảm nhiệm công tác pháp lý ở các doanh nghiệp thuộc các thành phần kinh tế; làm việc trong các cơ quan nhà nước, các tổ chức chính trị – xã hội; tham gia các hoạt động tố tụng liên quan đến thương mại, dân sự, lao động, hành chính; đảm đương công tác pháp chế ở các tổ chức phi chính phủ, các tổ chức quốc tế tại Việt Nam; nghiên cứu, đề ra các giải pháp mang tính pháp lý ở các doanh nghiệp cũng như ở các cơ quan quản lý Nhà nước. Ngoài ra, cử nhân Luật còn có thể học lên cao học để bổ sung, cập nhật và nâng cao kiến thức ngành luật.\nCử nhân\nToàn thời gian: 4 năm\nXem thông tin chi tiết về chương trình đào tạo\nXem thông tin chi tiết về chuẩn đầu ra\nTổ hợp: Văn*2, Anh, Sử\nKQ ĐGNL của ĐHQG TP. HCM\nƯu tiên xét tuyển theo TDTU\nTổ hợp: A00; A01; C00; D01\nTháng 9, năm 2025\nTừ 54 đến 55 triệu đồng/năm",
      "content": {
        "Bằng cấp": "Cử nhân",
        "Thời gian đào tạo": "Toàn thời gian: 4 năm",
        "Chương trình đào tạo": "Xem thông tin chi tiết về chương trình đào tạo",
        "Chuẩn đầu ra": "Xem thông tin chi tiết về chuẩn đầu ra",
        "Phương thức xét tuyển riêng": "Tổ hợp: Văn*2, Anh, Sử KQ ĐGNL của ĐHQG TP. HCM Ưu tiên xét tuyển theo TDTU",
        "Xét tuyển theo điểm thi THPT": "Tổ hợp: A00; A01; C00; D01",
        "Khai giảng": "Tháng 9, năm 2025",
        "Học phí": "Từ 54 đến 55 triệu đồng/năm"
      },
      "name": "Luật (Chuyên ngành Luật kinh tế)"
    },
    {
      "tab": "Tiên tiến: Luật (Chuyên ngành Luật thương mại quốc tế)",
      "major_code": "F7380101",
      "description": "Chương trình đào tạo đại học ngành Luật được xây dựng trên cơ sở đảm bảo chương trình khung do Bộ Giáo dục và Đào tạo ban hành, có đối sánh Chương trình đào tạo của một số trường đại học đào tạo Luật trong nước và quốc tế uy tín trên thế giới đảm bảo có đặc thù riêng của TDTU và được thiết kế một cách có hệ thống.\nToàn bộ nội dung chương trình cho đào tạo trình độ cử nhân được xây dựng được cấu trúc hợp lý, linh hoạt, thông qua các môn tự chọn, người học có thể chọn môn theo nguyện vọng, bổ sung thêm những học phần thiết yếu để trang bị kiến thức, kỹ năng theo yêu cầu cũng như để đáp ứng yêu cầu của thị trường lao động.\nMục tiêu của chương trình là trang bị cho sinh viên các kiến thức và kỹ năng cần thiết để ứng tuyển vào các vị trí như chuyên gia tư vấn; quản lý doanh nghiệp; chuyên gia đàm phán, soạn thảo và ký kết các hợp đồng thương mại; luật sư đảm nhiệm công tác pháp lý ở các doanh nghiệp thuộc các thành phần kinh tế; làm việc trong các cơ quan nhà nước, các tổ chức chính trị – xã hội; tham gia các hoạt động tố tụng liên quan đến thương mại, dân sự, lao động, hành chính; đảm đương công tác pháp chế ở các tổ chức phi chính phủ, các tổ chức quốc tế tại Việt Nam; nghiên cứu, đề ra các giải pháp mang tính pháp lý ở các doanh nghiệp cũng như ở các cơ quan quản lý Nhà nước. Ngoài ra, cử nhân Luật còn có thể học lên cao học để bổ sung, cập nhật và nâng cao kiến thức ngành luật.\nCử nhân\nToàn thời gian: 4 năm\nXem thông tin chi tiết về chương trình đào tạo\nXem thông tin chi tiết về chuẩn đầu ra\nTổ hợp: Văn*2, Anh, Sử\nKQ ĐGNL của ĐHQG TP. HCM\nƯu tiên xét tuyển theo TDTU\nTổ hợp: A00; A01; C00; D01\nTháng 9, năm 2025\nTừ 54 đến 55 triệu đồng/năm",
      "content": {
        "Bằng cấp": "Cử nhân",
        "Thời gian đào tạo": "Toàn thời gian: 4 năm",
        "Chương trình đào tạo": "Xem thông tin chi tiết về chương trình đào tạo",
        "Chuẩn đầu ra": "Xem thông tin chi tiết về chuẩn đầu ra",
        "Phương thức xét tuyển riêng": "Tổ hợp: Văn*2, Anh, Sử KQ ĐGNL của ĐHQG TP. HCM Ưu tiên xét tuyển theo TDTU",
        "Xét tuyển theo điểm thi THPT": "Tổ hợp: A00; A01; C00; D01",
        "Khai giảng": "Tháng 9, năm 2025",
        "Học phí": "Từ 54 đến 55 triệu đồng/năm"
      },
      "name": "Luật (Chuyên ngành Luật thương mại quốc tế)"
    }
  ],
  "images": [
    "https://admission.tdtu.edu.vn/sites/admission23/files/Tuyen-sinh/Dai-hoc/Nganh/Luat/1.png",
    "https://admission.tdtu.edu.vn/sites/admission23/files/Tuyen-sinh/Dai-hoc/Nganh/Luat/2.jpg",
    "https://admission.tdtu.edu.vn/sites/admission23/files/Tuyen-sinh/Dai-hoc/Nganh/Luat/3.jpg"
  ]
}