{
  "name": "Quản trị kinh doanh – Chuyên ngành Quản trị nguồn nhân lực",
  "description": "Quản trị kinh doanh – Chuyên ngành Quản trị nguồn nhân lực là một chương trình đào tạo xây dựng kiến thức nền tảng và kỹ năng quản lý nguồn nhân lực trong môi trường kinh doanh hiện đại cho người học. Sinh viên được trang bị các kiến thức về hoạch định chiến lược và kế hoạch nhân sự; tuyển dụng, đào tạo và phát triển, quan hệ lao động, đãi ngộ, đánh giá và quản lý hiệu quả công việc; duy trì và phát triển tổ chức. Thông qua việc kết hợp giữa lý thuyết và thực hành, sinh viên sẽ nắm bắt được các xu hướng mới nhất trong lĩnh vực nhân sự và có thể vận dụng linh hoạt trong công việc tương lai.\nNgoài ra, sinh viên có cơ hội tham gia vào các dự án thực tế, kiến tập tại doanh nghiệp, giúp phát triển các kỹ năng mềm quan trọng như lãnh đạo, giao tiếp, đàm phán, tư duy sáng tạo, và giải quyết vấn đề trong môi trường làm việc chuyên nghiệp. Qua đó, sinh viên hoàn thiện bộ khung năng lực của bản thân, bao gồm kiến thức – kỹ năng – thái độ, để sẵn sàng trở thành những nhà quản trị nhân sự tài năng, đáp ứng nhu cầu thị trường lao động hiện nay.",
  "reasons": [
    "Chương trình đào tạo tiên tiến, cập nhật xu hướng",
    "Đội ngũ giảng viên chuyên môn cao",
    "Hợp tác với các doanh nghiệp hàng đầu"
  ],
  "programs": [
    {
      "tab": "Tiêu chuẩn",
      "major_code": "7340101",
      "description": "Chương trình Tiêu chuẩn, sinh viên ngành Quản trị nhân lực sẽ được học các kiến thức từ tổng quan đến chuyên ngành trong lĩnh vực quản trị nhân sự, bao gồm tuyển dụng và thu hút nhân tài, hoạch định nguồn nhân lực, đào tạo và phát triển, tiền lương và phúc lợi, phát triển tổ chức,... Ngoài ra, ngành học còn tạo điều kiện cho người học được phát triển các kỹ năng nghề nghiệp như kỹ năng lập kế hoạch, quản lý hành chính, xử lý tình huống trong quan hệ lao động; chăm sóc sức khỏe nhân viên; bảo hiểm và trí tuệ cảm xúc.\nTất cả những cơ hội được học tập và thực hành đó luôn được Nhà trường tạo điều kiện thông qua các dự án nghiên cứu thực tiễn thuộc về lĩnh vực quản trị nhân lực, như phân tích thị trường lao động, các vấn đề nhân sự tại một công ty,... Từ đó, sinh viên sẽ hình thành các năng lực tư duy, kỹ năng phản biện, khả năng phân tích, đánh giá và giải quyết tình huống như một nhà quản trị thực thụ.\nBên cạnh đó, thông qua mạng lưới đối tác doanh nghiệp thân hữu trong nước và quốc tế, Nhà trường thường xuyên tổ chức các chương trình đi tham quan, kiến tập tại doanh nghiệp với chủ trương đổi mới căn bản, toàn diện giáo dục và đào tạo. Qua đó, sinh viên có cơ hội tiếp cận với đa dạng môi trường và văn hóa làm việc, đồng thời cập nhật xu hướng mới nhất trong lĩnh vực chuyên môn để tích lũy kinh nghiệm bản thân, chuẩn bị cho hành trang sự nghiệp trong tương lai.\nCử nhân\nToàn thời gian: 4 năm\nXem thông tin chi tiết về chương trình đào tạo\nXem thông tin chi tiết về chuẩn đầu ra\nKết quả quá trình học tập THPT\nKết quả bài thi ĐGNL năm 2025 của ĐHQG TP. HCM\nTổ hợp: Đang cập nhật\nĐiểm trúng tuyển 2024 (thang 40):33,00\nTháng 9, năm 2025\n29.770.000 đồng/năm",
      "content": {
        "Bằng cấp": "Cử nhân",
        "Thời gian đào tạo": "Toàn thời gian: 4 năm",
        "Chương trình đào tạo": "Xem thông tin chi tiết về chương trình đào tạo",
        "Chuẩn đầu ra": "Xem thông tin chi tiết về chuẩn đầu ra",
        "Phương thức xét tuyển riêng": "Kết quả quá trình học tập THPT Kết quả bài thi ĐGNL năm 2025 của ĐHQG TP. HCM",
        "Xét tuyển theo điểm thi THPT": "Tổ hợp: Đang cập nhật Điểm trúng tuyển 2024 (thang 40):33,00",
        "Khai giảng": "Tháng 9, năm 2025",
        "Học phí": "29.770.000 đồng/năm"
      },
      "name": "Quản trị kinh doanh – Chuyên ngành Quản trị nguồn nhân lực"
    },
    {
      "tab": "Tiên tiến",
      "major_code": "F7340101",
      "description": "Chương trình Tiên tiến (tiền thân là Chương trình đại học Chất lượng cao), Cử nhân ngành Quản trị nhân lực được trang bị đầy đủ các kiến thức về pháp luật; quản lý nguồn nhân lực từ cấp chiến lược đến cấp vận hành; các kỹ năng triển khai công việc quản lý nhân sự như săn tìm tài năng, sàng lọc ứng viên, tổ chức hành chính, và tái cơ cấu tổ chức vì mục tiêu phát triển chung.\nNgoài ra, chương trình có những đặc điểm nổi bật như sau:\nTham gia các hoạt động thực tế nghề nghiệp thông qua các cuộc thi chuyên ngành, các lớp học chuyên đề, hội thảo, tọa đàm, các buổi kiến tập tại doanh nghiệp ngay từ năm nhất;\nChương trình trao đổi một học kỳ, trao đổi hè với các trường đại học nước ngoài;\nĐào tạo ngoại ngữ và các kỹ năng mềm, bao gồm các kỹ năng làm việc độc lập, giao tiếp Tiếng Anh, tư duy đổi mới và sáng tạo, kỹ năng lãnh đạo, kỹ năng phân tích và xử lý dữ liệu trong quản lý nhân sự;\nGiáo trình giảng dạy được đối sánh với chương trình của các trường Đại học Top 100 thế giới; 50% môn học chuyên ngành được giảng dạy bằng tiếng Anh.\nCử nhân\nToàn thời gian: 4 năm\nXem thông tin chi tiết về chương trình đào tạo\nXem thông tin chi tiết về chuẩn đầu ra\nKết quả quá trình học tập THPT\nKết quả bài thi ĐGNL năm 2025 của ĐHQG TP. HCM\nTổ hợp: Đang cập nhật\nĐiểm trúng tuyển 2024 (thang 40):30,00\nTháng 9, năm 2025\nTừ 62 đến 64 triệu đồng/năm",
      "content": {
        "Bằng cấp": "Cử nhân",
        "Thời gian đào tạo": "Toàn thời gian: 4 năm",
        "Chương trình đào tạo": "Xem thông tin chi tiết về chương trình đào tạo",
        "Chuẩn đầu ra": "Xem thông tin chi tiết về chuẩn đầu ra",
        "Phương thức xét tuyển riêng": "Kết quả quá trình học tập THPT Kết quả bài thi ĐGNL năm 2025 của ĐHQG TP. HCM",
        "Xét tuyển theo điểm thi THPT": "Tổ hợp: Đang cập nhật Điểm trúng tuyển 2024 (thang 40):30,00",
        "Khai giảng": "Tháng 9, năm 2025",
        "Học phí": "Từ 62 đến 64 triệu đồng/năm"
      },
      "name": "Quản trị kinh doanh – Chuyên ngành Quản trị nguồn nhân lực"
    }
  ],
  "images": [
    "https://admission.tdtu.edu.vn/sites/admission23/files/Tuyen-sinh/Dai-hoc/Nganh/QLNL/1.JPG",
    "https://admission.tdtu.edu.vn/sites/admission23/files/Tuyen-sinh/Dai-hoc/Nganh/QLNL/2.jpg",
    "https://admission.tdtu.edu.vn/sites/admission23/files/Tuyen-sinh/Dai-hoc/Nganh/QLNL/3.jpg"
  ]
}