{
  "name": "Tài chính - Ngân hàng",
  "description": "Tài chính - Ngân hàng là ngành có lĩnh vực làm việc khá rộng, bao quát toàn bộ các hoạt động liên quan đến giao dịch tiền tệ và kinh doanh thông qua hệ thống ngân hàng như tài chính thuế, tài chính doanh nghiệp, các công cụ tài chính dùng để thanh toán trong nước và quốc tế. Là một trong những ngành mũi nhọn và đóng vai trò quan trọng trong lĩnh vực giao thương, tiền tệ, kinh doanh, ngành Tài chính - Ngân hàng luôn có sức hút với rất nhiều sinh viên bởi những cơ hội nghề nghiệp vô cùng đa dạng trong nền kinh tế toàn cầu hiện nay.\nCử nhân ngành Tài chính - Ngân hàng sau khi tốt nghiệp có thể tự tin ứng tuyển vào các hệ thống ngân hàng, định chế tài chính, doanh nghiệp hay các cơ quan ban ngành với nhiều vị trí đa dạng như chuyên viên tín dụng; chuyên viên phân tích và quản trị rủi ro; chuyên viên quan hệ khách hàng; chuyên viên thẩm định giá; chuyên viên kinh doanh tài chính quốc tế; chuyên viên phân tích và quản lý quỹ đầu tư; chuyên viên quản trị và huy động vốn; chuyên viên tài chính; kế toán; kiểm toán tại các doanh nghiệp, tổ chức kinh tế - xã hội, các cơ quan như Bộ Tài chính, cơ quan Thuế, Hải quan, Kho bạc Nhà nước, biên tập viên kinh tế - tài chính tại các cơ quan thông tấn, báo chí, công ty truyền thông; nghiên cứu viên tại các viện, trung tâm nghiên cứu trong và ngoài nước, … Ngoài ra, cử nhân ngành Tài chính - ngân hàng còn có thể tiếp tục nghiên cứu và học lên ở những bậc học cao hơn.",
  "reasons": [
    "Cơ hội trải nghiệm các học phần nghề nghiệp tại các doanh nghiệp trong và ngoài nước",
    "Cơ hội tham gia chương trình trao đổi ngắn hạn, dài hạn với các đại học uy tín trên thế giới",
    "100% sinh viên ra trường có việc làm trong vòng 12 tháng kể từ khi tốt nghiệp"
  ],
  "programs": [
    {
      "tab": "Tiêu chuẩn",
      "major_code": "7340201",
      "description": "Chương trình đào tạo ngành Tài chính - Ngân hàng sẽ trang bị cho sinh viên các khối kiến thức chung (ngoại ngữ, tin học, toán học, kiến thức xã hội), kiến thức cơ bản đến chuyên sâu trong lĩnh vực tài chính - ngân hàng như lập kế hoạch tài chính, định giá doanh nghiệp, phân tích tài chính doanh nghiệp, quản trị rủi ro tài chính, quản trị tín dụng, nghiệp vụ thanh toán, đầu tư tài chính, …\nChương trình còn chú trọng phát triển các kỹ năng chuyên dùng trong lĩnh vực tài chính - ngân hàng cho sinh viên như kỹ năng phân tích tài chính doanh nghiệp; kỹ năng lập kế hoạch tài chính; kỹ năng phát hiện và đưa ra các giải pháp quản trị rủi ro tài chính tại doanh nghiệp và tổ chức tín dụng; thẩm định giá trị tài sản, chứng khoán và các dự án đầu tư.\nThông qua chương trình đào tạo được xây dựng theo chuẩn quốc tế và bám sát nhu cầu thực tiễn của xã hội, sinh viên được học tập và ứng dụng các kiến thức chuyên ngành trong suốt 4 năm học với cơ hội trải nghiệm các học phần nghề nghiệp, tập sự nghề nghiệp tại các doanh nghiệp, định chế tài chính trong và ngoài nước. Ngoài ra, bên cạnh những giờ học lý thuyết, sinh viên còn được thực hành  tại phòng thực hành mô phỏng Ngân hàng thương mại và Công ty chứng khoán, được Nhà trường đầu tư xây dựng và bố trí hệ thống máy tính, phần mềm, trang thiết bị hiện đại, qua đó giúp sinh viên sớm thích nghi với môi trường làm việc tại các doanh nghiệp trong và ngoài nước.\nBên cạnh đó, sinh viên còn được rèn luyện kỹ năng giao tiếp, làm việc nhóm, các kỹ năng mềm khác nhằm xử lý công việc, sử dụng thành thạo ngoại ngữ và các kỹ năng công nghệ thông tin trong bối cảnh hội nhập toàn cầu. Những hoạt động nghiên cứu khoa học sinh viên được tổ chức thường niên nhằm nâng cao kỹ năng nghiên cứu khoa học cho sinh viên, tạo điều kiện giúp sinh viên phát huy năng lực sáng tạo, tìm tòi và học hỏi các kiến thức chuyên sâu.\nCử nhân\nToàn thời gian: 4 năm\nXem thông tin chi tiết về chương trình đào tạo\nXem thông tin chi tiết về chuẩn đầu ra\nKết quả quá trình học tập THPT\nKết quả bài thi ĐGNL năm 2025 của ĐHQG TP. HCM\nTổ hợp: Đang cập nhật\nĐiểm trúng tuyển 2024 (thang 40):33,00\nTháng 9, năm 2025\n29.770.000 đồng/năm",
      "content": {
        "Bằng cấp": "Cử nhân",
        "Thời gian đào tạo": "Toàn thời gian: 4 năm",
        "Chương trình đào tạo": "Xem thông tin chi tiết về chương trình đào tạo",
        "Chuẩn đầu ra": "Xem thông tin chi tiết về chuẩn đầu ra",
        "Phương thức xét tuyển riêng": "Kết quả quá trình học tập THPT Kết quả bài thi ĐGNL năm 2025 của ĐHQG TP. HCM",
        "Xét tuyển theo điểm thi THPT": "Tổ hợp: Đang cập nhật Điểm trúng tuyển 2024 (thang 40):33,00",
        "Khai giảng": "Tháng 9, năm 2025",
        "Học phí": "29.770.000 đồng/năm"
      },
      "name": "Tài chính - Ngân hàng"
    },
    {
      "tab": "Tiên tiến",
      "major_code": "F7340201",
      "description": "Chương trình cử nhân tiên tiến ngành Tài chính - Ngân hàng đào tạo cử nhân có phẩm chất đạo đức, chính trị và sức khỏe tốt. Nội dung chương trình cử nhân tiên tiến được xây dựng theo nhu cầu của thị trường lao động; gắn kết lý thuyết với thực tiễn; kết hợp kiến thức chuyên môn và chuyên ngành với rèn luyện kỹ năng thực hành; chú trọng đến các kỹ năng mềm và thực tập doanh nghiệp; xây dựng ý thức tự học, tự nghiên cứu giúp sinh viên rèn luyện và hoàn thiện các phẩm chất nghề nghiệp cần thiết, đáp ứng được nhu cầu làm việc đa dạng của thị trường lao động chất lượng cao trong và ngoài nước.\nTốt nghiệp cử nhân tiên tiến sinh viên có đủ năng lực chuyên môn, kỹ năng ngoại ngữ và kỹ năng mềm quản lý công việc, có thể đảm nhận được công việc liên quan tại các ngân hàng, tổ chức tín dụng phi ngân hàng, công ty chứng khoán, công ty bảo hiểm, các doanh nghiệp trong nước và ngoài nước, các tổ chức phi chính phủ, các Trung tâm/Viện/Phòng nghiên cứu và quản lý nghiên cứu về kinh tế; các trường đại học trong và ngoài nước; hoặc tiếp tục học lên cao học.\nCử nhân\nToàn thời gian: 4 năm\nXem thông tin chi tiết về chương trình đào tạo\nXem thông tin chi tiết về chuẩn đầu ra\nKết quả quá trình học tập THPT\nKết quả bài thi ĐGNL năm 2025 của ĐHQG TP. HCM\nTổ hợp: Đang cập nhật\nĐiểm trúng tuyển 2024 (thang 40):28,70\nTháng 9, năm 2025\nTừ 54 đến 55 triệu đồng/năm",
      "content": {
        "Bằng cấp": "Cử nhân",
        "Thời gian đào tạo": "Toàn thời gian: 4 năm",
        "Chương trình đào tạo": "Xem thông tin chi tiết về chương trình đào tạo",
        "Chuẩn đầu ra": "Xem thông tin chi tiết về chuẩn đầu ra",
        "Phương thức xét tuyển riêng": "Kết quả quá trình học tập THPT Kết quả bài thi ĐGNL năm 2025 của ĐHQG TP. HCM",
        "Xét tuyển theo điểm thi THPT": "Tổ hợp: Đang cập nhật Điểm trúng tuyển 2024 (thang 40):28,70",
        "Khai giảng": "Tháng 9, năm 2025",
        "Học phí": "Từ 54 đến 55 triệu đồng/năm"
      },
      "name": "Tài chính - Ngân hàng"
    },
    {
      "tab": "Đại học bằng tiếng Anh",
      "major_code": "FA7340201",
      "description": "Chương trình đại học bằng tiếng Anh ngành Tài chính - Ngân hàng được xây dựng dựa trên chương trình đào tạo của các trường đại học, viện đào tạo hàng đầu thế giới. Cùng với nhu cầu của thị trường lao động quốc tế hóa cao trong lĩnh vực tài chính, ngân hàng, chương trình được xây dựng gắn kết lý thuyết với thực tiễn; kết hợp kiến thức chuyên môn và chuyên ngành với rèn luyện kỹ năng thực hành; chú trọng đến các kỹ năng mềm và trải nghiệm doanh nghiệp; xây dựng ý thức tự học, tự nghiên cứu giúp sinh viên rèn luyện và hoàn thiện các phẩm chất nghề nghiệp cần thiết.\n100% các môn học trong chương trình được giảng dạy bằng tiếng Anh. Trong đó có một số môn học được các Giáo sư của những trường đại học từ các Quốc gia trên thế giới về giảng dạy.\nĐặc biệt, chương trình còn tích hợp các môn họcChứng chỉ CFA (Chartered Financial Analyst) giúp sinh viên trang bị kiến thức chuyên ngành, kỹ năng cần thiết để tham gia kỳ thi CFA level 1. Chứng chỉ CFA được công nhận rộng rãi trên khắp thế giới bởi tính thực tiễn cao và cung cấp nền tảng kiến thức và các nguyên tắc hoạt động của thị trường đầu tư toàn cầu do Viện CFA Hoa Kỳ cấp.\nCử nhân\nToàn thời gian: 4 năm\nXem thông tin chi tiết về chương trình đào tạo\nXem thông tin chi tiết về chuẩn đầu ra\nKết quả quá trình học tập THPT\nKết quả bài thi ĐGNL năm 2025 của ĐHQG TP. HCM\nTổ hợp: Đang cập nhật\nĐiểm trúng tuyển 2024 (thang 40):26,00\nTháng 9, năm 2025\nTừ 79 đến 80 triệu đồng/năm",
      "content": {
        "Bằng cấp": "Cử nhân",
        "Thời gian đào tạo": "Toàn thời gian: 4 năm",
        "Chương trình đào tạo": "Xem thông tin chi tiết về chương trình đào tạo",
        "Chuẩn đầu ra": "Xem thông tin chi tiết về chuẩn đầu ra",
        "Phương thức xét tuyển riêng": "Kết quả quá trình học tập THPT Kết quả bài thi ĐGNL năm 2025 của ĐHQG TP. HCM",
        "Xét tuyển theo điểm thi THPT": "Tổ hợp: Đang cập nhật Điểm trúng tuyển 2024 (thang 40):26,00",
        "Khai giảng": "Tháng 9, năm 2025",
        "Học phí": "Từ 79 đến 80 triệu đồng/năm"
      },
      "name": "Tài chính - Ngân hàng"
    },
    {
      "tab": "Liên kết quốc tế-K7340201X",
      "major_code": "K7340201",
      "description": "Cử nhân (song bằng)\n4 năm (3 năm đầu học tại TDTU, 1 năm sau học tại Trường liên kết)\nXem thông tin chi tiết về chương trình đào tạo\nXem thông tin chi tiết\nKết quả quá trình học tập THPT\nKết quả bài thi ĐGNL năm 2025 của ĐHQG TP. HCM\nTổ hợp: Đang cập nhật\nĐiểm trúng tuyển 2024 (thang 40):26,00\nTháng 9, năm 2025\nGiai đoạn 1: Từ 78 đến 79 triệu đồng/năm",
      "content": {
        "Bằng cấp": "Cử nhân (song bằng)",
        "Thời gian đào tạo": "4 năm (3 năm đầu học tại TDTU, 1 năm sau học tại Trường liên kết)",
        "Chương trình đào tạo": "Xem thông tin chi tiết về chương trình đào tạo",
        "Thông tin chương trình": "Xem thông tin chi tiết",
        "Phương thức xét tuyển riêng": "Kết quả quá trình học tập THPT Kết quả bài thi ĐGNL năm 2025 của ĐHQG TP. HCM",
        "Xét tuyển theo điểm thi THPT": "Tổ hợp: Đang cập nhật Điểm trúng tuyển 2024 (thang 40):26,00",
        "Khai giảng": "Tháng 9, năm 2025",
        "Học phí": "Giai đoạn 1: Từ 78 đến 79 triệu đồng/năm"
      },
      "name": "Tài chính và kiểm soát liên kết Đại học khoa học ứng dụng Saxion, Hà Lan"
    },
    {
      "tab": "Liên kết quốc tế-K7340201M",
      "major_code": "K7340201",
      "description": "Cử nhân (đơn bằng)\n3.5 năm (2 năm đầu học tại TDTU, 1.5 năm sau học tại Trường liên kết)\nXem thông tin chi tiết về chương trình đào tạo\nXem thông tin chi tiết\nKết quả quá trình học tập THPT\nKết quả bài thi ĐGNL năm 2025 của ĐHQG TP. HCM\nTổ hợp: Đang cập nhật\nĐiểm trúng tuyển 2024 (thang 40):26,00\nTháng 9, năm 2025\nGiai đoạn 1: 75 triệu đồng/năm",
      "content": {
        "Bằng cấp": "Cử nhân (đơn bằng)",
        "Thời gian đào tạo": "3.5 năm (2 năm đầu học tại TDTU, 1.5 năm sau học tại Trường liên kết)",
        "Chương trình đào tạo": "Xem thông tin chi tiết về chương trình đào tạo",
        "Thông tin chương trình": "Xem thông tin chi tiết",
        "Phương thức xét tuyển riêng": "Kết quả quá trình học tập THPT Kết quả bài thi ĐGNL năm 2025 của ĐHQG TP. HCM",
        "Xét tuyển theo điểm thi THPT": "Tổ hợp: Đang cập nhật Điểm trúng tuyển 2024 (thang 40):26,00",
        "Khai giảng": "Tháng 9, năm 2025",
        "Học phí": "Giai đoạn 1: 75 triệu đồng/năm"
      },
      "name": "Khối ngành Kinh doanh liên kết Đại học Massey, New Zealand"
    }
  ],
  "images": [
    "https://admission.tdtu.edu.vn",
    "https://admission.tdtu.edu.vn/sites/admission23/files/Tuyen-sinh/Dai-hoc/Nganh/TCNH/1_1.png",
    "https://admission.tdtu.edu.vn/sites/admission23/files/Tuyen-sinh/Dai-hoc/Nganh/TCNH/2_0.png",
    "https://admission.tdtu.edu.vn/sites/admission23/files/Tuyen-sinh/Dai-hoc/Nganh/TCNH/3.JPG"
  ]
}