{
  "name": "Xã hội học",
  "description": "Xã hội học là ngành khoa học về hành vi con người và tổ chức xã hội, chuyên điều tra, khảo sát xã hội, phản biện xã hội, xác định nguyên nhân của các hiện tượng xã hội bất ổn và tìm ra giải pháp nhằm góp phần quản lý xã hội hiệu quả hơn trong giai đoạn hội nhập và phát triển. Một số hiện tượng xã hội mà ngành xã hội học nghiên cứu như hành vi lệch chuẩn trên xã hội thực và trên mạng xã hội, sự bất bình đẳng xã hội, nghèo đói, thất nghiệp, tham nhũng, lãng phí, vô cảm; ảnh hưởng tiêu cực của truyền thông đại chúng, mạng xã hội,… đến đời sống cá nhân, gia đình, và các nhóm xã hội, cộng đồng.\n\nCử nhân ngành Xã hội học được trang bị kiến thức và kỹ năng nghề nghiệp để tự tin ứng tuyển vào các tổ chức chính trị - xã hội, doanh nghiệp, trung tâm nghiên cứu, các tổ chức NGO; có thể làm việc ở các vị trí: hành chính, nhân sự, hỗ trợ và tư vấn kỹ thuật trong các cuộc khảo sát điều tra, viết đề xuất các dự án phát triển, hoạch định chính sách xã hội cho các tổ chức chính phủ và phi chính phủ; các bộ phận tiếp thị, quảng cáo, tư vấn khách hàng, quan hệ công chúng, quản lý hệ thống thông tin nội bộ, tổ chức sự kiện truyền thông doanh nghiệp hay tiếp tục học các chương trình sau đại học để tham gia giảng dạy tại các trường đại học.",
  "reasons": [
    "Chương trình được trao chứng nhận kiểm định theo tiêu chuẩn FIBAA với thời hạn công nhận là 05 năm (2021 - 2026)",
    "Đội ngũ giảng viên có chuyên môn cao, có kinh nghiệm nghiên cứu và hướng dẫn sinh viên thực hiện các dự án nghiên cứu khoa học",
    "100% sinh viên ra trường có việc làm trong vòng 12 tháng kể từ khi tốt nghiệp"
  ],
  "programs": [
    {
      "tab": "Tiêu chuẩn",
      "major_code": "7310301",
      "description": "Chương trình đào tạo được xây dựng theo tiêu chuẩn quốc tế với hai định hướng: Quản lý xã hội và Truyền thông đại chúng. Đối với định hướng Quản lý xã hội, sinh viên được hướng dẫn tập trung vào việc ứng dụng các quan điểm lý thuyết và phương pháp nghiên cứu xã hội học, thiết kế nghiên cứu và công cụ thu thập thông tin, xử lý và phân tích thông tin vào khảo sát các vấn đề trong tất cả các lĩnh vực của đời sống xã hội theo nhu cầu của các tổ chức kinh tế, chính trị, xã hội, ...\nVới định hướng Truyền thông đại chúng, sinh viên được trang bị những kiến thức liên ngành khoa học xã hội, ứng dụng các quan điểm lý thuyết xã hội học, văn hóa, truyền thông và phương pháp nghiên cứu xã hội học để phân tích tác động & ảnh hưởng kinh tế, xã hội, văn hóa đến cá nhân, các nhóm xã hội, cộng đồng và xã hội nói chung trong bối cảnh thực hiện chuyển đổi số trong mọi lĩnh vực của đời sống kinh tế - xã hội hiện nay.\nCử nhân\nToàn thời gian: 4 năm\nXem thông tin chi tiết về chương trình đào tạo\nXem thông tin chi tiết về chuẩn đầu ra\nKết quả quá trình học tập THPT\nKết quả bài thi ĐGNL năm 2025 của ĐHQG TP. HCM\nTổ hợp: Đang cập nhật\nĐiểm trúng tuyển 2024 (thang 40):32,30\nTháng 9, năm 2025\n29.770.000 đồng/năm",
      "content": {
        "Bằng cấp": "Cử nhân",
        "Thời gian đào tạo": "Toàn thời gian: 4 năm",
        "Chương trình đào tạo": "Xem thông tin chi tiết về chương trình đào tạo",
        "Chuẩn đầu ra": "Xem thông tin chi tiết về chuẩn đầu ra",
        "Phương thức xét tuyển riêng": "Kết quả quá trình học tập THPT Kết quả bài thi ĐGNL năm 2025 của ĐHQG TP. HCM",
        "Xét tuyển theo điểm thi THPT": "Tổ hợp: Đang cập nhật Điểm trúng tuyển 2024 (thang 40):32,30",
        "Khai giảng": "Tháng 9, năm 2025",
        "Học phí": "29.770.000 đồng/năm"
      },
      "name": "Xã hội học"
    },
    {
      "tab": "Tiên tiến",
      "major_code": "F7310301",
      "description": "Chương trình đào tạo được thiết kế theo hướng hiện đại và hội nhập quốc tế nhằm đáp ứng nhu cầu của thị trường lao động trong bối cảnh cách mạng công nghiệp 4.0, phát triển phương tiện truyền thông mới. Đặc biệt nhấn mạnh kiến thức, kỹ năng công nghệ thông tin và công nghệ kỹ thuật số trong tổ chức và quản lý xã hội, phát triển kinh tế. Trong đó, gần 50% thời lượng chương trình được giảng dạy bằng tiếng Anh do giảng viên trong nước và quốc tế có kinh nghiệm và kiến thức chuyên môn cao thực hiện; Gần 30% thời lượng dành cho việc thực hành, thực tế nghề nghiệp, thực tập nghề nghiệp tại các cơ quan, doanh nghiệp trong các lĩnh vực về quản lý xã hội và truyền thông đại chúng. Phương pháp giảng dạy lấy người học làm trung tâm, kích thích sự sáng tạo, tư duy logic, phản biện của sinh viên.\nSinh viên có cơ hội tiếp cận các phương pháp nghiên cứu mới thông qua các hoạt động seminar, hội thảo quốc tế, hợp tác nghiên cứu khoa học sinh viên Việt Nam và quốc tế.\nNội dung chương trình đào tạo và phương pháp giảng dạy đáp ứng với tiêu chuẩn quốc tế đã giúp sinh viên xã hội học trở thành công dân toàn cầu, có thể tham gia vào thị trường lao động trong nước và Cộng đồng kinh tế ASEAN đặc biệt trong bối cảnh kiến thức và kỹ năng khảo sát (survey) – của ngành xã hội học, nằm trong 8 ngành nghề được tự do di chuyển trong thị trường lao động theo Hiệp định công nhận lẫn nhau (Mutual Recognition Agreements – MRAs).\nCử nhân\nToàn thời gian: 4 năm\nXem thông tin chi tiết về chương trình đào tạo\nXem thông tin chi tiết về chuẩn đầu ra\nTổ hợp: Văn*2, Anh, Sử\nKQ ĐGNL của ĐHQG TP. HCM\nƯu tiên xét tuyển theo TDTU\nTổ hợp: A01; C00; C01; D01\nTháng 9, năm 2025\nTừ 53 đến 54 triệu đồng/năm",
      "content": {
        "Bằng cấp": "Cử nhân",
        "Thời gian đào tạo": "Toàn thời gian: 4 năm",
        "Chương trình đào tạo": "Xem thông tin chi tiết về chương trình đào tạo",
        "Chuẩn đầu ra": "Xem thông tin chi tiết về chuẩn đầu ra",
        "Phương thức xét tuyển riêng": "Tổ hợp: Văn*2, Anh, Sử KQ ĐGNL của ĐHQG TP. HCM Ưu tiên xét tuyển theo TDTU",
        "Xét tuyển theo điểm thi THPT": "Tổ hợp: A01; C00; C01; D01",
        "Khai giảng": "Tháng 9, năm 2025",
        "Học phí": "Từ 53 đến 54 triệu đồng/năm"
      },
      "name": "Xã hội học"
    }
  ],
  "images": [
    "https://admission.tdtu.edu.vn/sites/admission23/files/Tuyen-sinh/Dai-hoc/Nganh/Xa-hoi-hoc/1.jpg",
    "https://admission.tdtu.edu.vn/sites/admission23/files/Tuyen-sinh/Dai-hoc/Nganh/Xa-hoi-hoc/2.jpg",
    "https://admission.tdtu.edu.vn/sites/admission23/files/Tuyen-sinh/Dai-hoc/Nganh/Xa-hoi-hoc/3.jpg"
  ]
}